Workbook

Sheet Configuración
A1: NAUKA
A2: Configuración del Proyecto
A3: Estos valores se usan en la Carátula. Edítalos según el proyecto.
A5: DATOS DEL PROYECTO
A6: # | B6: Campo | C6: Valor
A7: 1 | B7: Nombre del Proyecto | C7: NAUKA
A8: 2 | B8: Ubicación | C8: LOTE 44
A9: 3 | B9: Cliente | C9: NAUKA
A11: FIRMANTES (Aparecen al pie de cada carátula)
A12: # | B12: Nombre | C12: Cargo | D12: Empresa
A13: 1 | B13: Ing. Edy C. Rodriguez | C13: Director De Construcción | D13: IZ Arquitectos
A14: 2 | B14: Arq. Jose Ison | C14: Director General | D14: IZ Arquitectos
A15: 3 | B15: Ing. Marcos Fasja | C15: Director General | D15: GFA
A17: TIP | B17: Para generar una carátula: ve a la hoja "Carátula", elige Contratista y # Estimación en los dropdowns, y presiona Ctrl+P para imprimir/guardar como PDF.

Sheet Carátula
A1: =IF(B2="","NAUKA — SOLICITUD DE PAGO",B2 & IF(B4="",""," — " & B4)) -> ABIKAR — Colocaión cerca perimetral
A2: Propietario: | B2: ABIKAR
A3: Ubicación: | B3: =Configuración!C8 -> LOTE 44 | D3: ESTIMACION
A4: Partida: | B4: Colocaión cerca perimetral | D4: Finiquito
A5: Contrato Total: | B5: =IF(OR(B2="",B4=""),"",IFERROR(SUMIFS(Presupuesto!G:G,Presupuesto!B:B,B2,Presupuesto!C:C,B4),"")) -> 191168
A6: Saldo por Ejercer: | B6: =IF(OR(B2="",B4="",D4=""),"",IFERROR(G10,"")) -> 191168
A7: Fecha: | B7: =IF(OR(B2="",B4="",D4=""),"",IFERROR(SUMIFS('Flujo de Pagos'!C:C,'Flujo de Pagos'!E:E,B2,'Flujo de Pagos'!F:F,B4,'Flujo de Pagos'!H:H,D4),"")) -> 0
A9: ESTIMACION | B9: CATEGORIA | C9: NOMBRE CONTRATISTA | D9: IMPORTE | E9: ACUMULADO | F9: PPTO | G9: POR EJERCER
A10: =IF($B$2="","",$D$4) -> Finiquito | B10: =IF($B$2="","",$B$4) -> Colocaión cerca perimetral | C10: =IF($B$2="","",$B$2) -> ABIKAR | D10: =IF(OR($B$2="",$B$4="",$D$4=""),"",IFERROR(SUMIFS('Flujo de Pagos'!I:I,'Flujo de Pagos'!E:E,$B$2,'Flujo de Pagos'!F:F,$B$4,'Flujo de Pagos'!H:H,$D$4),0)) -> 0 | E10: =IF(OR($B$2="",$B$4="",$D$4=""),"",IFERROR(SUMIFS('Flujo de Pagos'!I:I,'Flujo de Pagos'!E:E,$B$2,'Flujo de Pagos'!F:F,$B$4,'Flujo de Pagos'!C:C,"<="&$B$7),0)) -> 0 | F10: =IF($B$2="","",$B$5) -> 191168 | G10: =IF($B$2="","",IFERROR(F10-E10,0)) -> 191168
A12: TOTAL ESTIMACION | B12: =IF($B$2="","",$B$4) -> Colocaión cerca perimetral | D12: =IF($B$2="","",D10) -> 0
A32: AUTORIZACIONES
B36: FIRMA | D36: FIRMA | F36: FIRMA
B37: =Configuración!B13 -> Ing. Edy C. Rodriguez | D37: =Configuración!B14 -> Arq. Jose Ison | F37: =Configuración!B15 -> Ing. Marcos Fasja
B38: =Configuración!C13 -> Director De Construcción | D38: =Configuración!C14 -> Director General | F38: =Configuración!C15 -> Director General
B39: =Configuración!D13 -> IZ Arquitectos | D39: =Configuración!D14 -> IZ Arquitectos | F39: =Configuración!D15 -> GFA

Sheet Presupuesto
A1: NAUKA
A2: Presupuesto por Contratista
A3: Cifras en MX$
A5: # | B5: CONTRATISTA / PROVEEDOR | C5: PARTIDA | D5: PRESUPUESTO | E5: IVA | F5: IVA | G5: PRESUPUESTO | H5: NOTAS
B6: INPUT | C6: INPUT | D6: INPUT | E6: INPUT | F6: INPUT | G6: INPUT | H6: INPUT
A7: 1 | B7: SAMSTORGAM | C7: Mecanica de Suelos | D7: 183440 | E7: 0.16 | F7: =D7*E7 -> 29350.4 | G7: =D7+F7 -> 212790.4
A8: =A7+1 -> 2 | B8: Hector Triana | C8: Diseño Estructural | D8: 243000 | E8: 0.16 | F8: =D8*E8 -> 38880 | G8: =D8+F8 -> 281880
A9: =A8+1 -> 3 | B9: ABIKAR | C9: Colocaión cerca perimetral | D9: 164800 | E9: 0.16 | F9: =D9*E9 -> 26368 | G9: =D9+F9 -> 191168
A10: =A9+1 -> 4 | B10: Urarq | C10: Derribo y Reubicacion de Arboles | D10: 237891.04 | E10: 0.16 | F10: =D10*E10 -> 38062.566 | G10: =D10+F10 -> 275953.61
A11: =A10+1 -> 5 | B11: Aquaconcepts | C11: Proyecto Alberca y Jacuzzi | D11: 50000 | E11: 0.16 | F11: =D11*E11 -> 8000 | G11: =D11+F11 -> 58000
A12: =A11+1 -> 6
A13: =A12+1 -> 7
A14: =A13+1 -> 8
A15: =A14+1 -> 9
A16: =A15+1 -> 10
A17: =A16+1 -> 11
A18: =A17+1 -> 12
A19: =A18+1 -> 13
A20: =A19+1 -> 14
A21: =A20+1 -> 15
A22: =A21+1 -> 16
A23: =A22+1 -> 17
... A67: =A66+1 -> 61
B68: TOTAL | G68: =SUM(G7:G67) -> 1019792

Sheet Flujo de Pagos
A1: NAUKA
A2: Flujo de Pagos a Contratistas
A3: Cifras en MX$
A5: x | B5: EOM | C5: FECHA DE PAGO | D5: PAGÓ | E5: CONTRATISTA | F5: PARTIDA | G5: CONCEPTO | H5: # ESTIMACION | I5: MONTO | J5: PRESUPUESTO | K5: PAGADO ACUM. | L5: RESTO POR PAGAR | M5: ESTATUS | N5: NOTAS
B6: AUTO | C6: INPUT | D6: DROPDOWN | E6: DROPDOWN | F6: DROPDOWN | G6: INPUT | H6: INPUT | I6: INPUT | J6: AUTO | K6: AUTO | L6: AUTO | M6: DROPDOWN | N6: INPUT
B7: =EOMONTH(C7,0) -> 46053 | C7: 46045 | D7: Salomon Ison | E7: SAMSTORGAM | F7: Mecanica de Suelos | H7: Anticipo | I7: 106395.2 | J7: =IF(OR(E7="",F7=""),"",SUMIFS(Presupuesto!G$7:G$67,Presupuesto!B$7:B$67,E7,Presupuesto!C$7:C$67,F7)) -> 212790.4 | K7: =IF(OR(E7="",F7=""),"",SUMIFS(I$7:I7,E$7:E7,E7,F$7:F7,F7)) -> 106395.2 | L7: =IF(OR(E7="",F7=""),"",J7-SUMIFS(I$7:I$506,E$7:E$506,E7,F$7:F$506,F7)) -> 106395.2 | M7: Pagado
B8: =EOMONTH(C8,0) -> 46081 | C8: 46054 | D8: Salomon Ison | E8: Hector Triana | F8: Diseño Estructural | H8: Anticipo | I8: 100000 | J8: =IF(OR(E8="",F8=""),"",SUMIFS(Presupuesto!G$7:G$67,Presupuesto!B$7:B$67,E8,Presupuesto!C$7:C$67,F8)) -> 281880 | K8: =IF(OR(E8="",F8=""),"",SUMIFS(I$7:I8,E$7:E8,E8,F$7:F8,F8)) -> 100000 | L8: =IF(OR(E8="",F8=""),"",J8-SUMIFS(I$7:I$506,E$7:E$506,E8,F$7:F$506,F8)) -> 181880 | M8: Pagado
B9: =EOMONTH(C9,0) -> 46142 | C9: 46113 | D9: Salomon Ison | E9: ABIKAR | F9: Colocaión cerca perimetral | H9: Anticipo | I9: 90000 | J9: =IF(OR(E9="",F9=""),"",SUMIFS(Presupuesto!G$7:G$67,Presupuesto!B$7:B$67,E9,Presupuesto!C$7:C$67,F9)) -> 191168 | K9: =IF(OR(E9="",F9=""),"",SUMIFS(I$7:I9,E$7:E9,E9,F$7:F9,F9)) -> 90000 | L9: =IF(OR(E9="",F9=""),"",J9-SUMIFS(I$7:I$506,E$7:E$506,E9,F$7:F$506,F9)) -> 101168 | M9: Pagado
B10: =EOMONTH(C10,0) -> 46142 | C10: 46114 | D10: Salomon Ison | E10: Urarq | F10: Derribo y Reubicacion de Arboles | H10: Anticipo | I10: 90000 | J10: =IF(OR(E10="",F10=""),"",SUMIFS(Presupuesto!G$7:G$67,Presupuesto!B$7:B$67,E10,Presupuesto!C$7:C$67,F10)) -> 275953.61 | K10: =IF(OR(E10="",F10=""),"",SUMIFS(I$7:I10,E$7:E10,E10,F$7:F10,F10)) -> 90000 | L10: =IF(OR(E10="",F10=""),"",J10-SUMIFS(I$7:I$506,E$7:E$506,E10,F$7:F$506,F10)) -> 0.7964 | M10: Pagado
B11: =EOMONTH(C11,0) -> 46173 | C11: 46149 | D11: Salomon Ison | E11: Urarq | F11: Derribo y Reubicacion de Arboles | H11: Finiquito | I11: 185952.81 | J11: =IF(OR(E11="",F11=""),"",SUMIFS(Presupuesto!G$7:G$67,Presupuesto!B$7:B$67,E11,Presupuesto!C$7:C$67,F11)) -> 275953.61 | K11: =IF(OR(E11="",F11=""),"",SUMIFS(I$7:I11,E$7:E11,E11,F$7:F11,F11)) -> 275952.81 | L11: =IF(OR(E11="",F11=""),"",J11-SUMIFS(I$7:I$506,E$7:E$506,E11,F$7:F$506,F11)) -> 0.7964 | M11: Pagado
B12: =EOMONTH(C12,0) -> 46173 | C12: 46149 | D12: Salomon Ison | E12: Aquaconcepts | F12: Proyecto Alberca y Jacuzzi | H12: Anticipo | I12: 17400 | J12: =IF(OR(E12="",F12=""),"",SUMIFS(Presupuesto!G$7:G$67,Presupuesto!B$7:B$67,E12,Presupuesto!C$7:C$67,F12)) -> 58000 | K12: =IF(OR(E12="",F12=""),"",SUMIFS(I$7:I12,E$7:E12,E12,F$7:F12,F12)) -> 17400 | L12: =IF(OR(E12="",F12=""),"",J12-SUMIFS(I$7:I$506,E$7:E$506,E12,F$7:F$506,F12)) -> 40600 | M12: Pagado
B13: =EOMONTH(C13,0) -> 1 | J13: =IF(OR(E13="",F13=""),"",SUMIFS(Presupuesto!G$7:G$67,Presupuesto!B$7:B$67,E13,Presupuesto!C$7:C$67,F13)) | K13: =IF(OR(E13="",F13=""),"",SUMIFS(I$7:I13,E$7:E13,E13,F$7:F13,F13)) | L13: =IF(OR(E13="",F13=""),"",J13-SUMIFS(I$7:I$506,E$7:E$506,E13,F$7:F$506,F13))
B14: =EOMONTH(C14,0) -> 1 | J14: =IF(OR(E14="",F14=""),"",SUMIFS(Presupuesto!G$7:G$67,Presupuesto!B$7:B$67,E14,Presupuesto!C$7:C$67,F14)) | K14: =IF(OR(E14="",F14=""),"",SUMIFS(I$7:I14,E$7:E14,E14,F$7:F14,F14)) | L14: =IF(OR(E14="",F14=""),"",J14-SUMIFS(I$7:I$506,E$7:E$506,E14,F$7:F$506,F14))
B15: =EOMONTH(C15,0) -> 1 | J15: =IF(OR(E15="",F15=""),"",SUMIFS(Presupuesto!G$7:G$67,Presupuesto!B$7:B$67,E15,Presupuesto!C$7:C$67,F15)) | K15: =IF(OR(E15="",F15=""),"",SUMIFS(I$7:I15,E$7:E15,E15,F$7:F15,F15)) | L15: =IF(OR(E15="",F15=""),"",J15-SUMIFS(I$7:I$506,E$7:E$506,E15,F$7:F$506,F15))
B16: =EOMONTH(C16,0) -> 1 | J16: =IF(OR(E16="",F16=""),"",SUMIFS(Presupuesto!G$7:G$67,Presupuesto!B$7:B$67,E16,Presupuesto!C$7:C$67,F16)) | K16: =IF(OR(E16="",F16=""),"",SUMIFS(I$7:I16,E$7:E16,E16,F$7:F16,F16)) | L16: =IF(OR(E16="",F16=""),"",J16-SUMIFS(I$7:I$506,E$7:E$506,E16,F$7:F$506,F16))
B17: =EOMONTH(C17,0) -> 1 | J17: =IF(OR(E17="",F17=""),"",SUMIFS(Presupuesto!G$7:G$67,Presupuesto!B$7:B$67,E17,Presupuesto!C$7:C$67,F17)) | K17: =IF(OR(E17="",F17=""),"",SUMIFS(I$7:I17,E$7:E17,E17,F$7:F17,F17)) | L17: =IF(OR(E17="",F17=""),"",J17-SUMIFS(I$7:I$506,E$7:E$506,E17,F$7:F$506,F17))
B18: =EOMONTH(C18,0) -> 1 | J18: =IF(OR(E18="",F18=""),"",SUMIFS(Presupuesto!G$7:G$67,Presupuesto!B$7:B$67,E18,Presupuesto!C$7:C$67,F18)) | K18: =IF(OR(E18="",F18=""),"",SUMIFS(I$7:I18,E$7:E18,E18,F$7:F18,F18)) | L18: =IF(OR(E18="",F18=""),"",J18-SUMIFS(I$7:I$506,E$7:E$506,E18,F$7:F$506,F18))
B19: =EOMONTH(C19,0) -> 1 | J19: =IF(OR(E19="",F19=""),"",SUMIFS(Presupuesto!G$7:G$67,Presupuesto!B$7:B$67,E19,Presupuesto!C$7:C$67,F19)) | K19: =IF(OR(E19="",F19=""),"",SUMIFS(I$7:I19,E$7:E19,E19,F$7:F19,F19)) | L19: =IF(OR(E19="",F19=""),"",J19-SUMIFS(I$7:I$506,E$7:E$506,E19,F$7:F$506,F19))
B20: =EOMONTH(C20,0) -> 1 | J20: =IF(OR(E20="",F20=""),"",SUMIFS(Presupuesto!G$7:G$67,Presupuesto!B$7:B$67,E20,Presupuesto!C$7:C$67,F20)) | K20: =IF(OR(E20="",F20=""),"",SUMIFS(I$7:I20,E$7:E20,E20,F$7:F20,F20)) | L20: =IF(OR(E20="",F20=""),"",J20-SUMIFS(I$7:I$506,E$7:E$506,E20,F$7:F$506,F20))
B21: =EOMONTH(C21,0) -> 1 | J21: =IF(OR(E21="",F21=""),"",SUMIFS(Presupuesto!G$7:G$67,Presupuesto!B$7:B$67,E21,Presupuesto!C$7:C$67,F21)) | K21: =IF(OR(E21="",F21=""),"",SUMIFS(I$7:I21,E$7:E21,E21,F$7:F21,F21)) | L21: =IF(OR(E21="",F21=""),"",J21-SUMIFS(I$7:I$506,E$7:E$506,E21,F$7:F$506,F21))
B22: =EOMONTH(C22,0) -> 1 | J22: =IF(OR(E22="",F22=""),"",SUMIFS(Presupuesto!G$7:G$67,Presupuesto!B$7:B$67,E22,Presupuesto!C$7:C$67,F22)) | K22: =IF(OR(E22="",F22=""),"",SUMIFS(I$7:I22,E$7:E22,E22,F$7:F22,F22)) | L22: =IF(OR(E22="",F22=""),"",J22-SUMIFS(I$7:I$506,E$7:E$506,E22,F$7:F$506,F22))
B23: =EOMONTH(C23,0) -> 1 | J23: =IF(OR(E23="",F23=""),"",SUMIFS(Presupuesto!G$7:G$67,Presupuesto!B$7:B$67,E23,Presupuesto!C$7:C$67,F23)) | K23: =IF(OR(E23="",F23=""),"",SUMIFS(I$7:I23,E$7:E23,E23,F$7:F23,F23)) | L23: =IF(OR(E23="",F23=""),"",J23-SUMIFS(I$7:I$506,E$7:E$506,E23,F$7:F$506,F23))
B24: =EOMONTH(C24,0) -> 1 | J24: =IF(OR(E24="",F24=""),"",SUMIFS(Presupuesto!G$7:G$67,Presupuesto!B$7:B$67,E24,Presupuesto!C$7:C$67,F24)) | K24: =IF(OR(E24="",F24=""),"",SUMIFS(I$7:I24,E$7:E24,E24,F$7:F24,F24)) | L24: =IF(OR(E24="",F24=""),"",J24-SUMIFS(I$7:I$506,E$7:E$506,E24,F$7:F$506,F24))
... B250: =EOMONTH(C250,0) -> 1 | J250: =IF(OR(E250="",F250=""),"",SUMIFS(Presupuesto!G$7:G$67,Presupuesto!B$7:B$67,E250,Presupuesto!C$7:C$67,F250)) | K250: =IF(OR(E250="",F250=""),"",SUMIFS(I$7:I250,E$7:E250,E250,F$7:F250,F250)) | L250: =IF(OR(E250="",F250=""),"",J250-SUMIFS(I$7:I$506,E$7:E$506,E250,F$7:F$506,F250))
B251: =IF(C251="","",DATE(YEAR(C251),MONTH(C251)+1,0)) | J251: =IF(OR(E251="",F251=""),"",SUMIFS(Presupuesto!G$7:G$67,Presupuesto!B$7:B$67,E251,Presupuesto!C$7:C$67,F251)) | K251: =IF(OR(E251="",F251=""),"",SUMIFS(I$7:I251,E$7:E251,E251,F$7:F251,F251)) | L251: =IF(OR(E251="",F251=""),"",J251-SUMIFS(I$7:I$506,E$7:E$506,E251,F$7:F$506,F251))
B252: =IF(C252="","",DATE(YEAR(C252),MONTH(C252)+1,0)) | J252: =IF(OR(E252="",F252=""),"",SUMIFS(Presupuesto!G$7:G$67,Presupuesto!B$7:B$67,E252,Presupuesto!C$7:C$67,F252)) | K252: =IF(OR(E252="",F252=""),"",SUMIFS(I$7:I252,E$7:E252,E252,F$7:F252,F252)) | L252: =IF(OR(E252="",F252=""),"",J252-SUMIFS(I$7:I$506,E$7:E$506,E252,F$7:F$506,F252))
B253: =IF(C253="","",DATE(YEAR(C253),MONTH(C253)+1,0)) | J253: =IF(OR(E253="",F253=""),"",SUMIFS(Presupuesto!G$7:G$67,Presupuesto!B$7:B$67,E253,Presupuesto!C$7:C$67,F253)) | K253: =IF(OR(E253="",F253=""),"",SUMIFS(I$7:I253,E$7:E253,E253,F$7:F253,F253)) | L253: =IF(OR(E253="",F253=""),"",J253-SUMIFS(I$7:I$506,E$7:E$506,E253,F$7:F$506,F253))
B254: =IF(C254="","",DATE(YEAR(C254),MONTH(C254)+1,0)) | J254: =IF(OR(E254="",F254=""),"",SUMIFS(Presupuesto!G$7:G$67,Presupuesto!B$7:B$67,E254,Presupuesto!C$7:C$67,F254)) | K254: =IF(OR(E254="",F254=""),"",SUMIFS(I$7:I254,E$7:E254,E254,F$7:F254,F254)) | L254: =IF(OR(E254="",F254=""),"",J254-SUMIFS(I$7:I$506,E$7:E$506,E254,F$7:F$506,F254))
B255: =IF(C255="","",DATE(YEAR(C255),MONTH(C255)+1,0)) | J255: =IF(OR(E255="",F255=""),"",SUMIFS(Presupuesto!G$7:G$67,Presupuesto!B$7:B$67,E255,Presupuesto!C$7:C$67,F255)) | K255: =IF(OR(E255="",F255=""),"",SUMIFS(I$7:I255,E$7:E255,E255,F$7:F255,F255)) | L255: =IF(OR(E255="",F255=""),"",J255-SUMIFS(I$7:I$506,E$7:E$506,E255,F$7:F$506,F255))
B256: =IF(C256="","",DATE(YEAR(C256),MONTH(C256)+1,0)) | J256: =IF(OR(E256="",F256=""),"",SUMIFS(Presupuesto!G$7:G$67,Presupuesto!B$7:B$67,E256,Presupuesto!C$7:C$67,F256)) | K256: =IF(OR(E256="",F256=""),"",SUMIFS(I$7:I256,E$7:E256,E256,F$7:F256,F256)) | L256: =IF(OR(E256="",F256=""),"",J256-SUMIFS(I$7:I$506,E$7:E$506,E256,F$7:F$506,F256))
B257: =IF(C257="","",DATE(YEAR(C257),MONTH(C257)+1,0)) | J257: =IF(OR(E257="",F257=""),"",SUMIFS(Presupuesto!G$7:G$67,Presupuesto!B$7:B$67,E257,Presupuesto!C$7:C$67,F257)) | K257: =IF(OR(E257="",F257=""),"",SUMIFS(I$7:I257,E$7:E257,E257,F$7:F257,F257)) | L257: =IF(OR(E257="",F257=""),"",J257-SUMIFS(I$7:I$506,E$7:E$506,E257,F$7:F$506,F257))
B258: =IF(C258="","",DATE(YEAR(C258),MONTH(C258)+1,0)) | J258: =IF(OR(E258="",F258=""),"",SUMIFS(Presupuesto!G$7:G$67,Presupuesto!B$7:B$67,E258,Presupuesto!C$7:C$67,F258)) | K258: =IF(OR(E258="",F258=""),"",SUMIFS(I$7:I258,E$7:E258,E258,F$7:F258,F258)) | L258: =IF(OR(E258="",F258=""),"",J258-SUMIFS(I$7:I$506,E$7:E$506,E258,F$7:F$506,F258))
B259: =IF(C259="","",DATE(YEAR(C259),MONTH(C259)+1,0)) | J259: =IF(OR(E259="",F259=""),"",SUMIFS(Presupuesto!G$7:G$67,Presupuesto!B$7:B$67,E259,Presupuesto!C$7:C$67,F259)) | K259: =IF(OR(E259="",F259=""),"",SUMIFS(I$7:I259,E$7:E259,E259,F$7:F259,F259)) | L259: =IF(OR(E259="",F259=""),"",J259-SUMIFS(I$7:I$506,E$7:E$506,E259,F$7:F$506,F259))
B260: =IF(C260="","",DATE(YEAR(C260),MONTH(C260)+1,0)) | J260: =IF(OR(E260="",F260=""),"",SUMIFS(Presupuesto!G$7:G$67,Presupuesto!B$7:B$67,E260,Presupuesto!C$7:C$67,F260)) | K260: =IF(OR(E260="",F260=""),"",SUMIFS(I$7:I260,E$7:E260,E260,F$7:F260,F260)) | L260: =IF(OR(E260="",F260=""),"",J260-SUMIFS(I$7:I$506,E$7:E$506,E260,F$7:F$506,F260))
B261: =IF(C261="","",DATE(YEAR(C261),MONTH(C261)+1,0)) | J261: =IF(OR(E261="",F261=""),"",SUMIFS(Presupuesto!G$7:G$67,Presupuesto!B$7:B$67,E261,Presupuesto!C$7:C$67,F261)) | K261: =IF(OR(E261="",F261=""),"",SUMIFS(I$7:I261,E$7:E261,E261,F$7:F261,F261)) | L261: =IF(OR(E261="",F261=""),"",J261-SUMIFS(I$7:I$506,E$7:E$506,E261,F$7:F$506,F261))
B262: =IF(C262="","",DATE(YEAR(C262),MONTH(C262)+1,0)) | J262: =IF(OR(E262="",F262=""),"",SUMIFS(Presupuesto!G$7:G$67,Presupuesto!B$7:B$67,E262,Presupuesto!C$7:C$67,F262)) | K262: =IF(OR(E262="",F262=""),"",SUMIFS(I$7:I262,E$7:E262,E262,F$7:F262,F262)) | L262: =IF(OR(E262="",F262=""),"",J262-SUMIFS(I$7:I$506,E$7:E$506,E262,F$7:F$506,F262))
... B506: =IF(C506="","",DATE(YEAR(C506),MONTH(C506)+1,0)) | J506: =IF(OR(E506="",F506=""),"",SUMIFS(Presupuesto!G$7:G$67,Presupuesto!B$7:B$67,E506,Presupuesto!C$7:C$67,F506)) | K506: =IF(OR(E506="",F506=""),"",SUMIFS(I$7:I506,E$7:E506,E506,F$7:F506,F506)) | L506: =IF(OR(E506="",F506=""),"",J506-SUMIFS(I$7:I$506,E$7:E$506,E506,F$7:F$506,F506))

Sheet Resumen Total
A1: NAUKA
A2: Resumen por Contratista (Acumulado)
A3: Cifras en MX$
A5: # | B5: CONTRATISTA | C5: PARTIDA | D5: PRESUPUESTO | E5: EJERCIDO | F5: % AVANCE | G5: DISPONIBLE
A6: 1 | B6: =IF(Presupuesto!B7="","",Presupuesto!B7) -> SAMSTORGAM | C6: =IF(Presupuesto!C7="","",Presupuesto!C7) -> Mecanica de Suelos | D6: =IF(Presupuesto!G7="","",Presupuesto!G7) -> 212790.4 | E6: =IF(B6="","",SUMIFS('Flujo de Pagos'!I$7:I$506,'Flujo de Pagos'!E$7:E$506,B6)) -> 106395.2 | F6: =IF(OR(D6="",D6=0),"",E6/D6) -> 0.5 | G6: =IF(D6="","",D6-E6) -> 106395.2
A7: 2 | B7: =IF(Presupuesto!B8="","",Presupuesto!B8) -> Hector Triana | C7: =IF(Presupuesto!C8="","",Presupuesto!C8) -> Diseño Estructural | D7: =IF(Presupuesto!G8="","",Presupuesto!G8) -> 281880 | E7: =IF(B7="","",SUMIFS('Flujo de Pagos'!I$7:I$506,'Flujo de Pagos'!E$7:E$506,B7)) -> 100000 | F7: =IF(OR(D7="",D7=0),"",E7/D7) -> 0.35476089 | G7: =IF(D7="","",D7-E7) -> 181880
A8: 3 | B8: =IF(Presupuesto!B9="","",Presupuesto!B9) -> ABIKAR | C8: =IF(Presupuesto!C9="","",Presupuesto!C9) -> Colocaión cerca perimetral | D8: =IF(Presupuesto!G9="","",Presupuesto!G9) -> 191168 | E8: =IF(B8="","",SUMIFS('Flujo de Pagos'!I$7:I$506,'Flujo de Pagos'!E$7:E$506,B8)) -> 90000 | F8: =IF(OR(D8="",D8=0),"",E8/D8) -> 0.47079009 | G8: =IF(D8="","",D8-E8) -> 101168
A9: 4 | B9: =IF(Presupuesto!B10="","",Presupuesto!B10) -> Urarq | C9: =IF(Presupuesto!C10="","",Presupuesto!C10) -> Derribo y Reubicacion de Arboles | D9: =IF(Presupuesto!G10="","",Presupuesto!G10) -> 275953.61 | E9: =IF(B9="","",SUMIFS('Flujo de Pagos'!I$7:I$506,'Flujo de Pagos'!E$7:E$506,B9)) -> 275952.81 | F9: =IF(OR(D9="",D9=0),"",E9/D9) -> 0.99999711 | G9: =IF(D9="","",D9-E9) -> 0.7964
A10: 5 | B10: =IF(Presupuesto!B11="","",Presupuesto!B11) -> Aquaconcepts | C10: =IF(Presupuesto!C11="","",Presupuesto!C11) -> Proyecto Alberca y Jacuzzi | D10: =IF(Presupuesto!G11="","",Presupuesto!G11) -> 58000 | E10: =IF(B10="","",SUMIFS('Flujo de Pagos'!I$7:I$506,'Flujo de Pagos'!E$7:E$506,B10)) -> 17400 | F10: =IF(OR(D10="",D10=0),"",E10/D10) -> 0.3 | G10: =IF(D10="","",D10-E10) -> 40600
A11: 6 | B11: =IF(Presupuesto!B12="","",Presupuesto!B12) | C11: =IF(Presupuesto!C12="","",Presupuesto!C12) | D11: =IF(Presupuesto!G12="","",Presupuesto!G12) | E11: =IF(B11="","",SUMIFS('Flujo de Pagos'!I$7:I$506,'Flujo de Pagos'!E$7:E$506,B11)) | F11: =IF(OR(D11="",D11=0),"",E11/D11) | G11: =IF(D11="","",D11-E11)
A12: 7 | B12: =IF(Presupuesto!B13="","",Presupuesto!B13) | C12: TOTAL | D12: =SUM(D6:D11) -> 1019792 | E12: =SUM(E6:E11) -> 589748.01 | F12: =IF(OR(D12="",D12=0),"",E12/D12) -> 0.57830225 | G12: =IF(D12="","",D12-E12) -> 430044
A13: 8 | B13: =IF(Presupuesto!B14="","",Presupuesto!B14) | C13: =IF(Presupuesto!C14="","",Presupuesto!C14) | D13: =IF(Presupuesto!G14="","",Presupuesto!G14) | F13: =IF(OR(D13="",D13=0),"",E13/D13) | G13: =IF(D13="","",D13-E13)
A14: 9 | B14: =IF(Presupuesto!B15="","",Presupuesto!B15) | C14: =IF(Presupuesto!C15="","",Presupuesto!C15) | D14: =IF(Presupuesto!G15="","",Presupuesto!G15) | E14: =IF(B14="","",SUMIFS('Flujo de Pagos'!I$7:I$506,'Flujo de Pagos'!E$7:E$506,B14)) | F14: =IF(OR(D14="",D14=0),"",E14/D14) | G14: =IF(D14="","",D14-E14)
A15: 10 | B15: =IF(Presupuesto!B16="","",Presupuesto!B16) | C15: =IF(Presupuesto!C16="","",Presupuesto!C16) | D15: =IF(Presupuesto!G16="","",Presupuesto!G16) | E15: =IF(B15="","",SUMIFS('Flujo de Pagos'!I$7:I$506,'Flujo de Pagos'!E$7:E$506,B15)) | F15: =IF(OR(D15="",D15=0),"",E15/D15) | G15: =IF(D15="","",D15-E15)
A16: 11 | B16: =IF(Presupuesto!B17="","",Presupuesto!B17) | C16: =IF(Presupuesto!C17="","",Presupuesto!C17) | D16: =IF(Presupuesto!G17="","",Presupuesto!G17) | E16: =IF(B16="","",SUMIFS('Flujo de Pagos'!I$7:I$506,'Flujo de Pagos'!E$7:E$506,B16)) | F16: =IF(OR(D16="",D16=0),"",E16/D16) | G16: =IF(D16="","",D16-E16)
A17: 12 | B17: =IF(Presupuesto!B18="","",Presupuesto!B18) | C17: =IF(Presupuesto!C18="","",Presupuesto!C18) | D17: =IF(Presupuesto!G18="","",Presupuesto!G18) | E17: =IF(B17="","",SUMIFS('Flujo de Pagos'!I$7:I$506,'Flujo de Pagos'!E$7:E$506,B17)) | F17: =IF(OR(D17="",D17=0),"",E17/D17) | G17: =IF(D17="","",D17-E17)
A18: 13 | B18: =IF(Presupuesto!B19="","",Presupuesto!B19) | C18: =IF(Presupuesto!C19="","",Presupuesto!C19) | D18: =IF(Presupuesto!G19="","",Presupuesto!G19) | E18: =IF(B18="","",SUMIFS('Flujo de Pagos'!I$7:I$506,'Flujo de Pagos'!E$7:E$506,B18)) | F18: =IF(OR(D18="",D18=0),"",E18/D18) | G18: =IF(D18="","",D18-E18)
A19: 14 | B19: =IF(Presupuesto!B20="","",Presupuesto!B20) | C19: =IF(Presupuesto!C20="","",Presupuesto!C20) | D19: =IF(Presupuesto!G20="","",Presupuesto!G20) | E19: =IF(B19="","",SUMIFS('Flujo de Pagos'!I$7:I$506,'Flujo de Pagos'!E$7:E$506,B19)) | F19: =IF(OR(D19="",D19=0),"",E19/D19) | G19: =IF(D19="","",D19-E19)
A20: 15 | B20: =IF(Presupuesto!B21="","",Presupuesto!B21) | C20: =IF(Presupuesto!C21="","",Presupuesto!C21) | D20: =IF(Presupuesto!G21="","",Presupuesto!G21) | E20: =IF(B20="","",SUMIFS('Flujo de Pagos'!I$7:I$506,'Flujo de Pagos'!E$7:E$506,B20)) | F20: =IF(OR(D20="",D20=0),"",E20/D20) | G20: =IF(D20="","",D20-E20)
A21: 16 | B21: =IF(Presupuesto!B22="","",Presupuesto!B22) | C21: =IF(Presupuesto!C22="","",Presupuesto!C22) | D21: =IF(Presupuesto!G22="","",Presupuesto!G22) | E21: =IF(B21="","",SUMIFS('Flujo de Pagos'!I$7:I$506,'Flujo de Pagos'!E$7:E$506,B21)) | F21: =IF(OR(D21="",D21=0),"",E21/D21) | G21: =IF(D21="","",D21-E21)
A22: 17 | B22: =IF(Presupuesto!B23="","",Presupuesto!B23) | C22: =IF(Presupuesto!C23="","",Presupuesto!C23) | D22: =IF(Presupuesto!G23="","",Presupuesto!G23) | E22: =IF(B22="","",SUMIFS('Flujo de Pagos'!I$7:I$506,'Flujo de Pagos'!E$7:E$506,B22)) | F22: =IF(OR(D22="",D22=0),"",E22/D22) | G22: =IF(D22="","",D22-E22)
A23: 18 | B23: =IF(Presupuesto!B24="","",Presupuesto!B24) | C23: =IF(Presupuesto!C24="","",Presupuesto!C24) | D23: =IF(Presupuesto!G24="","",Presupuesto!G24) | E23: =IF(B23="","",SUMIFS('Flujo de Pagos'!I$7:I$506,'Flujo de Pagos'!E$7:E$506,B23)) | F23: =IF(OR(D23="",D23=0),"",E23/D23) | G23: =IF(D23="","",D23-E23)
A24: 19 | B24: =IF(Presupuesto!B25="","",Presupuesto!B25) | C24: =IF(Presupuesto!C25="","",Presupuesto!C25) | D24: =IF(Presupuesto!G25="","",Presupuesto!G25) | E24: =IF(B24="","",SUMIFS('Flujo de Pagos'!I$7:I$506,'Flujo de Pagos'!E$7:E$506,B24)) | F24: =IF(OR(D24="",D24=0),"",E24/D24) | G24: =IF(D24="","",D24-E24)
A25: 20 | B25: =IF(Presupuesto!B26="","",Presupuesto!B26) | C25: =IF(Presupuesto!C26="","",Presupuesto!C26) | D25: =IF(Presupuesto!G26="","",Presupuesto!G26) | E25: =IF(B25="","",SUMIFS('Flujo de Pagos'!I$7:I$506,'Flujo de Pagos'!E$7:E$506,B25)) | F25: =IF(OR(D25="",D25=0),"",E25/D25) | G25: =IF(D25="","",D25-E25)
... A65: 60 | B65: =IF(Presupuesto!B66="","",Presupuesto!B66) | C65: =IF(Presupuesto!C66="","",Presupuesto!C66) | D65: =IF(Presupuesto!G66="","",Presupuesto!G66) | E65: =IF(B65="","",SUMIFS('Flujo de Pagos'!I$7:I$506,'Flujo de Pagos'!E$7:E$506,B65)) | F65: =IF(OR(D65="",D65=0),"",E65/D65) | G65: =IF(D65="","",D65-E65)
B66: TOTAL | D66: =SUM(D6:D65) -> 2039584 | E66: =SUM(E6:E65) -> 1179496 | F66: =IF(D66=0,"",E66/D66) -> 0.57830225 | G66: =SUM(G6:G65) -> 860087.99

Sheet Resumen Mensual
A1: NAUKA
A2: Resumen mensual de pagos
A3: Cifras en MX$
C6: =YEAR(C7) -> 2026 | D6: =YEAR(D7) -> 2026 | E6: =YEAR(E7) -> 2026 | F6: =YEAR(F7) -> 2026 | G6: =YEAR(G7) -> 2026 | H6: =YEAR(H7) -> 2026 | I6: =YEAR(I7) -> 2026 | J6: =YEAR(J7) -> 2026 | ... AM6: =YEAR(AM7) -> 1899
B7: FLUJO DE PAGOS | C7: 46053 | D7: =EOMONTH(C7,1) -> 46081 | E7: =EOMONTH(D7,1) -> 46112 | F7: =EOMONTH(E7,1) -> 46142 | G7: =EOMONTH(F7,1) -> 46173 | H7: =EOMONTH(G7,1) -> 46203 | I7: =EOMONTH(H7,1) -> 46234 | J7: =EOMONTH(I7,1) -> 46265 | K7: =EOMONTH(J7,1) -> 46295 | ... AL7: =EOMONTH(AK7,1) -> 47118
B9: PAGOS POR CONTRATISTA
B10: =IF(Presupuesto!B7="","",Presupuesto!B7) -> SAMSTORGAM | C10: =IF($B10="","",SUMIFS('Flujo de Pagos'!$I$7:$I$506,'Flujo de Pagos'!$E$7:$E$506,$B10,'Flujo de Pagos'!$B$7:$B$506,C$7)) -> 106395.2 | D10: =IF($B10="","",SUMIFS('Flujo de Pagos'!$I$7:$I$506,'Flujo de Pagos'!$E$7:$E$506,$B10,'Flujo de Pagos'!$B$7:$B$506,D$7)) -> 0 | E10: =IF($B10="","",SUMIFS('Flujo de Pagos'!$I$7:$I$506,'Flujo de Pagos'!$E$7:$E$506,$B10,'Flujo de Pagos'!$B$7:$B$506,E$7)) -> 0 | F10: =IF($B10="","",SUMIFS('Flujo de Pagos'!$I$7:$I$506,'Flujo de Pagos'!$E$7:$E$506,$B10,'Flujo de Pagos'!$B$7:$B$506,F$7)) -> 0 | G10: =IF($B10="","",SUMIFS('Flujo de Pagos'!$I$7:$I$506,'Flujo de Pagos'!$E$7:$E$506,$B10,'Flujo de Pagos'!$B$7:$B$506,G$7)) -> 0 | H10: =IF($B10="","",SUMIFS('Flujo de Pagos'!$I$7:$I$506,'Flujo de Pagos'!$E$7:$E$506,$B10,'Flujo de Pagos'!$B$7:$B$506,H$7)) -> 0 | I10: =IF($B10="","",SUMIFS('Flujo de Pagos'!$I$7:$I$506,'Flujo de Pagos'!$E$7:$E$506,$B10,'Flujo de Pagos'!$B$7:$B$506,I$7)) -> 0 | J10: =IF($B10="","",SUMIFS('Flujo de Pagos'!$I$7:$I$506,'Flujo de Pagos'!$E$7:$E$506,$B10,'Flujo de Pagos'!$B$7:$B$506,J$7)) -> 0 | ... AL10: =IF($B10="","",SUMIFS('Flujo de Pagos'!$I$7:$I$506,'Flujo de Pagos'!$E$7:$E$506,$B10,'Flujo de Pagos'!$B$7:$B$506,AL$7)) -> 0 | AM10: =SUM(C10:AL10) -> 106395.2
B11: =IF(Presupuesto!B8="","",Presupuesto!B8) -> Hector Triana | C11: =IF($B11="","",SUMIFS('Flujo de Pagos'!$I$7:$I$506,'Flujo de Pagos'!$E$7:$E$506,$B11,'Flujo de Pagos'!$B$7:$B$506,C$7)) -> 0 | D11: =IF($B11="","",SUMIFS('Flujo de Pagos'!$I$7:$I$506,'Flujo de Pagos'!$E$7:$E$506,$B11,'Flujo de Pagos'!$B$7:$B$506,D$7)) -> 100000 | E11: =IF($B11="","",SUMIFS('Flujo de Pagos'!$I$7:$I$506,'Flujo de Pagos'!$E$7:$E$506,$B11,'Flujo de Pagos'!$B$7:$B$506,E$7)) -> 0 | F11: =IF($B11="","",SUMIFS('Flujo de Pagos'!$I$7:$I$506,'Flujo de Pagos'!$E$7:$E$506,$B11,'Flujo de Pagos'!$B$7:$B$506,F$7)) -> 0 | G11: =IF($B11="","",SUMIFS('Flujo de Pagos'!$I$7:$I$506,'Flujo de Pagos'!$E$7:$E$506,$B11,'Flujo de Pagos'!$B$7:$B$506,G$7)) -> 0 | H11: =IF($B11="","",SUMIFS('Flujo de Pagos'!$I$7:$I$506,'Flujo de Pagos'!$E$7:$E$506,$B11,'Flujo de Pagos'!$B$7:$B$506,H$7)) -> 0 | I11: =IF($B11="","",SUMIFS('Flujo de Pagos'!$I$7:$I$506,'Flujo de Pagos'!$E$7:$E$506,$B11,'Flujo de Pagos'!$B$7:$B$506,I$7)) -> 0 | J11: =IF($B11="","",SUMIFS('Flujo de Pagos'!$I$7:$I$506,'Flujo de Pagos'!$E$7:$E$506,$B11,'Flujo de Pagos'!$B$7:$B$506,J$7)) -> 0 | ... AL11: =IF($B11="","",SUMIFS('Flujo de Pagos'!$I$7:$I$506,'Flujo de Pagos'!$E$7:$E$506,$B11,'Flujo de Pagos'!$B$7:$B$506,AL$7)) -> 0 | AM11: =SUM(C11:AL11) -> 100000
B12: =IF(Presupuesto!B9="","",Presupuesto!B9) -> ABIKAR | C12: =IF($B12="","",SUMIFS('Flujo de Pagos'!$I$7:$I$506,'Flujo de Pagos'!$E$7:$E$506,$B12,'Flujo de Pagos'!$B$7:$B$506,C$7)) -> 0 | D12: =IF($B12="","",SUMIFS('Flujo de Pagos'!$I$7:$I$506,'Flujo de Pagos'!$E$7:$E$506,$B12,'Flujo de Pagos'!$B$7:$B$506,D$7)) -> 0 | E12: =IF($B12="","",SUMIFS('Flujo de Pagos'!$I$7:$I$506,'Flujo de Pagos'!$E$7:$E$506,$B12,'Flujo de Pagos'!$B$7:$B$506,E$7)) -> 0 | F12: =IF($B12="","",SUMIFS('Flujo de Pagos'!$I$7:$I$506,'Flujo de Pagos'!$E$7:$E$506,$B12,'Flujo de Pagos'!$B$7:$B$506,F$7)) -> 90000 | G12: =IF($B12="","",SUMIFS('Flujo de Pagos'!$I$7:$I$506,'Flujo de Pagos'!$E$7:$E$506,$B12,'Flujo de Pagos'!$B$7:$B$506,G$7)) -> 0 | H12: =IF($B12="","",SUMIFS('Flujo de Pagos'!$I$7:$I$506,'Flujo de Pagos'!$E$7:$E$506,$B12,'Flujo de Pagos'!$B$7:$B$506,H$7)) -> 0 | I12: =IF($B12="","",SUMIFS('Flujo de Pagos'!$I$7:$I$506,'Flujo de Pagos'!$E$7:$E$506,$B12,'Flujo de Pagos'!$B$7:$B$506,I$7)) -> 0 | J12: =IF($B12="","",SUMIFS('Flujo de Pagos'!$I$7:$I$506,'Flujo de Pagos'!$E$7:$E$506,$B12,'Flujo de Pagos'!$B$7:$B$506,J$7)) -> 0 | ... AL12: =IF($B12="","",SUMIFS('Flujo de Pagos'!$I$7:$I$506,'Flujo de Pagos'!$E$7:$E$506,$B12,'Flujo de Pagos'!$B$7:$B$506,AL$7)) -> 0 | AM12: =SUM(C12:AL12) -> 90000
B13: =IF(Presupuesto!B10="","",Presupuesto!B10) -> Urarq | C13: =IF($B13="","",SUMIFS('Flujo de Pagos'!$I$7:$I$506,'Flujo de Pagos'!$E$7:$E$506,$B13,'Flujo de Pagos'!$B$7:$B$506,C$7)) -> 0 | D13: =IF($B13="","",SUMIFS('Flujo de Pagos'!$I$7:$I$506,'Flujo de Pagos'!$E$7:$E$506,$B13,'Flujo de Pagos'!$B$7:$B$506,D$7)) -> 0 | E13: =IF($B13="","",SUMIFS('Flujo de Pagos'!$I$7:$I$506,'Flujo de Pagos'!$E$7:$E$506,$B13,'Flujo de Pagos'!$B$7:$B$506,E$7)) -> 0 | F13: =IF($B13="","",SUMIFS('Flujo de Pagos'!$I$7:$I$506,'Flujo de Pagos'!$E$7:$E$506,$B13,'Flujo de Pagos'!$B$7:$B$506,F$7)) -> 90000 | G13: =IF($B13="","",SUMIFS('Flujo de Pagos'!$I$7:$I$506,'Flujo de Pagos'!$E$7:$E$506,$B13,'Flujo de Pagos'!$B$7:$B$506,G$7)) -> 185952.81 | H13: =IF($B13="","",SUMIFS('Flujo de Pagos'!$I$7:$I$506,'Flujo de Pagos'!$E$7:$E$506,$B13,'Flujo de Pagos'!$B$7:$B$506,H$7)) -> 0 | I13: =IF($B13="","",SUMIFS('Flujo de Pagos'!$I$7:$I$506,'Flujo de Pagos'!$E$7:$E$506,$B13,'Flujo de Pagos'!$B$7:$B$506,I$7)) -> 0 | J13: =IF($B13="","",SUMIFS('Flujo de Pagos'!$I$7:$I$506,'Flujo de Pagos'!$E$7:$E$506,$B13,'Flujo de Pagos'!$B$7:$B$506,J$7)) -> 0 | ... AL13: =IF($B13="","",SUMIFS('Flujo de Pagos'!$I$7:$I$506,'Flujo de Pagos'!$E$7:$E$506,$B13,'Flujo de Pagos'!$B$7:$B$506,AL$7)) -> 0 | AM13: =SUM(C13:AL13) -> 275952.81
B14: =IF(Presupuesto!B11="","",Presupuesto!B11) -> Aquaconcepts | C14: =IF(B14="","",SUMIFS('Flujo de Pagos'!I$7:I$506,'Flujo de Pagos'!E$7:E$506,B14,'Flujo de Pagos'!B$7:B$506,C7)) -> 0 | D14: =IF(B14="","",SUMIFS('Flujo de Pagos'!I$7:I$506,'Flujo de Pagos'!E$7:E$506,B14,'Flujo de Pagos'!B$7:B$506,D7)) -> 0 | E14: =IF(B14="","",SUMIFS('Flujo de Pagos'!I$7:I$506,'Flujo de Pagos'!E$7:E$506,B14,'Flujo de Pagos'!B$7:B$506,E7)) -> 0 | F14: =IF(B14="","",SUMIFS('Flujo de Pagos'!I$7:I$506,'Flujo de Pagos'!E$7:E$506,B14,'Flujo de Pagos'!B$7:B$506,F7)) -> 0 | G14: =IF(B14="","",SUMIFS('Flujo de Pagos'!I$7:I$506,'Flujo de Pagos'!E$7:E$506,B14,'Flujo de Pagos'!B$7:B$506,G7)) -> 17400 | H14: =IF(B14="","",SUMIFS('Flujo de Pagos'!I$7:I$506,'Flujo de Pagos'!E$7:E$506,B14,'Flujo de Pagos'!B$7:B$506,H7)) -> 0 | I14: =IF(B14="","",SUMIFS('Flujo de Pagos'!I$7:I$506,'Flujo de Pagos'!E$7:E$506,B14,'Flujo de Pagos'!B$7:B$506,I7)) -> 0 | J14: =IF(B14="","",SUMIFS('Flujo de Pagos'!I$7:I$506,'Flujo de Pagos'!E$7:E$506,B14,'Flujo de Pagos'!B$7:B$506,J7)) -> 0 | K14: =IF(B14="","",SUMIFS('Flujo de Pagos'!I$7:I$506,'Flujo de Pagos'!E$7:E$506,B14,'Flujo de Pagos'!B$7:B$506,K7)) -> 0 | L14: =IF(B14="","",SUMIFS('Flujo de Pagos'!I$7:I$506,'Flujo de Pagos'!E$7:E$506,B14,'Flujo de Pagos'!B$7:B$506,L7)) -> 0 | M14: =IF(B14="","",SUMIFS('Flujo de Pagos'!I$7:I$506,'Flujo de Pagos'!E$7:E$506,B14,'Flujo de Pagos'!B$7:B$506,M7)) -> 0 | N14: =IF(B14="","",SUMIFS('Flujo de Pagos'!I$7:I$506,'Flujo de Pagos'!E$7:E$506,B14,'Flujo de Pagos'!B$7:B$506,N7)) -> 0 | O14: =IF(B14="","",SUMIFS('Flujo de Pagos'!I$7:I$506,'Flujo de Pagos'!E$7:E$506,B14,'Flujo de Pagos'!B$7:B$506,O7)) -> 0 | P14: =IF(B14="","",SUMIFS('Flujo de Pagos'!I$7:I$506,'Flujo de Pagos'!E$7:E$506,B14,'Flujo de Pagos'!B$7:B$506,P7)) -> 0 | Q14: =IF(B14="","",SUMIFS('Flujo de Pagos'!I$7:I$506,'Flujo de Pagos'!E$7:E$506,B14,'Flujo de Pagos'!B$7:B$506,Q7)) -> 0 | R14: =IF(B14="","",SUMIFS('Flujo de Pagos'!I$7:I$506,'Flujo de Pagos'!E$7:E$506,B14,'Flujo de Pagos'!B$7:B$506,R7)) -> 0 | S14: =IF(B14="","",SUMIFS('Flujo de Pagos'!I$7:I$506,'Flujo de Pagos'!E$7:E$506,B14,'Flujo de Pagos'!B$7:B$506,S7)) -> 0 | T14: =IF(B14="","",SUMIFS('Flujo de Pagos'!I$7:I$506,'Flujo de Pagos'!E$7:E$506,B14,'Flujo de Pagos'!B$7:B$506,T7)) -> 0 | U14: =IF(B14="","",SUMIFS('Flujo de Pagos'!I$7:I$506,'Flujo de Pagos'!E$7:E$506,B14,'Flujo de Pagos'!B$7:B$506,U7)) -> 0 | V14: =IF(B14="","",SUMIFS('Flujo de Pagos'!I$7:I$506,'Flujo de Pagos'!E$7:E$506,B14,'Flujo de Pagos'!B$7:B$506,V7)) -> 0 | W14: =IF(B14="","",SUMIFS('Flujo de Pagos'!I$7:I$506,'Flujo de Pagos'!E$7:E$506,B14,'Flujo de Pagos'!B$7:B$506,W7)) -> 0 | X14: =IF(B14="","",SUMIFS('Flujo de Pagos'!I$7:I$506,'Flujo de Pagos'!E$7:E$506,B14,'Flujo de Pagos'!B$7:B$506,X7)) -> 0 | Y14: =IF(B14="","",SUMIFS('Flujo de Pagos'!I$7:I$506,'Flujo de Pagos'!E$7:E$506,B14,'Flujo de Pagos'!B$7:B$506,Y7)) -> 0 | Z14: =IF(B14="","",SUMIFS('Flujo de Pagos'!I$7:I$506,'Flujo de Pagos'!E$7:E$506,B14,'Flujo de Pagos'!B$7:B$506,Z7)) -> 0 | AA14: =IF(B14="","",SUMIFS('Flujo de Pagos'!I$7:I$506,'Flujo de Pagos'!E$7:E$506,B14,'Flujo de Pagos'!B$7:B$506,AA7)) -> 0 | AB14: =IF(B14="","",SUMIFS('Flujo de Pagos'!I$7:I$506,'Flujo de Pagos'!E$7:E$506,B14,'Flujo de Pagos'!B$7:B$506,AB7)) -> 0 | AC14: =IF(B14="","",SUMIFS('Flujo de Pagos'!I$7:I$506,'Flujo de Pagos'!E$7:E$506,B14,'Flujo de Pagos'!B$7:B$506,AC7)) -> 0 | AD14: =IF(B14="","",SUMIFS('Flujo de Pagos'!I$7:I$506,'Flujo de Pagos'!E$7:E$506,B14,'Flujo de Pagos'!B$7:B$506,AD7)) -> 0 | AE14: =IF(B14="","",SUMIFS('Flujo de Pagos'!I$7:I$506,'Flujo de Pagos'!E$7:E$506,B14,'Flujo de Pagos'!B$7:B$506,AE7)) -> 0 | AF14: =IF(B14="","",SUMIFS('Flujo de Pagos'!I$7:I$506,'Flujo de Pagos'!E$7:E$506,B14,'Flujo de Pagos'!B$7:B$506,AF7)) -> 0 | AG14: =IF(B14="","",SUMIFS('Flujo de Pagos'!I$7:I$506,'Flujo de Pagos'!E$7:E$506,B14,'Flujo de Pagos'!B$7:B$506,AG7)) -> 0 | AH14: =IF(B14="","",SUMIFS('Flujo de Pagos'!I$7:I$506,'Flujo de Pagos'!E$7:E$506,B14,'Flujo de Pagos'!B$7:B$506,AH7)) -> 0 | AI14: =IF(B14="","",SUMIFS('Flujo de Pagos'!I$7:I$506,'Flujo de Pagos'!E$7:E$506,B14,'Flujo de Pagos'!B$7:B$506,AI7)) -> 0 | AJ14: =IF(B14="","",SUMIFS('Flujo de Pagos'!I$7:I$506,'Flujo de Pagos'!E$7:E$506,B14,'Flujo de Pagos'!B$7:B$506,AJ7)) -> 0 | AK14: =IF(B14="","",SUMIFS('Flujo de Pagos'!I$7:I$506,'Flujo de Pagos'!E$7:E$506,B14,'Flujo de Pagos'!B$7:B$506,AK7)) -> 0 | AL14: =IF(B14="","",SUMIFS('Flujo de Pagos'!I$7:I$506,'Flujo de Pagos'!E$7:E$506,B14,'Flujo de Pagos'!B$7:B$506,AL7)) -> 0 | AM14: =IF(B14="","",SUM(C14:AL14)) -> 17400
B15: =IF(Presupuesto!B12="","",Presupuesto!B12) | C15: =IF(B15="","",SUMIFS('Flujo de Pagos'!I$7:I$506,'Flujo de Pagos'!E$7:E$506,B15,'Flujo de Pagos'!B$7:B$506,C7)) | D15: =IF(B15="","",SUMIFS('Flujo de Pagos'!I$7:I$506,'Flujo de Pagos'!E$7:E$506,B15,'Flujo de Pagos'!B$7:B$506,D7)) | E15: =IF(B15="","",SUMIFS('Flujo de Pagos'!I$7:I$506,'Flujo de Pagos'!E$7:E$506,B15,'Flujo de Pagos'!B$7:B$506,E7)) | F15: =IF(B15="","",SUMIFS('Flujo de Pagos'!I$7:I$506,'Flujo de Pagos'!E$7:E$506,B15,'Flujo de Pagos'!B$7:B$506,F7)) | G15: =IF(B15="","",SUMIFS('Flujo de Pagos'!I$7:I$506,'Flujo de Pagos'!E$7:E$506,B15,'Flujo de Pagos'!B$7:B$506,G7)) | H15: =IF(B15="","",SUMIFS('Flujo de Pagos'!I$7:I$506,'Flujo de Pagos'!E$7:E$506,B15,'Flujo de Pagos'!B$7:B$506,H7)) | I15: =IF(B15="","",SUMIFS('Flujo de Pagos'!I$7:I$506,'Flujo de Pagos'!E$7:E$506,B15,'Flujo de Pagos'!B$7:B$506,I7)) | J15: =IF(B15="","",SUMIFS('Flujo de Pagos'!I$7:I$506,'Flujo de Pagos'!E$7:E$506,B15,'Flujo de Pagos'!B$7:B$506,J7)) | K15: =IF(B15="","",SUMIFS('Flujo de Pagos'!I$7:I$506,'Flujo de Pagos'!E$7:E$506,B15,'Flujo de Pagos'!B$7:B$506,K7)) | L15: =IF(B15="","",SUMIFS('Flujo de Pagos'!I$7:I$506,'Flujo de Pagos'!E$7:E$506,B15,'Flujo de Pagos'!B$7:B$506,L7)) | M15: =IF(B15="","",SUMIFS('Flujo de Pagos'!I$7:I$506,'Flujo de Pagos'!E$7:E$506,B15,'Flujo de Pagos'!B$7:B$506,M7)) | N15: =IF(B15="","",SUMIFS('Flujo de Pagos'!I$7:I$506,'Flujo de Pagos'!E$7:E$506,B15,'Flujo de Pagos'!B$7:B$506,N7)) | O15: =IF(B15="","",SUMIFS('Flujo de Pagos'!I$7:I$506,'Flujo de Pagos'!E$7:E$506,B15,'Flujo de Pagos'!B$7:B$506,O7)) | P15: =IF(B15="","",SUMIFS('Flujo de Pagos'!I$7:I$506,'Flujo de Pagos'!E$7:E$506,B15,'Flujo de Pagos'!B$7:B$506,P7)) | Q15: =IF(B15="","",SUMIFS('Flujo de Pagos'!I$7:I$506,'Flujo de Pagos'!E$7:E$506,B15,'Flujo de Pagos'!B$7:B$506,Q7)) | R15: =IF(B15="","",SUMIFS('Flujo de Pagos'!I$7:I$506,'Flujo de Pagos'!E$7:E$506,B15,'Flujo de Pagos'!B$7:B$506,R7)) | S15: =IF(B15="","",SUMIFS('Flujo de Pagos'!I$7:I$506,'Flujo de Pagos'!E$7:E$506,B15,'Flujo de Pagos'!B$7:B$506,S7)) | T15: =IF(B15="","",SUMIFS('Flujo de Pagos'!I$7:I$506,'Flujo de Pagos'!E$7:E$506,B15,'Flujo de Pagos'!B$7:B$506,T7)) | U15: =IF(B15="","",SUMIFS('Flujo de Pagos'!I$7:I$506,'Flujo de Pagos'!E$7:E$506,B15,'Flujo de Pagos'!B$7:B$506,U7)) | V15: =IF(B15="","",SUMIFS('Flujo de Pagos'!I$7:I$506,'Flujo de Pagos'!E$7:E$506,B15,'Flujo de Pagos'!B$7:B$506,V7)) | W15: =IF(B15="","",SUMIFS('Flujo de Pagos'!I$7:I$506,'Flujo de Pagos'!E$7:E$506,B15,'Flujo de Pagos'!B$7:B$506,W7)) | X15: =IF(B15="","",SUMIFS('Flujo de Pagos'!I$7:I$506,'Flujo de Pagos'!E$7:E$506,B15,'Flujo de Pagos'!B$7:B$506,X7)) | Y15: =IF(B15="","",SUMIFS('Flujo de Pagos'!I$7:I$506,'Flujo de Pagos'!E$7:E$506,B15,'Flujo de Pagos'!B$7:B$506,Y7)) | Z15: =IF(B15="","",SUMIFS('Flujo de Pagos'!I$7:I$506,'Flujo de Pagos'!E$7:E$506,B15,'Flujo de Pagos'!B$7:B$506,Z7)) | AA15: =IF(B15="","",SUMIFS('Flujo de Pagos'!I$7:I$506,'Flujo de Pagos'!E$7:E$506,B15,'Flujo de Pagos'!B$7:B$506,AA7)) | AB15: =IF(B15="","",SUMIFS('Flujo de Pagos'!I$7:I$506,'Flujo de Pagos'!E$7:E$506,B15,'Flujo de Pagos'!B$7:B$506,AB7)) | AC15: =IF(B15="","",SUMIFS('Flujo de Pagos'!I$7:I$506,'Flujo de Pagos'!E$7:E$506,B15,'Flujo de Pagos'!B$7:B$506,AC7)) | AD15: =IF(B15="","",SUMIFS('Flujo de Pagos'!I$7:I$506,'Flujo de Pagos'!E$7:E$506,B15,'Flujo de Pagos'!B$7:B$506,AD7)) | AE15: =IF(B15="","",SUMIFS('Flujo de Pagos'!I$7:I$506,'Flujo de Pagos'!E$7:E$506,B15,'Flujo de Pagos'!B$7:B$506,AE7)) | AF15: =IF(B15="","",SUMIFS('Flujo de Pagos'!I$7:I$506,'Flujo de Pagos'!E$7:E$506,B15,'Flujo de Pagos'!B$7:B$506,AF7)) | AG15: =IF(B15="","",SUMIFS('Flujo de Pagos'!I$7:I$506,'Flujo de Pagos'!E$7:E$506,B15,'Flujo de Pagos'!B$7:B$506,AG7)) | AH15: =IF(B15="","",SUMIFS('Flujo de Pagos'!I$7:I$506,'Flujo de Pagos'!E$7:E$506,B15,'Flujo de Pagos'!B$7:B$506,AH7)) | AI15: =IF(B15="","",SUMIFS('Flujo de Pagos'!I$7:I$506,'Flujo de Pagos'!E$7:E$506,B15,'Flujo de Pagos'!B$7:B$506,AI7)) | AJ15: =IF(B15="","",SUMIFS('Flujo de Pagos'!I$7:I$506,'Flujo de Pagos'!E$7:E$506,B15,'Flujo de Pagos'!B$7:B$506,AJ7)) | AK15: =IF(B15="","",SUMIFS('Flujo de Pagos'!I$7:I$506,'Flujo de Pagos'!E$7:E$506,B15,'Flujo de Pagos'!B$7:B$506,AK7)) | AL15: =IF(B15="","",SUMIFS('Flujo de Pagos'!I$7:I$506,'Flujo de Pagos'!E$7:E$506,B15,'Flujo de Pagos'!B$7:B$506,AL7)) | AM15: =IF(B15="","",SUM(C15:AL15))
B16: =IF(Presupuesto!B13="","",Presupuesto!B13) | C16: =IF(B16="","",SUMIFS('Flujo de Pagos'!I$7:I$506,'Flujo de Pagos'!E$7:E$506,B16,'Flujo de Pagos'!B$7:B$506,C7)) | D16: =IF(B16="","",SUMIFS('Flujo de Pagos'!I$7:I$506,'Flujo de Pagos'!E$7:E$506,B16,'Flujo de Pagos'!B$7:B$506,D7)) | E16: =IF(B16="","",SUMIFS('Flujo de Pagos'!I$7:I$506,'Flujo de Pagos'!E$7:E$506,B16,'Flujo de Pagos'!B$7:B$506,E7)) | F16: =IF(B16="","",SUMIFS('Flujo de Pagos'!I$7:I$506,'Flujo de Pagos'!E$7:E$506,B16,'Flujo de Pagos'!B$7:B$506,F7)) | G16: =IF(B16="","",SUMIFS('Flujo de Pagos'!I$7:I$506,'Flujo de Pagos'!E$7:E$506,B16,'Flujo de Pagos'!B$7:B$506,G7)) | H16: =IF(B16="","",SUMIFS('Flujo de Pagos'!I$7:I$506,'Flujo de Pagos'!E$7:E$506,B16,'Flujo de Pagos'!B$7:B$506,H7)) | I16: =IF(B16="","",SUMIFS('Flujo de Pagos'!I$7:I$506,'Flujo de Pagos'!E$7:E$506,B16,'Flujo de Pagos'!B$7:B$506,I7)) | J16: =IF(B16="","",SUMIFS('Flujo de Pagos'!I$7:I$506,'Flujo de Pagos'!E$7:E$506,B16,'Flujo de Pagos'!B$7:B$506,J7)) | K16: =IF(B16="","",SUMIFS('Flujo de Pagos'!I$7:I$506,'Flujo de Pagos'!E$7:E$506,B16,'Flujo de Pagos'!B$7:B$506,K7)) | L16: =IF(B16="","",SUMIFS('Flujo de Pagos'!I$7:I$506,'Flujo de Pagos'!E$7:E$506,B16,'Flujo de Pagos'!B$7:B$506,L7)) | M16: =IF(B16="","",SUMIFS('Flujo de Pagos'!I$7:I$506,'Flujo de Pagos'!E$7:E$506,B16,'Flujo de Pagos'!B$7:B$506,M7)) | N16: =IF(B16="","",SUMIFS('Flujo de Pagos'!I$7:I$506,'Flujo de Pagos'!E$7:E$506,B16,'Flujo de Pagos'!B$7:B$506,N7)) | O16: =IF(B16="","",SUMIFS('Flujo de Pagos'!I$7:I$506,'Flujo de Pagos'!E$7:E$506,B16,'Flujo de Pagos'!B$7:B$506,O7)) | P16: =IF(B16="","",SUMIFS('Flujo de Pagos'!I$7:I$506,'Flujo de Pagos'!E$7:E$506,B16,'Flujo de Pagos'!B$7:B$506,P7)) | Q16: =IF(B16="","",SUMIFS('Flujo de Pagos'!I$7:I$506,'Flujo de Pagos'!E$7:E$506,B16,'Flujo de Pagos'!B$7:B$506,Q7)) | R16: =IF(B16="","",SUMIFS('Flujo de Pagos'!I$7:I$506,'Flujo de Pagos'!E$7:E$506,B16,'Flujo de Pagos'!B$7:B$506,R7)) | S16: =IF(B16="","",SUMIFS('Flujo de Pagos'!I$7:I$506,'Flujo de Pagos'!E$7:E$506,B16,'Flujo de Pagos'!B$7:B$506,S7)) | T16: =IF(B16="","",SUMIFS('Flujo de Pagos'!I$7:I$506,'Flujo de Pagos'!E$7:E$506,B16,'Flujo de Pagos'!B$7:B$506,T7)) | U16: =IF(B16="","",SUMIFS('Flujo de Pagos'!I$7:I$506,'Flujo de Pagos'!E$7:E$506,B16,'Flujo de Pagos'!B$7:B$506,U7)) | V16: =IF(B16="","",SUMIFS('Flujo de Pagos'!I$7:I$506,'Flujo de Pagos'!E$7:E$506,B16,'Flujo de Pagos'!B$7:B$506,V7)) | W16: =IF(B16="","",SUMIFS('Flujo de Pagos'!I$7:I$506,'Flujo de Pagos'!E$7:E$506,B16,'Flujo de Pagos'!B$7:B$506,W7)) | X16: =IF(B16="","",SUMIFS('Flujo de Pagos'!I$7:I$506,'Flujo de Pagos'!E$7:E$506,B16,'Flujo de Pagos'!B$7:B$506,X7)) | Y16: =IF(B16="","",SUMIFS('Flujo de Pagos'!I$7:I$506,'Flujo de Pagos'!E$7:E$506,B16,'Flujo de Pagos'!B$7:B$506,Y7)) | Z16: =IF(B16="","",SUMIFS('Flujo de Pagos'!I$7:I$506,'Flujo de Pagos'!E$7:E$506,B16,'Flujo de Pagos'!B$7:B$506,Z7)) | AA16: =IF(B16="","",SUMIFS('Flujo de Pagos'!I$7:I$506,'Flujo de Pagos'!E$7:E$506,B16,'Flujo de Pagos'!B$7:B$506,AA7)) | AB16: =IF(B16="","",SUMIFS('Flujo de Pagos'!I$7:I$506,'Flujo de Pagos'!E$7:E$506,B16,'Flujo de Pagos'!B$7:B$506,AB7)) | AC16: =IF(B16="","",SUMIFS('Flujo de Pagos'!I$7:I$506,'Flujo de Pagos'!E$7:E$506,B16,'Flujo de Pagos'!B$7:B$506,AC7)) | AD16: =IF(B16="","",SUMIFS('Flujo de Pagos'!I$7:I$506,'Flujo de Pagos'!E$7:E$506,B16,'Flujo de Pagos'!B$7:B$506,AD7)) | AE16: =IF(B16="","",SUMIFS('Flujo de Pagos'!I$7:I$506,'Flujo de Pagos'!E$7:E$506,B16,'Flujo de Pagos'!B$7:B$506,AE7)) | AF16: =IF(B16="","",SUMIFS('Flujo de Pagos'!I$7:I$506,'Flujo de Pagos'!E$7:E$506,B16,'Flujo de Pagos'!B$7:B$506,AF7)) | AG16: =IF(B16="","",SUMIFS('Flujo de Pagos'!I$7:I$506,'Flujo de Pagos'!E$7:E$506,B16,'Flujo de Pagos'!B$7:B$506,AG7)) | AH16: =IF(B16="","",SUMIFS('Flujo de Pagos'!I$7:I$506,'Flujo de Pagos'!E$7:E$506,B16,'Flujo de Pagos'!B$7:B$506,AH7)) | AI16: =IF(B16="","",SUMIFS('Flujo de Pagos'!I$7:I$506,'Flujo de Pagos'!E$7:E$506,B16,'Flujo de Pagos'!B$7:B$506,AI7)) | AJ16: =IF(B16="","",SUMIFS('Flujo de Pagos'!I$7:I$506,'Flujo de Pagos'!E$7:E$506,B16,'Flujo de Pagos'!B$7:B$506,AJ7)) | AK16: =IF(B16="","",SUMIFS('Flujo de Pagos'!I$7:I$506,'Flujo de Pagos'!E$7:E$506,B16,'Flujo de Pagos'!B$7:B$506,AK7)) | AL16: =IF(B16="","",SUMIFS('Flujo de Pagos'!I$7:I$506,'Flujo de Pagos'!E$7:E$506,B16,'Flujo de Pagos'!B$7:B$506,AL7)) | AM16: =IF(B16="","",SUM(C16:AL16))
B17: =IF(Presupuesto!B14="","",Presupuesto!B14) | C17: =IF(B17="","",SUMIFS('Flujo de Pagos'!I$7:I$506,'Flujo de Pagos'!E$7:E$506,B17,'Flujo de Pagos'!B$7:B$506,C7)) | D17: =IF(B17="","",SUMIFS('Flujo de Pagos'!I$7:I$506,'Flujo de Pagos'!E$7:E$506,B17,'Flujo de Pagos'!B$7:B$506,D7)) | E17: =IF(B17="","",SUMIFS('Flujo de Pagos'!I$7:I$506,'Flujo de Pagos'!E$7:E$506,B17,'Flujo de Pagos'!B$7:B$506,E7)) | F17: =IF(B17="","",SUMIFS('Flujo de Pagos'!I$7:I$506,'Flujo de Pagos'!E$7:E$506,B17,'Flujo de Pagos'!B$7:B$506,F7)) | G17: =IF(B17="","",SUMIFS('Flujo de Pagos'!I$7:I$506,'Flujo de Pagos'!E$7:E$506,B17,'Flujo de Pagos'!B$7:B$506,G7)) | H17: =IF(B17="","",SUMIFS('Flujo de Pagos'!I$7:I$506,'Flujo de Pagos'!E$7:E$506,B17,'Flujo de Pagos'!B$7:B$506,H7)) | I17: =IF(B17="","",SUMIFS('Flujo de Pagos'!I$7:I$506,'Flujo de Pagos'!E$7:E$506,B17,'Flujo de Pagos'!B$7:B$506,I7)) | J17: =IF(B17="","",SUMIFS('Flujo de Pagos'!I$7:I$506,'Flujo de Pagos'!E$7:E$506,B17,'Flujo de Pagos'!B$7:B$506,J7)) | K17: =IF(B17="","",SUMIFS('Flujo de Pagos'!I$7:I$506,'Flujo de Pagos'!E$7:E$506,B17,'Flujo de Pagos'!B$7:B$506,K7)) | L17: =IF(B17="","",SUMIFS('Flujo de Pagos'!I$7:I$506,'Flujo de Pagos'!E$7:E$506,B17,'Flujo de Pagos'!B$7:B$506,L7)) | M17: =IF(B17="","",SUMIFS('Flujo de Pagos'!I$7:I$506,'Flujo de Pagos'!E$7:E$506,B17,'Flujo de Pagos'!B$7:B$506,M7)) | N17: =IF(B17="","",SUMIFS('Flujo de Pagos'!I$7:I$506,'Flujo de Pagos'!E$7:E$506,B17,'Flujo de Pagos'!B$7:B$506,N7)) | O17: =IF(B17="","",SUMIFS('Flujo de Pagos'!I$7:I$506,'Flujo de Pagos'!E$7:E$506,B17,'Flujo de Pagos'!B$7:B$506,O7)) | P17: =IF(B17="","",SUMIFS('Flujo de Pagos'!I$7:I$506,'Flujo de Pagos'!E$7:E$506,B17,'Flujo de Pagos'!B$7:B$506,P7)) | Q17: =IF(B17="","",SUMIFS('Flujo de Pagos'!I$7:I$506,'Flujo de Pagos'!E$7:E$506,B17,'Flujo de Pagos'!B$7:B$506,Q7)) | R17: =IF(B17="","",SUMIFS('Flujo de Pagos'!I$7:I$506,'Flujo de Pagos'!E$7:E$506,B17,'Flujo de Pagos'!B$7:B$506,R7)) | S17: =IF(B17="","",SUMIFS('Flujo de Pagos'!I$7:I$506,'Flujo de Pagos'!E$7:E$506,B17,'Flujo de Pagos'!B$7:B$506,S7)) | T17: =IF(B17="","",SUMIFS('Flujo de Pagos'!I$7:I$506,'Flujo de Pagos'!E$7:E$506,B17,'Flujo de Pagos'!B$7:B$506,T7)) | U17: =IF(B17="","",SUMIFS('Flujo de Pagos'!I$7:I$506,'Flujo de Pagos'!E$7:E$506,B17,'Flujo de Pagos'!B$7:B$506,U7)) | V17: =IF(B17="","",SUMIFS('Flujo de Pagos'!I$7:I$506,'Flujo de Pagos'!E$7:E$506,B17,'Flujo de Pagos'!B$7:B$506,V7)) | W17: =IF(B17="","",SUMIFS('Flujo de Pagos'!I$7:I$506,'Flujo de Pagos'!E$7:E$506,B17,'Flujo de Pagos'!B$7:B$506,W7)) | X17: =IF(B17="","",SUMIFS('Flujo de Pagos'!I$7:I$506,'Flujo de Pagos'!E$7:E$506,B17,'Flujo de Pagos'!B$7:B$506,X7)) | Y17: =IF(B17="","",SUMIFS('Flujo de Pagos'!I$7:I$506,'Flujo de Pagos'!E$7:E$506,B17,'Flujo de Pagos'!B$7:B$506,Y7)) | Z17: =IF(B17="","",SUMIFS('Flujo de Pagos'!I$7:I$506,'Flujo de Pagos'!E$7:E$506,B17,'Flujo de Pagos'!B$7:B$506,Z7)) | AA17: =IF(B17="","",SUMIFS('Flujo de Pagos'!I$7:I$506,'Flujo de Pagos'!E$7:E$506,B17,'Flujo de Pagos'!B$7:B$506,AA7)) | AB17: =IF(B17="","",SUMIFS('Flujo de Pagos'!I$7:I$506,'Flujo de Pagos'!E$7:E$506,B17,'Flujo de Pagos'!B$7:B$506,AB7)) | AC17: =IF(B17="","",SUMIFS('Flujo de Pagos'!I$7:I$506,'Flujo de Pagos'!E$7:E$506,B17,'Flujo de Pagos'!B$7:B$506,AC7)) | AD17: =IF(B17="","",SUMIFS('Flujo de Pagos'!I$7:I$506,'Flujo de Pagos'!E$7:E$506,B17,'Flujo de Pagos'!B$7:B$506,AD7)) | AE17: =IF(B17="","",SUMIFS('Flujo de Pagos'!I$7:I$506,'Flujo de Pagos'!E$7:E$506,B17,'Flujo de Pagos'!B$7:B$506,AE7)) | AF17: =IF(B17="","",SUMIFS('Flujo de Pagos'!I$7:I$506,'Flujo de Pagos'!E$7:E$506,B17,'Flujo de Pagos'!B$7:B$506,AF7)) | AG17: =IF(B17="","",SUMIFS('Flujo de Pagos'!I$7:I$506,'Flujo de Pagos'!E$7:E$506,B17,'Flujo de Pagos'!B$7:B$506,AG7)) | AH17: =IF(B17="","",SUMIFS('Flujo de Pagos'!I$7:I$506,'Flujo de Pagos'!E$7:E$506,B17,'Flujo de Pagos'!B$7:B$506,AH7)) | AI17: =IF(B17="","",SUMIFS('Flujo de Pagos'!I$7:I$506,'Flujo de Pagos'!E$7:E$506,B17,'Flujo de Pagos'!B$7:B$506,AI7)) | AJ17: =IF(B17="","",SUMIFS('Flujo de Pagos'!I$7:I$506,'Flujo de Pagos'!E$7:E$506,B17,'Flujo de Pagos'!B$7:B$506,AJ7)) | AK17: =IF(B17="","",SUMIFS('Flujo de Pagos'!I$7:I$506,'Flujo de Pagos'!E$7:E$506,B17,'Flujo de Pagos'!B$7:B$506,AK7)) | AL17: =IF(B17="","",SUMIFS('Flujo de Pagos'!I$7:I$506,'Flujo de Pagos'!E$7:E$506,B17,'Flujo de Pagos'!B$7:B$506,AL7)) | AM17: =IF(B17="","",SUM(C17:AL17))
B18: =IF(Presupuesto!B15="","",Presupuesto!B15) | C18: =IF(B18="","",SUMIFS('Flujo de Pagos'!I$7:I$506,'Flujo de Pagos'!E$7:E$506,B18,'Flujo de Pagos'!B$7:B$506,C7)) | D18: =IF(B18="","",SUMIFS('Flujo de Pagos'!I$7:I$506,'Flujo de Pagos'!E$7:E$506,B18,'Flujo de Pagos'!B$7:B$506,D7)) | E18: =IF(B18="","",SUMIFS('Flujo de Pagos'!I$7:I$506,'Flujo de Pagos'!E$7:E$506,B18,'Flujo de Pagos'!B$7:B$506,E7)) | F18: =IF(B18="","",SUMIFS('Flujo de Pagos'!I$7:I$506,'Flujo de Pagos'!E$7:E$506,B18,'Flujo de Pagos'!B$7:B$506,F7)) | G18: =IF(B18="","",SUMIFS('Flujo de Pagos'!I$7:I$506,'Flujo de Pagos'!E$7:E$506,B18,'Flujo de Pagos'!B$7:B$506,G7)) | H18: =IF(B18="","",SUMIFS('Flujo de Pagos'!I$7:I$506,'Flujo de Pagos'!E$7:E$506,B18,'Flujo de Pagos'!B$7:B$506,H7)) | I18: =IF(B18="","",SUMIFS('Flujo de Pagos'!I$7:I$506,'Flujo de Pagos'!E$7:E$506,B18,'Flujo de Pagos'!B$7:B$506,I7)) | J18: =IF(B18="","",SUMIFS('Flujo de Pagos'!I$7:I$506,'Flujo de Pagos'!E$7:E$506,B18,'Flujo de Pagos'!B$7:B$506,J7)) | K18: =IF(B18="","",SUMIFS('Flujo de Pagos'!I$7:I$506,'Flujo de Pagos'!E$7:E$506,B18,'Flujo de Pagos'!B$7:B$506,K7)) | L18: =IF(B18="","",SUMIFS('Flujo de Pagos'!I$7:I$506,'Flujo de Pagos'!E$7:E$506,B18,'Flujo de Pagos'!B$7:B$506,L7)) | M18: =IF(B18="","",SUMIFS('Flujo de Pagos'!I$7:I$506,'Flujo de Pagos'!E$7:E$506,B18,'Flujo de Pagos'!B$7:B$506,M7)) | N18: =IF(B18="","",SUMIFS('Flujo de Pagos'!I$7:I$506,'Flujo de Pagos'!E$7:E$506,B18,'Flujo de Pagos'!B$7:B$506,N7)) | O18: =IF(B18="","",SUMIFS('Flujo de Pagos'!I$7:I$506,'Flujo de Pagos'!E$7:E$506,B18,'Flujo de Pagos'!B$7:B$506,O7)) | P18: =IF(B18="","",SUMIFS('Flujo de Pagos'!I$7:I$506,'Flujo de Pagos'!E$7:E$506,B18,'Flujo de Pagos'!B$7:B$506,P7)) | Q18: =IF(B18="","",SUMIFS('Flujo de Pagos'!I$7:I$506,'Flujo de Pagos'!E$7:E$506,B18,'Flujo de Pagos'!B$7:B$506,Q7)) | R18: =IF(B18="","",SUMIFS('Flujo de Pagos'!I$7:I$506,'Flujo de Pagos'!E$7:E$506,B18,'Flujo de Pagos'!B$7:B$506,R7)) | S18: =IF(B18="","",SUMIFS('Flujo de Pagos'!I$7:I$506,'Flujo de Pagos'!E$7:E$506,B18,'Flujo de Pagos'!B$7:B$506,S7)) | T18: =IF(B18="","",SUMIFS('Flujo de Pagos'!I$7:I$506,'Flujo de Pagos'!E$7:E$506,B18,'Flujo de Pagos'!B$7:B$506,T7)) | U18: =IF(B18="","",SUMIFS('Flujo de Pagos'!I$7:I$506,'Flujo de Pagos'!E$7:E$506,B18,'Flujo de Pagos'!B$7:B$506,U7)) | V18: =IF(B18="","",SUMIFS('Flujo de Pagos'!I$7:I$506,'Flujo de Pagos'!E$7:E$506,B18,'Flujo de Pagos'!B$7:B$506,V7)) | W18: =IF(B18="","",SUMIFS('Flujo de Pagos'!I$7:I$506,'Flujo de Pagos'!E$7:E$506,B18,'Flujo de Pagos'!B$7:B$506,W7)) | X18: =IF(B18="","",SUMIFS('Flujo de Pagos'!I$7:I$506,'Flujo de Pagos'!E$7:E$506,B18,'Flujo de Pagos'!B$7:B$506,X7)) | Y18: =IF(B18="","",SUMIFS('Flujo de Pagos'!I$7:I$506,'Flujo de Pagos'!E$7:E$506,B18,'Flujo de Pagos'!B$7:B$506,Y7)) | Z18: =IF(B18="","",SUMIFS('Flujo de Pagos'!I$7:I$506,'Flujo de Pagos'!E$7:E$506,B18,'Flujo de Pagos'!B$7:B$506,Z7)) | AA18: =IF(B18="","",SUMIFS('Flujo de Pagos'!I$7:I$506,'Flujo de Pagos'!E$7:E$506,B18,'Flujo de Pagos'!B$7:B$506,AA7)) | AB18: =IF(B18="","",SUMIFS('Flujo de Pagos'!I$7:I$506,'Flujo de Pagos'!E$7:E$506,B18,'Flujo de Pagos'!B$7:B$506,AB7)) | AC18: =IF(B18="","",SUMIFS('Flujo de Pagos'!I$7:I$506,'Flujo de Pagos'!E$7:E$506,B18,'Flujo de Pagos'!B$7:B$506,AC7)) | AD18: =IF(B18="","",SUMIFS('Flujo de Pagos'!I$7:I$506,'Flujo de Pagos'!E$7:E$506,B18,'Flujo de Pagos'!B$7:B$506,AD7)) | AE18: =IF(B18="","",SUMIFS('Flujo de Pagos'!I$7:I$506,'Flujo de Pagos'!E$7:E$506,B18,'Flujo de Pagos'!B$7:B$506,AE7)) | AF18: =IF(B18="","",SUMIFS('Flujo de Pagos'!I$7:I$506,'Flujo de Pagos'!E$7:E$506,B18,'Flujo de Pagos'!B$7:B$506,AF7)) | AG18: =IF(B18="","",SUMIFS('Flujo de Pagos'!I$7:I$506,'Flujo de Pagos'!E$7:E$506,B18,'Flujo de Pagos'!B$7:B$506,AG7)) | AH18: =IF(B18="","",SUMIFS('Flujo de Pagos'!I$7:I$506,'Flujo de Pagos'!E$7:E$506,B18,'Flujo de Pagos'!B$7:B$506,AH7)) | AI18: =IF(B18="","",SUMIFS('Flujo de Pagos'!I$7:I$506,'Flujo de Pagos'!E$7:E$506,B18,'Flujo de Pagos'!B$7:B$506,AI7)) | AJ18: =IF(B18="","",SUMIFS('Flujo de Pagos'!I$7:I$506,'Flujo de Pagos'!E$7:E$506,B18,'Flujo de Pagos'!B$7:B$506,AJ7)) | AK18: =IF(B18="","",SUMIFS('Flujo de Pagos'!I$7:I$506,'Flujo de Pagos'!E$7:E$506,B18,'Flujo de Pagos'!B$7:B$506,AK7)) | AL18: =IF(B18="","",SUMIFS('Flujo de Pagos'!I$7:I$506,'Flujo de Pagos'!E$7:E$506,B18,'Flujo de Pagos'!B$7:B$506,AL7)) | AM18: =IF(B18="","",SUM(C18:AL18))
B19: =IF(Presupuesto!B16="","",Presupuesto!B16) | C19: =IF(B19="","",SUMIFS('Flujo de Pagos'!I$7:I$506,'Flujo de Pagos'!E$7:E$506,B19,'Flujo de Pagos'!B$7:B$506,C7)) | D19: =IF(B19="","",SUMIFS('Flujo de Pagos'!I$7:I$506,'Flujo de Pagos'!E$7:E$506,B19,'Flujo de Pagos'!B$7:B$506,D7)) | E19: =IF(B19="","",SUMIFS('Flujo de Pagos'!I$7:I$506,'Flujo de Pagos'!E$7:E$506,B19,'Flujo de Pagos'!B$7:B$506,E7)) | F19: =IF(B19="","",SUMIFS('Flujo de Pagos'!I$7:I$506,'Flujo de Pagos'!E$7:E$506,B19,'Flujo de Pagos'!B$7:B$506,F7)) | G19: =IF(B19="","",SUMIFS('Flujo de Pagos'!I$7:I$506,'Flujo de Pagos'!E$7:E$506,B19,'Flujo de Pagos'!B$7:B$506,G7)) | H19: =IF(B19="","",SUMIFS('Flujo de Pagos'!I$7:I$506,'Flujo de Pagos'!E$7:E$506,B19,'Flujo de Pagos'!B$7:B$506,H7)) | I19: =IF(B19="","",SUMIFS('Flujo de Pagos'!I$7:I$506,'Flujo de Pagos'!E$7:E$506,B19,'Flujo de Pagos'!B$7:B$506,I7)) | J19: =IF(B19="","",SUMIFS('Flujo de Pagos'!I$7:I$506,'Flujo de Pagos'!E$7:E$506,B19,'Flujo de Pagos'!B$7:B$506,J7)) | K19: =IF(B19="","",SUMIFS('Flujo de Pagos'!I$7:I$506,'Flujo de Pagos'!E$7:E$506,B19,'Flujo de Pagos'!B$7:B$506,K7)) | L19: =IF(B19="","",SUMIFS('Flujo de Pagos'!I$7:I$506,'Flujo de Pagos'!E$7:E$506,B19,'Flujo de Pagos'!B$7:B$506,L7)) | M19: =IF(B19="","",SUMIFS('Flujo de Pagos'!I$7:I$506,'Flujo de Pagos'!E$7:E$506,B19,'Flujo de Pagos'!B$7:B$506,M7)) | N19: =IF(B19="","",SUMIFS('Flujo de Pagos'!I$7:I$506,'Flujo de Pagos'!E$7:E$506,B19,'Flujo de Pagos'!B$7:B$506,N7)) | O19: =IF(B19="","",SUMIFS('Flujo de Pagos'!I$7:I$506,'Flujo de Pagos'!E$7:E$506,B19,'Flujo de Pagos'!B$7:B$506,O7)) | P19: =IF(B19="","",SUMIFS('Flujo de Pagos'!I$7:I$506,'Flujo de Pagos'!E$7:E$506,B19,'Flujo de Pagos'!B$7:B$506,P7)) | Q19: =IF(B19="","",SUMIFS('Flujo de Pagos'!I$7:I$506,'Flujo de Pagos'!E$7:E$506,B19,'Flujo de Pagos'!B$7:B$506,Q7)) | R19: =IF(B19="","",SUMIFS('Flujo de Pagos'!I$7:I$506,'Flujo de Pagos'!E$7:E$506,B19,'Flujo de Pagos'!B$7:B$506,R7)) | S19: =IF(B19="","",SUMIFS('Flujo de Pagos'!I$7:I$506,'Flujo de Pagos'!E$7:E$506,B19,'Flujo de Pagos'!B$7:B$506,S7)) | T19: =IF(B19="","",SUMIFS('Flujo de Pagos'!I$7:I$506,'Flujo de Pagos'!E$7:E$506,B19,'Flujo de Pagos'!B$7:B$506,T7)) | U19: =IF(B19="","",SUMIFS('Flujo de Pagos'!I$7:I$506,'Flujo de Pagos'!E$7:E$506,B19,'Flujo de Pagos'!B$7:B$506,U7)) | V19: =IF(B19="","",SUMIFS('Flujo de Pagos'!I$7:I$506,'Flujo de Pagos'!E$7:E$506,B19,'Flujo de Pagos'!B$7:B$506,V7)) | W19: =IF(B19="","",SUMIFS('Flujo de Pagos'!I$7:I$506,'Flujo de Pagos'!E$7:E$506,B19,'Flujo de Pagos'!B$7:B$506,W7)) | X19: =IF(B19="","",SUMIFS('Flujo de Pagos'!I$7:I$506,'Flujo de Pagos'!E$7:E$506,B19,'Flujo de Pagos'!B$7:B$506,X7)) | Y19: =IF(B19="","",SUMIFS('Flujo de Pagos'!I$7:I$506,'Flujo de Pagos'!E$7:E$506,B19,'Flujo de Pagos'!B$7:B$506,Y7)) | Z19: =IF(B19="","",SUMIFS('Flujo de Pagos'!I$7:I$506,'Flujo de Pagos'!E$7:E$506,B19,'Flujo de Pagos'!B$7:B$506,Z7)) | AA19: =IF(B19="","",SUMIFS('Flujo de Pagos'!I$7:I$506,'Flujo de Pagos'!E$7:E$506,B19,'Flujo de Pagos'!B$7:B$506,AA7)) | AB19: =IF(B19="","",SUMIFS('Flujo de Pagos'!I$7:I$506,'Flujo de Pagos'!E$7:E$506,B19,'Flujo de Pagos'!B$7:B$506,AB7)) | AC19: =IF(B19="","",SUMIFS('Flujo de Pagos'!I$7:I$506,'Flujo de Pagos'!E$7:E$506,B19,'Flujo de Pagos'!B$7:B$506,AC7)) | AD19: =IF(B19="","",SUMIFS('Flujo de Pagos'!I$7:I$506,'Flujo de Pagos'!E$7:E$506,B19,'Flujo de Pagos'!B$7:B$506,AD7)) | AE19: =IF(B19="","",SUMIFS('Flujo de Pagos'!I$7:I$506,'Flujo de Pagos'!E$7:E$506,B19,'Flujo de Pagos'!B$7:B$506,AE7)) | AF19: =IF(B19="","",SUMIFS('Flujo de Pagos'!I$7:I$506,'Flujo de Pagos'!E$7:E$506,B19,'Flujo de Pagos'!B$7:B$506,AF7)) | AG19: =IF(B19="","",SUMIFS('Flujo de Pagos'!I$7:I$506,'Flujo de Pagos'!E$7:E$506,B19,'Flujo de Pagos'!B$7:B$506,AG7)) | AH19: =IF(B19="","",SUMIFS('Flujo de Pagos'!I$7:I$506,'Flujo de Pagos'!E$7:E$506,B19,'Flujo de Pagos'!B$7:B$506,AH7)) | AI19: =IF(B19="","",SUMIFS('Flujo de Pagos'!I$7:I$506,'Flujo de Pagos'!E$7:E$506,B19,'Flujo de Pagos'!B$7:B$506,AI7)) | AJ19: =IF(B19="","",SUMIFS('Flujo de Pagos'!I$7:I$506,'Flujo de Pagos'!E$7:E$506,B19,'Flujo de Pagos'!B$7:B$506,AJ7)) | AK19: =IF(B19="","",SUMIFS('Flujo de Pagos'!I$7:I$506,'Flujo de Pagos'!E$7:E$506,B19,'Flujo de Pagos'!B$7:B$506,AK7)) | AL19: =IF(B19="","",SUMIFS('Flujo de Pagos'!I$7:I$506,'Flujo de Pagos'!E$7:E$506,B19,'Flujo de Pagos'!B$7:B$506,AL7)) | AM19: =IF(B19="","",SUM(C19:AL19))
B20: =IF(Presupuesto!B17="","",Presupuesto!B17) | C20: =IF(B20="","",SUMIFS('Flujo de Pagos'!I$7:I$506,'Flujo de Pagos'!E$7:E$506,B20,'Flujo de Pagos'!B$7:B$506,C7)) | D20: =IF(B20="","",SUMIFS('Flujo de Pagos'!I$7:I$506,'Flujo de Pagos'!E$7:E$506,B20,'Flujo de Pagos'!B$7:B$506,D7)) | E20: =IF(B20="","",SUMIFS('Flujo de Pagos'!I$7:I$506,'Flujo de Pagos'!E$7:E$506,B20,'Flujo de Pagos'!B$7:B$506,E7)) | F20: =IF(B20="","",SUMIFS('Flujo de Pagos'!I$7:I$506,'Flujo de Pagos'!E$7:E$506,B20,'Flujo de Pagos'!B$7:B$506,F7)) | G20: =IF(B20="","",SUMIFS('Flujo de Pagos'!I$7:I$506,'Flujo de Pagos'!E$7:E$506,B20,'Flujo de Pagos'!B$7:B$506,G7)) | H20: =IF(B20="","",SUMIFS('Flujo de Pagos'!I$7:I$506,'Flujo de Pagos'!E$7:E$506,B20,'Flujo de Pagos'!B$7:B$506,H7)) | I20: =IF(B20="","",SUMIFS('Flujo de Pagos'!I$7:I$506,'Flujo de Pagos'!E$7:E$506,B20,'Flujo de Pagos'!B$7:B$506,I7)) | J20: =IF(B20="","",SUMIFS('Flujo de Pagos'!I$7:I$506,'Flujo de Pagos'!E$7:E$506,B20,'Flujo de Pagos'!B$7:B$506,J7)) | K20: =IF(B20="","",SUMIFS('Flujo de Pagos'!I$7:I$506,'Flujo de Pagos'!E$7:E$506,B20,'Flujo de Pagos'!B$7:B$506,K7)) | L20: =IF(B20="","",SUMIFS('Flujo de Pagos'!I$7:I$506,'Flujo de Pagos'!E$7:E$506,B20,'Flujo de Pagos'!B$7:B$506,L7)) | M20: =IF(B20="","",SUMIFS('Flujo de Pagos'!I$7:I$506,'Flujo de Pagos'!E$7:E$506,B20,'Flujo de Pagos'!B$7:B$506,M7)) | N20: =IF(B20="","",SUMIFS('Flujo de Pagos'!I$7:I$506,'Flujo de Pagos'!E$7:E$506,B20,'Flujo de Pagos'!B$7:B$506,N7)) | O20: =IF(B20="","",SUMIFS('Flujo de Pagos'!I$7:I$506,'Flujo de Pagos'!E$7:E$506,B20,'Flujo de Pagos'!B$7:B$506,O7)) | P20: =IF(B20="","",SUMIFS('Flujo de Pagos'!I$7:I$506,'Flujo de Pagos'!E$7:E$506,B20,'Flujo de Pagos'!B$7:B$506,P7)) | Q20: =IF(B20="","",SUMIFS('Flujo de Pagos'!I$7:I$506,'Flujo de Pagos'!E$7:E$506,B20,'Flujo de Pagos'!B$7:B$506,Q7)) | R20: =IF(B20="","",SUMIFS('Flujo de Pagos'!I$7:I$506,'Flujo de Pagos'!E$7:E$506,B20,'Flujo de Pagos'!B$7:B$506,R7)) | S20: =IF(B20="","",SUMIFS('Flujo de Pagos'!I$7:I$506,'Flujo de Pagos'!E$7:E$506,B20,'Flujo de Pagos'!B$7:B$506,S7)) | T20: =IF(B20="","",SUMIFS('Flujo de Pagos'!I$7:I$506,'Flujo de Pagos'!E$7:E$506,B20,'Flujo de Pagos'!B$7:B$506,T7)) | U20: =IF(B20="","",SUMIFS('Flujo de Pagos'!I$7:I$506,'Flujo de Pagos'!E$7:E$506,B20,'Flujo de Pagos'!B$7:B$506,U7)) | V20: =IF(B20="","",SUMIFS('Flujo de Pagos'!I$7:I$506,'Flujo de Pagos'!E$7:E$506,B20,'Flujo de Pagos'!B$7:B$506,V7)) | W20: =IF(B20="","",SUMIFS('Flujo de Pagos'!I$7:I$506,'Flujo de Pagos'!E$7:E$506,B20,'Flujo de Pagos'!B$7:B$506,W7)) | X20: =IF(B20="","",SUMIFS('Flujo de Pagos'!I$7:I$506,'Flujo de Pagos'!E$7:E$506,B20,'Flujo de Pagos'!B$7:B$506,X7)) | Y20: =IF(B20="","",SUMIFS('Flujo de Pagos'!I$7:I$506,'Flujo de Pagos'!E$7:E$506,B20,'Flujo de Pagos'!B$7:B$506,Y7)) | Z20: =IF(B20="","",SUMIFS('Flujo de Pagos'!I$7:I$506,'Flujo de Pagos'!E$7:E$506,B20,'Flujo de Pagos'!B$7:B$506,Z7)) | AA20: =IF(B20="","",SUMIFS('Flujo de Pagos'!I$7:I$506,'Flujo de Pagos'!E$7:E$506,B20,'Flujo de Pagos'!B$7:B$506,AA7)) | AB20: =IF(B20="","",SUMIFS('Flujo de Pagos'!I$7:I$506,'Flujo de Pagos'!E$7:E$506,B20,'Flujo de Pagos'!B$7:B$506,AB7)) | AC20: =IF(B20="","",SUMIFS('Flujo de Pagos'!I$7:I$506,'Flujo de Pagos'!E$7:E$506,B20,'Flujo de Pagos'!B$7:B$506,AC7)) | AD20: =IF(B20="","",SUMIFS('Flujo de Pagos'!I$7:I$506,'Flujo de Pagos'!E$7:E$506,B20,'Flujo de Pagos'!B$7:B$506,AD7)) | AE20: =IF(B20="","",SUMIFS('Flujo de Pagos'!I$7:I$506,'Flujo de Pagos'!E$7:E$506,B20,'Flujo de Pagos'!B$7:B$506,AE7)) | AF20: =IF(B20="","",SUMIFS('Flujo de Pagos'!I$7:I$506,'Flujo de Pagos'!E$7:E$506,B20,'Flujo de Pagos'!B$7:B$506,AF7)) | AG20: =IF(B20="","",SUMIFS('Flujo de Pagos'!I$7:I$506,'Flujo de Pagos'!E$7:E$506,B20,'Flujo de Pagos'!B$7:B$506,AG7)) | AH20: =IF(B20="","",SUMIFS('Flujo de Pagos'!I$7:I$506,'Flujo de Pagos'!E$7:E$506,B20,'Flujo de Pagos'!B$7:B$506,AH7)) | AI20: =IF(B20="","",SUMIFS('Flujo de Pagos'!I$7:I$506,'Flujo de Pagos'!E$7:E$506,B20,'Flujo de Pagos'!B$7:B$506,AI7)) | AJ20: =IF(B20="","",SUMIFS('Flujo de Pagos'!I$7:I$506,'Flujo de Pagos'!E$7:E$506,B20,'Flujo de Pagos'!B$7:B$506,AJ7)) | AK20: =IF(B20="","",SUMIFS('Flujo de Pagos'!I$7:I$506,'Flujo de Pagos'!E$7:E$506,B20,'Flujo de Pagos'!B$7:B$506,AK7)) | AL20: =IF(B20="","",SUMIFS('Flujo de Pagos'!I$7:I$506,'Flujo de Pagos'!E$7:E$506,B20,'Flujo de Pagos'!B$7:B$506,AL7)) | AM20: =IF(B20="","",SUM(C20:AL20))
B21: =IF(Presupuesto!B18="","",Presupuesto!B18) | C21: =IF(B21="","",SUMIFS('Flujo de Pagos'!I$7:I$506,'Flujo de Pagos'!E$7:E$506,B21,'Flujo de Pagos'!B$7:B$506,C7)) | D21: =IF(B21="","",SUMIFS('Flujo de Pagos'!I$7:I$506,'Flujo de Pagos'!E$7:E$506,B21,'Flujo de Pagos'!B$7:B$506,D7)) | E21: =IF(B21="","",SUMIFS('Flujo de Pagos'!I$7:I$506,'Flujo de Pagos'!E$7:E$506,B21,'Flujo de Pagos'!B$7:B$506,E7)) | F21: =IF(B21="","",SUMIFS('Flujo de Pagos'!I$7:I$506,'Flujo de Pagos'!E$7:E$506,B21,'Flujo de Pagos'!B$7:B$506,F7)) | G21: =IF(B21="","",SUMIFS('Flujo de Pagos'!I$7:I$506,'Flujo de Pagos'!E$7:E$506,B21,'Flujo de Pagos'!B$7:B$506,G7)) | H21: =IF(B21="","",SUMIFS('Flujo de Pagos'!I$7:I$506,'Flujo de Pagos'!E$7:E$506,B21,'Flujo de Pagos'!B$7:B$506,H7)) | I21: =IF(B21="","",SUMIFS('Flujo de Pagos'!I$7:I$506,'Flujo de Pagos'!E$7:E$506,B21,'Flujo de Pagos'!B$7:B$506,I7)) | J21: =IF(B21="","",SUMIFS('Flujo de Pagos'!I$7:I$506,'Flujo de Pagos'!E$7:E$506,B21,'Flujo de Pagos'!B$7:B$506,J7)) | K21: =IF(B21="","",SUMIFS('Flujo de Pagos'!I$7:I$506,'Flujo de Pagos'!E$7:E$506,B21,'Flujo de Pagos'!B$7:B$506,K7)) | L21: =IF(B21="","",SUMIFS('Flujo de Pagos'!I$7:I$506,'Flujo de Pagos'!E$7:E$506,B21,'Flujo de Pagos'!B$7:B$506,L7)) | M21: =IF(B21="","",SUMIFS('Flujo de Pagos'!I$7:I$506,'Flujo de Pagos'!E$7:E$506,B21,'Flujo de Pagos'!B$7:B$506,M7)) | N21: =IF(B21="","",SUMIFS('Flujo de Pagos'!I$7:I$506,'Flujo de Pagos'!E$7:E$506,B21,'Flujo de Pagos'!B$7:B$506,N7)) | O21: =IF(B21="","",SUMIFS('Flujo de Pagos'!I$7:I$506,'Flujo de Pagos'!E$7:E$506,B21,'Flujo de Pagos'!B$7:B$506,O7)) | P21: =IF(B21="","",SUMIFS('Flujo de Pagos'!I$7:I$506,'Flujo de Pagos'!E$7:E$506,B21,'Flujo de Pagos'!B$7:B$506,P7)) | Q21: =IF(B21="","",SUMIFS('Flujo de Pagos'!I$7:I$506,'Flujo de Pagos'!E$7:E$506,B21,'Flujo de Pagos'!B$7:B$506,Q7)) | R21: =IF(B21="","",SUMIFS('Flujo de Pagos'!I$7:I$506,'Flujo de Pagos'!E$7:E$506,B21,'Flujo de Pagos'!B$7:B$506,R7)) | S21: =IF(B21="","",SUMIFS('Flujo de Pagos'!I$7:I$506,'Flujo de Pagos'!E$7:E$506,B21,'Flujo de Pagos'!B$7:B$506,S7)) | T21: =IF(B21="","",SUMIFS('Flujo de Pagos'!I$7:I$506,'Flujo de Pagos'!E$7:E$506,B21,'Flujo de Pagos'!B$7:B$506,T7)) | U21: =IF(B21="","",SUMIFS('Flujo de Pagos'!I$7:I$506,'Flujo de Pagos'!E$7:E$506,B21,'Flujo de Pagos'!B$7:B$506,U7)) | V21: =IF(B21="","",SUMIFS('Flujo de Pagos'!I$7:I$506,'Flujo de Pagos'!E$7:E$506,B21,'Flujo de Pagos'!B$7:B$506,V7)) | W21: =IF(B21="","",SUMIFS('Flujo de Pagos'!I$7:I$506,'Flujo de Pagos'!E$7:E$506,B21,'Flujo de Pagos'!B$7:B$506,W7)) | X21: =IF(B21="","",SUMIFS('Flujo de Pagos'!I$7:I$506,'Flujo de Pagos'!E$7:E$506,B21,'Flujo de Pagos'!B$7:B$506,X7)) | Y21: =IF(B21="","",SUMIFS('Flujo de Pagos'!I$7:I$506,'Flujo de Pagos'!E$7:E$506,B21,'Flujo de Pagos'!B$7:B$506,Y7)) | Z21: =IF(B21="","",SUMIFS('Flujo de Pagos'!I$7:I$506,'Flujo de Pagos'!E$7:E$506,B21,'Flujo de Pagos'!B$7:B$506,Z7)) | AA21: =IF(B21="","",SUMIFS('Flujo de Pagos'!I$7:I$506,'Flujo de Pagos'!E$7:E$506,B21,'Flujo de Pagos'!B$7:B$506,AA7)) | AB21: =IF(B21="","",SUMIFS('Flujo de Pagos'!I$7:I$506,'Flujo de Pagos'!E$7:E$506,B21,'Flujo de Pagos'!B$7:B$506,AB7)) | AC21: =IF(B21="","",SUMIFS('Flujo de Pagos'!I$7:I$506,'Flujo de Pagos'!E$7:E$506,B21,'Flujo de Pagos'!B$7:B$506,AC7)) | AD21: =IF(B21="","",SUMIFS('Flujo de Pagos'!I$7:I$506,'Flujo de Pagos'!E$7:E$506,B21,'Flujo de Pagos'!B$7:B$506,AD7)) | AE21: =IF(B21="","",SUMIFS('Flujo de Pagos'!I$7:I$506,'Flujo de Pagos'!E$7:E$506,B21,'Flujo de Pagos'!B$7:B$506,AE7)) | AF21: =IF(B21="","",SUMIFS('Flujo de Pagos'!I$7:I$506,'Flujo de Pagos'!E$7:E$506,B21,'Flujo de Pagos'!B$7:B$506,AF7)) | AG21: =IF(B21="","",SUMIFS('Flujo de Pagos'!I$7:I$506,'Flujo de Pagos'!E$7:E$506,B21,'Flujo de Pagos'!B$7:B$506,AG7)) | AH21: =IF(B21="","",SUMIFS('Flujo de Pagos'!I$7:I$506,'Flujo de Pagos'!E$7:E$506,B21,'Flujo de Pagos'!B$7:B$506,AH7)) | AI21: =IF(B21="","",SUMIFS('Flujo de Pagos'!I$7:I$506,'Flujo de Pagos'!E$7:E$506,B21,'Flujo de Pagos'!B$7:B$506,AI7)) | AJ21: =IF(B21="","",SUMIFS('Flujo de Pagos'!I$7:I$506,'Flujo de Pagos'!E$7:E$506,B21,'Flujo de Pagos'!B$7:B$506,AJ7)) | AK21: =IF(B21="","",SUMIFS('Flujo de Pagos'!I$7:I$506,'Flujo de Pagos'!E$7:E$506,B21,'Flujo de Pagos'!B$7:B$506,AK7)) | AL21: =IF(B21="","",SUMIFS('Flujo de Pagos'!I$7:I$506,'Flujo de Pagos'!E$7:E$506,B21,'Flujo de Pagos'!B$7:B$506,AL7)) | AM21: =IF(B21="","",SUM(C21:AL21))
B22: =IF(Presupuesto!B19="","",Presupuesto!B19) | C22: =IF(B22="","",SUMIFS('Flujo de Pagos'!I$7:I$506,'Flujo de Pagos'!E$7:E$506,B22,'Flujo de Pagos'!B$7:B$506,C7)) | D22: =IF(B22="","",SUMIFS('Flujo de Pagos'!I$7:I$506,'Flujo de Pagos'!E$7:E$506,B22,'Flujo de Pagos'!B$7:B$506,D7)) | E22: =IF(B22="","",SUMIFS('Flujo de Pagos'!I$7:I$506,'Flujo de Pagos'!E$7:E$506,B22,'Flujo de Pagos'!B$7:B$506,E7)) | F22: =IF(B22="","",SUMIFS('Flujo de Pagos'!I$7:I$506,'Flujo de Pagos'!E$7:E$506,B22,'Flujo de Pagos'!B$7:B$506,F7)) | G22: =IF(B22="","",SUMIFS('Flujo de Pagos'!I$7:I$506,'Flujo de Pagos'!E$7:E$506,B22,'Flujo de Pagos'!B$7:B$506,G7)) | H22: =IF(B22="","",SUMIFS('Flujo de Pagos'!I$7:I$506,'Flujo de Pagos'!E$7:E$506,B22,'Flujo de Pagos'!B$7:B$506,H7)) | I22: =IF(B22="","",SUMIFS('Flujo de Pagos'!I$7:I$506,'Flujo de Pagos'!E$7:E$506,B22,'Flujo de Pagos'!B$7:B$506,I7)) | J22: =IF(B22="","",SUMIFS('Flujo de Pagos'!I$7:I$506,'Flujo de Pagos'!E$7:E$506,B22,'Flujo de Pagos'!B$7:B$506,J7)) | K22: =IF(B22="","",SUMIFS('Flujo de Pagos'!I$7:I$506,'Flujo de Pagos'!E$7:E$506,B22,'Flujo de Pagos'!B$7:B$506,K7)) | L22: =IF(B22="","",SUMIFS('Flujo de Pagos'!I$7:I$506,'Flujo de Pagos'!E$7:E$506,B22,'Flujo de Pagos'!B$7:B$506,L7)) | M22: =IF(B22="","",SUMIFS('Flujo de Pagos'!I$7:I$506,'Flujo de Pagos'!E$7:E$506,B22,'Flujo de Pagos'!B$7:B$506,M7)) | N22: =IF(B22="","",SUMIFS('Flujo de Pagos'!I$7:I$506,'Flujo de Pagos'!E$7:E$506,B22,'Flujo de Pagos'!B$7:B$506,N7)) | O22: =IF(B22="","",SUMIFS('Flujo de Pagos'!I$7:I$506,'Flujo de Pagos'!E$7:E$506,B22,'Flujo de Pagos'!B$7:B$506,O7)) | P22: =IF(B22="","",SUMIFS('Flujo de Pagos'!I$7:I$506,'Flujo de Pagos'!E$7:E$506,B22,'Flujo de Pagos'!B$7:B$506,P7)) | Q22: =IF(B22="","",SUMIFS('Flujo de Pagos'!I$7:I$506,'Flujo de Pagos'!E$7:E$506,B22,'Flujo de Pagos'!B$7:B$506,Q7)) | R22: =IF(B22="","",SUMIFS('Flujo de Pagos'!I$7:I$506,'Flujo de Pagos'!E$7:E$506,B22,'Flujo de Pagos'!B$7:B$506,R7)) | S22: =IF(B22="","",SUMIFS('Flujo de Pagos'!I$7:I$506,'Flujo de Pagos'!E$7:E$506,B22,'Flujo de Pagos'!B$7:B$506,S7)) | T22: =IF(B22="","",SUMIFS('Flujo de Pagos'!I$7:I$506,'Flujo de Pagos'!E$7:E$506,B22,'Flujo de Pagos'!B$7:B$506,T7)) | U22: =IF(B22="","",SUMIFS('Flujo de Pagos'!I$7:I$506,'Flujo de Pagos'!E$7:E$506,B22,'Flujo de Pagos'!B$7:B$506,U7)) | V22: =IF(B22="","",SUMIFS('Flujo de Pagos'!I$7:I$506,'Flujo de Pagos'!E$7:E$506,B22,'Flujo de Pagos'!B$7:B$506,V7)) | W22: =IF(B22="","",SUMIFS('Flujo de Pagos'!I$7:I$506,'Flujo de Pagos'!E$7:E$506,B22,'Flujo de Pagos'!B$7:B$506,W7)) | X22: =IF(B22="","",SUMIFS('Flujo de Pagos'!I$7:I$506,'Flujo de Pagos'!E$7:E$506,B22,'Flujo de Pagos'!B$7:B$506,X7)) | Y22: =IF(B22="","",SUMIFS('Flujo de Pagos'!I$7:I$506,'Flujo de Pagos'!E$7:E$506,B22,'Flujo de Pagos'!B$7:B$506,Y7)) | Z22: =IF(B22="","",SUMIFS('Flujo de Pagos'!I$7:I$506,'Flujo de Pagos'!E$7:E$506,B22,'Flujo de Pagos'!B$7:B$506,Z7)) | AA22: =IF(B22="","",SUMIFS('Flujo de Pagos'!I$7:I$506,'Flujo de Pagos'!E$7:E$506,B22,'Flujo de Pagos'!B$7:B$506,AA7)) | AB22: =IF(B22="","",SUMIFS('Flujo de Pagos'!I$7:I$506,'Flujo de Pagos'!E$7:E$506,B22,'Flujo de Pagos'!B$7:B$506,AB7)) | AC22: =IF(B22="","",SUMIFS('Flujo de Pagos'!I$7:I$506,'Flujo de Pagos'!E$7:E$506,B22,'Flujo de Pagos'!B$7:B$506,AC7)) | AD22: =IF(B22="","",SUMIFS('Flujo de Pagos'!I$7:I$506,'Flujo de Pagos'!E$7:E$506,B22,'Flujo de Pagos'!B$7:B$506,AD7)) | AE22: =IF(B22="","",SUMIFS('Flujo de Pagos'!I$7:I$506,'Flujo de Pagos'!E$7:E$506,B22,'Flujo de Pagos'!B$7:B$506,AE7)) | AF22: =IF(B22="","",SUMIFS('Flujo de Pagos'!I$7:I$506,'Flujo de Pagos'!E$7:E$506,B22,'Flujo de Pagos'!B$7:B$506,AF7)) | AG22: =IF(B22="","",SUMIFS('Flujo de Pagos'!I$7:I$506,'Flujo de Pagos'!E$7:E$506,B22,'Flujo de Pagos'!B$7:B$506,AG7)) | AH22: =IF(B22="","",SUMIFS('Flujo de Pagos'!I$7:I$506,'Flujo de Pagos'!E$7:E$506,B22,'Flujo de Pagos'!B$7:B$506,AH7)) | AI22: =IF(B22="","",SUMIFS('Flujo de Pagos'!I$7:I$506,'Flujo de Pagos'!E$7:E$506,B22,'Flujo de Pagos'!B$7:B$506,AI7)) | AJ22: =IF(B22="","",SUMIFS('Flujo de Pagos'!I$7:I$506,'Flujo de Pagos'!E$7:E$506,B22,'Flujo de Pagos'!B$7:B$506,AJ7)) | AK22: =IF(B22="","",SUMIFS('Flujo de Pagos'!I$7:I$506,'Flujo de Pagos'!E$7:E$506,B22,'Flujo de Pagos'!B$7:B$506,AK7)) | AL22: =IF(B22="","",SUMIFS('Flujo de Pagos'!I$7:I$506,'Flujo de Pagos'!E$7:E$506,B22,'Flujo de Pagos'!B$7:B$506,AL7)) | AM22: =IF(B22="","",SUM(C22:AL22))
B23: =IF(Presupuesto!B20="","",Presupuesto!B20) | C23: =IF(B23="","",SUMIFS('Flujo de Pagos'!I$7:I$506,'Flujo de Pagos'!E$7:E$506,B23,'Flujo de Pagos'!B$7:B$506,C7)) | D23: =IF(B23="","",SUMIFS('Flujo de Pagos'!I$7:I$506,'Flujo de Pagos'!E$7:E$506,B23,'Flujo de Pagos'!B$7:B$506,D7)) | E23: =IF(B23="","",SUMIFS('Flujo de Pagos'!I$7:I$506,'Flujo de Pagos'!E$7:E$506,B23,'Flujo de Pagos'!B$7:B$506,E7)) | F23: =IF(B23="","",SUMIFS('Flujo de Pagos'!I$7:I$506,'Flujo de Pagos'!E$7:E$506,B23,'Flujo de Pagos'!B$7:B$506,F7)) | G23: =IF(B23="","",SUMIFS('Flujo de Pagos'!I$7:I$506,'Flujo de Pagos'!E$7:E$506,B23,'Flujo de Pagos'!B$7:B$506,G7)) | H23: =IF(B23="","",SUMIFS('Flujo de Pagos'!I$7:I$506,'Flujo de Pagos'!E$7:E$506,B23,'Flujo de Pagos'!B$7:B$506,H7)) | I23: =IF(B23="","",SUMIFS('Flujo de Pagos'!I$7:I$506,'Flujo de Pagos'!E$7:E$506,B23,'Flujo de Pagos'!B$7:B$506,I7)) | J23: =IF(B23="","",SUMIFS('Flujo de Pagos'!I$7:I$506,'Flujo de Pagos'!E$7:E$506,B23,'Flujo de Pagos'!B$7:B$506,J7)) | K23: =IF(B23="","",SUMIFS('Flujo de Pagos'!I$7:I$506,'Flujo de Pagos'!E$7:E$506,B23,'Flujo de Pagos'!B$7:B$506,K7)) | L23: =IF(B23="","",SUMIFS('Flujo de Pagos'!I$7:I$506,'Flujo de Pagos'!E$7:E$506,B23,'Flujo de Pagos'!B$7:B$506,L7)) | M23: =IF(B23="","",SUMIFS('Flujo de Pagos'!I$7:I$506,'Flujo de Pagos'!E$7:E$506,B23,'Flujo de Pagos'!B$7:B$506,M7)) | N23: =IF(B23="","",SUMIFS('Flujo de Pagos'!I$7:I$506,'Flujo de Pagos'!E$7:E$506,B23,'Flujo de Pagos'!B$7:B$506,N7)) | O23: =IF(B23="","",SUMIFS('Flujo de Pagos'!I$7:I$506,'Flujo de Pagos'!E$7:E$506,B23,'Flujo de Pagos'!B$7:B$506,O7)) | P23: =IF(B23="","",SUMIFS('Flujo de Pagos'!I$7:I$506,'Flujo de Pagos'!E$7:E$506,B23,'Flujo de Pagos'!B$7:B$506,P7)) | Q23: =IF(B23="","",SUMIFS('Flujo de Pagos'!I$7:I$506,'Flujo de Pagos'!E$7:E$506,B23,'Flujo de Pagos'!B$7:B$506,Q7)) | R23: =IF(B23="","",SUMIFS('Flujo de Pagos'!I$7:I$506,'Flujo de Pagos'!E$7:E$506,B23,'Flujo de Pagos'!B$7:B$506,R7)) | S23: =IF(B23="","",SUMIFS('Flujo de Pagos'!I$7:I$506,'Flujo de Pagos'!E$7:E$506,B23,'Flujo de Pagos'!B$7:B$506,S7)) | T23: =IF(B23="","",SUMIFS('Flujo de Pagos'!I$7:I$506,'Flujo de Pagos'!E$7:E$506,B23,'Flujo de Pagos'!B$7:B$506,T7)) | U23: =IF(B23="","",SUMIFS('Flujo de Pagos'!I$7:I$506,'Flujo de Pagos'!E$7:E$506,B23,'Flujo de Pagos'!B$7:B$506,U7)) | V23: =IF(B23="","",SUMIFS('Flujo de Pagos'!I$7:I$506,'Flujo de Pagos'!E$7:E$506,B23,'Flujo de Pagos'!B$7:B$506,V7)) | W23: =IF(B23="","",SUMIFS('Flujo de Pagos'!I$7:I$506,'Flujo de Pagos'!E$7:E$506,B23,'Flujo de Pagos'!B$7:B$506,W7)) | X23: =IF(B23="","",SUMIFS('Flujo de Pagos'!I$7:I$506,'Flujo de Pagos'!E$7:E$506,B23,'Flujo de Pagos'!B$7:B$506,X7)) | Y23: =IF(B23="","",SUMIFS('Flujo de Pagos'!I$7:I$506,'Flujo de Pagos'!E$7:E$506,B23,'Flujo de Pagos'!B$7:B$506,Y7)) | Z23: =IF(B23="","",SUMIFS('Flujo de Pagos'!I$7:I$506,'Flujo de Pagos'!E$7:E$506,B23,'Flujo de Pagos'!B$7:B$506,Z7)) | AA23: =IF(B23="","",SUMIFS('Flujo de Pagos'!I$7:I$506,'Flujo de Pagos'!E$7:E$506,B23,'Flujo de Pagos'!B$7:B$506,AA7)) | AB23: =IF(B23="","",SUMIFS('Flujo de Pagos'!I$7:I$506,'Flujo de Pagos'!E$7:E$506,B23,'Flujo de Pagos'!B$7:B$506,AB7)) | AC23: =IF(B23="","",SUMIFS('Flujo de Pagos'!I$7:I$506,'Flujo de Pagos'!E$7:E$506,B23,'Flujo de Pagos'!B$7:B$506,AC7)) | AD23: =IF(B23="","",SUMIFS('Flujo de Pagos'!I$7:I$506,'Flujo de Pagos'!E$7:E$506,B23,'Flujo de Pagos'!B$7:B$506,AD7)) | AE23: =IF(B23="","",SUMIFS('Flujo de Pagos'!I$7:I$506,'Flujo de Pagos'!E$7:E$506,B23,'Flujo de Pagos'!B$7:B$506,AE7)) | AF23: =IF(B23="","",SUMIFS('Flujo de Pagos'!I$7:I$506,'Flujo de Pagos'!E$7:E$506,B23,'Flujo de Pagos'!B$7:B$506,AF7)) | AG23: =IF(B23="","",SUMIFS('Flujo de Pagos'!I$7:I$506,'Flujo de Pagos'!E$7:E$506,B23,'Flujo de Pagos'!B$7:B$506,AG7)) | AH23: =IF(B23="","",SUMIFS('Flujo de Pagos'!I$7:I$506,'Flujo de Pagos'!E$7:E$506,B23,'Flujo de Pagos'!B$7:B$506,AH7)) | AI23: =IF(B23="","",SUMIFS('Flujo de Pagos'!I$7:I$506,'Flujo de Pagos'!E$7:E$506,B23,'Flujo de Pagos'!B$7:B$506,AI7)) | AJ23: =IF(B23="","",SUMIFS('Flujo de Pagos'!I$7:I$506,'Flujo de Pagos'!E$7:E$506,B23,'Flujo de Pagos'!B$7:B$506,AJ7)) | AK23: =IF(B23="","",SUMIFS('Flujo de Pagos'!I$7:I$506,'Flujo de Pagos'!E$7:E$506,B23,'Flujo de Pagos'!B$7:B$506,AK7)) | AL23: =IF(B23="","",SUMIFS('Flujo de Pagos'!I$7:I$506,'Flujo de Pagos'!E$7:E$506,B23,'Flujo de Pagos'!B$7:B$506,AL7)) | AM23: =IF(B23="","",SUM(C23:AL23))
B24: =IF(Presupuesto!B21="","",Presupuesto!B21) | C24: =IF(B24="","",SUMIFS('Flujo de Pagos'!I$7:I$506,'Flujo de Pagos'!E$7:E$506,B24,'Flujo de Pagos'!B$7:B$506,C7)) | D24: =IF(B24="","",SUMIFS('Flujo de Pagos'!I$7:I$506,'Flujo de Pagos'!E$7:E$506,B24,'Flujo de Pagos'!B$7:B$506,D7)) | E24: =IF(B24="","",SUMIFS('Flujo de Pagos'!I$7:I$506,'Flujo de Pagos'!E$7:E$506,B24,'Flujo de Pagos'!B$7:B$506,E7)) | F24: =IF(B24="","",SUMIFS('Flujo de Pagos'!I$7:I$506,'Flujo de Pagos'!E$7:E$506,B24,'Flujo de Pagos'!B$7:B$506,F7)) | G24: =IF(B24="","",SUMIFS('Flujo de Pagos'!I$7:I$506,'Flujo de Pagos'!E$7:E$506,B24,'Flujo de Pagos'!B$7:B$506,G7)) | H24: =IF(B24="","",SUMIFS('Flujo de Pagos'!I$7:I$506,'Flujo de Pagos'!E$7:E$506,B24,'Flujo de Pagos'!B$7:B$506,H7)) | I24: =IF(B24="","",SUMIFS('Flujo de Pagos'!I$7:I$506,'Flujo de Pagos'!E$7:E$506,B24,'Flujo de Pagos'!B$7:B$506,I7)) | J24: =IF(B24="","",SUMIFS('Flujo de Pagos'!I$7:I$506,'Flujo de Pagos'!E$7:E$506,B24,'Flujo de Pagos'!B$7:B$506,J7)) | K24: =IF(B24="","",SUMIFS('Flujo de Pagos'!I$7:I$506,'Flujo de Pagos'!E$7:E$506,B24,'Flujo de Pagos'!B$7:B$506,K7)) | L24: =IF(B24="","",SUMIFS('Flujo de Pagos'!I$7:I$506,'Flujo de Pagos'!E$7:E$506,B24,'Flujo de Pagos'!B$7:B$506,L7)) | M24: =IF(B24="","",SUMIFS('Flujo de Pagos'!I$7:I$506,'Flujo de Pagos'!E$7:E$506,B24,'Flujo de Pagos'!B$7:B$506,M7)) | N24: =IF(B24="","",SUMIFS('Flujo de Pagos'!I$7:I$506,'Flujo de Pagos'!E$7:E$506,B24,'Flujo de Pagos'!B$7:B$506,N7)) | O24: =IF(B24="","",SUMIFS('Flujo de Pagos'!I$7:I$506,'Flujo de Pagos'!E$7:E$506,B24,'Flujo de Pagos'!B$7:B$506,O7)) | P24: =IF(B24="","",SUMIFS('Flujo de Pagos'!I$7:I$506,'Flujo de Pagos'!E$7:E$506,B24,'Flujo de Pagos'!B$7:B$506,P7)) | Q24: =IF(B24="","",SUMIFS('Flujo de Pagos'!I$7:I$506,'Flujo de Pagos'!E$7:E$506,B24,'Flujo de Pagos'!B$7:B$506,Q7)) | R24: =IF(B24="","",SUMIFS('Flujo de Pagos'!I$7:I$506,'Flujo de Pagos'!E$7:E$506,B24,'Flujo de Pagos'!B$7:B$506,R7)) | S24: =IF(B24="","",SUMIFS('Flujo de Pagos'!I$7:I$506,'Flujo de Pagos'!E$7:E$506,B24,'Flujo de Pagos'!B$7:B$506,S7)) | T24: =IF(B24="","",SUMIFS('Flujo de Pagos'!I$7:I$506,'Flujo de Pagos'!E$7:E$506,B24,'Flujo de Pagos'!B$7:B$506,T7)) | U24: =IF(B24="","",SUMIFS('Flujo de Pagos'!I$7:I$506,'Flujo de Pagos'!E$7:E$506,B24,'Flujo de Pagos'!B$7:B$506,U7)) | V24: =IF(B24="","",SUMIFS('Flujo de Pagos'!I$7:I$506,'Flujo de Pagos'!E$7:E$506,B24,'Flujo de Pagos'!B$7:B$506,V7)) | W24: =IF(B24="","",SUMIFS('Flujo de Pagos'!I$7:I$506,'Flujo de Pagos'!E$7:E$506,B24,'Flujo de Pagos'!B$7:B$506,W7)) | X24: =IF(B24="","",SUMIFS('Flujo de Pagos'!I$7:I$506,'Flujo de Pagos'!E$7:E$506,B24,'Flujo de Pagos'!B$7:B$506,X7)) | Y24: =IF(B24="","",SUMIFS('Flujo de Pagos'!I$7:I$506,'Flujo de Pagos'!E$7:E$506,B24,'Flujo de Pagos'!B$7:B$506,Y7)) | Z24: =IF(B24="","",SUMIFS('Flujo de Pagos'!I$7:I$506,'Flujo de Pagos'!E$7:E$506,B24,'Flujo de Pagos'!B$7:B$506,Z7)) | AA24: =IF(B24="","",SUMIFS('Flujo de Pagos'!I$7:I$506,'Flujo de Pagos'!E$7:E$506,B24,'Flujo de Pagos'!B$7:B$506,AA7)) | AB24: =IF(B24="","",SUMIFS('Flujo de Pagos'!I$7:I$506,'Flujo de Pagos'!E$7:E$506,B24,'Flujo de Pagos'!B$7:B$506,AB7)) | AC24: =IF(B24="","",SUMIFS('Flujo de Pagos'!I$7:I$506,'Flujo de Pagos'!E$7:E$506,B24,'Flujo de Pagos'!B$7:B$506,AC7)) | AD24: =IF(B24="","",SUMIFS('Flujo de Pagos'!I$7:I$506,'Flujo de Pagos'!E$7:E$506,B24,'Flujo de Pagos'!B$7:B$506,AD7)) | AE24: =IF(B24="","",SUMIFS('Flujo de Pagos'!I$7:I$506,'Flujo de Pagos'!E$7:E$506,B24,'Flujo de Pagos'!B$7:B$506,AE7)) | AF24: =IF(B24="","",SUMIFS('Flujo de Pagos'!I$7:I$506,'Flujo de Pagos'!E$7:E$506,B24,'Flujo de Pagos'!B$7:B$506,AF7)) | AG24: =IF(B24="","",SUMIFS('Flujo de Pagos'!I$7:I$506,'Flujo de Pagos'!E$7:E$506,B24,'Flujo de Pagos'!B$7:B$506,AG7)) | AH24: =IF(B24="","",SUMIFS('Flujo de Pagos'!I$7:I$506,'Flujo de Pagos'!E$7:E$506,B24,'Flujo de Pagos'!B$7:B$506,AH7)) | AI24: =IF(B24="","",SUMIFS('Flujo de Pagos'!I$7:I$506,'Flujo de Pagos'!E$7:E$506,B24,'Flujo de Pagos'!B$7:B$506,AI7)) | AJ24: =IF(B24="","",SUMIFS('Flujo de Pagos'!I$7:I$506,'Flujo de Pagos'!E$7:E$506,B24,'Flujo de Pagos'!B$7:B$506,AJ7)) | AK24: =IF(B24="","",SUMIFS('Flujo de Pagos'!I$7:I$506,'Flujo de Pagos'!E$7:E$506,B24,'Flujo de Pagos'!B$7:B$506,AK7)) | AL24: =IF(B24="","",SUMIFS('Flujo de Pagos'!I$7:I$506,'Flujo de Pagos'!E$7:E$506,B24,'Flujo de Pagos'!B$7:B$506,AL7)) | AM24: =IF(B24="","",SUM(C24:AL24))
B25: =IF(Presupuesto!B22="","",Presupuesto!B22) | C25: =IF(B25="","",SUMIFS('Flujo de Pagos'!I$7:I$506,'Flujo de Pagos'!E$7:E$506,B25,'Flujo de Pagos'!B$7:B$506,C7)) | D25: =IF(B25="","",SUMIFS('Flujo de Pagos'!I$7:I$506,'Flujo de Pagos'!E$7:E$506,B25,'Flujo de Pagos'!B$7:B$506,D7)) | E25: =IF(B25="","",SUMIFS('Flujo de Pagos'!I$7:I$506,'Flujo de Pagos'!E$7:E$506,B25,'Flujo de Pagos'!B$7:B$506,E7)) | F25: =IF(B25="","",SUMIFS('Flujo de Pagos'!I$7:I$506,'Flujo de Pagos'!E$7:E$506,B25,'Flujo de Pagos'!B$7:B$506,F7)) | G25: =IF(B25="","",SUMIFS('Flujo de Pagos'!I$7:I$506,'Flujo de Pagos'!E$7:E$506,B25,'Flujo de Pagos'!B$7:B$506,G7)) | H25: =IF(B25="","",SUMIFS('Flujo de Pagos'!I$7:I$506,'Flujo de Pagos'!E$7:E$506,B25,'Flujo de Pagos'!B$7:B$506,H7)) | I25: =IF(B25="","",SUMIFS('Flujo de Pagos'!I$7:I$506,'Flujo de Pagos'!E$7:E$506,B25,'Flujo de Pagos'!B$7:B$506,I7)) | J25: =IF(B25="","",SUMIFS('Flujo de Pagos'!I$7:I$506,'Flujo de Pagos'!E$7:E$506,B25,'Flujo de Pagos'!B$7:B$506,J7)) | K25: =IF(B25="","",SUMIFS('Flujo de Pagos'!I$7:I$506,'Flujo de Pagos'!E$7:E$506,B25,'Flujo de Pagos'!B$7:B$506,K7)) | L25: =IF(B25="","",SUMIFS('Flujo de Pagos'!I$7:I$506,'Flujo de Pagos'!E$7:E$506,B25,'Flujo de Pagos'!B$7:B$506,L7)) | M25: =IF(B25="","",SUMIFS('Flujo de Pagos'!I$7:I$506,'Flujo de Pagos'!E$7:E$506,B25,'Flujo de Pagos'!B$7:B$506,M7)) | N25: =IF(B25="","",SUMIFS('Flujo de Pagos'!I$7:I$506,'Flujo de Pagos'!E$7:E$506,B25,'Flujo de Pagos'!B$7:B$506,N7)) | O25: =IF(B25="","",SUMIFS('Flujo de Pagos'!I$7:I$506,'Flujo de Pagos'!E$7:E$506,B25,'Flujo de Pagos'!B$7:B$506,O7)) | P25: =IF(B25="","",SUMIFS('Flujo de Pagos'!I$7:I$506,'Flujo de Pagos'!E$7:E$506,B25,'Flujo de Pagos'!B$7:B$506,P7)) | Q25: =IF(B25="","",SUMIFS('Flujo de Pagos'!I$7:I$506,'Flujo de Pagos'!E$7:E$506,B25,'Flujo de Pagos'!B$7:B$506,Q7)) | R25: =IF(B25="","",SUMIFS('Flujo de Pagos'!I$7:I$506,'Flujo de Pagos'!E$7:E$506,B25,'Flujo de Pagos'!B$7:B$506,R7)) | S25: =IF(B25="","",SUMIFS('Flujo de Pagos'!I$7:I$506,'Flujo de Pagos'!E$7:E$506,B25,'Flujo de Pagos'!B$7:B$506,S7)) | T25: =IF(B25="","",SUMIFS('Flujo de Pagos'!I$7:I$506,'Flujo de Pagos'!E$7:E$506,B25,'Flujo de Pagos'!B$7:B$506,T7)) | U25: =IF(B25="","",SUMIFS('Flujo de Pagos'!I$7:I$506,'Flujo de Pagos'!E$7:E$506,B25,'Flujo de Pagos'!B$7:B$506,U7)) | V25: =IF(B25="","",SUMIFS('Flujo de Pagos'!I$7:I$506,'Flujo de Pagos'!E$7:E$506,B25,'Flujo de Pagos'!B$7:B$506,V7)) | W25: =IF(B25="","",SUMIFS('Flujo de Pagos'!I$7:I$506,'Flujo de Pagos'!E$7:E$506,B25,'Flujo de Pagos'!B$7:B$506,W7)) | X25: =IF(B25="","",SUMIFS('Flujo de Pagos'!I$7:I$506,'Flujo de Pagos'!E$7:E$506,B25,'Flujo de Pagos'!B$7:B$506,X7)) | Y25: =IF(B25="","",SUMIFS('Flujo de Pagos'!I$7:I$506,'Flujo de Pagos'!E$7:E$506,B25,'Flujo de Pagos'!B$7:B$506,Y7)) | Z25: =IF(B25="","",SUMIFS('Flujo de Pagos'!I$7:I$506,'Flujo de Pagos'!E$7:E$506,B25,'Flujo de Pagos'!B$7:B$506,Z7)) | AA25: =IF(B25="","",SUMIFS('Flujo de Pagos'!I$7:I$506,'Flujo de Pagos'!E$7:E$506,B25,'Flujo de Pagos'!B$7:B$506,AA7)) | AB25: =IF(B25="","",SUMIFS('Flujo de Pagos'!I$7:I$506,'Flujo de Pagos'!E$7:E$506,B25,'Flujo de Pagos'!B$7:B$506,AB7)) | AC25: =IF(B25="","",SUMIFS('Flujo de Pagos'!I$7:I$506,'Flujo de Pagos'!E$7:E$506,B25,'Flujo de Pagos'!B$7:B$506,AC7)) | AD25: =IF(B25="","",SUMIFS('Flujo de Pagos'!I$7:I$506,'Flujo de Pagos'!E$7:E$506,B25,'Flujo de Pagos'!B$7:B$506,AD7)) | AE25: =IF(B25="","",SUMIFS('Flujo de Pagos'!I$7:I$506,'Flujo de Pagos'!E$7:E$506,B25,'Flujo de Pagos'!B$7:B$506,AE7)) | AF25: =IF(B25="","",SUMIFS('Flujo de Pagos'!I$7:I$506,'Flujo de Pagos'!E$7:E$506,B25,'Flujo de Pagos'!B$7:B$506,AF7)) | AG25: =IF(B25="","",SUMIFS('Flujo de Pagos'!I$7:I$506,'Flujo de Pagos'!E$7:E$506,B25,'Flujo de Pagos'!B$7:B$506,AG7)) | AH25: =IF(B25="","",SUMIFS('Flujo de Pagos'!I$7:I$506,'Flujo de Pagos'!E$7:E$506,B25,'Flujo de Pagos'!B$7:B$506,AH7)) | AI25: =IF(B25="","",SUMIFS('Flujo de Pagos'!I$7:I$506,'Flujo de Pagos'!E$7:E$506,B25,'Flujo de Pagos'!B$7:B$506,AI7)) | AJ25: =IF(B25="","",SUMIFS('Flujo de Pagos'!I$7:I$506,'Flujo de Pagos'!E$7:E$506,B25,'Flujo de Pagos'!B$7:B$506,AJ7)) | AK25: =IF(B25="","",SUMIFS('Flujo de Pagos'!I$7:I$506,'Flujo de Pagos'!E$7:E$506,B25,'Flujo de Pagos'!B$7:B$506,AK7)) | AL25: =IF(B25="","",SUMIFS('Flujo de Pagos'!I$7:I$506,'Flujo de Pagos'!E$7:E$506,B25,'Flujo de Pagos'!B$7:B$506,AL7)) | AM25: =IF(B25="","",SUM(C25:AL25))
B26: =IF(Presupuesto!B23="","",Presupuesto!B23) | C26: =IF(B26="","",SUMIFS('Flujo de Pagos'!I$7:I$506,'Flujo de Pagos'!E$7:E$506,B26,'Flujo de Pagos'!B$7:B$506,C7)) | D26: =IF(B26="","",SUMIFS('Flujo de Pagos'!I$7:I$506,'Flujo de Pagos'!E$7:E$506,B26,'Flujo de Pagos'!B$7:B$506,D7)) | E26: =IF(B26="","",SUMIFS('Flujo de Pagos'!I$7:I$506,'Flujo de Pagos'!E$7:E$506,B26,'Flujo de Pagos'!B$7:B$506,E7)) | F26: =IF(B26="","",SUMIFS('Flujo de Pagos'!I$7:I$506,'Flujo de Pagos'!E$7:E$506,B26,'Flujo de Pagos'!B$7:B$506,F7)) | G26: =IF(B26="","",SUMIFS('Flujo de Pagos'!I$7:I$506,'Flujo de Pagos'!E$7:E$506,B26,'Flujo de Pagos'!B$7:B$506,G7)) | H26: =IF(B26="","",SUMIFS('Flujo de Pagos'!I$7:I$506,'Flujo de Pagos'!E$7:E$506,B26,'Flujo de Pagos'!B$7:B$506,H7)) | I26: =IF(B26="","",SUMIFS('Flujo de Pagos'!I$7:I$506,'Flujo de Pagos'!E$7:E$506,B26,'Flujo de Pagos'!B$7:B$506,I7)) | J26: =IF(B26="","",SUMIFS('Flujo de Pagos'!I$7:I$506,'Flujo de Pagos'!E$7:E$506,B26,'Flujo de Pagos'!B$7:B$506,J7)) | K26: =IF(B26="","",SUMIFS('Flujo de Pagos'!I$7:I$506,'Flujo de Pagos'!E$7:E$506,B26,'Flujo de Pagos'!B$7:B$506,K7)) | L26: =IF(B26="","",SUMIFS('Flujo de Pagos'!I$7:I$506,'Flujo de Pagos'!E$7:E$506,B26,'Flujo de Pagos'!B$7:B$506,L7)) | M26: =IF(B26="","",SUMIFS('Flujo de Pagos'!I$7:I$506,'Flujo de Pagos'!E$7:E$506,B26,'Flujo de Pagos'!B$7:B$506,M7)) | N26: =IF(B26="","",SUMIFS('Flujo de Pagos'!I$7:I$506,'Flujo de Pagos'!E$7:E$506,B26,'Flujo de Pagos'!B$7:B$506,N7)) | O26: =IF(B26="","",SUMIFS('Flujo de Pagos'!I$7:I$506,'Flujo de Pagos'!E$7:E$506,B26,'Flujo de Pagos'!B$7:B$506,O7)) | P26: =IF(B26="","",SUMIFS('Flujo de Pagos'!I$7:I$506,'Flujo de Pagos'!E$7:E$506,B26,'Flujo de Pagos'!B$7:B$506,P7)) | Q26: =IF(B26="","",SUMIFS('Flujo de Pagos'!I$7:I$506,'Flujo de Pagos'!E$7:E$506,B26,'Flujo de Pagos'!B$7:B$506,Q7)) | R26: =IF(B26="","",SUMIFS('Flujo de Pagos'!I$7:I$506,'Flujo de Pagos'!E$7:E$506,B26,'Flujo de Pagos'!B$7:B$506,R7)) | S26: =IF(B26="","",SUMIFS('Flujo de Pagos'!I$7:I$506,'Flujo de Pagos'!E$7:E$506,B26,'Flujo de Pagos'!B$7:B$506,S7)) | T26: =IF(B26="","",SUMIFS('Flujo de Pagos'!I$7:I$506,'Flujo de Pagos'!E$7:E$506,B26,'Flujo de Pagos'!B$7:B$506,T7)) | U26: =IF(B26="","",SUMIFS('Flujo de Pagos'!I$7:I$506,'Flujo de Pagos'!E$7:E$506,B26,'Flujo de Pagos'!B$7:B$506,U7)) | V26: =IF(B26="","",SUMIFS('Flujo de Pagos'!I$7:I$506,'Flujo de Pagos'!E$7:E$506,B26,'Flujo de Pagos'!B$7:B$506,V7)) | W26: =IF(B26="","",SUMIFS('Flujo de Pagos'!I$7:I$506,'Flujo de Pagos'!E$7:E$506,B26,'Flujo de Pagos'!B$7:B$506,W7)) | X26: =IF(B26="","",SUMIFS('Flujo de Pagos'!I$7:I$506,'Flujo de Pagos'!E$7:E$506,B26,'Flujo de Pagos'!B$7:B$506,X7)) | Y26: =IF(B26="","",SUMIFS('Flujo de Pagos'!I$7:I$506,'Flujo de Pagos'!E$7:E$506,B26,'Flujo de Pagos'!B$7:B$506,Y7)) | Z26: =IF(B26="","",SUMIFS('Flujo de Pagos'!I$7:I$506,'Flujo de Pagos'!E$7:E$506,B26,'Flujo de Pagos'!B$7:B$506,Z7)) | AA26: =IF(B26="","",SUMIFS('Flujo de Pagos'!I$7:I$506,'Flujo de Pagos'!E$7:E$506,B26,'Flujo de Pagos'!B$7:B$506,AA7)) | AB26: =IF(B26="","",SUMIFS('Flujo de Pagos'!I$7:I$506,'Flujo de Pagos'!E$7:E$506,B26,'Flujo de Pagos'!B$7:B$506,AB7)) | AC26: =IF(B26="","",SUMIFS('Flujo de Pagos'!I$7:I$506,'Flujo de Pagos'!E$7:E$506,B26,'Flujo de Pagos'!B$7:B$506,AC7)) | AD26: =IF(B26="","",SUMIFS('Flujo de Pagos'!I$7:I$506,'Flujo de Pagos'!E$7:E$506,B26,'Flujo de Pagos'!B$7:B$506,AD7)) | AE26: =IF(B26="","",SUMIFS('Flujo de Pagos'!I$7:I$506,'Flujo de Pagos'!E$7:E$506,B26,'Flujo de Pagos'!B$7:B$506,AE7)) | AF26: =IF(B26="","",SUMIFS('Flujo de Pagos'!I$7:I$506,'Flujo de Pagos'!E$7:E$506,B26,'Flujo de Pagos'!B$7:B$506,AF7)) | AG26: =IF(B26="","",SUMIFS('Flujo de Pagos'!I$7:I$506,'Flujo de Pagos'!E$7:E$506,B26,'Flujo de Pagos'!B$7:B$506,AG7)) | AH26: =IF(B26="","",SUMIFS('Flujo de Pagos'!I$7:I$506,'Flujo de Pagos'!E$7:E$506,B26,'Flujo de Pagos'!B$7:B$506,AH7)) | AI26: =IF(B26="","",SUMIFS('Flujo de Pagos'!I$7:I$506,'Flujo de Pagos'!E$7:E$506,B26,'Flujo de Pagos'!B$7:B$506,AI7)) | AJ26: =IF(B26="","",SUMIFS('Flujo de Pagos'!I$7:I$506,'Flujo de Pagos'!E$7:E$506,B26,'Flujo de Pagos'!B$7:B$506,AJ7)) | AK26: =IF(B26="","",SUMIFS('Flujo de Pagos'!I$7:I$506,'Flujo de Pagos'!E$7:E$506,B26,'Flujo de Pagos'!B$7:B$506,AK7)) | AL26: =IF(B26="","",SUMIFS('Flujo de Pagos'!I$7:I$506,'Flujo de Pagos'!E$7:E$506,B26,'Flujo de Pagos'!B$7:B$506,AL7)) | AM26: =IF(B26="","",SUM(C26:AL26))
B27: =IF(Presupuesto!B24="","",Presupuesto!B24) | C27: =IF(B27="","",SUMIFS('Flujo de Pagos'!I$7:I$506,'Flujo de Pagos'!E$7:E$506,B27,'Flujo de Pagos'!B$7:B$506,C7)) | D27: =IF(B27="","",SUMIFS('Flujo de Pagos'!I$7:I$506,'Flujo de Pagos'!E$7:E$506,B27,'Flujo de Pagos'!B$7:B$506,D7)) | E27: =IF(B27="","",SUMIFS('Flujo de Pagos'!I$7:I$506,'Flujo de Pagos'!E$7:E$506,B27,'Flujo de Pagos'!B$7:B$506,E7)) | F27: =IF(B27="","",SUMIFS('Flujo de Pagos'!I$7:I$506,'Flujo de Pagos'!E$7:E$506,B27,'Flujo de Pagos'!B$7:B$506,F7)) | G27: =IF(B27="","",SUMIFS('Flujo de Pagos'!I$7:I$506,'Flujo de Pagos'!E$7:E$506,B27,'Flujo de Pagos'!B$7:B$506,G7)) | H27: =IF(B27="","",SUMIFS('Flujo de Pagos'!I$7:I$506,'Flujo de Pagos'!E$7:E$506,B27,'Flujo de Pagos'!B$7:B$506,H7)) | I27: =IF(B27="","",SUMIFS('Flujo de Pagos'!I$7:I$506,'Flujo de Pagos'!E$7:E$506,B27,'Flujo de Pagos'!B$7:B$506,I7)) | J27: =IF(B27="","",SUMIFS('Flujo de Pagos'!I$7:I$506,'Flujo de Pagos'!E$7:E$506,B27,'Flujo de Pagos'!B$7:B$506,J7)) | K27: =IF(B27="","",SUMIFS('Flujo de Pagos'!I$7:I$506,'Flujo de Pagos'!E$7:E$506,B27,'Flujo de Pagos'!B$7:B$506,K7)) | L27: =IF(B27="","",SUMIFS('Flujo de Pagos'!I$7:I$506,'Flujo de Pagos'!E$7:E$506,B27,'Flujo de Pagos'!B$7:B$506,L7)) | M27: =IF(B27="","",SUMIFS('Flujo de Pagos'!I$7:I$506,'Flujo de Pagos'!E$7:E$506,B27,'Flujo de Pagos'!B$7:B$506,M7)) | N27: =IF(B27="","",SUMIFS('Flujo de Pagos'!I$7:I$506,'Flujo de Pagos'!E$7:E$506,B27,'Flujo de Pagos'!B$7:B$506,N7)) | O27: =IF(B27="","",SUMIFS('Flujo de Pagos'!I$7:I$506,'Flujo de Pagos'!E$7:E$506,B27,'Flujo de Pagos'!B$7:B$506,O7)) | P27: =IF(B27="","",SUMIFS('Flujo de Pagos'!I$7:I$506,'Flujo de Pagos'!E$7:E$506,B27,'Flujo de Pagos'!B$7:B$506,P7)) | Q27: =IF(B27="","",SUMIFS('Flujo de Pagos'!I$7:I$506,'Flujo de Pagos'!E$7:E$506,B27,'Flujo de Pagos'!B$7:B$506,Q7)) | R27: =IF(B27="","",SUMIFS('Flujo de Pagos'!I$7:I$506,'Flujo de Pagos'!E$7:E$506,B27,'Flujo de Pagos'!B$7:B$506,R7)) | S27: =IF(B27="","",SUMIFS('Flujo de Pagos'!I$7:I$506,'Flujo de Pagos'!E$7:E$506,B27,'Flujo de Pagos'!B$7:B$506,S7)) | T27: =IF(B27="","",SUMIFS('Flujo de Pagos'!I$7:I$506,'Flujo de Pagos'!E$7:E$506,B27,'Flujo de Pagos'!B$7:B$506,T7)) | U27: =IF(B27="","",SUMIFS('Flujo de Pagos'!I$7:I$506,'Flujo de Pagos'!E$7:E$506,B27,'Flujo de Pagos'!B$7:B$506,U7)) | V27: =IF(B27="","",SUMIFS('Flujo de Pagos'!I$7:I$506,'Flujo de Pagos'!E$7:E$506,B27,'Flujo de Pagos'!B$7:B$506,V7)) | W27: =IF(B27="","",SUMIFS('Flujo de Pagos'!I$7:I$506,'Flujo de Pagos'!E$7:E$506,B27,'Flujo de Pagos'!B$7:B$506,W7)) | X27: =IF(B27="","",SUMIFS('Flujo de Pagos'!I$7:I$506,'Flujo de Pagos'!E$7:E$506,B27,'Flujo de Pagos'!B$7:B$506,X7)) | Y27: =IF(B27="","",SUMIFS('Flujo de Pagos'!I$7:I$506,'Flujo de Pagos'!E$7:E$506,B27,'Flujo de Pagos'!B$7:B$506,Y7)) | Z27: =IF(B27="","",SUMIFS('Flujo de Pagos'!I$7:I$506,'Flujo de Pagos'!E$7:E$506,B27,'Flujo de Pagos'!B$7:B$506,Z7)) | AA27: =IF(B27="","",SUMIFS('Flujo de Pagos'!I$7:I$506,'Flujo de Pagos'!E$7:E$506,B27,'Flujo de Pagos'!B$7:B$506,AA7)) | AB27: =IF(B27="","",SUMIFS('Flujo de Pagos'!I$7:I$506,'Flujo de Pagos'!E$7:E$506,B27,'Flujo de Pagos'!B$7:B$506,AB7)) | AC27: =IF(B27="","",SUMIFS('Flujo de Pagos'!I$7:I$506,'Flujo de Pagos'!E$7:E$506,B27,'Flujo de Pagos'!B$7:B$506,AC7)) | AD27: =IF(B27="","",SUMIFS('Flujo de Pagos'!I$7:I$506,'Flujo de Pagos'!E$7:E$506,B27,'Flujo de Pagos'!B$7:B$506,AD7)) | AE27: =IF(B27="","",SUMIFS('Flujo de Pagos'!I$7:I$506,'Flujo de Pagos'!E$7:E$506,B27,'Flujo de Pagos'!B$7:B$506,AE7)) | AF27: =IF(B27="","",SUMIFS('Flujo de Pagos'!I$7:I$506,'Flujo de Pagos'!E$7:E$506,B27,'Flujo de Pagos'!B$7:B$506,AF7)) | AG27: =IF(B27="","",SUMIFS('Flujo de Pagos'!I$7:I$506,'Flujo de Pagos'!E$7:E$506,B27,'Flujo de Pagos'!B$7:B$506,AG7)) | AH27: =IF(B27="","",SUMIFS('Flujo de Pagos'!I$7:I$506,'Flujo de Pagos'!E$7:E$506,B27,'Flujo de Pagos'!B$7:B$506,AH7)) | AI27: =IF(B27="","",SUMIFS('Flujo de Pagos'!I$7:I$506,'Flujo de Pagos'!E$7:E$506,B27,'Flujo de Pagos'!B$7:B$506,AI7)) | AJ27: =IF(B27="","",SUMIFS('Flujo de Pagos'!I$7:I$506,'Flujo de Pagos'!E$7:E$506,B27,'Flujo de Pagos'!B$7:B$506,AJ7)) | AK27: =IF(B27="","",SUMIFS('Flujo de Pagos'!I$7:I$506,'Flujo de Pagos'!E$7:E$506,B27,'Flujo de Pagos'!B$7:B$506,AK7)) | AL27: =IF(B27="","",SUMIFS('Flujo de Pagos'!I$7:I$506,'Flujo de Pagos'!E$7:E$506,B27,'Flujo de Pagos'!B$7:B$506,AL7)) | AM27: =IF(B27="","",SUM(C27:AL27))
B28: =IF(Presupuesto!B25="","",Presupuesto!B25) | C28: =IF(B28="","",SUMIFS('Flujo de Pagos'!I$7:I$506,'Flujo de Pagos'!E$7:E$506,B28,'Flujo de Pagos'!B$7:B$506,C7)) | D28: =IF(B28="","",SUMIFS('Flujo de Pagos'!I$7:I$506,'Flujo de Pagos'!E$7:E$506,B28,'Flujo de Pagos'!B$7:B$506,D7)) | E28: =IF(B28="","",SUMIFS('Flujo de Pagos'!I$7:I$506,'Flujo de Pagos'!E$7:E$506,B28,'Flujo de Pagos'!B$7:B$506,E7)) | F28: =IF(B28="","",SUMIFS('Flujo de Pagos'!I$7:I$506,'Flujo de Pagos'!E$7:E$506,B28,'Flujo de Pagos'!B$7:B$506,F7)) | G28: =IF(B28="","",SUMIFS('Flujo de Pagos'!I$7:I$506,'Flujo de Pagos'!E$7:E$506,B28,'Flujo de Pagos'!B$7:B$506,G7)) | H28: =IF(B28="","",SUMIFS('Flujo de Pagos'!I$7:I$506,'Flujo de Pagos'!E$7:E$506,B28,'Flujo de Pagos'!B$7:B$506,H7)) | I28: =IF(B28="","",SUMIFS('Flujo de Pagos'!I$7:I$506,'Flujo de Pagos'!E$7:E$506,B28,'Flujo de Pagos'!B$7:B$506,I7)) | J28: =IF(B28="","",SUMIFS('Flujo de Pagos'!I$7:I$506,'Flujo de Pagos'!E$7:E$506,B28,'Flujo de Pagos'!B$7:B$506,J7)) | K28: =IF(B28="","",SUMIFS('Flujo de Pagos'!I$7:I$506,'Flujo de Pagos'!E$7:E$506,B28,'Flujo de Pagos'!B$7:B$506,K7)) | L28: =IF(B28="","",SUMIFS('Flujo de Pagos'!I$7:I$506,'Flujo de Pagos'!E$7:E$506,B28,'Flujo de Pagos'!B$7:B$506,L7)) | M28: =IF(B28="","",SUMIFS('Flujo de Pagos'!I$7:I$506,'Flujo de Pagos'!E$7:E$506,B28,'Flujo de Pagos'!B$7:B$506,M7)) | N28: =IF(B28="","",SUMIFS('Flujo de Pagos'!I$7:I$506,'Flujo de Pagos'!E$7:E$506,B28,'Flujo de Pagos'!B$7:B$506,N7)) | O28: =IF(B28="","",SUMIFS('Flujo de Pagos'!I$7:I$506,'Flujo de Pagos'!E$7:E$506,B28,'Flujo de Pagos'!B$7:B$506,O7)) | P28: =IF(B28="","",SUMIFS('Flujo de Pagos'!I$7:I$506,'Flujo de Pagos'!E$7:E$506,B28,'Flujo de Pagos'!B$7:B$506,P7)) | Q28: =IF(B28="","",SUMIFS('Flujo de Pagos'!I$7:I$506,'Flujo de Pagos'!E$7:E$506,B28,'Flujo de Pagos'!B$7:B$506,Q7)) | R28: =IF(B28="","",SUMIFS('Flujo de Pagos'!I$7:I$506,'Flujo de Pagos'!E$7:E$506,B28,'Flujo de Pagos'!B$7:B$506,R7)) | S28: =IF(B28="","",SUMIFS('Flujo de Pagos'!I$7:I$506,'Flujo de Pagos'!E$7:E$506,B28,'Flujo de Pagos'!B$7:B$506,S7)) | T28: =IF(B28="","",SUMIFS('Flujo de Pagos'!I$7:I$506,'Flujo de Pagos'!E$7:E$506,B28,'Flujo de Pagos'!B$7:B$506,T7)) | U28: =IF(B28="","",SUMIFS('Flujo de Pagos'!I$7:I$506,'Flujo de Pagos'!E$7:E$506,B28,'Flujo de Pagos'!B$7:B$506,U7)) | V28: =IF(B28="","",SUMIFS('Flujo de Pagos'!I$7:I$506,'Flujo de Pagos'!E$7:E$506,B28,'Flujo de Pagos'!B$7:B$506,V7)) | W28: =IF(B28="","",SUMIFS('Flujo de Pagos'!I$7:I$506,'Flujo de Pagos'!E$7:E$506,B28,'Flujo de Pagos'!B$7:B$506,W7)) | X28: =IF(B28="","",SUMIFS('Flujo de Pagos'!I$7:I$506,'Flujo de Pagos'!E$7:E$506,B28,'Flujo de Pagos'!B$7:B$506,X7)) | Y28: =IF(B28="","",SUMIFS('Flujo de Pagos'!I$7:I$506,'Flujo de Pagos'!E$7:E$506,B28,'Flujo de Pagos'!B$7:B$506,Y7)) | Z28: =IF(B28="","",SUMIFS('Flujo de Pagos'!I$7:I$506,'Flujo de Pagos'!E$7:E$506,B28,'Flujo de Pagos'!B$7:B$506,Z7)) | AA28: =IF(B28="","",SUMIFS('Flujo de Pagos'!I$7:I$506,'Flujo de Pagos'!E$7:E$506,B28,'Flujo de Pagos'!B$7:B$506,AA7)) | AB28: =IF(B28="","",SUMIFS('Flujo de Pagos'!I$7:I$506,'Flujo de Pagos'!E$7:E$506,B28,'Flujo de Pagos'!B$7:B$506,AB7)) | AC28: =IF(B28="","",SUMIFS('Flujo de Pagos'!I$7:I$506,'Flujo de Pagos'!E$7:E$506,B28,'Flujo de Pagos'!B$7:B$506,AC7)) | AD28: =IF(B28="","",SUMIFS('Flujo de Pagos'!I$7:I$506,'Flujo de Pagos'!E$7:E$506,B28,'Flujo de Pagos'!B$7:B$506,AD7)) | AE28: =IF(B28="","",SUMIFS('Flujo de Pagos'!I$7:I$506,'Flujo de Pagos'!E$7:E$506,B28,'Flujo de Pagos'!B$7:B$506,AE7)) | AF28: =IF(B28="","",SUMIFS('Flujo de Pagos'!I$7:I$506,'Flujo de Pagos'!E$7:E$506,B28,'Flujo de Pagos'!B$7:B$506,AF7)) | AG28: =IF(B28="","",SUMIFS('Flujo de Pagos'!I$7:I$506,'Flujo de Pagos'!E$7:E$506,B28,'Flujo de Pagos'!B$7:B$506,AG7)) | AH28: =IF(B28="","",SUMIFS('Flujo de Pagos'!I$7:I$506,'Flujo de Pagos'!E$7:E$506,B28,'Flujo de Pagos'!B$7:B$506,AH7)) | AI28: =IF(B28="","",SUMIFS('Flujo de Pagos'!I$7:I$506,'Flujo de Pagos'!E$7:E$506,B28,'Flujo de Pagos'!B$7:B$506,AI7)) | AJ28: =IF(B28="","",SUMIFS('Flujo de Pagos'!I$7:I$506,'Flujo de Pagos'!E$7:E$506,B28,'Flujo de Pagos'!B$7:B$506,AJ7)) | AK28: =IF(B28="","",SUMIFS('Flujo de Pagos'!I$7:I$506,'Flujo de Pagos'!E$7:E$506,B28,'Flujo de Pagos'!B$7:B$506,AK7)) | AL28: =IF(B28="","",SUMIFS('Flujo de Pagos'!I$7:I$506,'Flujo de Pagos'!E$7:E$506,B28,'Flujo de Pagos'!B$7:B$506,AL7)) | AM28: =IF(B28="","",SUM(C28:AL28))
B29: =IF(Presupuesto!B26="","",Presupuesto!B26) | C29: =IF(B29="","",SUMIFS('Flujo de Pagos'!I$7:I$506,'Flujo de Pagos'!E$7:E$506,B29,'Flujo de Pagos'!B$7:B$506,C7)) | D29: =IF(B29="","",SUMIFS('Flujo de Pagos'!I$7:I$506,'Flujo de Pagos'!E$7:E$506,B29,'Flujo de Pagos'!B$7:B$506,D7)) | E29: =IF(B29="","",SUMIFS('Flujo de Pagos'!I$7:I$506,'Flujo de Pagos'!E$7:E$506,B29,'Flujo de Pagos'!B$7:B$506,E7)) | F29: =IF(B29="","",SUMIFS('Flujo de Pagos'!I$7:I$506,'Flujo de Pagos'!E$7:E$506,B29,'Flujo de Pagos'!B$7:B$506,F7)) | G29: =IF(B29="","",SUMIFS('Flujo de Pagos'!I$7:I$506,'Flujo de Pagos'!E$7:E$506,B29,'Flujo de Pagos'!B$7:B$506,G7)) | H29: =IF(B29="","",SUMIFS('Flujo de Pagos'!I$7:I$506,'Flujo de Pagos'!E$7:E$506,B29,'Flujo de Pagos'!B$7:B$506,H7)) | I29: =IF(B29="","",SUMIFS('Flujo de Pagos'!I$7:I$506,'Flujo de Pagos'!E$7:E$506,B29,'Flujo de Pagos'!B$7:B$506,I7)) | J29: =IF(B29="","",SUMIFS('Flujo de Pagos'!I$7:I$506,'Flujo de Pagos'!E$7:E$506,B29,'Flujo de Pagos'!B$7:B$506,J7)) | K29: =IF(B29="","",SUMIFS('Flujo de Pagos'!I$7:I$506,'Flujo de Pagos'!E$7:E$506,B29,'Flujo de Pagos'!B$7:B$506,K7)) | L29: =IF(B29="","",SUMIFS('Flujo de Pagos'!I$7:I$506,'Flujo de Pagos'!E$7:E$506,B29,'Flujo de Pagos'!B$7:B$506,L7)) | M29: =IF(B29="","",SUMIFS('Flujo de Pagos'!I$7:I$506,'Flujo de Pagos'!E$7:E$506,B29,'Flujo de Pagos'!B$7:B$506,M7)) | N29: =IF(B29="","",SUMIFS('Flujo de Pagos'!I$7:I$506,'Flujo de Pagos'!E$7:E$506,B29,'Flujo de Pagos'!B$7:B$506,N7)) | O29: =IF(B29="","",SUMIFS('Flujo de Pagos'!I$7:I$506,'Flujo de Pagos'!E$7:E$506,B29,'Flujo de Pagos'!B$7:B$506,O7)) | P29: =IF(B29="","",SUMIFS('Flujo de Pagos'!I$7:I$506,'Flujo de Pagos'!E$7:E$506,B29,'Flujo de Pagos'!B$7:B$506,P7)) | Q29: =IF(B29="","",SUMIFS('Flujo de Pagos'!I$7:I$506,'Flujo de Pagos'!E$7:E$506,B29,'Flujo de Pagos'!B$7:B$506,Q7)) | R29: =IF(B29="","",SUMIFS('Flujo de Pagos'!I$7:I$506,'Flujo de Pagos'!E$7:E$506,B29,'Flujo de Pagos'!B$7:B$506,R7)) | S29: =IF(B29="","",SUMIFS('Flujo de Pagos'!I$7:I$506,'Flujo de Pagos'!E$7:E$506,B29,'Flujo de Pagos'!B$7:B$506,S7)) | T29: =IF(B29="","",SUMIFS('Flujo de Pagos'!I$7:I$506,'Flujo de Pagos'!E$7:E$506,B29,'Flujo de Pagos'!B$7:B$506,T7)) | U29: =IF(B29="","",SUMIFS('Flujo de Pagos'!I$7:I$506,'Flujo de Pagos'!E$7:E$506,B29,'Flujo de Pagos'!B$7:B$506,U7)) | V29: =IF(B29="","",SUMIFS('Flujo de Pagos'!I$7:I$506,'Flujo de Pagos'!E$7:E$506,B29,'Flujo de Pagos'!B$7:B$506,V7)) | W29: =IF(B29="","",SUMIFS('Flujo de Pagos'!I$7:I$506,'Flujo de Pagos'!E$7:E$506,B29,'Flujo de Pagos'!B$7:B$506,W7)) | X29: =IF(B29="","",SUMIFS('Flujo de Pagos'!I$7:I$506,'Flujo de Pagos'!E$7:E$506,B29,'Flujo de Pagos'!B$7:B$506,X7)) | Y29: =IF(B29="","",SUMIFS('Flujo de Pagos'!I$7:I$506,'Flujo de Pagos'!E$7:E$506,B29,'Flujo de Pagos'!B$7:B$506,Y7)) | Z29: =IF(B29="","",SUMIFS('Flujo de Pagos'!I$7:I$506,'Flujo de Pagos'!E$7:E$506,B29,'Flujo de Pagos'!B$7:B$506,Z7)) | AA29: =IF(B29="","",SUMIFS('Flujo de Pagos'!I$7:I$506,'Flujo de Pagos'!E$7:E$506,B29,'Flujo de Pagos'!B$7:B$506,AA7)) | AB29: =IF(B29="","",SUMIFS('Flujo de Pagos'!I$7:I$506,'Flujo de Pagos'!E$7:E$506,B29,'Flujo de Pagos'!B$7:B$506,AB7)) | AC29: =IF(B29="","",SUMIFS('Flujo de Pagos'!I$7:I$506,'Flujo de Pagos'!E$7:E$506,B29,'Flujo de Pagos'!B$7:B$506,AC7)) | AD29: =IF(B29="","",SUMIFS('Flujo de Pagos'!I$7:I$506,'Flujo de Pagos'!E$7:E$506,B29,'Flujo de Pagos'!B$7:B$506,AD7)) | AE29: =IF(B29="","",SUMIFS('Flujo de Pagos'!I$7:I$506,'Flujo de Pagos'!E$7:E$506,B29,'Flujo de Pagos'!B$7:B$506,AE7)) | AF29: =IF(B29="","",SUMIFS('Flujo de Pagos'!I$7:I$506,'Flujo de Pagos'!E$7:E$506,B29,'Flujo de Pagos'!B$7:B$506,AF7)) | AG29: =IF(B29="","",SUMIFS('Flujo de Pagos'!I$7:I$506,'Flujo de Pagos'!E$7:E$506,B29,'Flujo de Pagos'!B$7:B$506,AG7)) | AH29: =IF(B29="","",SUMIFS('Flujo de Pagos'!I$7:I$506,'Flujo de Pagos'!E$7:E$506,B29,'Flujo de Pagos'!B$7:B$506,AH7)) | AI29: =IF(B29="","",SUMIFS('Flujo de Pagos'!I$7:I$506,'Flujo de Pagos'!E$7:E$506,B29,'Flujo de Pagos'!B$7:B$506,AI7)) | AJ29: =IF(B29="","",SUMIFS('Flujo de Pagos'!I$7:I$506,'Flujo de Pagos'!E$7:E$506,B29,'Flujo de Pagos'!B$7:B$506,AJ7)) | AK29: =IF(B29="","",SUMIFS('Flujo de Pagos'!I$7:I$506,'Flujo de Pagos'!E$7:E$506,B29,'Flujo de Pagos'!B$7:B$506,AK7)) | AL29: =IF(B29="","",SUMIFS('Flujo de Pagos'!I$7:I$506,'Flujo de Pagos'!E$7:E$506,B29,'Flujo de Pagos'!B$7:B$506,AL7)) | AM29: =IF(B29="","",SUM(C29:AL29))
B30: =IF(Presupuesto!B27="","",Presupuesto!B27) | C30: =IF(B30="","",SUMIFS('Flujo de Pagos'!I$7:I$506,'Flujo de Pagos'!E$7:E$506,B30,'Flujo de Pagos'!B$7:B$506,C7)) | D30: =IF(B30="","",SUMIFS('Flujo de Pagos'!I$7:I$506,'Flujo de Pagos'!E$7:E$506,B30,'Flujo de Pagos'!B$7:B$506,D7)) | E30: =IF(B30="","",SUMIFS('Flujo de Pagos'!I$7:I$506,'Flujo de Pagos'!E$7:E$506,B30,'Flujo de Pagos'!B$7:B$506,E7)) | F30: =IF(B30="","",SUMIFS('Flujo de Pagos'!I$7:I$506,'Flujo de Pagos'!E$7:E$506,B30,'Flujo de Pagos'!B$7:B$506,F7)) | G30: =IF(B30="","",SUMIFS('Flujo de Pagos'!I$7:I$506,'Flujo de Pagos'!E$7:E$506,B30,'Flujo de Pagos'!B$7:B$506,G7)) | H30: =IF(B30="","",SUMIFS('Flujo de Pagos'!I$7:I$506,'Flujo de Pagos'!E$7:E$506,B30,'Flujo de Pagos'!B$7:B$506,H7)) | I30: =IF(B30="","",SUMIFS('Flujo de Pagos'!I$7:I$506,'Flujo de Pagos'!E$7:E$506,B30,'Flujo de Pagos'!B$7:B$506,I7)) | J30: =IF(B30="","",SUMIFS('Flujo de Pagos'!I$7:I$506,'Flujo de Pagos'!E$7:E$506,B30,'Flujo de Pagos'!B$7:B$506,J7)) | K30: =IF(B30="","",SUMIFS('Flujo de Pagos'!I$7:I$506,'Flujo de Pagos'!E$7:E$506,B30,'Flujo de Pagos'!B$7:B$506,K7)) | L30: =IF(B30="","",SUMIFS('Flujo de Pagos'!I$7:I$506,'Flujo de Pagos'!E$7:E$506,B30,'Flujo de Pagos'!B$7:B$506,L7)) | M30: =IF(B30="","",SUMIFS('Flujo de Pagos'!I$7:I$506,'Flujo de Pagos'!E$7:E$506,B30,'Flujo de Pagos'!B$7:B$506,M7)) | N30: =IF(B30="","",SUMIFS('Flujo de Pagos'!I$7:I$506,'Flujo de Pagos'!E$7:E$506,B30,'Flujo de Pagos'!B$7:B$506,N7)) | O30: =IF(B30="","",SUMIFS('Flujo de Pagos'!I$7:I$506,'Flujo de Pagos'!E$7:E$506,B30,'Flujo de Pagos'!B$7:B$506,O7)) | P30: =IF(B30="","",SUMIFS('Flujo de Pagos'!I$7:I$506,'Flujo de Pagos'!E$7:E$506,B30,'Flujo de Pagos'!B$7:B$506,P7)) | Q30: =IF(B30="","",SUMIFS('Flujo de Pagos'!I$7:I$506,'Flujo de Pagos'!E$7:E$506,B30,'Flujo de Pagos'!B$7:B$506,Q7)) | R30: =IF(B30="","",SUMIFS('Flujo de Pagos'!I$7:I$506,'Flujo de Pagos'!E$7:E$506,B30,'Flujo de Pagos'!B$7:B$506,R7)) | S30: =IF(B30="","",SUMIFS('Flujo de Pagos'!I$7:I$506,'Flujo de Pagos'!E$7:E$506,B30,'Flujo de Pagos'!B$7:B$506,S7)) | T30: =IF(B30="","",SUMIFS('Flujo de Pagos'!I$7:I$506,'Flujo de Pagos'!E$7:E$506,B30,'Flujo de Pagos'!B$7:B$506,T7)) | U30: =IF(B30="","",SUMIFS('Flujo de Pagos'!I$7:I$506,'Flujo de Pagos'!E$7:E$506,B30,'Flujo de Pagos'!B$7:B$506,U7)) | V30: =IF(B30="","",SUMIFS('Flujo de Pagos'!I$7:I$506,'Flujo de Pagos'!E$7:E$506,B30,'Flujo de Pagos'!B$7:B$506,V7)) | W30: =IF(B30="","",SUMIFS('Flujo de Pagos'!I$7:I$506,'Flujo de Pagos'!E$7:E$506,B30,'Flujo de Pagos'!B$7:B$506,W7)) | X30: =IF(B30="","",SUMIFS('Flujo de Pagos'!I$7:I$506,'Flujo de Pagos'!E$7:E$506,B30,'Flujo de Pagos'!B$7:B$506,X7)) | Y30: =IF(B30="","",SUMIFS('Flujo de Pagos'!I$7:I$506,'Flujo de Pagos'!E$7:E$506,B30,'Flujo de Pagos'!B$7:B$506,Y7)) | Z30: =IF(B30="","",SUMIFS('Flujo de Pagos'!I$7:I$506,'Flujo de Pagos'!E$7:E$506,B30,'Flujo de Pagos'!B$7:B$506,Z7)) | AA30: =IF(B30="","",SUMIFS('Flujo de Pagos'!I$7:I$506,'Flujo de Pagos'!E$7:E$506,B30,'Flujo de Pagos'!B$7:B$506,AA7)) | AB30: =IF(B30="","",SUMIFS('Flujo de Pagos'!I$7:I$506,'Flujo de Pagos'!E$7:E$506,B30,'Flujo de Pagos'!B$7:B$506,AB7)) | AC30: =IF(B30="","",SUMIFS('Flujo de Pagos'!I$7:I$506,'Flujo de Pagos'!E$7:E$506,B30,'Flujo de Pagos'!B$7:B$506,AC7)) | AD30: =IF(B30="","",SUMIFS('Flujo de Pagos'!I$7:I$506,'Flujo de Pagos'!E$7:E$506,B30,'Flujo de Pagos'!B$7:B$506,AD7)) | AE30: =IF(B30="","",SUMIFS('Flujo de Pagos'!I$7:I$506,'Flujo de Pagos'!E$7:E$506,B30,'Flujo de Pagos'!B$7:B$506,AE7)) | AF30: =IF(B30="","",SUMIFS('Flujo de Pagos'!I$7:I$506,'Flujo de Pagos'!E$7:E$506,B30,'Flujo de Pagos'!B$7:B$506,AF7)) | AG30: =IF(B30="","",SUMIFS('Flujo de Pagos'!I$7:I$506,'Flujo de Pagos'!E$7:E$506,B30,'Flujo de Pagos'!B$7:B$506,AG7)) | AH30: =IF(B30="","",SUMIFS('Flujo de Pagos'!I$7:I$506,'Flujo de Pagos'!E$7:E$506,B30,'Flujo de Pagos'!B$7:B$506,AH7)) | AI30: =IF(B30="","",SUMIFS('Flujo de Pagos'!I$7:I$506,'Flujo de Pagos'!E$7:E$506,B30,'Flujo de Pagos'!B$7:B$506,AI7)) | AJ30: =IF(B30="","",SUMIFS('Flujo de Pagos'!I$7:I$506,'Flujo de Pagos'!E$7:E$506,B30,'Flujo de Pagos'!B$7:B$506,AJ7)) | AK30: =IF(B30="","",SUMIFS('Flujo de Pagos'!I$7:I$506,'Flujo de Pagos'!E$7:E$506,B30,'Flujo de Pagos'!B$7:B$506,AK7)) | AL30: =IF(B30="","",SUMIFS('Flujo de Pagos'!I$7:I$506,'Flujo de Pagos'!E$7:E$506,B30,'Flujo de Pagos'!B$7:B$506,AL7)) | AM30: =IF(B30="","",SUM(C30:AL30))
B31: =IF(Presupuesto!B28="","",Presupuesto!B28) | C31: =IF(B31="","",SUMIFS('Flujo de Pagos'!I$7:I$506,'Flujo de Pagos'!E$7:E$506,B31,'Flujo de Pagos'!B$7:B$506,C7)) | D31: =IF(B31="","",SUMIFS('Flujo de Pagos'!I$7:I$506,'Flujo de Pagos'!E$7:E$506,B31,'Flujo de Pagos'!B$7:B$506,D7)) | E31: =IF(B31="","",SUMIFS('Flujo de Pagos'!I$7:I$506,'Flujo de Pagos'!E$7:E$506,B31,'Flujo de Pagos'!B$7:B$506,E7)) | F31: =IF(B31="","",SUMIFS('Flujo de Pagos'!I$7:I$506,'Flujo de Pagos'!E$7:E$506,B31,'Flujo de Pagos'!B$7:B$506,F7)) | G31: =IF(B31="","",SUMIFS('Flujo de Pagos'!I$7:I$506,'Flujo de Pagos'!E$7:E$506,B31,'Flujo de Pagos'!B$7:B$506,G7)) | H31: =IF(B31="","",SUMIFS('Flujo de Pagos'!I$7:I$506,'Flujo de Pagos'!E$7:E$506,B31,'Flujo de Pagos'!B$7:B$506,H7)) | I31: =IF(B31="","",SUMIFS('Flujo de Pagos'!I$7:I$506,'Flujo de Pagos'!E$7:E$506,B31,'Flujo de Pagos'!B$7:B$506,I7)) | J31: =IF(B31="","",SUMIFS('Flujo de Pagos'!I$7:I$506,'Flujo de Pagos'!E$7:E$506,B31,'Flujo de Pagos'!B$7:B$506,J7)) | K31: =IF(B31="","",SUMIFS('Flujo de Pagos'!I$7:I$506,'Flujo de Pagos'!E$7:E$506,B31,'Flujo de Pagos'!B$7:B$506,K7)) | L31: =IF(B31="","",SUMIFS('Flujo de Pagos'!I$7:I$506,'Flujo de Pagos'!E$7:E$506,B31,'Flujo de Pagos'!B$7:B$506,L7)) | M31: =IF(B31="","",SUMIFS('Flujo de Pagos'!I$7:I$506,'Flujo de Pagos'!E$7:E$506,B31,'Flujo de Pagos'!B$7:B$506,M7)) | N31: =IF(B31="","",SUMIFS('Flujo de Pagos'!I$7:I$506,'Flujo de Pagos'!E$7:E$506,B31,'Flujo de Pagos'!B$7:B$506,N7)) | O31: =IF(B31="","",SUMIFS('Flujo de Pagos'!I$7:I$506,'Flujo de Pagos'!E$7:E$506,B31,'Flujo de Pagos'!B$7:B$506,O7)) | P31: =IF(B31="","",SUMIFS('Flujo de Pagos'!I$7:I$506,'Flujo de Pagos'!E$7:E$506,B31,'Flujo de Pagos'!B$7:B$506,P7)) | Q31: =IF(B31="","",SUMIFS('Flujo de Pagos'!I$7:I$506,'Flujo de Pagos'!E$7:E$506,B31,'Flujo de Pagos'!B$7:B$506,Q7)) | R31: =IF(B31="","",SUMIFS('Flujo de Pagos'!I$7:I$506,'Flujo de Pagos'!E$7:E$506,B31,'Flujo de Pagos'!B$7:B$506,R7)) | S31: =IF(B31="","",SUMIFS('Flujo de Pagos'!I$7:I$506,'Flujo de Pagos'!E$7:E$506,B31,'Flujo de Pagos'!B$7:B$506,S7)) | T31: =IF(B31="","",SUMIFS('Flujo de Pagos'!I$7:I$506,'Flujo de Pagos'!E$7:E$506,B31,'Flujo de Pagos'!B$7:B$506,T7)) | U31: =IF(B31="","",SUMIFS('Flujo de Pagos'!I$7:I$506,'Flujo de Pagos'!E$7:E$506,B31,'Flujo de Pagos'!B$7:B$506,U7)) | V31: =IF(B31="","",SUMIFS('Flujo de Pagos'!I$7:I$506,'Flujo de Pagos'!E$7:E$506,B31,'Flujo de Pagos'!B$7:B$506,V7)) | W31: =IF(B31="","",SUMIFS('Flujo de Pagos'!I$7:I$506,'Flujo de Pagos'!E$7:E$506,B31,'Flujo de Pagos'!B$7:B$506,W7)) | X31: =IF(B31="","",SUMIFS('Flujo de Pagos'!I$7:I$506,'Flujo de Pagos'!E$7:E$506,B31,'Flujo de Pagos'!B$7:B$506,X7)) | Y31: =IF(B31="","",SUMIFS('Flujo de Pagos'!I$7:I$506,'Flujo de Pagos'!E$7:E$506,B31,'Flujo de Pagos'!B$7:B$506,Y7)) | Z31: =IF(B31="","",SUMIFS('Flujo de Pagos'!I$7:I$506,'Flujo de Pagos'!E$7:E$506,B31,'Flujo de Pagos'!B$7:B$506,Z7)) | AA31: =IF(B31="","",SUMIFS('Flujo de Pagos'!I$7:I$506,'Flujo de Pagos'!E$7:E$506,B31,'Flujo de Pagos'!B$7:B$506,AA7)) | AB31: =IF(B31="","",SUMIFS('Flujo de Pagos'!I$7:I$506,'Flujo de Pagos'!E$7:E$506,B31,'Flujo de Pagos'!B$7:B$506,AB7)) | AC31: =IF(B31="","",SUMIFS('Flujo de Pagos'!I$7:I$506,'Flujo de Pagos'!E$7:E$506,B31,'Flujo de Pagos'!B$7:B$506,AC7)) | AD31: =IF(B31="","",SUMIFS('Flujo de Pagos'!I$7:I$506,'Flujo de Pagos'!E$7:E$506,B31,'Flujo de Pagos'!B$7:B$506,AD7)) | AE31: =IF(B31="","",SUMIFS('Flujo de Pagos'!I$7:I$506,'Flujo de Pagos'!E$7:E$506,B31,'Flujo de Pagos'!B$7:B$506,AE7)) | AF31: =IF(B31="","",SUMIFS('Flujo de Pagos'!I$7:I$506,'Flujo de Pagos'!E$7:E$506,B31,'Flujo de Pagos'!B$7:B$506,AF7)) | AG31: =IF(B31="","",SUMIFS('Flujo de Pagos'!I$7:I$506,'Flujo de Pagos'!E$7:E$506,B31,'Flujo de Pagos'!B$7:B$506,AG7)) | AH31: =IF(B31="","",SUMIFS('Flujo de Pagos'!I$7:I$506,'Flujo de Pagos'!E$7:E$506,B31,'Flujo de Pagos'!B$7:B$506,AH7)) | AI31: =IF(B31="","",SUMIFS('Flujo de Pagos'!I$7:I$506,'Flujo de Pagos'!E$7:E$506,B31,'Flujo de Pagos'!B$7:B$506,AI7)) | AJ31: =IF(B31="","",SUMIFS('Flujo de Pagos'!I$7:I$506,'Flujo de Pagos'!E$7:E$506,B31,'Flujo de Pagos'!B$7:B$506,AJ7)) | AK31: =IF(B31="","",SUMIFS('Flujo de Pagos'!I$7:I$506,'Flujo de Pagos'!E$7:E$506,B31,'Flujo de Pagos'!B$7:B$506,AK7)) | AL31: =IF(B31="","",SUMIFS('Flujo de Pagos'!I$7:I$506,'Flujo de Pagos'!E$7:E$506,B31,'Flujo de Pagos'!B$7:B$506,AL7)) | AM31: =IF(B31="","",SUM(C31:AL31))
B32: =IF(Presupuesto!B29="","",Presupuesto!B29) | C32: =IF(B32="","",SUMIFS('Flujo de Pagos'!I$7:I$506,'Flujo de Pagos'!E$7:E$506,B32,'Flujo de Pagos'!B$7:B$506,C7)) | D32: =IF(B32="","",SUMIFS('Flujo de Pagos'!I$7:I$506,'Flujo de Pagos'!E$7:E$506,B32,'Flujo de Pagos'!B$7:B$506,D7)) | E32: =IF(B32="","",SUMIFS('Flujo de Pagos'!I$7:I$506,'Flujo de Pagos'!E$7:E$506,B32,'Flujo de Pagos'!B$7:B$506,E7)) | F32: =IF(B32="","",SUMIFS('Flujo de Pagos'!I$7:I$506,'Flujo de Pagos'!E$7:E$506,B32,'Flujo de Pagos'!B$7:B$506,F7)) | G32: =IF(B32="","",SUMIFS('Flujo de Pagos'!I$7:I$506,'Flujo de Pagos'!E$7:E$506,B32,'Flujo de Pagos'!B$7:B$506,G7)) | H32: =IF(B32="","",SUMIFS('Flujo de Pagos'!I$7:I$506,'Flujo de Pagos'!E$7:E$506,B32,'Flujo de Pagos'!B$7:B$506,H7)) | I32: =IF(B32="","",SUMIFS('Flujo de Pagos'!I$7:I$506,'Flujo de Pagos'!E$7:E$506,B32,'Flujo de Pagos'!B$7:B$506,I7)) | J32: =IF(B32="","",SUMIFS('Flujo de Pagos'!I$7:I$506,'Flujo de Pagos'!E$7:E$506,B32,'Flujo de Pagos'!B$7:B$506,J7)) | K32: =IF(B32="","",SUMIFS('Flujo de Pagos'!I$7:I$506,'Flujo de Pagos'!E$7:E$506,B32,'Flujo de Pagos'!B$7:B$506,K7)) | L32: =IF(B32="","",SUMIFS('Flujo de Pagos'!I$7:I$506,'Flujo de Pagos'!E$7:E$506,B32,'Flujo de Pagos'!B$7:B$506,L7)) | M32: =IF(B32="","",SUMIFS('Flujo de Pagos'!I$7:I$506,'Flujo de Pagos'!E$7:E$506,B32,'Flujo de Pagos'!B$7:B$506,M7)) | N32: =IF(B32="","",SUMIFS('Flujo de Pagos'!I$7:I$506,'Flujo de Pagos'!E$7:E$506,B32,'Flujo de Pagos'!B$7:B$506,N7)) | O32: =IF(B32="","",SUMIFS('Flujo de Pagos'!I$7:I$506,'Flujo de Pagos'!E$7:E$506,B32,'Flujo de Pagos'!B$7:B$506,O7)) | P32: =IF(B32="","",SUMIFS('Flujo de Pagos'!I$7:I$506,'Flujo de Pagos'!E$7:E$506,B32,'Flujo de Pagos'!B$7:B$506,P7)) | Q32: =IF(B32="","",SUMIFS('Flujo de Pagos'!I$7:I$506,'Flujo de Pagos'!E$7:E$506,B32,'Flujo de Pagos'!B$7:B$506,Q7)) | R32: =IF(B32="","",SUMIFS('Flujo de Pagos'!I$7:I$506,'Flujo de Pagos'!E$7:E$506,B32,'Flujo de Pagos'!B$7:B$506,R7)) | S32: =IF(B32="","",SUMIFS('Flujo de Pagos'!I$7:I$506,'Flujo de Pagos'!E$7:E$506,B32,'Flujo de Pagos'!B$7:B$506,S7)) | T32: =IF(B32="","",SUMIFS('Flujo de Pagos'!I$7:I$506,'Flujo de Pagos'!E$7:E$506,B32,'Flujo de Pagos'!B$7:B$506,T7)) | U32: =IF(B32="","",SUMIFS('Flujo de Pagos'!I$7:I$506,'Flujo de Pagos'!E$7:E$506,B32,'Flujo de Pagos'!B$7:B$506,U7)) | V32: =IF(B32="","",SUMIFS('Flujo de Pagos'!I$7:I$506,'Flujo de Pagos'!E$7:E$506,B32,'Flujo de Pagos'!B$7:B$506,V7)) | W32: =IF(B32="","",SUMIFS('Flujo de Pagos'!I$7:I$506,'Flujo de Pagos'!E$7:E$506,B32,'Flujo de Pagos'!B$7:B$506,W7)) | X32: =IF(B32="","",SUMIFS('Flujo de Pagos'!I$7:I$506,'Flujo de Pagos'!E$7:E$506,B32,'Flujo de Pagos'!B$7:B$506,X7)) | Y32: =IF(B32="","",SUMIFS('Flujo de Pagos'!I$7:I$506,'Flujo de Pagos'!E$7:E$506,B32,'Flujo de Pagos'!B$7:B$506,Y7)) | Z32: =IF(B32="","",SUMIFS('Flujo de Pagos'!I$7:I$506,'Flujo de Pagos'!E$7:E$506,B32,'Flujo de Pagos'!B$7:B$506,Z7)) | AA32: =IF(B32="","",SUMIFS('Flujo de Pagos'!I$7:I$506,'Flujo de Pagos'!E$7:E$506,B32,'Flujo de Pagos'!B$7:B$506,AA7)) | AB32: =IF(B32="","",SUMIFS('Flujo de Pagos'!I$7:I$506,'Flujo de Pagos'!E$7:E$506,B32,'Flujo de Pagos'!B$7:B$506,AB7)) | AC32: =IF(B32="","",SUMIFS('Flujo de Pagos'!I$7:I$506,'Flujo de Pagos'!E$7:E$506,B32,'Flujo de Pagos'!B$7:B$506,AC7)) | AD32: =IF(B32="","",SUMIFS('Flujo de Pagos'!I$7:I$506,'Flujo de Pagos'!E$7:E$506,B32,'Flujo de Pagos'!B$7:B$506,AD7)) | AE32: =IF(B32="","",SUMIFS('Flujo de Pagos'!I$7:I$506,'Flujo de Pagos'!E$7:E$506,B32,'Flujo de Pagos'!B$7:B$506,AE7)) | AF32: =IF(B32="","",SUMIFS('Flujo de Pagos'!I$7:I$506,'Flujo de Pagos'!E$7:E$506,B32,'Flujo de Pagos'!B$7:B$506,AF7)) | AG32: =IF(B32="","",SUMIFS('Flujo de Pagos'!I$7:I$506,'Flujo de Pagos'!E$7:E$506,B32,'Flujo de Pagos'!B$7:B$506,AG7)) | AH32: =IF(B32="","",SUMIFS('Flujo de Pagos'!I$7:I$506,'Flujo de Pagos'!E$7:E$506,B32,'Flujo de Pagos'!B$7:B$506,AH7)) | AI32: =IF(B32="","",SUMIFS('Flujo de Pagos'!I$7:I$506,'Flujo de Pagos'!E$7:E$506,B32,'Flujo de Pagos'!B$7:B$506,AI7)) | AJ32: =IF(B32="","",SUMIFS('Flujo de Pagos'!I$7:I$506,'Flujo de Pagos'!E$7:E$506,B32,'Flujo de Pagos'!B$7:B$506,AJ7)) | AK32: =IF(B32="","",SUMIFS('Flujo de Pagos'!I$7:I$506,'Flujo de Pagos'!E$7:E$506,B32,'Flujo de Pagos'!B$7:B$506,AK7)) | AL32: =IF(B32="","",SUMIFS('Flujo de Pagos'!I$7:I$506,'Flujo de Pagos'!E$7:E$506,B32,'Flujo de Pagos'!B$7:B$506,AL7)) | AM32: =IF(B32="","",SUM(C32:AL32))
B33: =IF(Presupuesto!B30="","",Presupuesto!B30) | C33: =IF(B33="","",SUMIFS('Flujo de Pagos'!I$7:I$506,'Flujo de Pagos'!E$7:E$506,B33,'Flujo de Pagos'!B$7:B$506,C7)) | D33: =IF(B33="","",SUMIFS('Flujo de Pagos'!I$7:I$506,'Flujo de Pagos'!E$7:E$506,B33,'Flujo de Pagos'!B$7:B$506,D7)) | E33: =IF(B33="","",SUMIFS('Flujo de Pagos'!I$7:I$506,'Flujo de Pagos'!E$7:E$506,B33,'Flujo de Pagos'!B$7:B$506,E7)) | F33: =IF(B33="","",SUMIFS('Flujo de Pagos'!I$7:I$506,'Flujo de Pagos'!E$7:E$506,B33,'Flujo de Pagos'!B$7:B$506,F7)) | G33: =IF(B33="","",SUMIFS('Flujo de Pagos'!I$7:I$506,'Flujo de Pagos'!E$7:E$506,B33,'Flujo de Pagos'!B$7:B$506,G7)) | H33: =IF(B33="","",SUMIFS('Flujo de Pagos'!I$7:I$506,'Flujo de Pagos'!E$7:E$506,B33,'Flujo de Pagos'!B$7:B$506,H7)) | I33: =IF(B33="","",SUMIFS('Flujo de Pagos'!I$7:I$506,'Flujo de Pagos'!E$7:E$506,B33,'Flujo de Pagos'!B$7:B$506,I7)) | J33: =IF(B33="","",SUMIFS('Flujo de Pagos'!I$7:I$506,'Flujo de Pagos'!E$7:E$506,B33,'Flujo de Pagos'!B$7:B$506,J7)) | K33: =IF(B33="","",SUMIFS('Flujo de Pagos'!I$7:I$506,'Flujo de Pagos'!E$7:E$506,B33,'Flujo de Pagos'!B$7:B$506,K7)) | L33: =IF(B33="","",SUMIFS('Flujo de Pagos'!I$7:I$506,'Flujo de Pagos'!E$7:E$506,B33,'Flujo de Pagos'!B$7:B$506,L7)) | M33: =IF(B33="","",SUMIFS('Flujo de Pagos'!I$7:I$506,'Flujo de Pagos'!E$7:E$506,B33,'Flujo de Pagos'!B$7:B$506,M7)) | N33: =IF(B33="","",SUMIFS('Flujo de Pagos'!I$7:I$506,'Flujo de Pagos'!E$7:E$506,B33,'Flujo de Pagos'!B$7:B$506,N7)) | O33: =IF(B33="","",SUMIFS('Flujo de Pagos'!I$7:I$506,'Flujo de Pagos'!E$7:E$506,B33,'Flujo de Pagos'!B$7:B$506,O7)) | P33: =IF(B33="","",SUMIFS('Flujo de Pagos'!I$7:I$506,'Flujo de Pagos'!E$7:E$506,B33,'Flujo de Pagos'!B$7:B$506,P7)) | Q33: =IF(B33="","",SUMIFS('Flujo de Pagos'!I$7:I$506,'Flujo de Pagos'!E$7:E$506,B33,'Flujo de Pagos'!B$7:B$506,Q7)) | R33: =IF(B33="","",SUMIFS('Flujo de Pagos'!I$7:I$506,'Flujo de Pagos'!E$7:E$506,B33,'Flujo de Pagos'!B$7:B$506,R7)) | S33: =IF(B33="","",SUMIFS('Flujo de Pagos'!I$7:I$506,'Flujo de Pagos'!E$7:E$506,B33,'Flujo de Pagos'!B$7:B$506,S7)) | T33: =IF(B33="","",SUMIFS('Flujo de Pagos'!I$7:I$506,'Flujo de Pagos'!E$7:E$506,B33,'Flujo de Pagos'!B$7:B$506,T7)) | U33: =IF(B33="","",SUMIFS('Flujo de Pagos'!I$7:I$506,'Flujo de Pagos'!E$7:E$506,B33,'Flujo de Pagos'!B$7:B$506,U7)) | V33: =IF(B33="","",SUMIFS('Flujo de Pagos'!I$7:I$506,'Flujo de Pagos'!E$7:E$506,B33,'Flujo de Pagos'!B$7:B$506,V7)) | W33: =IF(B33="","",SUMIFS('Flujo de Pagos'!I$7:I$506,'Flujo de Pagos'!E$7:E$506,B33,'Flujo de Pagos'!B$7:B$506,W7)) | X33: =IF(B33="","",SUMIFS('Flujo de Pagos'!I$7:I$506,'Flujo de Pagos'!E$7:E$506,B33,'Flujo de Pagos'!B$7:B$506,X7)) | Y33: =IF(B33="","",SUMIFS('Flujo de Pagos'!I$7:I$506,'Flujo de Pagos'!E$7:E$506,B33,'Flujo de Pagos'!B$7:B$506,Y7)) | Z33: =IF(B33="","",SUMIFS('Flujo de Pagos'!I$7:I$506,'Flujo de Pagos'!E$7:E$506,B33,'Flujo de Pagos'!B$7:B$506,Z7)) | AA33: =IF(B33="","",SUMIFS('Flujo de Pagos'!I$7:I$506,'Flujo de Pagos'!E$7:E$506,B33,'Flujo de Pagos'!B$7:B$506,AA7)) | AB33: =IF(B33="","",SUMIFS('Flujo de Pagos'!I$7:I$506,'Flujo de Pagos'!E$7:E$506,B33,'Flujo de Pagos'!B$7:B$506,AB7)) | AC33: =IF(B33="","",SUMIFS('Flujo de Pagos'!I$7:I$506,'Flujo de Pagos'!E$7:E$506,B33,'Flujo de Pagos'!B$7:B$506,AC7)) | AD33: =IF(B33="","",SUMIFS('Flujo de Pagos'!I$7:I$506,'Flujo de Pagos'!E$7:E$506,B33,'Flujo de Pagos'!B$7:B$506,AD7)) | AE33: =IF(B33="","",SUMIFS('Flujo de Pagos'!I$7:I$506,'Flujo de Pagos'!E$7:E$506,B33,'Flujo de Pagos'!B$7:B$506,AE7)) | AF33: =IF(B33="","",SUMIFS('Flujo de Pagos'!I$7:I$506,'Flujo de Pagos'!E$7:E$506,B33,'Flujo de Pagos'!B$7:B$506,AF7)) | AG33: =IF(B33="","",SUMIFS('Flujo de Pagos'!I$7:I$506,'Flujo de Pagos'!E$7:E$506,B33,'Flujo de Pagos'!B$7:B$506,AG7)) | AH33: =IF(B33="","",SUMIFS('Flujo de Pagos'!I$7:I$506,'Flujo de Pagos'!E$7:E$506,B33,'Flujo de Pagos'!B$7:B$506,AH7)) | AI33: =IF(B33="","",SUMIFS('Flujo de Pagos'!I$7:I$506,'Flujo de Pagos'!E$7:E$506,B33,'Flujo de Pagos'!B$7:B$506,AI7)) | AJ33: =IF(B33="","",SUMIFS('Flujo de Pagos'!I$7:I$506,'Flujo de Pagos'!E$7:E$506,B33,'Flujo de Pagos'!B$7:B$506,AJ7)) | AK33: =IF(B33="","",SUMIFS('Flujo de Pagos'!I$7:I$506,'Flujo de Pagos'!E$7:E$506,B33,'Flujo de Pagos'!B$7:B$506,AK7)) | AL33: =IF(B33="","",SUMIFS('Flujo de Pagos'!I$7:I$506,'Flujo de Pagos'!E$7:E$506,B33,'Flujo de Pagos'!B$7:B$506,AL7)) | AM33: =IF(B33="","",SUM(C33:AL33))
B34: =IF(Presupuesto!B31="","",Presupuesto!B31) | C34: =IF(B34="","",SUMIFS('Flujo de Pagos'!I$7:I$506,'Flujo de Pagos'!E$7:E$506,B34,'Flujo de Pagos'!B$7:B$506,C7)) | D34: =IF(B34="","",SUMIFS('Flujo de Pagos'!I$7:I$506,'Flujo de Pagos'!E$7:E$506,B34,'Flujo de Pagos'!B$7:B$506,D7)) | E34: =IF(B34="","",SUMIFS('Flujo de Pagos'!I$7:I$506,'Flujo de Pagos'!E$7:E$506,B34,'Flujo de Pagos'!B$7:B$506,E7)) | F34: =IF(B34="","",SUMIFS('Flujo de Pagos'!I$7:I$506,'Flujo de Pagos'!E$7:E$506,B34,'Flujo de Pagos'!B$7:B$506,F7)) | G34: =IF(B34="","",SUMIFS('Flujo de Pagos'!I$7:I$506,'Flujo de Pagos'!E$7:E$506,B34,'Flujo de Pagos'!B$7:B$506,G7)) | H34: =IF(B34="","",SUMIFS('Flujo de Pagos'!I$7:I$506,'Flujo de Pagos'!E$7:E$506,B34,'Flujo de Pagos'!B$7:B$506,H7)) | I34: =IF(B34="","",SUMIFS('Flujo de Pagos'!I$7:I$506,'Flujo de Pagos'!E$7:E$506,B34,'Flujo de Pagos'!B$7:B$506,I7)) | J34: =IF(B34="","",SUMIFS('Flujo de Pagos'!I$7:I$506,'Flujo de Pagos'!E$7:E$506,B34,'Flujo de Pagos'!B$7:B$506,J7)) | K34: =IF(B34="","",SUMIFS('Flujo de Pagos'!I$7:I$506,'Flujo de Pagos'!E$7:E$506,B34,'Flujo de Pagos'!B$7:B$506,K7)) | L34: =IF(B34="","",SUMIFS('Flujo de Pagos'!I$7:I$506,'Flujo de Pagos'!E$7:E$506,B34,'Flujo de Pagos'!B$7:B$506,L7)) | M34: =IF(B34="","",SUMIFS('Flujo de Pagos'!I$7:I$506,'Flujo de Pagos'!E$7:E$506,B34,'Flujo de Pagos'!B$7:B$506,M7)) | N34: =IF(B34="","",SUMIFS('Flujo de Pagos'!I$7:I$506,'Flujo de Pagos'!E$7:E$506,B34,'Flujo de Pagos'!B$7:B$506,N7)) | O34: =IF(B34="","",SUMIFS('Flujo de Pagos'!I$7:I$506,'Flujo de Pagos'!E$7:E$506,B34,'Flujo de Pagos'!B$7:B$506,O7)) | P34: =IF(B34="","",SUMIFS('Flujo de Pagos'!I$7:I$506,'Flujo de Pagos'!E$7:E$506,B34,'Flujo de Pagos'!B$7:B$506,P7)) | Q34: =IF(B34="","",SUMIFS('Flujo de Pagos'!I$7:I$506,'Flujo de Pagos'!E$7:E$506,B34,'Flujo de Pagos'!B$7:B$506,Q7)) | R34: =IF(B34="","",SUMIFS('Flujo de Pagos'!I$7:I$506,'Flujo de Pagos'!E$7:E$506,B34,'Flujo de Pagos'!B$7:B$506,R7)) | S34: =IF(B34="","",SUMIFS('Flujo de Pagos'!I$7:I$506,'Flujo de Pagos'!E$7:E$506,B34,'Flujo de Pagos'!B$7:B$506,S7)) | T34: =IF(B34="","",SUMIFS('Flujo de Pagos'!I$7:I$506,'Flujo de Pagos'!E$7:E$506,B34,'Flujo de Pagos'!B$7:B$506,T7)) | U34: =IF(B34="","",SUMIFS('Flujo de Pagos'!I$7:I$506,'Flujo de Pagos'!E$7:E$506,B34,'Flujo de Pagos'!B$7:B$506,U7)) | V34: =IF(B34="","",SUMIFS('Flujo de Pagos'!I$7:I$506,'Flujo de Pagos'!E$7:E$506,B34,'Flujo de Pagos'!B$7:B$506,V7)) | W34: =IF(B34="","",SUMIFS('Flujo de Pagos'!I$7:I$506,'Flujo de Pagos'!E$7:E$506,B34,'Flujo de Pagos'!B$7:B$506,W7)) | X34: =IF(B34="","",SUMIFS('Flujo de Pagos'!I$7:I$506,'Flujo de Pagos'!E$7:E$506,B34,'Flujo de Pagos'!B$7:B$506,X7)) | Y34: =IF(B34="","",SUMIFS('Flujo de Pagos'!I$7:I$506,'Flujo de Pagos'!E$7:E$506,B34,'Flujo de Pagos'!B$7:B$506,Y7)) | Z34: =IF(B34="","",SUMIFS('Flujo de Pagos'!I$7:I$506,'Flujo de Pagos'!E$7:E$506,B34,'Flujo de Pagos'!B$7:B$506,Z7)) | AA34: =IF(B34="","",SUMIFS('Flujo de Pagos'!I$7:I$506,'Flujo de Pagos'!E$7:E$506,B34,'Flujo de Pagos'!B$7:B$506,AA7)) | AB34: =IF(B34="","",SUMIFS('Flujo de Pagos'!I$7:I$506,'Flujo de Pagos'!E$7:E$506,B34,'Flujo de Pagos'!B$7:B$506,AB7)) | AC34: =IF(B34="","",SUMIFS('Flujo de Pagos'!I$7:I$506,'Flujo de Pagos'!E$7:E$506,B34,'Flujo de Pagos'!B$7:B$506,AC7)) | AD34: =IF(B34="","",SUMIFS('Flujo de Pagos'!I$7:I$506,'Flujo de Pagos'!E$7:E$506,B34,'Flujo de Pagos'!B$7:B$506,AD7)) | AE34: =IF(B34="","",SUMIFS('Flujo de Pagos'!I$7:I$506,'Flujo de Pagos'!E$7:E$506,B34,'Flujo de Pagos'!B$7:B$506,AE7)) | AF34: =IF(B34="","",SUMIFS('Flujo de Pagos'!I$7:I$506,'Flujo de Pagos'!E$7:E$506,B34,'Flujo de Pagos'!B$7:B$506,AF7)) | AG34: =IF(B34="","",SUMIFS('Flujo de Pagos'!I$7:I$506,'Flujo de Pagos'!E$7:E$506,B34,'Flujo de Pagos'!B$7:B$506,AG7)) | AH34: =IF(B34="","",SUMIFS('Flujo de Pagos'!I$7:I$506,'Flujo de Pagos'!E$7:E$506,B34,'Flujo de Pagos'!B$7:B$506,AH7)) | AI34: =IF(B34="","",SUMIFS('Flujo de Pagos'!I$7:I$506,'Flujo de Pagos'!E$7:E$506,B34,'Flujo de Pagos'!B$7:B$506,AI7)) | AJ34: =IF(B34="","",SUMIFS('Flujo de Pagos'!I$7:I$506,'Flujo de Pagos'!E$7:E$506,B34,'Flujo de Pagos'!B$7:B$506,AJ7)) | AK34: =IF(B34="","",SUMIFS('Flujo de Pagos'!I$7:I$506,'Flujo de Pagos'!E$7:E$506,B34,'Flujo de Pagos'!B$7:B$506,AK7)) | AL34: =IF(B34="","",SUMIFS('Flujo de Pagos'!I$7:I$506,'Flujo de Pagos'!E$7:E$506,B34,'Flujo de Pagos'!B$7:B$506,AL7)) | AM34: =IF(B34="","",SUM(C34:AL34))
B35: =IF(Presupuesto!B32="","",Presupuesto!B32) | C35: =IF(B35="","",SUMIFS('Flujo de Pagos'!I$7:I$506,'Flujo de Pagos'!E$7:E$506,B35,'Flujo de Pagos'!B$7:B$506,C7)) | D35: =IF(B35="","",SUMIFS('Flujo de Pagos'!I$7:I$506,'Flujo de Pagos'!E$7:E$506,B35,'Flujo de Pagos'!B$7:B$506,D7)) | E35: =IF(B35="","",SUMIFS('Flujo de Pagos'!I$7:I$506,'Flujo de Pagos'!E$7:E$506,B35,'Flujo de Pagos'!B$7:B$506,E7)) | F35: =IF(B35="","",SUMIFS('Flujo de Pagos'!I$7:I$506,'Flujo de Pagos'!E$7:E$506,B35,'Flujo de Pagos'!B$7:B$506,F7)) | G35: =IF(B35="","",SUMIFS('Flujo de Pagos'!I$7:I$506,'Flujo de Pagos'!E$7:E$506,B35,'Flujo de Pagos'!B$7:B$506,G7)) | H35: =IF(B35="","",SUMIFS('Flujo de Pagos'!I$7:I$506,'Flujo de Pagos'!E$7:E$506,B35,'Flujo de Pagos'!B$7:B$506,H7)) | I35: =IF(B35="","",SUMIFS('Flujo de Pagos'!I$7:I$506,'Flujo de Pagos'!E$7:E$506,B35,'Flujo de Pagos'!B$7:B$506,I7)) | J35: =IF(B35="","",SUMIFS('Flujo de Pagos'!I$7:I$506,'Flujo de Pagos'!E$7:E$506,B35,'Flujo de Pagos'!B$7:B$506,J7)) | K35: =IF(B35="","",SUMIFS('Flujo de Pagos'!I$7:I$506,'Flujo de Pagos'!E$7:E$506,B35,'Flujo de Pagos'!B$7:B$506,K7)) | L35: =IF(B35="","",SUMIFS('Flujo de Pagos'!I$7:I$506,'Flujo de Pagos'!E$7:E$506,B35,'Flujo de Pagos'!B$7:B$506,L7)) | M35: =IF(B35="","",SUMIFS('Flujo de Pagos'!I$7:I$506,'Flujo de Pagos'!E$7:E$506,B35,'Flujo de Pagos'!B$7:B$506,M7)) | N35: =IF(B35="","",SUMIFS('Flujo de Pagos'!I$7:I$506,'Flujo de Pagos'!E$7:E$506,B35,'Flujo de Pagos'!B$7:B$506,N7)) | O35: =IF(B35="","",SUMIFS('Flujo de Pagos'!I$7:I$506,'Flujo de Pagos'!E$7:E$506,B35,'Flujo de Pagos'!B$7:B$506,O7)) | P35: =IF(B35="","",SUMIFS('Flujo de Pagos'!I$7:I$506,'Flujo de Pagos'!E$7:E$506,B35,'Flujo de Pagos'!B$7:B$506,P7)) | Q35: =IF(B35="","",SUMIFS('Flujo de Pagos'!I$7:I$506,'Flujo de Pagos'!E$7:E$506,B35,'Flujo de Pagos'!B$7:B$506,Q7)) | R35: =IF(B35="","",SUMIFS('Flujo de Pagos'!I$7:I$506,'Flujo de Pagos'!E$7:E$506,B35,'Flujo de Pagos'!B$7:B$506,R7)) | S35: =IF(B35="","",SUMIFS('Flujo de Pagos'!I$7:I$506,'Flujo de Pagos'!E$7:E$506,B35,'Flujo de Pagos'!B$7:B$506,S7)) | T35: =IF(B35="","",SUMIFS('Flujo de Pagos'!I$7:I$506,'Flujo de Pagos'!E$7:E$506,B35,'Flujo de Pagos'!B$7:B$506,T7)) | U35: =IF(B35="","",SUMIFS('Flujo de Pagos'!I$7:I$506,'Flujo de Pagos'!E$7:E$506,B35,'Flujo de Pagos'!B$7:B$506,U7)) | V35: =IF(B35="","",SUMIFS('Flujo de Pagos'!I$7:I$506,'Flujo de Pagos'!E$7:E$506,B35,'Flujo de Pagos'!B$7:B$506,V7)) | W35: =IF(B35="","",SUMIFS('Flujo de Pagos'!I$7:I$506,'Flujo de Pagos'!E$7:E$506,B35,'Flujo de Pagos'!B$7:B$506,W7)) | X35: =IF(B35="","",SUMIFS('Flujo de Pagos'!I$7:I$506,'Flujo de Pagos'!E$7:E$506,B35,'Flujo de Pagos'!B$7:B$506,X7)) | Y35: =IF(B35="","",SUMIFS('Flujo de Pagos'!I$7:I$506,'Flujo de Pagos'!E$7:E$506,B35,'Flujo de Pagos'!B$7:B$506,Y7)) | Z35: =IF(B35="","",SUMIFS('Flujo de Pagos'!I$7:I$506,'Flujo de Pagos'!E$7:E$506,B35,'Flujo de Pagos'!B$7:B$506,Z7)) | AA35: =IF(B35="","",SUMIFS('Flujo de Pagos'!I$7:I$506,'Flujo de Pagos'!E$7:E$506,B35,'Flujo de Pagos'!B$7:B$506,AA7)) | AB35: =IF(B35="","",SUMIFS('Flujo de Pagos'!I$7:I$506,'Flujo de Pagos'!E$7:E$506,B35,'Flujo de Pagos'!B$7:B$506,AB7)) | AC35: =IF(B35="","",SUMIFS('Flujo de Pagos'!I$7:I$506,'Flujo de Pagos'!E$7:E$506,B35,'Flujo de Pagos'!B$7:B$506,AC7)) | AD35: =IF(B35="","",SUMIFS('Flujo de Pagos'!I$7:I$506,'Flujo de Pagos'!E$7:E$506,B35,'Flujo de Pagos'!B$7:B$506,AD7)) | AE35: =IF(B35="","",SUMIFS('Flujo de Pagos'!I$7:I$506,'Flujo de Pagos'!E$7:E$506,B35,'Flujo de Pagos'!B$7:B$506,AE7)) | AF35: =IF(B35="","",SUMIFS('Flujo de Pagos'!I$7:I$506,'Flujo de Pagos'!E$7:E$506,B35,'Flujo de Pagos'!B$7:B$506,AF7)) | AG35: =IF(B35="","",SUMIFS('Flujo de Pagos'!I$7:I$506,'Flujo de Pagos'!E$7:E$506,B35,'Flujo de Pagos'!B$7:B$506,AG7)) | AH35: =IF(B35="","",SUMIFS('Flujo de Pagos'!I$7:I$506,'Flujo de Pagos'!E$7:E$506,B35,'Flujo de Pagos'!B$7:B$506,AH7)) | AI35: =IF(B35="","",SUMIFS('Flujo de Pagos'!I$7:I$506,'Flujo de Pagos'!E$7:E$506,B35,'Flujo de Pagos'!B$7:B$506,AI7)) | AJ35: =IF(B35="","",SUMIFS('Flujo de Pagos'!I$7:I$506,'Flujo de Pagos'!E$7:E$506,B35,'Flujo de Pagos'!B$7:B$506,AJ7)) | AK35: =IF(B35="","",SUMIFS('Flujo de Pagos'!I$7:I$506,'Flujo de Pagos'!E$7:E$506,B35,'Flujo de Pagos'!B$7:B$506,AK7)) | AL35: =IF(B35="","",SUMIFS('Flujo de Pagos'!I$7:I$506,'Flujo de Pagos'!E$7:E$506,B35,'Flujo de Pagos'!B$7:B$506,AL7)) | AM35: =IF(B35="","",SUM(C35:AL35))
B36: =IF(Presupuesto!B33="","",Presupuesto!B33) | C36: =IF(B36="","",SUMIFS('Flujo de Pagos'!I$7:I$506,'Flujo de Pagos'!E$7:E$506,B36,'Flujo de Pagos'!B$7:B$506,C7)) | D36: =IF(B36="","",SUMIFS('Flujo de Pagos'!I$7:I$506,'Flujo de Pagos'!E$7:E$506,B36,'Flujo de Pagos'!B$7:B$506,D7)) | E36: =IF(B36="","",SUMIFS('Flujo de Pagos'!I$7:I$506,'Flujo de Pagos'!E$7:E$506,B36,'Flujo de Pagos'!B$7:B$506,E7)) | F36: =IF(B36="","",SUMIFS('Flujo de Pagos'!I$7:I$506,'Flujo de Pagos'!E$7:E$506,B36,'Flujo de Pagos'!B$7:B$506,F7)) | G36: =IF(B36="","",SUMIFS('Flujo de Pagos'!I$7:I$506,'Flujo de Pagos'!E$7:E$506,B36,'Flujo de Pagos'!B$7:B$506,G7)) | H36: =IF(B36="","",SUMIFS('Flujo de Pagos'!I$7:I$506,'Flujo de Pagos'!E$7:E$506,B36,'Flujo de Pagos'!B$7:B$506,H7)) | I36: =IF(B36="","",SUMIFS('Flujo de Pagos'!I$7:I$506,'Flujo de Pagos'!E$7:E$506,B36,'Flujo de Pagos'!B$7:B$506,I7)) | J36: =IF(B36="","",SUMIFS('Flujo de Pagos'!I$7:I$506,'Flujo de Pagos'!E$7:E$506,B36,'Flujo de Pagos'!B$7:B$506,J7)) | K36: =IF(B36="","",SUMIFS('Flujo de Pagos'!I$7:I$506,'Flujo de Pagos'!E$7:E$506,B36,'Flujo de Pagos'!B$7:B$506,K7)) | L36: =IF(B36="","",SUMIFS('Flujo de Pagos'!I$7:I$506,'Flujo de Pagos'!E$7:E$506,B36,'Flujo de Pagos'!B$7:B$506,L7)) | M36: =IF(B36="","",SUMIFS('Flujo de Pagos'!I$7:I$506,'Flujo de Pagos'!E$7:E$506,B36,'Flujo de Pagos'!B$7:B$506,M7)) | N36: =IF(B36="","",SUMIFS('Flujo de Pagos'!I$7:I$506,'Flujo de Pagos'!E$7:E$506,B36,'Flujo de Pagos'!B$7:B$506,N7)) | O36: =IF(B36="","",SUMIFS('Flujo de Pagos'!I$7:I$506,'Flujo de Pagos'!E$7:E$506,B36,'Flujo de Pagos'!B$7:B$506,O7)) | P36: =IF(B36="","",SUMIFS('Flujo de Pagos'!I$7:I$506,'Flujo de Pagos'!E$7:E$506,B36,'Flujo de Pagos'!B$7:B$506,P7)) | Q36: =IF(B36="","",SUMIFS('Flujo de Pagos'!I$7:I$506,'Flujo de Pagos'!E$7:E$506,B36,'Flujo de Pagos'!B$7:B$506,Q7)) | R36: =IF(B36="","",SUMIFS('Flujo de Pagos'!I$7:I$506,'Flujo de Pagos'!E$7:E$506,B36,'Flujo de Pagos'!B$7:B$506,R7)) | S36: =IF(B36="","",SUMIFS('Flujo de Pagos'!I$7:I$506,'Flujo de Pagos'!E$7:E$506,B36,'Flujo de Pagos'!B$7:B$506,S7)) | T36: =IF(B36="","",SUMIFS('Flujo de Pagos'!I$7:I$506,'Flujo de Pagos'!E$7:E$506,B36,'Flujo de Pagos'!B$7:B$506,T7)) | U36: =IF(B36="","",SUMIFS('Flujo de Pagos'!I$7:I$506,'Flujo de Pagos'!E$7:E$506,B36,'Flujo de Pagos'!B$7:B$506,U7)) | V36: =IF(B36="","",SUMIFS('Flujo de Pagos'!I$7:I$506,'Flujo de Pagos'!E$7:E$506,B36,'Flujo de Pagos'!B$7:B$506,V7)) | W36: =IF(B36="","",SUMIFS('Flujo de Pagos'!I$7:I$506,'Flujo de Pagos'!E$7:E$506,B36,'Flujo de Pagos'!B$7:B$506,W7)) | X36: =IF(B36="","",SUMIFS('Flujo de Pagos'!I$7:I$506,'Flujo de Pagos'!E$7:E$506,B36,'Flujo de Pagos'!B$7:B$506,X7)) | Y36: =IF(B36="","",SUMIFS('Flujo de Pagos'!I$7:I$506,'Flujo de Pagos'!E$7:E$506,B36,'Flujo de Pagos'!B$7:B$506,Y7)) | Z36: =IF(B36="","",SUMIFS('Flujo de Pagos'!I$7:I$506,'Flujo de Pagos'!E$7:E$506,B36,'Flujo de Pagos'!B$7:B$506,Z7)) | AA36: =IF(B36="","",SUMIFS('Flujo de Pagos'!I$7:I$506,'Flujo de Pagos'!E$7:E$506,B36,'Flujo de Pagos'!B$7:B$506,AA7)) | AB36: =IF(B36="","",SUMIFS('Flujo de Pagos'!I$7:I$506,'Flujo de Pagos'!E$7:E$506,B36,'Flujo de Pagos'!B$7:B$506,AB7)) | AC36: =IF(B36="","",SUMIFS('Flujo de Pagos'!I$7:I$506,'Flujo de Pagos'!E$7:E$506,B36,'Flujo de Pagos'!B$7:B$506,AC7)) | AD36: =IF(B36="","",SUMIFS('Flujo de Pagos'!I$7:I$506,'Flujo de Pagos'!E$7:E$506,B36,'Flujo de Pagos'!B$7:B$506,AD7)) | AE36: =IF(B36="","",SUMIFS('Flujo de Pagos'!I$7:I$506,'Flujo de Pagos'!E$7:E$506,B36,'Flujo de Pagos'!B$7:B$506,AE7)) | AF36: =IF(B36="","",SUMIFS('Flujo de Pagos'!I$7:I$506,'Flujo de Pagos'!E$7:E$506,B36,'Flujo de Pagos'!B$7:B$506,AF7)) | AG36: =IF(B36="","",SUMIFS('Flujo de Pagos'!I$7:I$506,'Flujo de Pagos'!E$7:E$506,B36,'Flujo de Pagos'!B$7:B$506,AG7)) | AH36: =IF(B36="","",SUMIFS('Flujo de Pagos'!I$7:I$506,'Flujo de Pagos'!E$7:E$506,B36,'Flujo de Pagos'!B$7:B$506,AH7)) | AI36: =IF(B36="","",SUMIFS('Flujo de Pagos'!I$7:I$506,'Flujo de Pagos'!E$7:E$506,B36,'Flujo de Pagos'!B$7:B$506,AI7)) | AJ36: =IF(B36="","",SUMIFS('Flujo de Pagos'!I$7:I$506,'Flujo de Pagos'!E$7:E$506,B36,'Flujo de Pagos'!B$7:B$506,AJ7)) | AK36: =IF(B36="","",SUMIFS('Flujo de Pagos'!I$7:I$506,'Flujo de Pagos'!E$7:E$506,B36,'Flujo de Pagos'!B$7:B$506,AK7)) | AL36: =IF(B36="","",SUMIFS('Flujo de Pagos'!I$7:I$506,'Flujo de Pagos'!E$7:E$506,B36,'Flujo de Pagos'!B$7:B$506,AL7)) | AM36: =IF(B36="","",SUM(C36:AL36))
B37: =IF(Presupuesto!B34="","",Presupuesto!B34) | C37: =IF(B37="","",SUMIFS('Flujo de Pagos'!I$7:I$506,'Flujo de Pagos'!E$7:E$506,B37,'Flujo de Pagos'!B$7:B$506,C7)) | D37: =IF(B37="","",SUMIFS('Flujo de Pagos'!I$7:I$506,'Flujo de Pagos'!E$7:E$506,B37,'Flujo de Pagos'!B$7:B$506,D7)) | E37: =IF(B37="","",SUMIFS('Flujo de Pagos'!I$7:I$506,'Flujo de Pagos'!E$7:E$506,B37,'Flujo de Pagos'!B$7:B$506,E7)) | F37: =IF(B37="","",SUMIFS('Flujo de Pagos'!I$7:I$506,'Flujo de Pagos'!E$7:E$506,B37,'Flujo de Pagos'!B$7:B$506,F7)) | G37: =IF(B37="","",SUMIFS('Flujo de Pagos'!I$7:I$506,'Flujo de Pagos'!E$7:E$506,B37,'Flujo de Pagos'!B$7:B$506,G7)) | H37: =IF(B37="","",SUMIFS('Flujo de Pagos'!I$7:I$506,'Flujo de Pagos'!E$7:E$506,B37,'Flujo de Pagos'!B$7:B$506,H7)) | I37: =IF(B37="","",SUMIFS('Flujo de Pagos'!I$7:I$506,'Flujo de Pagos'!E$7:E$506,B37,'Flujo de Pagos'!B$7:B$506,I7)) | J37: =IF(B37="","",SUMIFS('Flujo de Pagos'!I$7:I$506,'Flujo de Pagos'!E$7:E$506,B37,'Flujo de Pagos'!B$7:B$506,J7)) | K37: =IF(B37="","",SUMIFS('Flujo de Pagos'!I$7:I$506,'Flujo de Pagos'!E$7:E$506,B37,'Flujo de Pagos'!B$7:B$506,K7)) | L37: =IF(B37="","",SUMIFS('Flujo de Pagos'!I$7:I$506,'Flujo de Pagos'!E$7:E$506,B37,'Flujo de Pagos'!B$7:B$506,L7)) | M37: =IF(B37="","",SUMIFS('Flujo de Pagos'!I$7:I$506,'Flujo de Pagos'!E$7:E$506,B37,'Flujo de Pagos'!B$7:B$506,M7)) | N37: =IF(B37="","",SUMIFS('Flujo de Pagos'!I$7:I$506,'Flujo de Pagos'!E$7:E$506,B37,'Flujo de Pagos'!B$7:B$506,N7)) | O37: =IF(B37="","",SUMIFS('Flujo de Pagos'!I$7:I$506,'Flujo de Pagos'!E$7:E$506,B37,'Flujo de Pagos'!B$7:B$506,O7)) | P37: =IF(B37="","",SUMIFS('Flujo de Pagos'!I$7:I$506,'Flujo de Pagos'!E$7:E$506,B37,'Flujo de Pagos'!B$7:B$506,P7)) | Q37: =IF(B37="","",SUMIFS('Flujo de Pagos'!I$7:I$506,'Flujo de Pagos'!E$7:E$506,B37,'Flujo de Pagos'!B$7:B$506,Q7)) | R37: =IF(B37="","",SUMIFS('Flujo de Pagos'!I$7:I$506,'Flujo de Pagos'!E$7:E$506,B37,'Flujo de Pagos'!B$7:B$506,R7)) | S37: =IF(B37="","",SUMIFS('Flujo de Pagos'!I$7:I$506,'Flujo de Pagos'!E$7:E$506,B37,'Flujo de Pagos'!B$7:B$506,S7)) | T37: =IF(B37="","",SUMIFS('Flujo de Pagos'!I$7:I$506,'Flujo de Pagos'!E$7:E$506,B37,'Flujo de Pagos'!B$7:B$506,T7)) | U37: =IF(B37="","",SUMIFS('Flujo de Pagos'!I$7:I$506,'Flujo de Pagos'!E$7:E$506,B37,'Flujo de Pagos'!B$7:B$506,U7)) | V37: =IF(B37="","",SUMIFS('Flujo de Pagos'!I$7:I$506,'Flujo de Pagos'!E$7:E$506,B37,'Flujo de Pagos'!B$7:B$506,V7)) | W37: =IF(B37="","",SUMIFS('Flujo de Pagos'!I$7:I$506,'Flujo de Pagos'!E$7:E$506,B37,'Flujo de Pagos'!B$7:B$506,W7)) | X37: =IF(B37="","",SUMIFS('Flujo de Pagos'!I$7:I$506,'Flujo de Pagos'!E$7:E$506,B37,'Flujo de Pagos'!B$7:B$506,X7)) | Y37: =IF(B37="","",SUMIFS('Flujo de Pagos'!I$7:I$506,'Flujo de Pagos'!E$7:E$506,B37,'Flujo de Pagos'!B$7:B$506,Y7)) | Z37: =IF(B37="","",SUMIFS('Flujo de Pagos'!I$7:I$506,'Flujo de Pagos'!E$7:E$506,B37,'Flujo de Pagos'!B$7:B$506,Z7)) | AA37: =IF(B37="","",SUMIFS('Flujo de Pagos'!I$7:I$506,'Flujo de Pagos'!E$7:E$506,B37,'Flujo de Pagos'!B$7:B$506,AA7)) | AB37: =IF(B37="","",SUMIFS('Flujo de Pagos'!I$7:I$506,'Flujo de Pagos'!E$7:E$506,B37,'Flujo de Pagos'!B$7:B$506,AB7)) | AC37: =IF(B37="","",SUMIFS('Flujo de Pagos'!I$7:I$506,'Flujo de Pagos'!E$7:E$506,B37,'Flujo de Pagos'!B$7:B$506,AC7)) | AD37: =IF(B37="","",SUMIFS('Flujo de Pagos'!I$7:I$506,'Flujo de Pagos'!E$7:E$506,B37,'Flujo de Pagos'!B$7:B$506,AD7)) | AE37: =IF(B37="","",SUMIFS('Flujo de Pagos'!I$7:I$506,'Flujo de Pagos'!E$7:E$506,B37,'Flujo de Pagos'!B$7:B$506,AE7)) | AF37: =IF(B37="","",SUMIFS('Flujo de Pagos'!I$7:I$506,'Flujo de Pagos'!E$7:E$506,B37,'Flujo de Pagos'!B$7:B$506,AF7)) | AG37: =IF(B37="","",SUMIFS('Flujo de Pagos'!I$7:I$506,'Flujo de Pagos'!E$7:E$506,B37,'Flujo de Pagos'!B$7:B$506,AG7)) | AH37: =IF(B37="","",SUMIFS('Flujo de Pagos'!I$7:I$506,'Flujo de Pagos'!E$7:E$506,B37,'Flujo de Pagos'!B$7:B$506,AH7)) | AI37: =IF(B37="","",SUMIFS('Flujo de Pagos'!I$7:I$506,'Flujo de Pagos'!E$7:E$506,B37,'Flujo de Pagos'!B$7:B$506,AI7)) | AJ37: =IF(B37="","",SUMIFS('Flujo de Pagos'!I$7:I$506,'Flujo de Pagos'!E$7:E$506,B37,'Flujo de Pagos'!B$7:B$506,AJ7)) | AK37: =IF(B37="","",SUMIFS('Flujo de Pagos'!I$7:I$506,'Flujo de Pagos'!E$7:E$506,B37,'Flujo de Pagos'!B$7:B$506,AK7)) | AL37: =IF(B37="","",SUMIFS('Flujo de Pagos'!I$7:I$506,'Flujo de Pagos'!E$7:E$506,B37,'Flujo de Pagos'!B$7:B$506,AL7)) | AM37: =IF(B37="","",SUM(C37:AL37))
B38: =IF(Presupuesto!B35="","",Presupuesto!B35) | C38: =IF(B38="","",SUMIFS('Flujo de Pagos'!I$7:I$506,'Flujo de Pagos'!E$7:E$506,B38,'Flujo de Pagos'!B$7:B$506,C7)) | D38: =IF(B38="","",SUMIFS('Flujo de Pagos'!I$7:I$506,'Flujo de Pagos'!E$7:E$506,B38,'Flujo de Pagos'!B$7:B$506,D7)) | E38: =IF(B38="","",SUMIFS('Flujo de Pagos'!I$7:I$506,'Flujo de Pagos'!E$7:E$506,B38,'Flujo de Pagos'!B$7:B$506,E7)) | F38: =IF(B38="","",SUMIFS('Flujo de Pagos'!I$7:I$506,'Flujo de Pagos'!E$7:E$506,B38,'Flujo de Pagos'!B$7:B$506,F7)) | G38: =IF(B38="","",SUMIFS('Flujo de Pagos'!I$7:I$506,'Flujo de Pagos'!E$7:E$506,B38,'Flujo de Pagos'!B$7:B$506,G7)) | H38: =IF(B38="","",SUMIFS('Flujo de Pagos'!I$7:I$506,'Flujo de Pagos'!E$7:E$506,B38,'Flujo de Pagos'!B$7:B$506,H7)) | I38: =IF(B38="","",SUMIFS('Flujo de Pagos'!I$7:I$506,'Flujo de Pagos'!E$7:E$506,B38,'Flujo de Pagos'!B$7:B$506,I7)) | J38: =IF(B38="","",SUMIFS('Flujo de Pagos'!I$7:I$506,'Flujo de Pagos'!E$7:E$506,B38,'Flujo de Pagos'!B$7:B$506,J7)) | K38: =IF(B38="","",SUMIFS('Flujo de Pagos'!I$7:I$506,'Flujo de Pagos'!E$7:E$506,B38,'Flujo de Pagos'!B$7:B$506,K7)) | L38: =IF(B38="","",SUMIFS('Flujo de Pagos'!I$7:I$506,'Flujo de Pagos'!E$7:E$506,B38,'Flujo de Pagos'!B$7:B$506,L7)) | M38: =IF(B38="","",SUMIFS('Flujo de Pagos'!I$7:I$506,'Flujo de Pagos'!E$7:E$506,B38,'Flujo de Pagos'!B$7:B$506,M7)) | N38: =IF(B38="","",SUMIFS('Flujo de Pagos'!I$7:I$506,'Flujo de Pagos'!E$7:E$506,B38,'Flujo de Pagos'!B$7:B$506,N7)) | O38: =IF(B38="","",SUMIFS('Flujo de Pagos'!I$7:I$506,'Flujo de Pagos'!E$7:E$506,B38,'Flujo de Pagos'!B$7:B$506,O7)) | P38: =IF(B38="","",SUMIFS('Flujo de Pagos'!I$7:I$506,'Flujo de Pagos'!E$7:E$506,B38,'Flujo de Pagos'!B$7:B$506,P7)) | Q38: =IF(B38="","",SUMIFS('Flujo de Pagos'!I$7:I$506,'Flujo de Pagos'!E$7:E$506,B38,'Flujo de Pagos'!B$7:B$506,Q7)) | R38: =IF(B38="","",SUMIFS('Flujo de Pagos'!I$7:I$506,'Flujo de Pagos'!E$7:E$506,B38,'Flujo de Pagos'!B$7:B$506,R7)) | S38: =IF(B38="","",SUMIFS('Flujo de Pagos'!I$7:I$506,'Flujo de Pagos'!E$7:E$506,B38,'Flujo de Pagos'!B$7:B$506,S7)) | T38: =IF(B38="","",SUMIFS('Flujo de Pagos'!I$7:I$506,'Flujo de Pagos'!E$7:E$506,B38,'Flujo de Pagos'!B$7:B$506,T7)) | U38: =IF(B38="","",SUMIFS('Flujo de Pagos'!I$7:I$506,'Flujo de Pagos'!E$7:E$506,B38,'Flujo de Pagos'!B$7:B$506,U7)) | V38: =IF(B38="","",SUMIFS('Flujo de Pagos'!I$7:I$506,'Flujo de Pagos'!E$7:E$506,B38,'Flujo de Pagos'!B$7:B$506,V7)) | W38: =IF(B38="","",SUMIFS('Flujo de Pagos'!I$7:I$506,'Flujo de Pagos'!E$7:E$506,B38,'Flujo de Pagos'!B$7:B$506,W7)) | X38: =IF(B38="","",SUMIFS('Flujo de Pagos'!I$7:I$506,'Flujo de Pagos'!E$7:E$506,B38,'Flujo de Pagos'!B$7:B$506,X7)) | Y38: =IF(B38="","",SUMIFS('Flujo de Pagos'!I$7:I$506,'Flujo de Pagos'!E$7:E$506,B38,'Flujo de Pagos'!B$7:B$506,Y7)) | Z38: =IF(B38="","",SUMIFS('Flujo de Pagos'!I$7:I$506,'Flujo de Pagos'!E$7:E$506,B38,'Flujo de Pagos'!B$7:B$506,Z7)) | AA38: =IF(B38="","",SUMIFS('Flujo de Pagos'!I$7:I$506,'Flujo de Pagos'!E$7:E$506,B38,'Flujo de Pagos'!B$7:B$506,AA7)) | AB38: =IF(B38="","",SUMIFS('Flujo de Pagos'!I$7:I$506,'Flujo de Pagos'!E$7:E$506,B38,'Flujo de Pagos'!B$7:B$506,AB7)) | AC38: =IF(B38="","",SUMIFS('Flujo de Pagos'!I$7:I$506,'Flujo de Pagos'!E$7:E$506,B38,'Flujo de Pagos'!B$7:B$506,AC7)) | AD38: =IF(B38="","",SUMIFS('Flujo de Pagos'!I$7:I$506,'Flujo de Pagos'!E$7:E$506,B38,'Flujo de Pagos'!B$7:B$506,AD7)) | AE38: =IF(B38="","",SUMIFS('Flujo de Pagos'!I$7:I$506,'Flujo de Pagos'!E$7:E$506,B38,'Flujo de Pagos'!B$7:B$506,AE7)) | AF38: =IF(B38="","",SUMIFS('Flujo de Pagos'!I$7:I$506,'Flujo de Pagos'!E$7:E$506,B38,'Flujo de Pagos'!B$7:B$506,AF7)) | AG38: =IF(B38="","",SUMIFS('Flujo de Pagos'!I$7:I$506,'Flujo de Pagos'!E$7:E$506,B38,'Flujo de Pagos'!B$7:B$506,AG7)) | AH38: =IF(B38="","",SUMIFS('Flujo de Pagos'!I$7:I$506,'Flujo de Pagos'!E$7:E$506,B38,'Flujo de Pagos'!B$7:B$506,AH7)) | AI38: =IF(B38="","",SUMIFS('Flujo de Pagos'!I$7:I$506,'Flujo de Pagos'!E$7:E$506,B38,'Flujo de Pagos'!B$7:B$506,AI7)) | AJ38: =IF(B38="","",SUMIFS('Flujo de Pagos'!I$7:I$506,'Flujo de Pagos'!E$7:E$506,B38,'Flujo de Pagos'!B$7:B$506,AJ7)) | AK38: =IF(B38="","",SUMIFS('Flujo de Pagos'!I$7:I$506,'Flujo de Pagos'!E$7:E$506,B38,'Flujo de Pagos'!B$7:B$506,AK7)) | AL38: =IF(B38="","",SUMIFS('Flujo de Pagos'!I$7:I$506,'Flujo de Pagos'!E$7:E$506,B38,'Flujo de Pagos'!B$7:B$506,AL7)) | AM38: =IF(B38="","",SUM(C38:AL38))
B39: =IF(Presupuesto!B36="","",Presupuesto!B36) | C39: =IF(B39="","",SUMIFS('Flujo de Pagos'!I$7:I$506,'Flujo de Pagos'!E$7:E$506,B39,'Flujo de Pagos'!B$7:B$506,C7)) | D39: =IF(B39="","",SUMIFS('Flujo de Pagos'!I$7:I$506,'Flujo de Pagos'!E$7:E$506,B39,'Flujo de Pagos'!B$7:B$506,D7)) | E39: =IF(B39="","",SUMIFS('Flujo de Pagos'!I$7:I$506,'Flujo de Pagos'!E$7:E$506,B39,'Flujo de Pagos'!B$7:B$506,E7)) | F39: =IF(B39="","",SUMIFS('Flujo de Pagos'!I$7:I$506,'Flujo de Pagos'!E$7:E$506,B39,'Flujo de Pagos'!B$7:B$506,F7)) | G39: =IF(B39="","",SUMIFS('Flujo de Pagos'!I$7:I$506,'Flujo de Pagos'!E$7:E$506,B39,'Flujo de Pagos'!B$7:B$506,G7)) | H39: =IF(B39="","",SUMIFS('Flujo de Pagos'!I$7:I$506,'Flujo de Pagos'!E$7:E$506,B39,'Flujo de Pagos'!B$7:B$506,H7)) | I39: =IF(B39="","",SUMIFS('Flujo de Pagos'!I$7:I$506,'Flujo de Pagos'!E$7:E$506,B39,'Flujo de Pagos'!B$7:B$506,I7)) | J39: =IF(B39="","",SUMIFS('Flujo de Pagos'!I$7:I$506,'Flujo de Pagos'!E$7:E$506,B39,'Flujo de Pagos'!B$7:B$506,J7)) | K39: =IF(B39="","",SUMIFS('Flujo de Pagos'!I$7:I$506,'Flujo de Pagos'!E$7:E$506,B39,'Flujo de Pagos'!B$7:B$506,K7)) | L39: =IF(B39="","",SUMIFS('Flujo de Pagos'!I$7:I$506,'Flujo de Pagos'!E$7:E$506,B39,'Flujo de Pagos'!B$7:B$506,L7)) | M39: =IF(B39="","",SUMIFS('Flujo de Pagos'!I$7:I$506,'Flujo de Pagos'!E$7:E$506,B39,'Flujo de Pagos'!B$7:B$506,M7)) | N39: =IF(B39="","",SUMIFS('Flujo de Pagos'!I$7:I$506,'Flujo de Pagos'!E$7:E$506,B39,'Flujo de Pagos'!B$7:B$506,N7)) | O39: =IF(B39="","",SUMIFS('Flujo de Pagos'!I$7:I$506,'Flujo de Pagos'!E$7:E$506,B39,'Flujo de Pagos'!B$7:B$506,O7)) | P39: =IF(B39="","",SUMIFS('Flujo de Pagos'!I$7:I$506,'Flujo de Pagos'!E$7:E$506,B39,'Flujo de Pagos'!B$7:B$506,P7)) | Q39: =IF(B39="","",SUMIFS('Flujo de Pagos'!I$7:I$506,'Flujo de Pagos'!E$7:E$506,B39,'Flujo de Pagos'!B$7:B$506,Q7)) | R39: =IF(B39="","",SUMIFS('Flujo de Pagos'!I$7:I$506,'Flujo de Pagos'!E$7:E$506,B39,'Flujo de Pagos'!B$7:B$506,R7)) | S39: =IF(B39="","",SUMIFS('Flujo de Pagos'!I$7:I$506,'Flujo de Pagos'!E$7:E$506,B39,'Flujo de Pagos'!B$7:B$506,S7)) | T39: =IF(B39="","",SUMIFS('Flujo de Pagos'!I$7:I$506,'Flujo de Pagos'!E$7:E$506,B39,'Flujo de Pagos'!B$7:B$506,T7)) | U39: =IF(B39="","",SUMIFS('Flujo de Pagos'!I$7:I$506,'Flujo de Pagos'!E$7:E$506,B39,'Flujo de Pagos'!B$7:B$506,U7)) | V39: =IF(B39="","",SUMIFS('Flujo de Pagos'!I$7:I$506,'Flujo de Pagos'!E$7:E$506,B39,'Flujo de Pagos'!B$7:B$506,V7)) | W39: =IF(B39="","",SUMIFS('Flujo de Pagos'!I$7:I$506,'Flujo de Pagos'!E$7:E$506,B39,'Flujo de Pagos'!B$7:B$506,W7)) | X39: =IF(B39="","",SUMIFS('Flujo de Pagos'!I$7:I$506,'Flujo de Pagos'!E$7:E$506,B39,'Flujo de Pagos'!B$7:B$506,X7)) | Y39: =IF(B39="","",SUMIFS('Flujo de Pagos'!I$7:I$506,'Flujo de Pagos'!E$7:E$506,B39,'Flujo de Pagos'!B$7:B$506,Y7)) | Z39: =IF(B39="","",SUMIFS('Flujo de Pagos'!I$7:I$506,'Flujo de Pagos'!E$7:E$506,B39,'Flujo de Pagos'!B$7:B$506,Z7)) | AA39: =IF(B39="","",SUMIFS('Flujo de Pagos'!I$7:I$506,'Flujo de Pagos'!E$7:E$506,B39,'Flujo de Pagos'!B$7:B$506,AA7)) | AB39: =IF(B39="","",SUMIFS('Flujo de Pagos'!I$7:I$506,'Flujo de Pagos'!E$7:E$506,B39,'Flujo de Pagos'!B$7:B$506,AB7)) | AC39: =IF(B39="","",SUMIFS('Flujo de Pagos'!I$7:I$506,'Flujo de Pagos'!E$7:E$506,B39,'Flujo de Pagos'!B$7:B$506,AC7)) | AD39: =IF(B39="","",SUMIFS('Flujo de Pagos'!I$7:I$506,'Flujo de Pagos'!E$7:E$506,B39,'Flujo de Pagos'!B$7:B$506,AD7)) | AE39: =IF(B39="","",SUMIFS('Flujo de Pagos'!I$7:I$506,'Flujo de Pagos'!E$7:E$506,B39,'Flujo de Pagos'!B$7:B$506,AE7)) | AF39: =IF(B39="","",SUMIFS('Flujo de Pagos'!I$7:I$506,'Flujo de Pagos'!E$7:E$506,B39,'Flujo de Pagos'!B$7:B$506,AF7)) | AG39: =IF(B39="","",SUMIFS('Flujo de Pagos'!I$7:I$506,'Flujo de Pagos'!E$7:E$506,B39,'Flujo de Pagos'!B$7:B$506,AG7)) | AH39: =IF(B39="","",SUMIFS('Flujo de Pagos'!I$7:I$506,'Flujo de Pagos'!E$7:E$506,B39,'Flujo de Pagos'!B$7:B$506,AH7)) | AI39: =IF(B39="","",SUMIFS('Flujo de Pagos'!I$7:I$506,'Flujo de Pagos'!E$7:E$506,B39,'Flujo de Pagos'!B$7:B$506,AI7)) | AJ39: =IF(B39="","",SUMIFS('Flujo de Pagos'!I$7:I$506,'Flujo de Pagos'!E$7:E$506,B39,'Flujo de Pagos'!B$7:B$506,AJ7)) | AK39: =IF(B39="","",SUMIFS('Flujo de Pagos'!I$7:I$506,'Flujo de Pagos'!E$7:E$506,B39,'Flujo de Pagos'!B$7:B$506,AK7)) | AL39: =IF(B39="","",SUMIFS('Flujo de Pagos'!I$7:I$506,'Flujo de Pagos'!E$7:E$506,B39,'Flujo de Pagos'!B$7:B$506,AL7)) | AM39: =IF(B39="","",SUM(C39:AL39))
B40: =IF(Presupuesto!B37="","",Presupuesto!B37) | C40: =IF(B40="","",SUMIFS('Flujo de Pagos'!I$7:I$506,'Flujo de Pagos'!E$7:E$506,B40,'Flujo de Pagos'!B$7:B$506,C7)) | D40: =IF(B40="","",SUMIFS('Flujo de Pagos'!I$7:I$506,'Flujo de Pagos'!E$7:E$506,B40,'Flujo de Pagos'!B$7:B$506,D7)) | E40: =IF(B40="","",SUMIFS('Flujo de Pagos'!I$7:I$506,'Flujo de Pagos'!E$7:E$506,B40,'Flujo de Pagos'!B$7:B$506,E7)) | F40: =IF(B40="","",SUMIFS('Flujo de Pagos'!I$7:I$506,'Flujo de Pagos'!E$7:E$506,B40,'Flujo de Pagos'!B$7:B$506,F7)) | G40: =IF(B40="","",SUMIFS('Flujo de Pagos'!I$7:I$506,'Flujo de Pagos'!E$7:E$506,B40,'Flujo de Pagos'!B$7:B$506,G7)) | H40: =IF(B40="","",SUMIFS('Flujo de Pagos'!I$7:I$506,'Flujo de Pagos'!E$7:E$506,B40,'Flujo de Pagos'!B$7:B$506,H7)) | I40: =IF(B40="","",SUMIFS('Flujo de Pagos'!I$7:I$506,'Flujo de Pagos'!E$7:E$506,B40,'Flujo de Pagos'!B$7:B$506,I7)) | J40: =IF(B40="","",SUMIFS('Flujo de Pagos'!I$7:I$506,'Flujo de Pagos'!E$7:E$506,B40,'Flujo de Pagos'!B$7:B$506,J7)) | K40: =IF(B40="","",SUMIFS('Flujo de Pagos'!I$7:I$506,'Flujo de Pagos'!E$7:E$506,B40,'Flujo de Pagos'!B$7:B$506,K7)) | L40: =IF(B40="","",SUMIFS('Flujo de Pagos'!I$7:I$506,'Flujo de Pagos'!E$7:E$506,B40,'Flujo de Pagos'!B$7:B$506,L7)) | M40: =IF(B40="","",SUMIFS('Flujo de Pagos'!I$7:I$506,'Flujo de Pagos'!E$7:E$506,B40,'Flujo de Pagos'!B$7:B$506,M7)) | N40: =IF(B40="","",SUMIFS('Flujo de Pagos'!I$7:I$506,'Flujo de Pagos'!E$7:E$506,B40,'Flujo de Pagos'!B$7:B$506,N7)) | O40: =IF(B40="","",SUMIFS('Flujo de Pagos'!I$7:I$506,'Flujo de Pagos'!E$7:E$506,B40,'Flujo de Pagos'!B$7:B$506,O7)) | P40: =IF(B40="","",SUMIFS('Flujo de Pagos'!I$7:I$506,'Flujo de Pagos'!E$7:E$506,B40,'Flujo de Pagos'!B$7:B$506,P7)) | Q40: =IF(B40="","",SUMIFS('Flujo de Pagos'!I$7:I$506,'Flujo de Pagos'!E$7:E$506,B40,'Flujo de Pagos'!B$7:B$506,Q7)) | R40: =IF(B40="","",SUMIFS('Flujo de Pagos'!I$7:I$506,'Flujo de Pagos'!E$7:E$506,B40,'Flujo de Pagos'!B$7:B$506,R7)) | S40: =IF(B40="","",SUMIFS('Flujo de Pagos'!I$7:I$506,'Flujo de Pagos'!E$7:E$506,B40,'Flujo de Pagos'!B$7:B$506,S7)) | T40: =IF(B40="","",SUMIFS('Flujo de Pagos'!I$7:I$506,'Flujo de Pagos'!E$7:E$506,B40,'Flujo de Pagos'!B$7:B$506,T7)) | U40: =IF(B40="","",SUMIFS('Flujo de Pagos'!I$7:I$506,'Flujo de Pagos'!E$7:E$506,B40,'Flujo de Pagos'!B$7:B$506,U7)) | V40: =IF(B40="","",SUMIFS('Flujo de Pagos'!I$7:I$506,'Flujo de Pagos'!E$7:E$506,B40,'Flujo de Pagos'!B$7:B$506,V7)) | W40: =IF(B40="","",SUMIFS('Flujo de Pagos'!I$7:I$506,'Flujo de Pagos'!E$7:E$506,B40,'Flujo de Pagos'!B$7:B$506,W7)) | X40: =IF(B40="","",SUMIFS('Flujo de Pagos'!I$7:I$506,'Flujo de Pagos'!E$7:E$506,B40,'Flujo de Pagos'!B$7:B$506,X7)) | Y40: =IF(B40="","",SUMIFS('Flujo de Pagos'!I$7:I$506,'Flujo de Pagos'!E$7:E$506,B40,'Flujo de Pagos'!B$7:B$506,Y7)) | Z40: =IF(B40="","",SUMIFS('Flujo de Pagos'!I$7:I$506,'Flujo de Pagos'!E$7:E$506,B40,'Flujo de Pagos'!B$7:B$506,Z7)) | AA40: =IF(B40="","",SUMIFS('Flujo de Pagos'!I$7:I$506,'Flujo de Pagos'!E$7:E$506,B40,'Flujo de Pagos'!B$7:B$506,AA7)) | AB40: =IF(B40="","",SUMIFS('Flujo de Pagos'!I$7:I$506,'Flujo de Pagos'!E$7:E$506,B40,'Flujo de Pagos'!B$7:B$506,AB7)) | AC40: =IF(B40="","",SUMIFS('Flujo de Pagos'!I$7:I$506,'Flujo de Pagos'!E$7:E$506,B40,'Flujo de Pagos'!B$7:B$506,AC7)) | AD40: =IF(B40="","",SUMIFS('Flujo de Pagos'!I$7:I$506,'Flujo de Pagos'!E$7:E$506,B40,'Flujo de Pagos'!B$7:B$506,AD7)) | AE40: =IF(B40="","",SUMIFS('Flujo de Pagos'!I$7:I$506,'Flujo de Pagos'!E$7:E$506,B40,'Flujo de Pagos'!B$7:B$506,AE7)) | AF40: =IF(B40="","",SUMIFS('Flujo de Pagos'!I$7:I$506,'Flujo de Pagos'!E$7:E$506,B40,'Flujo de Pagos'!B$7:B$506,AF7)) | AG40: =IF(B40="","",SUMIFS('Flujo de Pagos'!I$7:I$506,'Flujo de Pagos'!E$7:E$506,B40,'Flujo de Pagos'!B$7:B$506,AG7)) | AH40: =IF(B40="","",SUMIFS('Flujo de Pagos'!I$7:I$506,'Flujo de Pagos'!E$7:E$506,B40,'Flujo de Pagos'!B$7:B$506,AH7)) | AI40: =IF(B40="","",SUMIFS('Flujo de Pagos'!I$7:I$506,'Flujo de Pagos'!E$7:E$506,B40,'Flujo de Pagos'!B$7:B$506,AI7)) | AJ40: =IF(B40="","",SUMIFS('Flujo de Pagos'!I$7:I$506,'Flujo de Pagos'!E$7:E$506,B40,'Flujo de Pagos'!B$7:B$506,AJ7)) | AK40: =IF(B40="","",SUMIFS('Flujo de Pagos'!I$7:I$506,'Flujo de Pagos'!E$7:E$506,B40,'Flujo de Pagos'!B$7:B$506,AK7)) | AL40: =IF(B40="","",SUMIFS('Flujo de Pagos'!I$7:I$506,'Flujo de Pagos'!E$7:E$506,B40,'Flujo de Pagos'!B$7:B$506,AL7)) | AM40: =IF(B40="","",SUM(C40:AL40))
B41: =IF(Presupuesto!B38="","",Presupuesto!B38) | C41: =IF(B41="","",SUMIFS('Flujo de Pagos'!I$7:I$506,'Flujo de Pagos'!E$7:E$506,B41,'Flujo de Pagos'!B$7:B$506,C7)) | D41: =IF(B41="","",SUMIFS('Flujo de Pagos'!I$7:I$506,'Flujo de Pagos'!E$7:E$506,B41,'Flujo de Pagos'!B$7:B$506,D7)) | E41: =IF(B41="","",SUMIFS('Flujo de Pagos'!I$7:I$506,'Flujo de Pagos'!E$7:E$506,B41,'Flujo de Pagos'!B$7:B$506,E7)) | F41: =IF(B41="","",SUMIFS('Flujo de Pagos'!I$7:I$506,'Flujo de Pagos'!E$7:E$506,B41,'Flujo de Pagos'!B$7:B$506,F7)) | G41: =IF(B41="","",SUMIFS('Flujo de Pagos'!I$7:I$506,'Flujo de Pagos'!E$7:E$506,B41,'Flujo de Pagos'!B$7:B$506,G7)) | H41: =IF(B41="","",SUMIFS('Flujo de Pagos'!I$7:I$506,'Flujo de Pagos'!E$7:E$506,B41,'Flujo de Pagos'!B$7:B$506,H7)) | I41: =IF(B41="","",SUMIFS('Flujo de Pagos'!I$7:I$506,'Flujo de Pagos'!E$7:E$506,B41,'Flujo de Pagos'!B$7:B$506,I7)) | J41: =IF(B41="","",SUMIFS('Flujo de Pagos'!I$7:I$506,'Flujo de Pagos'!E$7:E$506,B41,'Flujo de Pagos'!B$7:B$506,J7)) | K41: =IF(B41="","",SUMIFS('Flujo de Pagos'!I$7:I$506,'Flujo de Pagos'!E$7:E$506,B41,'Flujo de Pagos'!B$7:B$506,K7)) | L41: =IF(B41="","",SUMIFS('Flujo de Pagos'!I$7:I$506,'Flujo de Pagos'!E$7:E$506,B41,'Flujo de Pagos'!B$7:B$506,L7)) | M41: =IF(B41="","",SUMIFS('Flujo de Pagos'!I$7:I$506,'Flujo de Pagos'!E$7:E$506,B41,'Flujo de Pagos'!B$7:B$506,M7)) | N41: =IF(B41="","",SUMIFS('Flujo de Pagos'!I$7:I$506,'Flujo de Pagos'!E$7:E$506,B41,'Flujo de Pagos'!B$7:B$506,N7)) | O41: =IF(B41="","",SUMIFS('Flujo de Pagos'!I$7:I$506,'Flujo de Pagos'!E$7:E$506,B41,'Flujo de Pagos'!B$7:B$506,O7)) | P41: =IF(B41="","",SUMIFS('Flujo de Pagos'!I$7:I$506,'Flujo de Pagos'!E$7:E$506,B41,'Flujo de Pagos'!B$7:B$506,P7)) | Q41: =IF(B41="","",SUMIFS('Flujo de Pagos'!I$7:I$506,'Flujo de Pagos'!E$7:E$506,B41,'Flujo de Pagos'!B$7:B$506,Q7)) | R41: =IF(B41="","",SUMIFS('Flujo de Pagos'!I$7:I$506,'Flujo de Pagos'!E$7:E$506,B41,'Flujo de Pagos'!B$7:B$506,R7)) | S41: =IF(B41="","",SUMIFS('Flujo de Pagos'!I$7:I$506,'Flujo de Pagos'!E$7:E$506,B41,'Flujo de Pagos'!B$7:B$506,S7)) | T41: =IF(B41="","",SUMIFS('Flujo de Pagos'!I$7:I$506,'Flujo de Pagos'!E$7:E$506,B41,'Flujo de Pagos'!B$7:B$506,T7)) | U41: =IF(B41="","",SUMIFS('Flujo de Pagos'!I$7:I$506,'Flujo de Pagos'!E$7:E$506,B41,'Flujo de Pagos'!B$7:B$506,U7)) | V41: =IF(B41="","",SUMIFS('Flujo de Pagos'!I$7:I$506,'Flujo de Pagos'!E$7:E$506,B41,'Flujo de Pagos'!B$7:B$506,V7)) | W41: =IF(B41="","",SUMIFS('Flujo de Pagos'!I$7:I$506,'Flujo de Pagos'!E$7:E$506,B41,'Flujo de Pagos'!B$7:B$506,W7)) | X41: =IF(B41="","",SUMIFS('Flujo de Pagos'!I$7:I$506,'Flujo de Pagos'!E$7:E$506,B41,'Flujo de Pagos'!B$7:B$506,X7)) | Y41: =IF(B41="","",SUMIFS('Flujo de Pagos'!I$7:I$506,'Flujo de Pagos'!E$7:E$506,B41,'Flujo de Pagos'!B$7:B$506,Y7)) | Z41: =IF(B41="","",SUMIFS('Flujo de Pagos'!I$7:I$506,'Flujo de Pagos'!E$7:E$506,B41,'Flujo de Pagos'!B$7:B$506,Z7)) | AA41: =IF(B41="","",SUMIFS('Flujo de Pagos'!I$7:I$506,'Flujo de Pagos'!E$7:E$506,B41,'Flujo de Pagos'!B$7:B$506,AA7)) | AB41: =IF(B41="","",SUMIFS('Flujo de Pagos'!I$7:I$506,'Flujo de Pagos'!E$7:E$506,B41,'Flujo de Pagos'!B$7:B$506,AB7)) | AC41: =IF(B41="","",SUMIFS('Flujo de Pagos'!I$7:I$506,'Flujo de Pagos'!E$7:E$506,B41,'Flujo de Pagos'!B$7:B$506,AC7)) | AD41: =IF(B41="","",SUMIFS('Flujo de Pagos'!I$7:I$506,'Flujo de Pagos'!E$7:E$506,B41,'Flujo de Pagos'!B$7:B$506,AD7)) | AE41: =IF(B41="","",SUMIFS('Flujo de Pagos'!I$7:I$506,'Flujo de Pagos'!E$7:E$506,B41,'Flujo de Pagos'!B$7:B$506,AE7)) | AF41: =IF(B41="","",SUMIFS('Flujo de Pagos'!I$7:I$506,'Flujo de Pagos'!E$7:E$506,B41,'Flujo de Pagos'!B$7:B$506,AF7)) | AG41: =IF(B41="","",SUMIFS('Flujo de Pagos'!I$7:I$506,'Flujo de Pagos'!E$7:E$506,B41,'Flujo de Pagos'!B$7:B$506,AG7)) | AH41: =IF(B41="","",SUMIFS('Flujo de Pagos'!I$7:I$506,'Flujo de Pagos'!E$7:E$506,B41,'Flujo de Pagos'!B$7:B$506,AH7)) | AI41: =IF(B41="","",SUMIFS('Flujo de Pagos'!I$7:I$506,'Flujo de Pagos'!E$7:E$506,B41,'Flujo de Pagos'!B$7:B$506,AI7)) | AJ41: =IF(B41="","",SUMIFS('Flujo de Pagos'!I$7:I$506,'Flujo de Pagos'!E$7:E$506,B41,'Flujo de Pagos'!B$7:B$506,AJ7)) | AK41: =IF(B41="","",SUMIFS('Flujo de Pagos'!I$7:I$506,'Flujo de Pagos'!E$7:E$506,B41,'Flujo de Pagos'!B$7:B$506,AK7)) | AL41: =IF(B41="","",SUMIFS('Flujo de Pagos'!I$7:I$506,'Flujo de Pagos'!E$7:E$506,B41,'Flujo de Pagos'!B$7:B$506,AL7)) | AM41: =IF(B41="","",SUM(C41:AL41))
B42: =IF(Presupuesto!B39="","",Presupuesto!B39) | C42: =IF(B42="","",SUMIFS('Flujo de Pagos'!I$7:I$506,'Flujo de Pagos'!E$7:E$506,B42,'Flujo de Pagos'!B$7:B$506,C7)) | D42: =IF(B42="","",SUMIFS('Flujo de Pagos'!I$7:I$506,'Flujo de Pagos'!E$7:E$506,B42,'Flujo de Pagos'!B$7:B$506,D7)) | E42: =IF(B42="","",SUMIFS('Flujo de Pagos'!I$7:I$506,'Flujo de Pagos'!E$7:E$506,B42,'Flujo de Pagos'!B$7:B$506,E7)) | F42: =IF(B42="","",SUMIFS('Flujo de Pagos'!I$7:I$506,'Flujo de Pagos'!E$7:E$506,B42,'Flujo de Pagos'!B$7:B$506,F7)) | G42: =IF(B42="","",SUMIFS('Flujo de Pagos'!I$7:I$506,'Flujo de Pagos'!E$7:E$506,B42,'Flujo de Pagos'!B$7:B$506,G7)) | H42: =IF(B42="","",SUMIFS('Flujo de Pagos'!I$7:I$506,'Flujo de Pagos'!E$7:E$506,B42,'Flujo de Pagos'!B$7:B$506,H7)) | I42: =IF(B42="","",SUMIFS('Flujo de Pagos'!I$7:I$506,'Flujo de Pagos'!E$7:E$506,B42,'Flujo de Pagos'!B$7:B$506,I7)) | J42: =IF(B42="","",SUMIFS('Flujo de Pagos'!I$7:I$506,'Flujo de Pagos'!E$7:E$506,B42,'Flujo de Pagos'!B$7:B$506,J7)) | K42: =IF(B42="","",SUMIFS('Flujo de Pagos'!I$7:I$506,'Flujo de Pagos'!E$7:E$506,B42,'Flujo de Pagos'!B$7:B$506,K7)) | L42: =IF(B42="","",SUMIFS('Flujo de Pagos'!I$7:I$506,'Flujo de Pagos'!E$7:E$506,B42,'Flujo de Pagos'!B$7:B$506,L7)) | M42: =IF(B42="","",SUMIFS('Flujo de Pagos'!I$7:I$506,'Flujo de Pagos'!E$7:E$506,B42,'Flujo de Pagos'!B$7:B$506,M7)) | N42: =IF(B42="","",SUMIFS('Flujo de Pagos'!I$7:I$506,'Flujo de Pagos'!E$7:E$506,B42,'Flujo de Pagos'!B$7:B$506,N7)) | O42: =IF(B42="","",SUMIFS('Flujo de Pagos'!I$7:I$506,'Flujo de Pagos'!E$7:E$506,B42,'Flujo de Pagos'!B$7:B$506,O7)) | P42: =IF(B42="","",SUMIFS('Flujo de Pagos'!I$7:I$506,'Flujo de Pagos'!E$7:E$506,B42,'Flujo de Pagos'!B$7:B$506,P7)) | Q42: =IF(B42="","",SUMIFS('Flujo de Pagos'!I$7:I$506,'Flujo de Pagos'!E$7:E$506,B42,'Flujo de Pagos'!B$7:B$506,Q7)) | R42: =IF(B42="","",SUMIFS('Flujo de Pagos'!I$7:I$506,'Flujo de Pagos'!E$7:E$506,B42,'Flujo de Pagos'!B$7:B$506,R7)) | S42: =IF(B42="","",SUMIFS('Flujo de Pagos'!I$7:I$506,'Flujo de Pagos'!E$7:E$506,B42,'Flujo de Pagos'!B$7:B$506,S7)) | T42: =IF(B42="","",SUMIFS('Flujo de Pagos'!I$7:I$506,'Flujo de Pagos'!E$7:E$506,B42,'Flujo de Pagos'!B$7:B$506,T7)) | U42: =IF(B42="","",SUMIFS('Flujo de Pagos'!I$7:I$506,'Flujo de Pagos'!E$7:E$506,B42,'Flujo de Pagos'!B$7:B$506,U7)) | V42: =IF(B42="","",SUMIFS('Flujo de Pagos'!I$7:I$506,'Flujo de Pagos'!E$7:E$506,B42,'Flujo de Pagos'!B$7:B$506,V7)) | W42: =IF(B42="","",SUMIFS('Flujo de Pagos'!I$7:I$506,'Flujo de Pagos'!E$7:E$506,B42,'Flujo de Pagos'!B$7:B$506,W7)) | X42: =IF(B42="","",SUMIFS('Flujo de Pagos'!I$7:I$506,'Flujo de Pagos'!E$7:E$506,B42,'Flujo de Pagos'!B$7:B$506,X7)) | Y42: =IF(B42="","",SUMIFS('Flujo de Pagos'!I$7:I$506,'Flujo de Pagos'!E$7:E$506,B42,'Flujo de Pagos'!B$7:B$506,Y7)) | Z42: =IF(B42="","",SUMIFS('Flujo de Pagos'!I$7:I$506,'Flujo de Pagos'!E$7:E$506,B42,'Flujo de Pagos'!B$7:B$506,Z7)) | AA42: =IF(B42="","",SUMIFS('Flujo de Pagos'!I$7:I$506,'Flujo de Pagos'!E$7:E$506,B42,'Flujo de Pagos'!B$7:B$506,AA7)) | AB42: =IF(B42="","",SUMIFS('Flujo de Pagos'!I$7:I$506,'Flujo de Pagos'!E$7:E$506,B42,'Flujo de Pagos'!B$7:B$506,AB7)) | AC42: =IF(B42="","",SUMIFS('Flujo de Pagos'!I$7:I$506,'Flujo de Pagos'!E$7:E$506,B42,'Flujo de Pagos'!B$7:B$506,AC7)) | AD42: =IF(B42="","",SUMIFS('Flujo de Pagos'!I$7:I$506,'Flujo de Pagos'!E$7:E$506,B42,'Flujo de Pagos'!B$7:B$506,AD7)) | AE42: =IF(B42="","",SUMIFS('Flujo de Pagos'!I$7:I$506,'Flujo de Pagos'!E$7:E$506,B42,'Flujo de Pagos'!B$7:B$506,AE7)) | AF42: =IF(B42="","",SUMIFS('Flujo de Pagos'!I$7:I$506,'Flujo de Pagos'!E$7:E$506,B42,'Flujo de Pagos'!B$7:B$506,AF7)) | AG42: =IF(B42="","",SUMIFS('Flujo de Pagos'!I$7:I$506,'Flujo de Pagos'!E$7:E$506,B42,'Flujo de Pagos'!B$7:B$506,AG7)) | AH42: =IF(B42="","",SUMIFS('Flujo de Pagos'!I$7:I$506,'Flujo de Pagos'!E$7:E$506,B42,'Flujo de Pagos'!B$7:B$506,AH7)) | AI42: =IF(B42="","",SUMIFS('Flujo de Pagos'!I$7:I$506,'Flujo de Pagos'!E$7:E$506,B42,'Flujo de Pagos'!B$7:B$506,AI7)) | AJ42: =IF(B42="","",SUMIFS('Flujo de Pagos'!I$7:I$506,'Flujo de Pagos'!E$7:E$506,B42,'Flujo de Pagos'!B$7:B$506,AJ7)) | AK42: =IF(B42="","",SUMIFS('Flujo de Pagos'!I$7:I$506,'Flujo de Pagos'!E$7:E$506,B42,'Flujo de Pagos'!B$7:B$506,AK7)) | AL42: =IF(B42="","",SUMIFS('Flujo de Pagos'!I$7:I$506,'Flujo de Pagos'!E$7:E$506,B42,'Flujo de Pagos'!B$7:B$506,AL7)) | AM42: =IF(B42="","",SUM(C42:AL42))
B43: =IF(Presupuesto!B40="","",Presupuesto!B40) | C43: =IF(B43="","",SUMIFS('Flujo de Pagos'!I$7:I$506,'Flujo de Pagos'!E$7:E$506,B43,'Flujo de Pagos'!B$7:B$506,C7)) | D43: =IF(B43="","",SUMIFS('Flujo de Pagos'!I$7:I$506,'Flujo de Pagos'!E$7:E$506,B43,'Flujo de Pagos'!B$7:B$506,D7)) | E43: =IF(B43="","",SUMIFS('Flujo de Pagos'!I$7:I$506,'Flujo de Pagos'!E$7:E$506,B43,'Flujo de Pagos'!B$7:B$506,E7)) | F43: =IF(B43="","",SUMIFS('Flujo de Pagos'!I$7:I$506,'Flujo de Pagos'!E$7:E$506,B43,'Flujo de Pagos'!B$7:B$506,F7)) | G43: =IF(B43="","",SUMIFS('Flujo de Pagos'!I$7:I$506,'Flujo de Pagos'!E$7:E$506,B43,'Flujo de Pagos'!B$7:B$506,G7)) | H43: =IF(B43="","",SUMIFS('Flujo de Pagos'!I$7:I$506,'Flujo de Pagos'!E$7:E$506,B43,'Flujo de Pagos'!B$7:B$506,H7)) | I43: =IF(B43="","",SUMIFS('Flujo de Pagos'!I$7:I$506,'Flujo de Pagos'!E$7:E$506,B43,'Flujo de Pagos'!B$7:B$506,I7)) | J43: =IF(B43="","",SUMIFS('Flujo de Pagos'!I$7:I$506,'Flujo de Pagos'!E$7:E$506,B43,'Flujo de Pagos'!B$7:B$506,J7)) | K43: =IF(B43="","",SUMIFS('Flujo de Pagos'!I$7:I$506,'Flujo de Pagos'!E$7:E$506,B43,'Flujo de Pagos'!B$7:B$506,K7)) | L43: =IF(B43="","",SUMIFS('Flujo de Pagos'!I$7:I$506,'Flujo de Pagos'!E$7:E$506,B43,'Flujo de Pagos'!B$7:B$506,L7)) | M43: =IF(B43="","",SUMIFS('Flujo de Pagos'!I$7:I$506,'Flujo de Pagos'!E$7:E$506,B43,'Flujo de Pagos'!B$7:B$506,M7)) | N43: =IF(B43="","",SUMIFS('Flujo de Pagos'!I$7:I$506,'Flujo de Pagos'!E$7:E$506,B43,'Flujo de Pagos'!B$7:B$506,N7)) | O43: =IF(B43="","",SUMIFS('Flujo de Pagos'!I$7:I$506,'Flujo de Pagos'!E$7:E$506,B43,'Flujo de Pagos'!B$7:B$506,O7)) | P43: =IF(B43="","",SUMIFS('Flujo de Pagos'!I$7:I$506,'Flujo de Pagos'!E$7:E$506,B43,'Flujo de Pagos'!B$7:B$506,P7)) | Q43: =IF(B43="","",SUMIFS('Flujo de Pagos'!I$7:I$506,'Flujo de Pagos'!E$7:E$506,B43,'Flujo de Pagos'!B$7:B$506,Q7)) | R43: =IF(B43="","",SUMIFS('Flujo de Pagos'!I$7:I$506,'Flujo de Pagos'!E$7:E$506,B43,'Flujo de Pagos'!B$7:B$506,R7)) | S43: =IF(B43="","",SUMIFS('Flujo de Pagos'!I$7:I$506,'Flujo de Pagos'!E$7:E$506,B43,'Flujo de Pagos'!B$7:B$506,S7)) | T43: =IF(B43="","",SUMIFS('Flujo de Pagos'!I$7:I$506,'Flujo de Pagos'!E$7:E$506,B43,'Flujo de Pagos'!B$7:B$506,T7)) | U43: =IF(B43="","",SUMIFS('Flujo de Pagos'!I$7:I$506,'Flujo de Pagos'!E$7:E$506,B43,'Flujo de Pagos'!B$7:B$506,U7)) | V43: =IF(B43="","",SUMIFS('Flujo de Pagos'!I$7:I$506,'Flujo de Pagos'!E$7:E$506,B43,'Flujo de Pagos'!B$7:B$506,V7)) | W43: =IF(B43="","",SUMIFS('Flujo de Pagos'!I$7:I$506,'Flujo de Pagos'!E$7:E$506,B43,'Flujo de Pagos'!B$7:B$506,W7)) | X43: =IF(B43="","",SUMIFS('Flujo de Pagos'!I$7:I$506,'Flujo de Pagos'!E$7:E$506,B43,'Flujo de Pagos'!B$7:B$506,X7)) | Y43: =IF(B43="","",SUMIFS('Flujo de Pagos'!I$7:I$506,'Flujo de Pagos'!E$7:E$506,B43,'Flujo de Pagos'!B$7:B$506,Y7)) | Z43: =IF(B43="","",SUMIFS('Flujo de Pagos'!I$7:I$506,'Flujo de Pagos'!E$7:E$506,B43,'Flujo de Pagos'!B$7:B$506,Z7)) | AA43: =IF(B43="","",SUMIFS('Flujo de Pagos'!I$7:I$506,'Flujo de Pagos'!E$7:E$506,B43,'Flujo de Pagos'!B$7:B$506,AA7)) | AB43: =IF(B43="","",SUMIFS('Flujo de Pagos'!I$7:I$506,'Flujo de Pagos'!E$7:E$506,B43,'Flujo de Pagos'!B$7:B$506,AB7)) | AC43: =IF(B43="","",SUMIFS('Flujo de Pagos'!I$7:I$506,'Flujo de Pagos'!E$7:E$506,B43,'Flujo de Pagos'!B$7:B$506,AC7)) | AD43: =IF(B43="","",SUMIFS('Flujo de Pagos'!I$7:I$506,'Flujo de Pagos'!E$7:E$506,B43,'Flujo de Pagos'!B$7:B$506,AD7)) | AE43: =IF(B43="","",SUMIFS('Flujo de Pagos'!I$7:I$506,'Flujo de Pagos'!E$7:E$506,B43,'Flujo de Pagos'!B$7:B$506,AE7)) | AF43: =IF(B43="","",SUMIFS('Flujo de Pagos'!I$7:I$506,'Flujo de Pagos'!E$7:E$506,B43,'Flujo de Pagos'!B$7:B$506,AF7)) | AG43: =IF(B43="","",SUMIFS('Flujo de Pagos'!I$7:I$506,'Flujo de Pagos'!E$7:E$506,B43,'Flujo de Pagos'!B$7:B$506,AG7)) | AH43: =IF(B43="","",SUMIFS('Flujo de Pagos'!I$7:I$506,'Flujo de Pagos'!E$7:E$506,B43,'Flujo de Pagos'!B$7:B$506,AH7)) | AI43: =IF(B43="","",SUMIFS('Flujo de Pagos'!I$7:I$506,'Flujo de Pagos'!E$7:E$506,B43,'Flujo de Pagos'!B$7:B$506,AI7)) | AJ43: =IF(B43="","",SUMIFS('Flujo de Pagos'!I$7:I$506,'Flujo de Pagos'!E$7:E$506,B43,'Flujo de Pagos'!B$7:B$506,AJ7)) | AK43: =IF(B43="","",SUMIFS('Flujo de Pagos'!I$7:I$506,'Flujo de Pagos'!E$7:E$506,B43,'Flujo de Pagos'!B$7:B$506,AK7)) | AL43: =IF(B43="","",SUMIFS('Flujo de Pagos'!I$7:I$506,'Flujo de Pagos'!E$7:E$506,B43,'Flujo de Pagos'!B$7:B$506,AL7)) | AM43: =IF(B43="","",SUM(C43:AL43))
B44: =IF(Presupuesto!B41="","",Presupuesto!B41) | C44: =IF(B44="","",SUMIFS('Flujo de Pagos'!I$7:I$506,'Flujo de Pagos'!E$7:E$506,B44,'Flujo de Pagos'!B$7:B$506,C7)) | D44: =IF(B44="","",SUMIFS('Flujo de Pagos'!I$7:I$506,'Flujo de Pagos'!E$7:E$506,B44,'Flujo de Pagos'!B$7:B$506,D7)) | E44: =IF(B44="","",SUMIFS('Flujo de Pagos'!I$7:I$506,'Flujo de Pagos'!E$7:E$506,B44,'Flujo de Pagos'!B$7:B$506,E7)) | F44: =IF(B44="","",SUMIFS('Flujo de Pagos'!I$7:I$506,'Flujo de Pagos'!E$7:E$506,B44,'Flujo de Pagos'!B$7:B$506,F7)) | G44: =IF(B44="","",SUMIFS('Flujo de Pagos'!I$7:I$506,'Flujo de Pagos'!E$7:E$506,B44,'Flujo de Pagos'!B$7:B$506,G7)) | H44: =IF(B44="","",SUMIFS('Flujo de Pagos'!I$7:I$506,'Flujo de Pagos'!E$7:E$506,B44,'Flujo de Pagos'!B$7:B$506,H7)) | I44: =IF(B44="","",SUMIFS('Flujo de Pagos'!I$7:I$506,'Flujo de Pagos'!E$7:E$506,B44,'Flujo de Pagos'!B$7:B$506,I7)) | J44: =IF(B44="","",SUMIFS('Flujo de Pagos'!I$7:I$506,'Flujo de Pagos'!E$7:E$506,B44,'Flujo de Pagos'!B$7:B$506,J7)) | K44: =IF(B44="","",SUMIFS('Flujo de Pagos'!I$7:I$506,'Flujo de Pagos'!E$7:E$506,B44,'Flujo de Pagos'!B$7:B$506,K7)) | L44: =IF(B44="","",SUMIFS('Flujo de Pagos'!I$7:I$506,'Flujo de Pagos'!E$7:E$506,B44,'Flujo de Pagos'!B$7:B$506,L7)) | M44: =IF(B44="","",SUMIFS('Flujo de Pagos'!I$7:I$506,'Flujo de Pagos'!E$7:E$506,B44,'Flujo de Pagos'!B$7:B$506,M7)) | N44: =IF(B44="","",SUMIFS('Flujo de Pagos'!I$7:I$506,'Flujo de Pagos'!E$7:E$506,B44,'Flujo de Pagos'!B$7:B$506,N7)) | O44: =IF(B44="","",SUMIFS('Flujo de Pagos'!I$7:I$506,'Flujo de Pagos'!E$7:E$506,B44,'Flujo de Pagos'!B$7:B$506,O7)) | P44: =IF(B44="","",SUMIFS('Flujo de Pagos'!I$7:I$506,'Flujo de Pagos'!E$7:E$506,B44,'Flujo de Pagos'!B$7:B$506,P7)) | Q44: =IF(B44="","",SUMIFS('Flujo de Pagos'!I$7:I$506,'Flujo de Pagos'!E$7:E$506,B44,'Flujo de Pagos'!B$7:B$506,Q7)) | R44: =IF(B44="","",SUMIFS('Flujo de Pagos'!I$7:I$506,'Flujo de Pagos'!E$7:E$506,B44,'Flujo de Pagos'!B$7:B$506,R7)) | S44: =IF(B44="","",SUMIFS('Flujo de Pagos'!I$7:I$506,'Flujo de Pagos'!E$7:E$506,B44,'Flujo de Pagos'!B$7:B$506,S7)) | T44: =IF(B44="","",SUMIFS('Flujo de Pagos'!I$7:I$506,'Flujo de Pagos'!E$7:E$506,B44,'Flujo de Pagos'!B$7:B$506,T7)) | U44: =IF(B44="","",SUMIFS('Flujo de Pagos'!I$7:I$506,'Flujo de Pagos'!E$7:E$506,B44,'Flujo de Pagos'!B$7:B$506,U7)) | V44: =IF(B44="","",SUMIFS('Flujo de Pagos'!I$7:I$506,'Flujo de Pagos'!E$7:E$506,B44,'Flujo de Pagos'!B$7:B$506,V7)) | W44: =IF(B44="","",SUMIFS('Flujo de Pagos'!I$7:I$506,'Flujo de Pagos'!E$7:E$506,B44,'Flujo de Pagos'!B$7:B$506,W7)) | X44: =IF(B44="","",SUMIFS('Flujo de Pagos'!I$7:I$506,'Flujo de Pagos'!E$7:E$506,B44,'Flujo de Pagos'!B$7:B$506,X7)) | Y44: =IF(B44="","",SUMIFS('Flujo de Pagos'!I$7:I$506,'Flujo de Pagos'!E$7:E$506,B44,'Flujo de Pagos'!B$7:B$506,Y7)) | Z44: =IF(B44="","",SUMIFS('Flujo de Pagos'!I$7:I$506,'Flujo de Pagos'!E$7:E$506,B44,'Flujo de Pagos'!B$7:B$506,Z7)) | AA44: =IF(B44="","",SUMIFS('Flujo de Pagos'!I$7:I$506,'Flujo de Pagos'!E$7:E$506,B44,'Flujo de Pagos'!B$7:B$506,AA7)) | AB44: =IF(B44="","",SUMIFS('Flujo de Pagos'!I$7:I$506,'Flujo de Pagos'!E$7:E$506,B44,'Flujo de Pagos'!B$7:B$506,AB7)) | AC44: =IF(B44="","",SUMIFS('Flujo de Pagos'!I$7:I$506,'Flujo de Pagos'!E$7:E$506,B44,'Flujo de Pagos'!B$7:B$506,AC7)) | AD44: =IF(B44="","",SUMIFS('Flujo de Pagos'!I$7:I$506,'Flujo de Pagos'!E$7:E$506,B44,'Flujo de Pagos'!B$7:B$506,AD7)) | AE44: =IF(B44="","",SUMIFS('Flujo de Pagos'!I$7:I$506,'Flujo de Pagos'!E$7:E$506,B44,'Flujo de Pagos'!B$7:B$506,AE7)) | AF44: =IF(B44="","",SUMIFS('Flujo de Pagos'!I$7:I$506,'Flujo de Pagos'!E$7:E$506,B44,'Flujo de Pagos'!B$7:B$506,AF7)) | AG44: =IF(B44="","",SUMIFS('Flujo de Pagos'!I$7:I$506,'Flujo de Pagos'!E$7:E$506,B44,'Flujo de Pagos'!B$7:B$506,AG7)) | AH44: =IF(B44="","",SUMIFS('Flujo de Pagos'!I$7:I$506,'Flujo de Pagos'!E$7:E$506,B44,'Flujo de Pagos'!B$7:B$506,AH7)) | AI44: =IF(B44="","",SUMIFS('Flujo de Pagos'!I$7:I$506,'Flujo de Pagos'!E$7:E$506,B44,'Flujo de Pagos'!B$7:B$506,AI7)) | AJ44: =IF(B44="","",SUMIFS('Flujo de Pagos'!I$7:I$506,'Flujo de Pagos'!E$7:E$506,B44,'Flujo de Pagos'!B$7:B$506,AJ7)) | AK44: =IF(B44="","",SUMIFS('Flujo de Pagos'!I$7:I$506,'Flujo de Pagos'!E$7:E$506,B44,'Flujo de Pagos'!B$7:B$506,AK7)) | AL44: =IF(B44="","",SUMIFS('Flujo de Pagos'!I$7:I$506,'Flujo de Pagos'!E$7:E$506,B44,'Flujo de Pagos'!B$7:B$506,AL7)) | AM44: =IF(B44="","",SUM(C44:AL44))
B45: =IF(Presupuesto!B42="","",Presupuesto!B42) | C45: =IF(B45="","",SUMIFS('Flujo de Pagos'!I$7:I$506,'Flujo de Pagos'!E$7:E$506,B45,'Flujo de Pagos'!B$7:B$506,C7)) | D45: =IF(B45="","",SUMIFS('Flujo de Pagos'!I$7:I$506,'Flujo de Pagos'!E$7:E$506,B45,'Flujo de Pagos'!B$7:B$506,D7)) | E45: =IF(B45="","",SUMIFS('Flujo de Pagos'!I$7:I$506,'Flujo de Pagos'!E$7:E$506,B45,'Flujo de Pagos'!B$7:B$506,E7)) | F45: =IF(B45="","",SUMIFS('Flujo de Pagos'!I$7:I$506,'Flujo de Pagos'!E$7:E$506,B45,'Flujo de Pagos'!B$7:B$506,F7)) | G45: =IF(B45="","",SUMIFS('Flujo de Pagos'!I$7:I$506,'Flujo de Pagos'!E$7:E$506,B45,'Flujo de Pagos'!B$7:B$506,G7)) | H45: =IF(B45="","",SUMIFS('Flujo de Pagos'!I$7:I$506,'Flujo de Pagos'!E$7:E$506,B45,'Flujo de Pagos'!B$7:B$506,H7)) | I45: =IF(B45="","",SUMIFS('Flujo de Pagos'!I$7:I$506,'Flujo de Pagos'!E$7:E$506,B45,'Flujo de Pagos'!B$7:B$506,I7)) | J45: =IF(B45="","",SUMIFS('Flujo de Pagos'!I$7:I$506,'Flujo de Pagos'!E$7:E$506,B45,'Flujo de Pagos'!B$7:B$506,J7)) | K45: =IF(B45="","",SUMIFS('Flujo de Pagos'!I$7:I$506,'Flujo de Pagos'!E$7:E$506,B45,'Flujo de Pagos'!B$7:B$506,K7)) | L45: =IF(B45="","",SUMIFS('Flujo de Pagos'!I$7:I$506,'Flujo de Pagos'!E$7:E$506,B45,'Flujo de Pagos'!B$7:B$506,L7)) | M45: =IF(B45="","",SUMIFS('Flujo de Pagos'!I$7:I$506,'Flujo de Pagos'!E$7:E$506,B45,'Flujo de Pagos'!B$7:B$506,M7)) | N45: =IF(B45="","",SUMIFS('Flujo de Pagos'!I$7:I$506,'Flujo de Pagos'!E$7:E$506,B45,'Flujo de Pagos'!B$7:B$506,N7)) | O45: =IF(B45="","",SUMIFS('Flujo de Pagos'!I$7:I$506,'Flujo de Pagos'!E$7:E$506,B45,'Flujo de Pagos'!B$7:B$506,O7)) | P45: =IF(B45="","",SUMIFS('Flujo de Pagos'!I$7:I$506,'Flujo de Pagos'!E$7:E$506,B45,'Flujo de Pagos'!B$7:B$506,P7)) | Q45: =IF(B45="","",SUMIFS('Flujo de Pagos'!I$7:I$506,'Flujo de Pagos'!E$7:E$506,B45,'Flujo de Pagos'!B$7:B$506,Q7)) | R45: =IF(B45="","",SUMIFS('Flujo de Pagos'!I$7:I$506,'Flujo de Pagos'!E$7:E$506,B45,'Flujo de Pagos'!B$7:B$506,R7)) | S45: =IF(B45="","",SUMIFS('Flujo de Pagos'!I$7:I$506,'Flujo de Pagos'!E$7:E$506,B45,'Flujo de Pagos'!B$7:B$506,S7)) | T45: =IF(B45="","",SUMIFS('Flujo de Pagos'!I$7:I$506,'Flujo de Pagos'!E$7:E$506,B45,'Flujo de Pagos'!B$7:B$506,T7)) | U45: =IF(B45="","",SUMIFS('Flujo de Pagos'!I$7:I$506,'Flujo de Pagos'!E$7:E$506,B45,'Flujo de Pagos'!B$7:B$506,U7)) | V45: =IF(B45="","",SUMIFS('Flujo de Pagos'!I$7:I$506,'Flujo de Pagos'!E$7:E$506,B45,'Flujo de Pagos'!B$7:B$506,V7)) | W45: =IF(B45="","",SUMIFS('Flujo de Pagos'!I$7:I$506,'Flujo de Pagos'!E$7:E$506,B45,'Flujo de Pagos'!B$7:B$506,W7)) | X45: =IF(B45="","",SUMIFS('Flujo de Pagos'!I$7:I$506,'Flujo de Pagos'!E$7:E$506,B45,'Flujo de Pagos'!B$7:B$506,X7)) | Y45: =IF(B45="","",SUMIFS('Flujo de Pagos'!I$7:I$506,'Flujo de Pagos'!E$7:E$506,B45,'Flujo de Pagos'!B$7:B$506,Y7)) | Z45: =IF(B45="","",SUMIFS('Flujo de Pagos'!I$7:I$506,'Flujo de Pagos'!E$7:E$506,B45,'Flujo de Pagos'!B$7:B$506,Z7)) | AA45: =IF(B45="","",SUMIFS('Flujo de Pagos'!I$7:I$506,'Flujo de Pagos'!E$7:E$506,B45,'Flujo de Pagos'!B$7:B$506,AA7)) | AB45: =IF(B45="","",SUMIFS('Flujo de Pagos'!I$7:I$506,'Flujo de Pagos'!E$7:E$506,B45,'Flujo de Pagos'!B$7:B$506,AB7)) | AC45: =IF(B45="","",SUMIFS('Flujo de Pagos'!I$7:I$506,'Flujo de Pagos'!E$7:E$506,B45,'Flujo de Pagos'!B$7:B$506,AC7)) | AD45: =IF(B45="","",SUMIFS('Flujo de Pagos'!I$7:I$506,'Flujo de Pagos'!E$7:E$506,B45,'Flujo de Pagos'!B$7:B$506,AD7)) | AE45: =IF(B45="","",SUMIFS('Flujo de Pagos'!I$7:I$506,'Flujo de Pagos'!E$7:E$506,B45,'Flujo de Pagos'!B$7:B$506,AE7)) | AF45: =IF(B45="","",SUMIFS('Flujo de Pagos'!I$7:I$506,'Flujo de Pagos'!E$7:E$506,B45,'Flujo de Pagos'!B$7:B$506,AF7)) | AG45: =IF(B45="","",SUMIFS('Flujo de Pagos'!I$7:I$506,'Flujo de Pagos'!E$7:E$506,B45,'Flujo de Pagos'!B$7:B$506,AG7)) | AH45: =IF(B45="","",SUMIFS('Flujo de Pagos'!I$7:I$506,'Flujo de Pagos'!E$7:E$506,B45,'Flujo de Pagos'!B$7:B$506,AH7)) | AI45: =IF(B45="","",SUMIFS('Flujo de Pagos'!I$7:I$506,'Flujo de Pagos'!E$7:E$506,B45,'Flujo de Pagos'!B$7:B$506,AI7)) | AJ45: =IF(B45="","",SUMIFS('Flujo de Pagos'!I$7:I$506,'Flujo de Pagos'!E$7:E$506,B45,'Flujo de Pagos'!B$7:B$506,AJ7)) | AK45: =IF(B45="","",SUMIFS('Flujo de Pagos'!I$7:I$506,'Flujo de Pagos'!E$7:E$506,B45,'Flujo de Pagos'!B$7:B$506,AK7)) | AL45: =IF(B45="","",SUMIFS('Flujo de Pagos'!I$7:I$506,'Flujo de Pagos'!E$7:E$506,B45,'Flujo de Pagos'!B$7:B$506,AL7)) | AM45: =IF(B45="","",SUM(C45:AL45))
B46: =IF(Presupuesto!B43="","",Presupuesto!B43) | C46: =IF(B46="","",SUMIFS('Flujo de Pagos'!I$7:I$506,'Flujo de Pagos'!E$7:E$506,B46,'Flujo de Pagos'!B$7:B$506,C7)) | D46: =IF(B46="","",SUMIFS('Flujo de Pagos'!I$7:I$506,'Flujo de Pagos'!E$7:E$506,B46,'Flujo de Pagos'!B$7:B$506,D7)) | E46: =IF(B46="","",SUMIFS('Flujo de Pagos'!I$7:I$506,'Flujo de Pagos'!E$7:E$506,B46,'Flujo de Pagos'!B$7:B$506,E7)) | F46: =IF(B46="","",SUMIFS('Flujo de Pagos'!I$7:I$506,'Flujo de Pagos'!E$7:E$506,B46,'Flujo de Pagos'!B$7:B$506,F7)) | G46: =IF(B46="","",SUMIFS('Flujo de Pagos'!I$7:I$506,'Flujo de Pagos'!E$7:E$506,B46,'Flujo de Pagos'!B$7:B$506,G7)) | H46: =IF(B46="","",SUMIFS('Flujo de Pagos'!I$7:I$506,'Flujo de Pagos'!E$7:E$506,B46,'Flujo de Pagos'!B$7:B$506,H7)) | I46: =IF(B46="","",SUMIFS('Flujo de Pagos'!I$7:I$506,'Flujo de Pagos'!E$7:E$506,B46,'Flujo de Pagos'!B$7:B$506,I7)) | J46: =IF(B46="","",SUMIFS('Flujo de Pagos'!I$7:I$506,'Flujo de Pagos'!E$7:E$506,B46,'Flujo de Pagos'!B$7:B$506,J7)) | K46: =IF(B46="","",SUMIFS('Flujo de Pagos'!I$7:I$506,'Flujo de Pagos'!E$7:E$506,B46,'Flujo de Pagos'!B$7:B$506,K7)) | L46: =IF(B46="","",SUMIFS('Flujo de Pagos'!I$7:I$506,'Flujo de Pagos'!E$7:E$506,B46,'Flujo de Pagos'!B$7:B$506,L7)) | M46: =IF(B46="","",SUMIFS('Flujo de Pagos'!I$7:I$506,'Flujo de Pagos'!E$7:E$506,B46,'Flujo de Pagos'!B$7:B$506,M7)) | N46: =IF(B46="","",SUMIFS('Flujo de Pagos'!I$7:I$506,'Flujo de Pagos'!E$7:E$506,B46,'Flujo de Pagos'!B$7:B$506,N7)) | O46: =IF(B46="","",SUMIFS('Flujo de Pagos'!I$7:I$506,'Flujo de Pagos'!E$7:E$506,B46,'Flujo de Pagos'!B$7:B$506,O7)) | P46: =IF(B46="","",SUMIFS('Flujo de Pagos'!I$7:I$506,'Flujo de Pagos'!E$7:E$506,B46,'Flujo de Pagos'!B$7:B$506,P7)) | Q46: =IF(B46="","",SUMIFS('Flujo de Pagos'!I$7:I$506,'Flujo de Pagos'!E$7:E$506,B46,'Flujo de Pagos'!B$7:B$506,Q7)) | R46: =IF(B46="","",SUMIFS('Flujo de Pagos'!I$7:I$506,'Flujo de Pagos'!E$7:E$506,B46,'Flujo de Pagos'!B$7:B$506,R7)) | S46: =IF(B46="","",SUMIFS('Flujo de Pagos'!I$7:I$506,'Flujo de Pagos'!E$7:E$506,B46,'Flujo de Pagos'!B$7:B$506,S7)) | T46: =IF(B46="","",SUMIFS('Flujo de Pagos'!I$7:I$506,'Flujo de Pagos'!E$7:E$506,B46,'Flujo de Pagos'!B$7:B$506,T7)) | U46: =IF(B46="","",SUMIFS('Flujo de Pagos'!I$7:I$506,'Flujo de Pagos'!E$7:E$506,B46,'Flujo de Pagos'!B$7:B$506,U7)) | V46: =IF(B46="","",SUMIFS('Flujo de Pagos'!I$7:I$506,'Flujo de Pagos'!E$7:E$506,B46,'Flujo de Pagos'!B$7:B$506,V7)) | W46: =IF(B46="","",SUMIFS('Flujo de Pagos'!I$7:I$506,'Flujo de Pagos'!E$7:E$506,B46,'Flujo de Pagos'!B$7:B$506,W7)) | X46: =IF(B46="","",SUMIFS('Flujo de Pagos'!I$7:I$506,'Flujo de Pagos'!E$7:E$506,B46,'Flujo de Pagos'!B$7:B$506,X7)) | Y46: =IF(B46="","",SUMIFS('Flujo de Pagos'!I$7:I$506,'Flujo de Pagos'!E$7:E$506,B46,'Flujo de Pagos'!B$7:B$506,Y7)) | Z46: =IF(B46="","",SUMIFS('Flujo de Pagos'!I$7:I$506,'Flujo de Pagos'!E$7:E$506,B46,'Flujo de Pagos'!B$7:B$506,Z7)) | AA46: =IF(B46="","",SUMIFS('Flujo de Pagos'!I$7:I$506,'Flujo de Pagos'!E$7:E$506,B46,'Flujo de Pagos'!B$7:B$506,AA7)) | AB46: =IF(B46="","",SUMIFS('Flujo de Pagos'!I$7:I$506,'Flujo de Pagos'!E$7:E$506,B46,'Flujo de Pagos'!B$7:B$506,AB7)) | AC46: =IF(B46="","",SUMIFS('Flujo de Pagos'!I$7:I$506,'Flujo de Pagos'!E$7:E$506,B46,'Flujo de Pagos'!B$7:B$506,AC7)) | AD46: =IF(B46="","",SUMIFS('Flujo de Pagos'!I$7:I$506,'Flujo de Pagos'!E$7:E$506,B46,'Flujo de Pagos'!B$7:B$506,AD7)) | AE46: =IF(B46="","",SUMIFS('Flujo de Pagos'!I$7:I$506,'Flujo de Pagos'!E$7:E$506,B46,'Flujo de Pagos'!B$7:B$506,AE7)) | AF46: =IF(B46="","",SUMIFS('Flujo de Pagos'!I$7:I$506,'Flujo de Pagos'!E$7:E$506,B46,'Flujo de Pagos'!B$7:B$506,AF7)) | AG46: =IF(B46="","",SUMIFS('Flujo de Pagos'!I$7:I$506,'Flujo de Pagos'!E$7:E$506,B46,'Flujo de Pagos'!B$7:B$506,AG7)) | AH46: =IF(B46="","",SUMIFS('Flujo de Pagos'!I$7:I$506,'Flujo de Pagos'!E$7:E$506,B46,'Flujo de Pagos'!B$7:B$506,AH7)) | AI46: =IF(B46="","",SUMIFS('Flujo de Pagos'!I$7:I$506,'Flujo de Pagos'!E$7:E$506,B46,'Flujo de Pagos'!B$7:B$506,AI7)) | AJ46: =IF(B46="","",SUMIFS('Flujo de Pagos'!I$7:I$506,'Flujo de Pagos'!E$7:E$506,B46,'Flujo de Pagos'!B$7:B$506,AJ7)) | AK46: =IF(B46="","",SUMIFS('Flujo de Pagos'!I$7:I$506,'Flujo de Pagos'!E$7:E$506,B46,'Flujo de Pagos'!B$7:B$506,AK7)) | AL46: =IF(B46="","",SUMIFS('Flujo de Pagos'!I$7:I$506,'Flujo de Pagos'!E$7:E$506,B46,'Flujo de Pagos'!B$7:B$506,AL7)) | AM46: =IF(B46="","",SUM(C46:AL46))
B47: =IF(Presupuesto!B44="","",Presupuesto!B44) | C47: =IF(B47="","",SUMIFS('Flujo de Pagos'!I$7:I$506,'Flujo de Pagos'!E$7:E$506,B47,'Flujo de Pagos'!B$7:B$506,C7)) | D47: =IF(B47="","",SUMIFS('Flujo de Pagos'!I$7:I$506,'Flujo de Pagos'!E$7:E$506,B47,'Flujo de Pagos'!B$7:B$506,D7)) | E47: =IF(B47="","",SUMIFS('Flujo de Pagos'!I$7:I$506,'Flujo de Pagos'!E$7:E$506,B47,'Flujo de Pagos'!B$7:B$506,E7)) | F47: =IF(B47="","",SUMIFS('Flujo de Pagos'!I$7:I$506,'Flujo de Pagos'!E$7:E$506,B47,'Flujo de Pagos'!B$7:B$506,F7)) | G47: =IF(B47="","",SUMIFS('Flujo de Pagos'!I$7:I$506,'Flujo de Pagos'!E$7:E$506,B47,'Flujo de Pagos'!B$7:B$506,G7)) | H47: =IF(B47="","",SUMIFS('Flujo de Pagos'!I$7:I$506,'Flujo de Pagos'!E$7:E$506,B47,'Flujo de Pagos'!B$7:B$506,H7)) | I47: =IF(B47="","",SUMIFS('Flujo de Pagos'!I$7:I$506,'Flujo de Pagos'!E$7:E$506,B47,'Flujo de Pagos'!B$7:B$506,I7)) | J47: =IF(B47="","",SUMIFS('Flujo de Pagos'!I$7:I$506,'Flujo de Pagos'!E$7:E$506,B47,'Flujo de Pagos'!B$7:B$506,J7)) | K47: =IF(B47="","",SUMIFS('Flujo de Pagos'!I$7:I$506,'Flujo de Pagos'!E$7:E$506,B47,'Flujo de Pagos'!B$7:B$506,K7)) | L47: =IF(B47="","",SUMIFS('Flujo de Pagos'!I$7:I$506,'Flujo de Pagos'!E$7:E$506,B47,'Flujo de Pagos'!B$7:B$506,L7)) | M47: =IF(B47="","",SUMIFS('Flujo de Pagos'!I$7:I$506,'Flujo de Pagos'!E$7:E$506,B47,'Flujo de Pagos'!B$7:B$506,M7)) | N47: =IF(B47="","",SUMIFS('Flujo de Pagos'!I$7:I$506,'Flujo de Pagos'!E$7:E$506,B47,'Flujo de Pagos'!B$7:B$506,N7)) | O47: =IF(B47="","",SUMIFS('Flujo de Pagos'!I$7:I$506,'Flujo de Pagos'!E$7:E$506,B47,'Flujo de Pagos'!B$7:B$506,O7)) | P47: =IF(B47="","",SUMIFS('Flujo de Pagos'!I$7:I$506,'Flujo de Pagos'!E$7:E$506,B47,'Flujo de Pagos'!B$7:B$506,P7)) | Q47: =IF(B47="","",SUMIFS('Flujo de Pagos'!I$7:I$506,'Flujo de Pagos'!E$7:E$506,B47,'Flujo de Pagos'!B$7:B$506,Q7)) | R47: =IF(B47="","",SUMIFS('Flujo de Pagos'!I$7:I$506,'Flujo de Pagos'!E$7:E$506,B47,'Flujo de Pagos'!B$7:B$506,R7)) | S47: =IF(B47="","",SUMIFS('Flujo de Pagos'!I$7:I$506,'Flujo de Pagos'!E$7:E$506,B47,'Flujo de Pagos'!B$7:B$506,S7)) | T47: =IF(B47="","",SUMIFS('Flujo de Pagos'!I$7:I$506,'Flujo de Pagos'!E$7:E$506,B47,'Flujo de Pagos'!B$7:B$506,T7)) | U47: =IF(B47="","",SUMIFS('Flujo de Pagos'!I$7:I$506,'Flujo de Pagos'!E$7:E$506,B47,'Flujo de Pagos'!B$7:B$506,U7)) | V47: =IF(B47="","",SUMIFS('Flujo de Pagos'!I$7:I$506,'Flujo de Pagos'!E$7:E$506,B47,'Flujo de Pagos'!B$7:B$506,V7)) | W47: =IF(B47="","",SUMIFS('Flujo de Pagos'!I$7:I$506,'Flujo de Pagos'!E$7:E$506,B47,'Flujo de Pagos'!B$7:B$506,W7)) | X47: =IF(B47="","",SUMIFS('Flujo de Pagos'!I$7:I$506,'Flujo de Pagos'!E$7:E$506,B47,'Flujo de Pagos'!B$7:B$506,X7)) | Y47: =IF(B47="","",SUMIFS('Flujo de Pagos'!I$7:I$506,'Flujo de Pagos'!E$7:E$506,B47,'Flujo de Pagos'!B$7:B$506,Y7)) | Z47: =IF(B47="","",SUMIFS('Flujo de Pagos'!I$7:I$506,'Flujo de Pagos'!E$7:E$506,B47,'Flujo de Pagos'!B$7:B$506,Z7)) | AA47: =IF(B47="","",SUMIFS('Flujo de Pagos'!I$7:I$506,'Flujo de Pagos'!E$7:E$506,B47,'Flujo de Pagos'!B$7:B$506,AA7)) | AB47: =IF(B47="","",SUMIFS('Flujo de Pagos'!I$7:I$506,'Flujo de Pagos'!E$7:E$506,B47,'Flujo de Pagos'!B$7:B$506,AB7)) | AC47: =IF(B47="","",SUMIFS('Flujo de Pagos'!I$7:I$506,'Flujo de Pagos'!E$7:E$506,B47,'Flujo de Pagos'!B$7:B$506,AC7)) | AD47: =IF(B47="","",SUMIFS('Flujo de Pagos'!I$7:I$506,'Flujo de Pagos'!E$7:E$506,B47,'Flujo de Pagos'!B$7:B$506,AD7)) | AE47: =IF(B47="","",SUMIFS('Flujo de Pagos'!I$7:I$506,'Flujo de Pagos'!E$7:E$506,B47,'Flujo de Pagos'!B$7:B$506,AE7)) | AF47: =IF(B47="","",SUMIFS('Flujo de Pagos'!I$7:I$506,'Flujo de Pagos'!E$7:E$506,B47,'Flujo de Pagos'!B$7:B$506,AF7)) | AG47: =IF(B47="","",SUMIFS('Flujo de Pagos'!I$7:I$506,'Flujo de Pagos'!E$7:E$506,B47,'Flujo de Pagos'!B$7:B$506,AG7)) | AH47: =IF(B47="","",SUMIFS('Flujo de Pagos'!I$7:I$506,'Flujo de Pagos'!E$7:E$506,B47,'Flujo de Pagos'!B$7:B$506,AH7)) | AI47: =IF(B47="","",SUMIFS('Flujo de Pagos'!I$7:I$506,'Flujo de Pagos'!E$7:E$506,B47,'Flujo de Pagos'!B$7:B$506,AI7)) | AJ47: =IF(B47="","",SUMIFS('Flujo de Pagos'!I$7:I$506,'Flujo de Pagos'!E$7:E$506,B47,'Flujo de Pagos'!B$7:B$506,AJ7)) | AK47: =IF(B47="","",SUMIFS('Flujo de Pagos'!I$7:I$506,'Flujo de Pagos'!E$7:E$506,B47,'Flujo de Pagos'!B$7:B$506,AK7)) | AL47: =IF(B47="","",SUMIFS('Flujo de Pagos'!I$7:I$506,'Flujo de Pagos'!E$7:E$506,B47,'Flujo de Pagos'!B$7:B$506,AL7)) | AM47: =IF(B47="","",SUM(C47:AL47))
B48: =IF(Presupuesto!B45="","",Presupuesto!B45) | C48: =IF(B48="","",SUMIFS('Flujo de Pagos'!I$7:I$506,'Flujo de Pagos'!E$7:E$506,B48,'Flujo de Pagos'!B$7:B$506,C7)) | D48: =IF(B48="","",SUMIFS('Flujo de Pagos'!I$7:I$506,'Flujo de Pagos'!E$7:E$506,B48,'Flujo de Pagos'!B$7:B$506,D7)) | E48: =IF(B48="","",SUMIFS('Flujo de Pagos'!I$7:I$506,'Flujo de Pagos'!E$7:E$506,B48,'Flujo de Pagos'!B$7:B$506,E7)) | F48: =IF(B48="","",SUMIFS('Flujo de Pagos'!I$7:I$506,'Flujo de Pagos'!E$7:E$506,B48,'Flujo de Pagos'!B$7:B$506,F7)) | G48: =IF(B48="","",SUMIFS('Flujo de Pagos'!I$7:I$506,'Flujo de Pagos'!E$7:E$506,B48,'Flujo de Pagos'!B$7:B$506,G7)) | H48: =IF(B48="","",SUMIFS('Flujo de Pagos'!I$7:I$506,'Flujo de Pagos'!E$7:E$506,B48,'Flujo de Pagos'!B$7:B$506,H7)) | I48: =IF(B48="","",SUMIFS('Flujo de Pagos'!I$7:I$506,'Flujo de Pagos'!E$7:E$506,B48,'Flujo de Pagos'!B$7:B$506,I7)) | J48: =IF(B48="","",SUMIFS('Flujo de Pagos'!I$7:I$506,'Flujo de Pagos'!E$7:E$506,B48,'Flujo de Pagos'!B$7:B$506,J7)) | K48: =IF(B48="","",SUMIFS('Flujo de Pagos'!I$7:I$506,'Flujo de Pagos'!E$7:E$506,B48,'Flujo de Pagos'!B$7:B$506,K7)) | L48: =IF(B48="","",SUMIFS('Flujo de Pagos'!I$7:I$506,'Flujo de Pagos'!E$7:E$506,B48,'Flujo de Pagos'!B$7:B$506,L7)) | M48: =IF(B48="","",SUMIFS('Flujo de Pagos'!I$7:I$506,'Flujo de Pagos'!E$7:E$506,B48,'Flujo de Pagos'!B$7:B$506,M7)) | N48: =IF(B48="","",SUMIFS('Flujo de Pagos'!I$7:I$506,'Flujo de Pagos'!E$7:E$506,B48,'Flujo de Pagos'!B$7:B$506,N7)) | O48: =IF(B48="","",SUMIFS('Flujo de Pagos'!I$7:I$506,'Flujo de Pagos'!E$7:E$506,B48,'Flujo de Pagos'!B$7:B$506,O7)) | P48: =IF(B48="","",SUMIFS('Flujo de Pagos'!I$7:I$506,'Flujo de Pagos'!E$7:E$506,B48,'Flujo de Pagos'!B$7:B$506,P7)) | Q48: =IF(B48="","",SUMIFS('Flujo de Pagos'!I$7:I$506,'Flujo de Pagos'!E$7:E$506,B48,'Flujo de Pagos'!B$7:B$506,Q7)) | R48: =IF(B48="","",SUMIFS('Flujo de Pagos'!I$7:I$506,'Flujo de Pagos'!E$7:E$506,B48,'Flujo de Pagos'!B$7:B$506,R7)) | S48: =IF(B48="","",SUMIFS('Flujo de Pagos'!I$7:I$506,'Flujo de Pagos'!E$7:E$506,B48,'Flujo de Pagos'!B$7:B$506,S7)) | T48: =IF(B48="","",SUMIFS('Flujo de Pagos'!I$7:I$506,'Flujo de Pagos'!E$7:E$506,B48,'Flujo de Pagos'!B$7:B$506,T7)) | U48: =IF(B48="","",SUMIFS('Flujo de Pagos'!I$7:I$506,'Flujo de Pagos'!E$7:E$506,B48,'Flujo de Pagos'!B$7:B$506,U7)) | V48: =IF(B48="","",SUMIFS('Flujo de Pagos'!I$7:I$506,'Flujo de Pagos'!E$7:E$506,B48,'Flujo de Pagos'!B$7:B$506,V7)) | W48: =IF(B48="","",SUMIFS('Flujo de Pagos'!I$7:I$506,'Flujo de Pagos'!E$7:E$506,B48,'Flujo de Pagos'!B$7:B$506,W7)) | X48: =IF(B48="","",SUMIFS('Flujo de Pagos'!I$7:I$506,'Flujo de Pagos'!E$7:E$506,B48,'Flujo de Pagos'!B$7:B$506,X7)) | Y48: =IF(B48="","",SUMIFS('Flujo de Pagos'!I$7:I$506,'Flujo de Pagos'!E$7:E$506,B48,'Flujo de Pagos'!B$7:B$506,Y7)) | Z48: =IF(B48="","",SUMIFS('Flujo de Pagos'!I$7:I$506,'Flujo de Pagos'!E$7:E$506,B48,'Flujo de Pagos'!B$7:B$506,Z7)) | AA48: =IF(B48="","",SUMIFS('Flujo de Pagos'!I$7:I$506,'Flujo de Pagos'!E$7:E$506,B48,'Flujo de Pagos'!B$7:B$506,AA7)) | AB48: =IF(B48="","",SUMIFS('Flujo de Pagos'!I$7:I$506,'Flujo de Pagos'!E$7:E$506,B48,'Flujo de Pagos'!B$7:B$506,AB7)) | AC48: =IF(B48="","",SUMIFS('Flujo de Pagos'!I$7:I$506,'Flujo de Pagos'!E$7:E$506,B48,'Flujo de Pagos'!B$7:B$506,AC7)) | AD48: =IF(B48="","",SUMIFS('Flujo de Pagos'!I$7:I$506,'Flujo de Pagos'!E$7:E$506,B48,'Flujo de Pagos'!B$7:B$506,AD7)) | AE48: =IF(B48="","",SUMIFS('Flujo de Pagos'!I$7:I$506,'Flujo de Pagos'!E$7:E$506,B48,'Flujo de Pagos'!B$7:B$506,AE7)) | AF48: =IF(B48="","",SUMIFS('Flujo de Pagos'!I$7:I$506,'Flujo de Pagos'!E$7:E$506,B48,'Flujo de Pagos'!B$7:B$506,AF7)) | AG48: =IF(B48="","",SUMIFS('Flujo de Pagos'!I$7:I$506,'Flujo de Pagos'!E$7:E$506,B48,'Flujo de Pagos'!B$7:B$506,AG7)) | AH48: =IF(B48="","",SUMIFS('Flujo de Pagos'!I$7:I$506,'Flujo de Pagos'!E$7:E$506,B48,'Flujo de Pagos'!B$7:B$506,AH7)) | AI48: =IF(B48="","",SUMIFS('Flujo de Pagos'!I$7:I$506,'Flujo de Pagos'!E$7:E$506,B48,'Flujo de Pagos'!B$7:B$506,AI7)) | AJ48: =IF(B48="","",SUMIFS('Flujo de Pagos'!I$7:I$506,'Flujo de Pagos'!E$7:E$506,B48,'Flujo de Pagos'!B$7:B$506,AJ7)) | AK48: =IF(B48="","",SUMIFS('Flujo de Pagos'!I$7:I$506,'Flujo de Pagos'!E$7:E$506,B48,'Flujo de Pagos'!B$7:B$506,AK7)) | AL48: =IF(B48="","",SUMIFS('Flujo de Pagos'!I$7:I$506,'Flujo de Pagos'!E$7:E$506,B48,'Flujo de Pagos'!B$7:B$506,AL7)) | AM48: =IF(B48="","",SUM(C48:AL48))
B49: =IF(Presupuesto!B46="","",Presupuesto!B46) | C49: =IF(B49="","",SUMIFS('Flujo de Pagos'!I$7:I$506,'Flujo de Pagos'!E$7:E$506,B49,'Flujo de Pagos'!B$7:B$506,C7)) | D49: =IF(B49="","",SUMIFS('Flujo de Pagos'!I$7:I$506,'Flujo de Pagos'!E$7:E$506,B49,'Flujo de Pagos'!B$7:B$506,D7)) | E49: =IF(B49="","",SUMIFS('Flujo de Pagos'!I$7:I$506,'Flujo de Pagos'!E$7:E$506,B49,'Flujo de Pagos'!B$7:B$506,E7)) | F49: =IF(B49="","",SUMIFS('Flujo de Pagos'!I$7:I$506,'Flujo de Pagos'!E$7:E$506,B49,'Flujo de Pagos'!B$7:B$506,F7)) | G49: =IF(B49="","",SUMIFS('Flujo de Pagos'!I$7:I$506,'Flujo de Pagos'!E$7:E$506,B49,'Flujo de Pagos'!B$7:B$506,G7)) | H49: =IF(B49="","",SUMIFS('Flujo de Pagos'!I$7:I$506,'Flujo de Pagos'!E$7:E$506,B49,'Flujo de Pagos'!B$7:B$506,H7)) | I49: =IF(B49="","",SUMIFS('Flujo de Pagos'!I$7:I$506,'Flujo de Pagos'!E$7:E$506,B49,'Flujo de Pagos'!B$7:B$506,I7)) | J49: =IF(B49="","",SUMIFS('Flujo de Pagos'!I$7:I$506,'Flujo de Pagos'!E$7:E$506,B49,'Flujo de Pagos'!B$7:B$506,J7)) | K49: =IF(B49="","",SUMIFS('Flujo de Pagos'!I$7:I$506,'Flujo de Pagos'!E$7:E$506,B49,'Flujo de Pagos'!B$7:B$506,K7)) | L49: =IF(B49="","",SUMIFS('Flujo de Pagos'!I$7:I$506,'Flujo de Pagos'!E$7:E$506,B49,'Flujo de Pagos'!B$7:B$506,L7)) | M49: =IF(B49="","",SUMIFS('Flujo de Pagos'!I$7:I$506,'Flujo de Pagos'!E$7:E$506,B49,'Flujo de Pagos'!B$7:B$506,M7)) | N49: =IF(B49="","",SUMIFS('Flujo de Pagos'!I$7:I$506,'Flujo de Pagos'!E$7:E$506,B49,'Flujo de Pagos'!B$7:B$506,N7)) | O49: =IF(B49="","",SUMIFS('Flujo de Pagos'!I$7:I$506,'Flujo de Pagos'!E$7:E$506,B49,'Flujo de Pagos'!B$7:B$506,O7)) | P49: =IF(B49="","",SUMIFS('Flujo de Pagos'!I$7:I$506,'Flujo de Pagos'!E$7:E$506,B49,'Flujo de Pagos'!B$7:B$506,P7)) | Q49: =IF(B49="","",SUMIFS('Flujo de Pagos'!I$7:I$506,'Flujo de Pagos'!E$7:E$506,B49,'Flujo de Pagos'!B$7:B$506,Q7)) | R49: =IF(B49="","",SUMIFS('Flujo de Pagos'!I$7:I$506,'Flujo de Pagos'!E$7:E$506,B49,'Flujo de Pagos'!B$7:B$506,R7)) | S49: =IF(B49="","",SUMIFS('Flujo de Pagos'!I$7:I$506,'Flujo de Pagos'!E$7:E$506,B49,'Flujo de Pagos'!B$7:B$506,S7)) | T49: =IF(B49="","",SUMIFS('Flujo de Pagos'!I$7:I$506,'Flujo de Pagos'!E$7:E$506,B49,'Flujo de Pagos'!B$7:B$506,T7)) | U49: =IF(B49="","",SUMIFS('Flujo de Pagos'!I$7:I$506,'Flujo de Pagos'!E$7:E$506,B49,'Flujo de Pagos'!B$7:B$506,U7)) | V49: =IF(B49="","",SUMIFS('Flujo de Pagos'!I$7:I$506,'Flujo de Pagos'!E$7:E$506,B49,'Flujo de Pagos'!B$7:B$506,V7)) | W49: =IF(B49="","",SUMIFS('Flujo de Pagos'!I$7:I$506,'Flujo de Pagos'!E$7:E$506,B49,'Flujo de Pagos'!B$7:B$506,W7)) | X49: =IF(B49="","",SUMIFS('Flujo de Pagos'!I$7:I$506,'Flujo de Pagos'!E$7:E$506,B49,'Flujo de Pagos'!B$7:B$506,X7)) | Y49: =IF(B49="","",SUMIFS('Flujo de Pagos'!I$7:I$506,'Flujo de Pagos'!E$7:E$506,B49,'Flujo de Pagos'!B$7:B$506,Y7)) | Z49: =IF(B49="","",SUMIFS('Flujo de Pagos'!I$7:I$506,'Flujo de Pagos'!E$7:E$506,B49,'Flujo de Pagos'!B$7:B$506,Z7)) | AA49: =IF(B49="","",SUMIFS('Flujo de Pagos'!I$7:I$506,'Flujo de Pagos'!E$7:E$506,B49,'Flujo de Pagos'!B$7:B$506,AA7)) | AB49: =IF(B49="","",SUMIFS('Flujo de Pagos'!I$7:I$506,'Flujo de Pagos'!E$7:E$506,B49,'Flujo de Pagos'!B$7:B$506,AB7)) | AC49: =IF(B49="","",SUMIFS('Flujo de Pagos'!I$7:I$506,'Flujo de Pagos'!E$7:E$506,B49,'Flujo de Pagos'!B$7:B$506,AC7)) | AD49: =IF(B49="","",SUMIFS('Flujo de Pagos'!I$7:I$506,'Flujo de Pagos'!E$7:E$506,B49,'Flujo de Pagos'!B$7:B$506,AD7)) | AE49: =IF(B49="","",SUMIFS('Flujo de Pagos'!I$7:I$506,'Flujo de Pagos'!E$7:E$506,B49,'Flujo de Pagos'!B$7:B$506,AE7)) | AF49: =IF(B49="","",SUMIFS('Flujo de Pagos'!I$7:I$506,'Flujo de Pagos'!E$7:E$506,B49,'Flujo de Pagos'!B$7:B$506,AF7)) | AG49: =IF(B49="","",SUMIFS('Flujo de Pagos'!I$7:I$506,'Flujo de Pagos'!E$7:E$506,B49,'Flujo de Pagos'!B$7:B$506,AG7)) | AH49: =IF(B49="","",SUMIFS('Flujo de Pagos'!I$7:I$506,'Flujo de Pagos'!E$7:E$506,B49,'Flujo de Pagos'!B$7:B$506,AH7)) | AI49: =IF(B49="","",SUMIFS('Flujo de Pagos'!I$7:I$506,'Flujo de Pagos'!E$7:E$506,B49,'Flujo de Pagos'!B$7:B$506,AI7)) | AJ49: =IF(B49="","",SUMIFS('Flujo de Pagos'!I$7:I$506,'Flujo de Pagos'!E$7:E$506,B49,'Flujo de Pagos'!B$7:B$506,AJ7)) | AK49: =IF(B49="","",SUMIFS('Flujo de Pagos'!I$7:I$506,'Flujo de Pagos'!E$7:E$506,B49,'Flujo de Pagos'!B$7:B$506,AK7)) | AL49: =IF(B49="","",SUMIFS('Flujo de Pagos'!I$7:I$506,'Flujo de Pagos'!E$7:E$506,B49,'Flujo de Pagos'!B$7:B$506,AL7)) | AM49: =IF(B49="","",SUM(C49:AL49))
B50: =IF(Presupuesto!B47="","",Presupuesto!B47) | C50: =IF(B50="","",SUMIFS('Flujo de Pagos'!I$7:I$506,'Flujo de Pagos'!E$7:E$506,B50,'Flujo de Pagos'!B$7:B$506,C7)) | D50: =IF(B50="","",SUMIFS('Flujo de Pagos'!I$7:I$506,'Flujo de Pagos'!E$7:E$506,B50,'Flujo de Pagos'!B$7:B$506,D7)) | E50: =IF(B50="","",SUMIFS('Flujo de Pagos'!I$7:I$506,'Flujo de Pagos'!E$7:E$506,B50,'Flujo de Pagos'!B$7:B$506,E7)) | F50: =IF(B50="","",SUMIFS('Flujo de Pagos'!I$7:I$506,'Flujo de Pagos'!E$7:E$506,B50,'Flujo de Pagos'!B$7:B$506,F7)) | G50: =IF(B50="","",SUMIFS('Flujo de Pagos'!I$7:I$506,'Flujo de Pagos'!E$7:E$506,B50,'Flujo de Pagos'!B$7:B$506,G7)) | H50: =IF(B50="","",SUMIFS('Flujo de Pagos'!I$7:I$506,'Flujo de Pagos'!E$7:E$506,B50,'Flujo de Pagos'!B$7:B$506,H7)) | I50: =IF(B50="","",SUMIFS('Flujo de Pagos'!I$7:I$506,'Flujo de Pagos'!E$7:E$506,B50,'Flujo de Pagos'!B$7:B$506,I7)) | J50: =IF(B50="","",SUMIFS('Flujo de Pagos'!I$7:I$506,'Flujo de Pagos'!E$7:E$506,B50,'Flujo de Pagos'!B$7:B$506,J7)) | K50: =IF(B50="","",SUMIFS('Flujo de Pagos'!I$7:I$506,'Flujo de Pagos'!E$7:E$506,B50,'Flujo de Pagos'!B$7:B$506,K7)) | L50: =IF(B50="","",SUMIFS('Flujo de Pagos'!I$7:I$506,'Flujo de Pagos'!E$7:E$506,B50,'Flujo de Pagos'!B$7:B$506,L7)) | M50: =IF(B50="","",SUMIFS('Flujo de Pagos'!I$7:I$506,'Flujo de Pagos'!E$7:E$506,B50,'Flujo de Pagos'!B$7:B$506,M7)) | N50: =IF(B50="","",SUMIFS('Flujo de Pagos'!I$7:I$506,'Flujo de Pagos'!E$7:E$506,B50,'Flujo de Pagos'!B$7:B$506,N7)) | O50: =IF(B50="","",SUMIFS('Flujo de Pagos'!I$7:I$506,'Flujo de Pagos'!E$7:E$506,B50,'Flujo de Pagos'!B$7:B$506,O7)) | P50: =IF(B50="","",SUMIFS('Flujo de Pagos'!I$7:I$506,'Flujo de Pagos'!E$7:E$506,B50,'Flujo de Pagos'!B$7:B$506,P7)) | Q50: =IF(B50="","",SUMIFS('Flujo de Pagos'!I$7:I$506,'Flujo de Pagos'!E$7:E$506,B50,'Flujo de Pagos'!B$7:B$506,Q7)) | R50: =IF(B50="","",SUMIFS('Flujo de Pagos'!I$7:I$506,'Flujo de Pagos'!E$7:E$506,B50,'Flujo de Pagos'!B$7:B$506,R7)) | S50: =IF(B50="","",SUMIFS('Flujo de Pagos'!I$7:I$506,'Flujo de Pagos'!E$7:E$506,B50,'Flujo de Pagos'!B$7:B$506,S7)) | T50: =IF(B50="","",SUMIFS('Flujo de Pagos'!I$7:I$506,'Flujo de Pagos'!E$7:E$506,B50,'Flujo de Pagos'!B$7:B$506,T7)) | U50: =IF(B50="","",SUMIFS('Flujo de Pagos'!I$7:I$506,'Flujo de Pagos'!E$7:E$506,B50,'Flujo de Pagos'!B$7:B$506,U7)) | V50: =IF(B50="","",SUMIFS('Flujo de Pagos'!I$7:I$506,'Flujo de Pagos'!E$7:E$506,B50,'Flujo de Pagos'!B$7:B$506,V7)) | W50: =IF(B50="","",SUMIFS('Flujo de Pagos'!I$7:I$506,'Flujo de Pagos'!E$7:E$506,B50,'Flujo de Pagos'!B$7:B$506,W7)) | X50: =IF(B50="","",SUMIFS('Flujo de Pagos'!I$7:I$506,'Flujo de Pagos'!E$7:E$506,B50,'Flujo de Pagos'!B$7:B$506,X7)) | Y50: =IF(B50="","",SUMIFS('Flujo de Pagos'!I$7:I$506,'Flujo de Pagos'!E$7:E$506,B50,'Flujo de Pagos'!B$7:B$506,Y7)) | Z50: =IF(B50="","",SUMIFS('Flujo de Pagos'!I$7:I$506,'Flujo de Pagos'!E$7:E$506,B50,'Flujo de Pagos'!B$7:B$506,Z7)) | AA50: =IF(B50="","",SUMIFS('Flujo de Pagos'!I$7:I$506,'Flujo de Pagos'!E$7:E$506,B50,'Flujo de Pagos'!B$7:B$506,AA7)) | AB50: =IF(B50="","",SUMIFS('Flujo de Pagos'!I$7:I$506,'Flujo de Pagos'!E$7:E$506,B50,'Flujo de Pagos'!B$7:B$506,AB7)) | AC50: =IF(B50="","",SUMIFS('Flujo de Pagos'!I$7:I$506,'Flujo de Pagos'!E$7:E$506,B50,'Flujo de Pagos'!B$7:B$506,AC7)) | AD50: =IF(B50="","",SUMIFS('Flujo de Pagos'!I$7:I$506,'Flujo de Pagos'!E$7:E$506,B50,'Flujo de Pagos'!B$7:B$506,AD7)) | AE50: =IF(B50="","",SUMIFS('Flujo de Pagos'!I$7:I$506,'Flujo de Pagos'!E$7:E$506,B50,'Flujo de Pagos'!B$7:B$506,AE7)) | AF50: =IF(B50="","",SUMIFS('Flujo de Pagos'!I$7:I$506,'Flujo de Pagos'!E$7:E$506,B50,'Flujo de Pagos'!B$7:B$506,AF7)) | AG50: =IF(B50="","",SUMIFS('Flujo de Pagos'!I$7:I$506,'Flujo de Pagos'!E$7:E$506,B50,'Flujo de Pagos'!B$7:B$506,AG7)) | AH50: =IF(B50="","",SUMIFS('Flujo de Pagos'!I$7:I$506,'Flujo de Pagos'!E$7:E$506,B50,'Flujo de Pagos'!B$7:B$506,AH7)) | AI50: =IF(B50="","",SUMIFS('Flujo de Pagos'!I$7:I$506,'Flujo de Pagos'!E$7:E$506,B50,'Flujo de Pagos'!B$7:B$506,AI7)) | AJ50: =IF(B50="","",SUMIFS('Flujo de Pagos'!I$7:I$506,'Flujo de Pagos'!E$7:E$506,B50,'Flujo de Pagos'!B$7:B$506,AJ7)) | AK50: =IF(B50="","",SUMIFS('Flujo de Pagos'!I$7:I$506,'Flujo de Pagos'!E$7:E$506,B50,'Flujo de Pagos'!B$7:B$506,AK7)) | AL50: =IF(B50="","",SUMIFS('Flujo de Pagos'!I$7:I$506,'Flujo de Pagos'!E$7:E$506,B50,'Flujo de Pagos'!B$7:B$506,AL7)) | AM50: =IF(B50="","",SUM(C50:AL50))
B51: =IF(Presupuesto!B48="","",Presupuesto!B48) | C51: =IF(B51="","",SUMIFS('Flujo de Pagos'!I$7:I$506,'Flujo de Pagos'!E$7:E$506,B51,'Flujo de Pagos'!B$7:B$506,C7)) | D51: =IF(B51="","",SUMIFS('Flujo de Pagos'!I$7:I$506,'Flujo de Pagos'!E$7:E$506,B51,'Flujo de Pagos'!B$7:B$506,D7)) | E51: =IF(B51="","",SUMIFS('Flujo de Pagos'!I$7:I$506,'Flujo de Pagos'!E$7:E$506,B51,'Flujo de Pagos'!B$7:B$506,E7)) | F51: =IF(B51="","",SUMIFS('Flujo de Pagos'!I$7:I$506,'Flujo de Pagos'!E$7:E$506,B51,'Flujo de Pagos'!B$7:B$506,F7)) | G51: =IF(B51="","",SUMIFS('Flujo de Pagos'!I$7:I$506,'Flujo de Pagos'!E$7:E$506,B51,'Flujo de Pagos'!B$7:B$506,G7)) | H51: =IF(B51="","",SUMIFS('Flujo de Pagos'!I$7:I$506,'Flujo de Pagos'!E$7:E$506,B51,'Flujo de Pagos'!B$7:B$506,H7)) | I51: =IF(B51="","",SUMIFS('Flujo de Pagos'!I$7:I$506,'Flujo de Pagos'!E$7:E$506,B51,'Flujo de Pagos'!B$7:B$506,I7)) | J51: =IF(B51="","",SUMIFS('Flujo de Pagos'!I$7:I$506,'Flujo de Pagos'!E$7:E$506,B51,'Flujo de Pagos'!B$7:B$506,J7)) | K51: =IF(B51="","",SUMIFS('Flujo de Pagos'!I$7:I$506,'Flujo de Pagos'!E$7:E$506,B51,'Flujo de Pagos'!B$7:B$506,K7)) | L51: =IF(B51="","",SUMIFS('Flujo de Pagos'!I$7:I$506,'Flujo de Pagos'!E$7:E$506,B51,'Flujo de Pagos'!B$7:B$506,L7)) | M51: =IF(B51="","",SUMIFS('Flujo de Pagos'!I$7:I$506,'Flujo de Pagos'!E$7:E$506,B51,'Flujo de Pagos'!B$7:B$506,M7)) | N51: =IF(B51="","",SUMIFS('Flujo de Pagos'!I$7:I$506,'Flujo de Pagos'!E$7:E$506,B51,'Flujo de Pagos'!B$7:B$506,N7)) | O51: =IF(B51="","",SUMIFS('Flujo de Pagos'!I$7:I$506,'Flujo de Pagos'!E$7:E$506,B51,'Flujo de Pagos'!B$7:B$506,O7)) | P51: =IF(B51="","",SUMIFS('Flujo de Pagos'!I$7:I$506,'Flujo de Pagos'!E$7:E$506,B51,'Flujo de Pagos'!B$7:B$506,P7)) | Q51: =IF(B51="","",SUMIFS('Flujo de Pagos'!I$7:I$506,'Flujo de Pagos'!E$7:E$506,B51,'Flujo de Pagos'!B$7:B$506,Q7)) | R51: =IF(B51="","",SUMIFS('Flujo de Pagos'!I$7:I$506,'Flujo de Pagos'!E$7:E$506,B51,'Flujo de Pagos'!B$7:B$506,R7)) | S51: =IF(B51="","",SUMIFS('Flujo de Pagos'!I$7:I$506,'Flujo de Pagos'!E$7:E$506,B51,'Flujo de Pagos'!B$7:B$506,S7)) | T51: =IF(B51="","",SUMIFS('Flujo de Pagos'!I$7:I$506,'Flujo de Pagos'!E$7:E$506,B51,'Flujo de Pagos'!B$7:B$506,T7)) | U51: =IF(B51="","",SUMIFS('Flujo de Pagos'!I$7:I$506,'Flujo de Pagos'!E$7:E$506,B51,'Flujo de Pagos'!B$7:B$506,U7)) | V51: =IF(B51="","",SUMIFS('Flujo de Pagos'!I$7:I$506,'Flujo de Pagos'!E$7:E$506,B51,'Flujo de Pagos'!B$7:B$506,V7)) | W51: =IF(B51="","",SUMIFS('Flujo de Pagos'!I$7:I$506,'Flujo de Pagos'!E$7:E$506,B51,'Flujo de Pagos'!B$7:B$506,W7)) | X51: =IF(B51="","",SUMIFS('Flujo de Pagos'!I$7:I$506,'Flujo de Pagos'!E$7:E$506,B51,'Flujo de Pagos'!B$7:B$506,X7)) | Y51: =IF(B51="","",SUMIFS('Flujo de Pagos'!I$7:I$506,'Flujo de Pagos'!E$7:E$506,B51,'Flujo de Pagos'!B$7:B$506,Y7)) | Z51: =IF(B51="","",SUMIFS('Flujo de Pagos'!I$7:I$506,'Flujo de Pagos'!E$7:E$506,B51,'Flujo de Pagos'!B$7:B$506,Z7)) | AA51: =IF(B51="","",SUMIFS('Flujo de Pagos'!I$7:I$506,'Flujo de Pagos'!E$7:E$506,B51,'Flujo de Pagos'!B$7:B$506,AA7)) | AB51: =IF(B51="","",SUMIFS('Flujo de Pagos'!I$7:I$506,'Flujo de Pagos'!E$7:E$506,B51,'Flujo de Pagos'!B$7:B$506,AB7)) | AC51: =IF(B51="","",SUMIFS('Flujo de Pagos'!I$7:I$506,'Flujo de Pagos'!E$7:E$506,B51,'Flujo de Pagos'!B$7:B$506,AC7)) | AD51: =IF(B51="","",SUMIFS('Flujo de Pagos'!I$7:I$506,'Flujo de Pagos'!E$7:E$506,B51,'Flujo de Pagos'!B$7:B$506,AD7)) | AE51: =IF(B51="","",SUMIFS('Flujo de Pagos'!I$7:I$506,'Flujo de Pagos'!E$7:E$506,B51,'Flujo de Pagos'!B$7:B$506,AE7)) | AF51: =IF(B51="","",SUMIFS('Flujo de Pagos'!I$7:I$506,'Flujo de Pagos'!E$7:E$506,B51,'Flujo de Pagos'!B$7:B$506,AF7)) | AG51: =IF(B51="","",SUMIFS('Flujo de Pagos'!I$7:I$506,'Flujo de Pagos'!E$7:E$506,B51,'Flujo de Pagos'!B$7:B$506,AG7)) | AH51: =IF(B51="","",SUMIFS('Flujo de Pagos'!I$7:I$506,'Flujo de Pagos'!E$7:E$506,B51,'Flujo de Pagos'!B$7:B$506,AH7)) | AI51: =IF(B51="","",SUMIFS('Flujo de Pagos'!I$7:I$506,'Flujo de Pagos'!E$7:E$506,B51,'Flujo de Pagos'!B$7:B$506,AI7)) | AJ51: =IF(B51="","",SUMIFS('Flujo de Pagos'!I$7:I$506,'Flujo de Pagos'!E$7:E$506,B51,'Flujo de Pagos'!B$7:B$506,AJ7)) | AK51: =IF(B51="","",SUMIFS('Flujo de Pagos'!I$7:I$506,'Flujo de Pagos'!E$7:E$506,B51,'Flujo de Pagos'!B$7:B$506,AK7)) | AL51: =IF(B51="","",SUMIFS('Flujo de Pagos'!I$7:I$506,'Flujo de Pagos'!E$7:E$506,B51,'Flujo de Pagos'!B$7:B$506,AL7)) | AM51: =IF(B51="","",SUM(C51:AL51))
B52: =IF(Presupuesto!B49="","",Presupuesto!B49) | C52: =IF(B52="","",SUMIFS('Flujo de Pagos'!I$7:I$506,'Flujo de Pagos'!E$7:E$506,B52,'Flujo de Pagos'!B$7:B$506,C7)) | D52: =IF(B52="","",SUMIFS('Flujo de Pagos'!I$7:I$506,'Flujo de Pagos'!E$7:E$506,B52,'Flujo de Pagos'!B$7:B$506,D7)) | E52: =IF(B52="","",SUMIFS('Flujo de Pagos'!I$7:I$506,'Flujo de Pagos'!E$7:E$506,B52,'Flujo de Pagos'!B$7:B$506,E7)) | F52: =IF(B52="","",SUMIFS('Flujo de Pagos'!I$7:I$506,'Flujo de Pagos'!E$7:E$506,B52,'Flujo de Pagos'!B$7:B$506,F7)) | G52: =IF(B52="","",SUMIFS('Flujo de Pagos'!I$7:I$506,'Flujo de Pagos'!E$7:E$506,B52,'Flujo de Pagos'!B$7:B$506,G7)) | H52: =IF(B52="","",SUMIFS('Flujo de Pagos'!I$7:I$506,'Flujo de Pagos'!E$7:E$506,B52,'Flujo de Pagos'!B$7:B$506,H7)) | I52: =IF(B52="","",SUMIFS('Flujo de Pagos'!I$7:I$506,'Flujo de Pagos'!E$7:E$506,B52,'Flujo de Pagos'!B$7:B$506,I7)) | J52: =IF(B52="","",SUMIFS('Flujo de Pagos'!I$7:I$506,'Flujo de Pagos'!E$7:E$506,B52,'Flujo de Pagos'!B$7:B$506,J7)) | K52: =IF(B52="","",SUMIFS('Flujo de Pagos'!I$7:I$506,'Flujo de Pagos'!E$7:E$506,B52,'Flujo de Pagos'!B$7:B$506,K7)) | L52: =IF(B52="","",SUMIFS('Flujo de Pagos'!I$7:I$506,'Flujo de Pagos'!E$7:E$506,B52,'Flujo de Pagos'!B$7:B$506,L7)) | M52: =IF(B52="","",SUMIFS('Flujo de Pagos'!I$7:I$506,'Flujo de Pagos'!E$7:E$506,B52,'Flujo de Pagos'!B$7:B$506,M7)) | N52: =IF(B52="","",SUMIFS('Flujo de Pagos'!I$7:I$506,'Flujo de Pagos'!E$7:E$506,B52,'Flujo de Pagos'!B$7:B$506,N7)) | O52: =IF(B52="","",SUMIFS('Flujo de Pagos'!I$7:I$506,'Flujo de Pagos'!E$7:E$506,B52,'Flujo de Pagos'!B$7:B$506,O7)) | P52: =IF(B52="","",SUMIFS('Flujo de Pagos'!I$7:I$506,'Flujo de Pagos'!E$7:E$506,B52,'Flujo de Pagos'!B$7:B$506,P7)) | Q52: =IF(B52="","",SUMIFS('Flujo de Pagos'!I$7:I$506,'Flujo de Pagos'!E$7:E$506,B52,'Flujo de Pagos'!B$7:B$506,Q7)) | R52: =IF(B52="","",SUMIFS('Flujo de Pagos'!I$7:I$506,'Flujo de Pagos'!E$7:E$506,B52,'Flujo de Pagos'!B$7:B$506,R7)) | S52: =IF(B52="","",SUMIFS('Flujo de Pagos'!I$7:I$506,'Flujo de Pagos'!E$7:E$506,B52,'Flujo de Pagos'!B$7:B$506,S7)) | T52: =IF(B52="","",SUMIFS('Flujo de Pagos'!I$7:I$506,'Flujo de Pagos'!E$7:E$506,B52,'Flujo de Pagos'!B$7:B$506,T7)) | U52: =IF(B52="","",SUMIFS('Flujo de Pagos'!I$7:I$506,'Flujo de Pagos'!E$7:E$506,B52,'Flujo de Pagos'!B$7:B$506,U7)) | V52: =IF(B52="","",SUMIFS('Flujo de Pagos'!I$7:I$506,'Flujo de Pagos'!E$7:E$506,B52,'Flujo de Pagos'!B$7:B$506,V7)) | W52: =IF(B52="","",SUMIFS('Flujo de Pagos'!I$7:I$506,'Flujo de Pagos'!E$7:E$506,B52,'Flujo de Pagos'!B$7:B$506,W7)) | X52: =IF(B52="","",SUMIFS('Flujo de Pagos'!I$7:I$506,'Flujo de Pagos'!E$7:E$506,B52,'Flujo de Pagos'!B$7:B$506,X7)) | Y52: =IF(B52="","",SUMIFS('Flujo de Pagos'!I$7:I$506,'Flujo de Pagos'!E$7:E$506,B52,'Flujo de Pagos'!B$7:B$506,Y7)) | Z52: =IF(B52="","",SUMIFS('Flujo de Pagos'!I$7:I$506,'Flujo de Pagos'!E$7:E$506,B52,'Flujo de Pagos'!B$7:B$506,Z7)) | AA52: =IF(B52="","",SUMIFS('Flujo de Pagos'!I$7:I$506,'Flujo de Pagos'!E$7:E$506,B52,'Flujo de Pagos'!B$7:B$506,AA7)) | AB52: =IF(B52="","",SUMIFS('Flujo de Pagos'!I$7:I$506,'Flujo de Pagos'!E$7:E$506,B52,'Flujo de Pagos'!B$7:B$506,AB7)) | AC52: =IF(B52="","",SUMIFS('Flujo de Pagos'!I$7:I$506,'Flujo de Pagos'!E$7:E$506,B52,'Flujo de Pagos'!B$7:B$506,AC7)) | AD52: =IF(B52="","",SUMIFS('Flujo de Pagos'!I$7:I$506,'Flujo de Pagos'!E$7:E$506,B52,'Flujo de Pagos'!B$7:B$506,AD7)) | AE52: =IF(B52="","",SUMIFS('Flujo de Pagos'!I$7:I$506,'Flujo de Pagos'!E$7:E$506,B52,'Flujo de Pagos'!B$7:B$506,AE7)) | AF52: =IF(B52="","",SUMIFS('Flujo de Pagos'!I$7:I$506,'Flujo de Pagos'!E$7:E$506,B52,'Flujo de Pagos'!B$7:B$506,AF7)) | AG52: =IF(B52="","",SUMIFS('Flujo de Pagos'!I$7:I$506,'Flujo de Pagos'!E$7:E$506,B52,'Flujo de Pagos'!B$7:B$506,AG7)) | AH52: =IF(B52="","",SUMIFS('Flujo de Pagos'!I$7:I$506,'Flujo de Pagos'!E$7:E$506,B52,'Flujo de Pagos'!B$7:B$506,AH7)) | AI52: =IF(B52="","",SUMIFS('Flujo de Pagos'!I$7:I$506,'Flujo de Pagos'!E$7:E$506,B52,'Flujo de Pagos'!B$7:B$506,AI7)) | AJ52: =IF(B52="","",SUMIFS('Flujo de Pagos'!I$7:I$506,'Flujo de Pagos'!E$7:E$506,B52,'Flujo de Pagos'!B$7:B$506,AJ7)) | AK52: =IF(B52="","",SUMIFS('Flujo de Pagos'!I$7:I$506,'Flujo de Pagos'!E$7:E$506,B52,'Flujo de Pagos'!B$7:B$506,AK7)) | AL52: =IF(B52="","",SUMIFS('Flujo de Pagos'!I$7:I$506,'Flujo de Pagos'!E$7:E$506,B52,'Flujo de Pagos'!B$7:B$506,AL7)) | AM52: =IF(B52="","",SUM(C52:AL52))
