Workbook

Sheet BUY OUT
A1: MXN PER USD | D1: ='Glosario Partidas'!M9 -> 17.5
U3: PROYECCION | V3: PROYECCION | W3: PROYECCION | X3: PROYECCION | Y3: PROYECCION | Z3: PROYECCION | AA3: PROYECCION | AB3: PROYECCION | AC3: PROYECCION | AD3: PROYECCION | AE3: PROYECCION | AF3: PROYECCION | AG3: PROYECCION | AH3: PROYECCION | AI3: PROYECCION | AJ3: PROYECCION | AK3: PROYECCION | AL3: PROYECCION | AM3: PROYECCION | AN3: PROYECCION | AO3: PROYECCION | AP3: PROYECCION | AQ3: PROYECCION | AR3: PROYECCION | AS3: PROYECCION | AT3: PROYECCION | AU3: PROYECCION | AV3: PROYECCION | AW3: PROYECCION | AX3: PROYECCION | AY3: PROYECCION | AZ3: PROYECCION | BA3: PROYECCION | BB3: PROYECCION | BC3: PROYECCION | BD3: PROYECCION | BE3: PROYECCION | BF3: PROYECCION | BG3: PROYECCION | BH3: PROYECCION | BI3: PROYECCION | BJ3: PROYECCION | BK3: PROYECCION | BL3: PROYECCION | BM3: PROYECCION | BN3: PROYECCION | BO3: PROYECCION | BP3: PROYECCION | BQ3: PROYECCION | BR3: PROYECCION | BS3: PROYECCION
B4: CONCEPTO | E4: PRESUPUESTO IZ MXN BASE | F4: PPTO MARZO MXN | G4: PPTO ABRIL MXN | H4: PPTO MAYO MXN | I4: PPTO JUNIO MXN | J4: DIF BASE VS. JUNIO | K4: COSTO M2 INTERIOR JUNIO | L4: PRESUPUESTO IZ USD BASE | M4: PPTO JUNIO USD | O4: PPTO | P4: PARAMETRICO | R4: CONTRATADO | S4: NO CONTRATADO | U4: 45792 | V4: 45807 | W4: 45823 | X4: 45838 | Y4: 45853 | Z4: 45868 | AA4: 45884 | AB4: 45899 | AC4: 45915 | AD4: 45930 | AE4: 45945 | AF4: 45960 | AG4: 45976 | AH4: 45991 | AI4: 46006 | AJ4: 46021 | AK4: 46037 | AL4: 46052 | AM4: 46068 | AN4: 46081 | AO4: 46096 | AP4: 46111 | AQ4: 46127 | AR4: 46142 | AS4: 46157 | AT4: 46172 | AU4: 46188 | AV4: 46203 | AW4: 46218 | AX4: 46233 | AY4: 46249 | AZ4: 46264 | BA4: 46280 | BB4: 46295 | BC4: 46310 | BD4: 46325 | BE4: 46341 | BF4: 46356 | BG4: 46371 | BH4: 46386 | BI4: 46402 | BJ4: 46417 | BK4: 46433 | BL4: 46446 | BM4: 46461 | BN4: 46476 | BO4: 46492 | BP4: 46507 | BQ4: 46522 | BR4: 46537 | BS4: 46553 | BT4: CONSTRUCTION SCHEDULE | BU4: COMMENTS
B6: NAUKA BEACHFRONT - GOLF VILLAS
B8: DISEÑO | E8: =E15+E27 -> 2229156.1 | F8: =F15+F27 -> 2029156.1 | G8: =G15+G27 -> 5004956.1 | H8: =H15+H27 -> 4891556.1 | I8: =I15+I27 -> 5091556.1 | J8: =IFERROR(I8/E8-1,0) -> 1.2840734 | K8: =I8/(UNITARIO!$D$9+UNITARIO!$I$9) -> 1739.157 | L8: =E8/$D$1 -> 127380.35 | M8: =I8/$D$1 -> 290946.06 | O8: =O15+O27 -> 5091556.1 | P8: =P15+P27 -> 0 | R8: =R15+R27 -> 4929156.1 | S8: =S15+S27 -> 162400
B9: ARQUITECTURA
B10: Supervision Diseño Iluminacion | E10: 0 | F10: 0 | G10: 0 | H10: 0 | I10: =SUMIFS(Arquitectura!$T:$T,Arquitectura!$C:$C,$B10) -> 0 | J10: =IFERROR(I10/E10-1,0) -> 0 | K10: =I10/(UNITARIO!$D$9+UNITARIO!$I$9) -> 0 | L10: =E10/$D$1 -> 0 | M10: =I10/$D$1 -> 0 | O10: =SUMIFS(Arquitectura!$T:$T,Arquitectura!$C:$C,$B10,Arquitectura!$V:$V,$O$4) -> 0 | P10: =SUMIFS(Arquitectura!$T:$T,Arquitectura!$C:$C,$B10,Arquitectura!$V:$V,$P$4) -> 0 | R10: =SUMIFS(Arquitectura!$T:$T,Arquitectura!$C:$C,$B10,Arquitectura!$W:$W,$R$4) -> 0 | S10: =SUMIFS(Arquitectura!$T:$T,Arquitectura!$C:$C,$B10,Arquitectura!$W:$W,$S$4) -> 0
B11: Diseño Arquitectonico | E11: 0 | F11: 0 | G11: 2700000 | H11: 2700000 | I11: =SUMIFS(Arquitectura!$T:$T,Arquitectura!$C:$C,$B11) -> 2700000 | J11: =IFERROR(I11/E11-1,0) -> 0 | K11: =I11/(UNITARIO!$D$9+UNITARIO!$I$9) -> 922.25714 | L11: =E11/$D$1 -> 0 | M11: =I11/$D$1 -> 154285.71 | O11: =SUMIFS(Arquitectura!$T:$T,Arquitectura!$C:$C,$B11,Arquitectura!$V:$V,$O$4) -> 2700000 | P11: =SUMIFS(Arquitectura!$T:$T,Arquitectura!$C:$C,$B11,Arquitectura!$V:$V,$P$4) -> 0 | R11: =SUMIFS(Arquitectura!$T:$T,Arquitectura!$C:$C,$B11,Arquitectura!$W:$W,$R$4) -> 2700000 | S11: =SUMIFS(Arquitectura!$T:$T,Arquitectura!$C:$C,$B11,Arquitectura!$W:$W,$S$4) -> 0
B12: Diseño Jardineria | E12: 0 | F12: 0 | G12: 208800 | H12: 162400 | I12: =SUMIFS(Arquitectura!$T:$T,Arquitectura!$C:$C,$B12) -> 162400 | J12: =IFERROR(I12/E12-1,0) -> 0 | K12: =I12/(UNITARIO!$D$9+UNITARIO!$I$9) -> 55.472059 | L12: =E12/$D$1 -> 0 | M12: =I12/$D$1 -> 9280 | O12: =SUMIFS(Arquitectura!$T:$T,Arquitectura!$C:$C,$B12,Arquitectura!$V:$V,$O$4) -> 162400 | P12: =SUMIFS(Arquitectura!$T:$T,Arquitectura!$C:$C,$B12,Arquitectura!$V:$V,$P$4) -> 0 | R12: =SUMIFS(Arquitectura!$T:$T,Arquitectura!$C:$C,$B12,Arquitectura!$W:$W,$R$4) -> 0 | S12: =SUMIFS(Arquitectura!$T:$T,Arquitectura!$C:$C,$B12,Arquitectura!$W:$W,$S$4) -> 162400
B13: Cuantificacion M2 | E13: 0 | F13: 0 | G13: 67000 | H13: 0 | I13: =SUMIFS(Arquitectura!$T:$T,Arquitectura!$C:$C,$B13) -> 0 | J13: =IFERROR(I13/E13-1,0) -> 0 | K13: =I13/(UNITARIO!$D$9+UNITARIO!$I$9) -> 0 | L13: =E13/$D$1 -> 0 | M13: =I13/$D$1 -> 0 | O13: =SUMIFS(Arquitectura!$T:$T,Arquitectura!$C:$C,$B13,Arquitectura!$V:$V,$O$4) -> 0 | P13: =SUMIFS(Arquitectura!$T:$T,Arquitectura!$C:$C,$B13,Arquitectura!$V:$V,$P$4) -> 0 | R13: =SUMIFS(Arquitectura!$T:$T,Arquitectura!$C:$C,$B13,Arquitectura!$W:$W,$R$4) -> 0 | S13: =SUMIFS(Arquitectura!$T:$T,Arquitectura!$C:$C,$B13,Arquitectura!$W:$W,$S$4) -> 0
B14: Supervision Diseño Jardineria | E14: 0 | F14: 0 | G14: 0 | H14: 0 | I14: =SUMIFS(Arquitectura!$T:$T,Arquitectura!$C:$C,$B14) -> 0 | J14: =IFERROR(I14/E14-1,0) -> 0 | K14: =I14/(UNITARIO!$D$9+UNITARIO!$I$9) -> 0 | L14: =E14/$D$1 -> 0 | M14: =I14/$D$1 -> 0 | O14: =SUMIFS(Arquitectura!$T:$T,Arquitectura!$C:$C,$B14,Arquitectura!$V:$V,$O$4) -> 0 | P14: =SUMIFS(Arquitectura!$T:$T,Arquitectura!$C:$C,$B14,Arquitectura!$V:$V,$P$4) -> 0 | R14: =SUMIFS(Arquitectura!$T:$T,Arquitectura!$C:$C,$B14,Arquitectura!$W:$W,$R$4) -> 0 | S14: =SUMIFS(Arquitectura!$T:$T,Arquitectura!$C:$C,$B14,Arquitectura!$W:$W,$S$4) -> 0
B15: SUBTOTAL ARQUITECTURA | E15: =SUM(E10:E14) -> 0 | F15: =SUM(F10:F14) -> 0 | G15: =SUM(G10:G14) -> 2975800 | H15: =SUM(H10:H14) -> 2862400 | I15: =SUM(I10:I14) -> 2862400 | J15: =IFERROR(I15/E15-1,0) -> 0 | K15: =I15/(UNITARIO!$D$9+UNITARIO!$I$9) -> 977.7292 | L15: =SUM(L10:L14) -> 0 | M15: =SUM(M10:M14) -> 163565.71 | O15: =SUM(O10:O14) -> 2862400 | P15: =SUM(P10:P14) -> 0 | R15: =SUM(R10:R14) -> 2700000 | S15: =SUM(S10:S14) -> 162400
B17: INGENIERIAS Y TOPOGRAFIA
B18: Topografia Gestoria | E18: 0 | F18: 0 | G18: 0 | H18: 0 | I18: =SUMIFS(Ingenierias_Y_Topografia!$T:$T,Ingenierias_Y_Topografia!$C:$C,$B18) -> 0 | J18: =IFERROR(I18/E18-1,0) -> 0 | K18: =I18/(UNITARIO!$D$9+UNITARIO!$I$9) -> 0 | L18: =E18/$D$1 -> 0 | M18: =I18/$D$1 -> 0 | O18: =SUMIFS(Ingenierias_Y_Topografia!$T:$T,Ingenierias_Y_Topografia!$C:$C,$B18,Ingenierias_Y_Topografia!$V:$V,$O$4) -> 0 | P18: =SUMIFS(Ingenierias_Y_Topografia!$T:$T,Ingenierias_Y_Topografia!$C:$C,$B18,Ingenierias_Y_Topografia!$V:$V,$P$4) -> 0 | R18: =SUMIFS(Ingenierias_Y_Topografia!$T:$T,Ingenierias_Y_Topografia!$C:$C,$B18,Ingenierias_Y_Topografia!$W:$W,$R$4) -> 0 | S18: =SUMIFS(Ingenierias_Y_Topografia!$T:$T,Ingenierias_Y_Topografia!$C:$C,$B18,Ingenierias_Y_Topografia!$W:$W,$S$4) -> 0
B19: Topografia Obra | E19: 0 | F19: 0 | G19: 0 | H19: 0 | I19: =SUMIFS(Ingenierias_Y_Topografia!$T:$T,Ingenierias_Y_Topografia!$C:$C,$B19) -> 0 | J19: =IFERROR(I19/E19-1,0) -> 0 | K19: =I19/(UNITARIO!$D$9+UNITARIO!$I$9) -> 0 | L19: =E19/$D$1 -> 0 | M19: =I19/$D$1 -> 0 | O19: =SUMIFS(Ingenierias_Y_Topografia!$T:$T,Ingenierias_Y_Topografia!$C:$C,$B19,Ingenierias_Y_Topografia!$V:$V,$O$4) -> 0 | P19: =SUMIFS(Ingenierias_Y_Topografia!$T:$T,Ingenierias_Y_Topografia!$C:$C,$B19,Ingenierias_Y_Topografia!$V:$V,$P$4) -> 0 | R19: =SUMIFS(Ingenierias_Y_Topografia!$T:$T,Ingenierias_Y_Topografia!$C:$C,$B19,Ingenierias_Y_Topografia!$W:$W,$R$4) -> 0 | S19: =SUMIFS(Ingenierias_Y_Topografia!$T:$T,Ingenierias_Y_Topografia!$C:$C,$B19,Ingenierias_Y_Topografia!$W:$W,$S$4) -> 0
B20: Mecanica De Suelos | E20: 195384.6 | F20: 195384.6 | G20: 195384.6 | H20: 195384.6 | I20: =SUMIFS(Ingenierias_Y_Topografia!$T:$T,Ingenierias_Y_Topografia!$C:$C,$B20) -> 195384.6 | J20: =IFERROR(I20/E20-1,0) -> 0 | K20: =I20/(UNITARIO!$D$9+UNITARIO!$I$9) -> 66.73883 | L20: =E20/$D$1 -> 11164.834 | M20: =I20/$D$1 -> 11164.834 | O20: =SUMIFS(Ingenierias_Y_Topografia!$T:$T,Ingenierias_Y_Topografia!$C:$C,$B20,Ingenierias_Y_Topografia!$V:$V,$O$4) -> 195384.6 | P20: =SUMIFS(Ingenierias_Y_Topografia!$T:$T,Ingenierias_Y_Topografia!$C:$C,$B20,Ingenierias_Y_Topografia!$V:$V,$P$4) -> 0 | R20: =SUMIFS(Ingenierias_Y_Topografia!$T:$T,Ingenierias_Y_Topografia!$C:$C,$B20,Ingenierias_Y_Topografia!$W:$W,$R$4) -> 195384.6 | S20: =SUMIFS(Ingenierias_Y_Topografia!$T:$T,Ingenierias_Y_Topografia!$C:$C,$B20,Ingenierias_Y_Topografia!$W:$W,$S$4) -> 0
B21: Calculo Estructural | E21: 429200 | F21: 429200 | G21: 429200 | H21: 429200 | I21: =SUMIFS(Ingenierias_Y_Topografia!$T:$T,Ingenierias_Y_Topografia!$C:$C,$B21) -> 429200 | J21: =IFERROR(I21/E21-1,0) -> 0 | K21: =I21/(UNITARIO!$D$9+UNITARIO!$I$9) -> 146.60473 | L21: =E21/$D$1 -> 24525.714 | M21: =I21/$D$1 -> 24525.714 | O21: =SUMIFS(Ingenierias_Y_Topografia!$T:$T,Ingenierias_Y_Topografia!$C:$C,$B21,Ingenierias_Y_Topografia!$V:$V,$O$4) -> 429200 | P21: =SUMIFS(Ingenierias_Y_Topografia!$T:$T,Ingenierias_Y_Topografia!$C:$C,$B21,Ingenierias_Y_Topografia!$V:$V,$P$4) -> 0 | R21: =SUMIFS(Ingenierias_Y_Topografia!$T:$T,Ingenierias_Y_Topografia!$C:$C,$B21,Ingenierias_Y_Topografia!$W:$W,$R$4) -> 429200 | S21: =SUMIFS(Ingenierias_Y_Topografia!$T:$T,Ingenierias_Y_Topografia!$C:$C,$B21,Ingenierias_Y_Topografia!$W:$W,$S$4) -> 0
B22: Diseño HVAC | E22: 150800 | F22: 150800 | G22: 150800 | H22: 150800 | I22: =SUMIFS(Ingenierias_Y_Topografia!$T:$T,Ingenierias_Y_Topografia!$C:$C,$B22) -> 150800 | J22: =IFERROR(I22/E22-1,0) -> 0 | K22: =I22/(UNITARIO!$D$9+UNITARIO!$I$9) -> 51.509769 | L22: =E22/$D$1 -> 8617.1429 | M22: =I22/$D$1 -> 8617.1429 | O22: =SUMIFS(Ingenierias_Y_Topografia!$T:$T,Ingenierias_Y_Topografia!$C:$C,$B22,Ingenierias_Y_Topografia!$V:$V,$O$4) -> 150800 | P22: =SUMIFS(Ingenierias_Y_Topografia!$T:$T,Ingenierias_Y_Topografia!$C:$C,$B22,Ingenierias_Y_Topografia!$V:$V,$P$4) -> 0 | R22: =SUMIFS(Ingenierias_Y_Topografia!$T:$T,Ingenierias_Y_Topografia!$C:$C,$B22,Ingenierias_Y_Topografia!$W:$W,$R$4) -> 150800 | S22: =SUMIFS(Ingenierias_Y_Topografia!$T:$T,Ingenierias_Y_Topografia!$C:$C,$B22,Ingenierias_Y_Topografia!$W:$W,$S$4) -> 0
B23: Diseño Alberca | E23: 139200 | F23: 139200 | G23: 139200 | H23: 139200 | I23: =SUMIFS(Ingenierias_Y_Topografia!$T:$T,Ingenierias_Y_Topografia!$C:$C,$B23) -> 139200 | J23: =IFERROR(I23/E23-1,0) -> 0 | K23: =I23/(UNITARIO!$D$9+UNITARIO!$I$9) -> 47.547479 | L23: =E23/$D$1 -> 7954.2857 | M23: =I23/$D$1 -> 7954.2857 | O23: =SUMIFS(Ingenierias_Y_Topografia!$T:$T,Ingenierias_Y_Topografia!$C:$C,$B23,Ingenierias_Y_Topografia!$V:$V,$O$4) -> 139200 | P23: =SUMIFS(Ingenierias_Y_Topografia!$T:$T,Ingenierias_Y_Topografia!$C:$C,$B23,Ingenierias_Y_Topografia!$V:$V,$P$4) -> 0 | R23: =SUMIFS(Ingenierias_Y_Topografia!$T:$T,Ingenierias_Y_Topografia!$C:$C,$B23,Ingenierias_Y_Topografia!$W:$W,$R$4) -> 139200 | S23: =SUMIFS(Ingenierias_Y_Topografia!$T:$T,Ingenierias_Y_Topografia!$C:$C,$B23,Ingenierias_Y_Topografia!$W:$W,$S$4) -> 0
B24: Diseño Instalaciones HS-E-G | E24: 441728 | F24: 441728 | G24: 441728 | H24: 441728 | I24: =SUMIFS(Ingenierias_Y_Topografia!$T:$T,Ingenierias_Y_Topografia!$C:$C,$B24) -> 441728 | J24: =IFERROR(I24/E24-1,0) -> 0 | K24: =I24/(UNITARIO!$D$9+UNITARIO!$I$9) -> 150.884 | L24: =E24/$D$1 -> 25241.6 | M24: =I24/$D$1 -> 25241.6 | O24: =SUMIFS(Ingenierias_Y_Topografia!$T:$T,Ingenierias_Y_Topografia!$C:$C,$B24,Ingenierias_Y_Topografia!$V:$V,$O$4) -> 441728 | P24: =SUMIFS(Ingenierias_Y_Topografia!$T:$T,Ingenierias_Y_Topografia!$C:$C,$B24,Ingenierias_Y_Topografia!$V:$V,$P$4) -> 0 | R24: =SUMIFS(Ingenierias_Y_Topografia!$T:$T,Ingenierias_Y_Topografia!$C:$C,$B24,Ingenierias_Y_Topografia!$W:$W,$R$4) -> 441728 | S24: =SUMIFS(Ingenierias_Y_Topografia!$T:$T,Ingenierias_Y_Topografia!$C:$C,$B24,Ingenierias_Y_Topografia!$W:$W,$S$4) -> 0
B25: Diseño Iluminacion | D25: Habra extraordinarios | E25: 672843.5 | F25: 672843.5 | G25: 672843.5 | H25: 672843.5 | I25: =SUMIFS(Ingenierias_Y_Topografia!$T:$T,Ingenierias_Y_Topografia!$C:$C,$B25) -> 672843.5 | J25: =IFERROR(I25/E25-1,0) -> 0 | K25: =I25/(UNITARIO!$D$9+UNITARIO!$I$9) -> 229.82767 | L25: =E25/$D$1 -> 38448.2 | M25: =I25/$D$1 -> 38448.2 | O25: =SUMIFS(Ingenierias_Y_Topografia!$T:$T,Ingenierias_Y_Topografia!$C:$C,$B25,Ingenierias_Y_Topografia!$V:$V,$O$4) -> 672843.5 | P25: =SUMIFS(Ingenierias_Y_Topografia!$T:$T,Ingenierias_Y_Topografia!$C:$C,$B25,Ingenierias_Y_Topografia!$V:$V,$P$4) -> 0 | R25: =SUMIFS(Ingenierias_Y_Topografia!$T:$T,Ingenierias_Y_Topografia!$C:$C,$B25,Ingenierias_Y_Topografia!$W:$W,$R$4) -> 672843.5 | S25: =SUMIFS(Ingenierias_Y_Topografia!$T:$T,Ingenierias_Y_Topografia!$C:$C,$B25,Ingenierias_Y_Topografia!$W:$W,$S$4) -> 0
B26: Diseño Acustica | E26: 200000 | F26: 0 | G26: 0 | H26: 0 | I26: =SUMIFS(Ingenierias_Y_Topografia!$T:$T,Ingenierias_Y_Topografia!$C:$C,$B26) -> 200000 | J26: =IFERROR(I26/E26-1,0) -> -1.5543122e-15 | K26: =I26/(UNITARIO!$D$9+UNITARIO!$I$9) -> 68.315344 | L26: =E26/$D$1 -> 11428.571 | M26: =I26/$D$1 -> 11428.571 | O26: =SUMIFS(Ingenierias_Y_Topografia!$T:$T,Ingenierias_Y_Topografia!$C:$C,$B26,Ingenierias_Y_Topografia!$V:$V,$O$4) -> 200000 | P26: =SUMIFS(Ingenierias_Y_Topografia!$T:$T,Ingenierias_Y_Topografia!$C:$C,$B26,Ingenierias_Y_Topografia!$V:$V,$P$4) -> 0 | R26: =SUMIFS(Ingenierias_Y_Topografia!$T:$T,Ingenierias_Y_Topografia!$C:$C,$B26,Ingenierias_Y_Topografia!$W:$W,$R$4) -> 200000 | S26: =SUMIFS(Ingenierias_Y_Topografia!$T:$T,Ingenierias_Y_Topografia!$C:$C,$B26,Ingenierias_Y_Topografia!$W:$W,$S$4) -> 0
B27: SUBTOTAL INGENIERIAS Y TOPOGRAFIA | E27: =SUM(E18:E26) -> 2229156.1 | F27: =SUM(F18:F26) -> 2029156.1 | G27: =SUM(G18:G26) -> 2029156.1 | H27: =SUM(H18:H26) -> 2029156.1 | I27: =SUM(I18:I26) -> 2229156.1 | J27: =IFERROR(I27/E27-1,0) -> -2.220446e-16 | K27: =I27/(UNITARIO!$D$9+UNITARIO!$I$9) -> 761.42782 | L27: =SUM(L18:L25) -> 115951.78 | M27: =SUM(M18:M25) -> 115951.78 | O27: =SUM(O18:O26) -> 2229156.1 | P27: =SUM(P18:P26) -> 0 | R27: =SUM(R18:R26) -> 2229156.1 | S27: =SUM(S18:S26) -> 0
B29: PILAS | E29: =E32 -> 8935744 | F29: =F32 -> 8935744 | G29: =G32 -> 8935744 | H29: =H32 -> 8365678.7 | I29: =I32 -> 8365678.7 | J29: =IFERROR(I29/E29-1,0) -> -0.063796071 | K29: =I29/(UNITARIO!$D$9+UNITARIO!$I$9) -> 2857.5211 | L29: =E29/$D$1 -> 510613.94 | M29: =I29/$D$1 -> 478038.78 | O29: =O32 -> 8365678.7 | P29: =P32 -> 0 | R29: =R32 -> 4182839.3 | S29: =S32 -> 4182839.3
B30: PILAS
B31: Pilas | E31: =4467872.0135*2 -> 8935744 | F31: =4467872.0135*2 -> 8935744 | G31: 8935744 | H31: 8365678.7 | I31: =SUMIFS(Pilas!$T:$T,Pilas!$C:$C,$B31) -> 8365678.7 | J31: =IFERROR(I31/E31-1,0) -> -0.063796071 | K31: =I31/(UNITARIO!$D$9+UNITARIO!$I$9) -> 2857.5211 | L31: =E31/$D$1 -> 510613.94 | M31: =I31/$D$1 -> 478038.78 | O31: =SUMIFS(Pilas!$T:$T,Pilas!$C:$C,$B31,Pilas!$V:$V,$O$4) -> 8365678.7 | P31: =SUMIFS(Pilas!$T:$T,Pilas!$C:$C,$B31,Pilas!$V:$V,$P$4) -> 0 | R31: =SUMIFS(Pilas!$T:$T,Pilas!$C:$C,$B31,Pilas!$W:$W,$R$4) -> 4182839.3 | S31: =SUMIFS(Pilas!$T:$T,Pilas!$C:$C,$B31,Pilas!$W:$W,$S$4) -> 4182839.3
B32: SUBTOTAL PILAS | E32: =SUM(E31) -> 8935744 | F32: =SUM(F31) -> 8935744 | G32: =SUM(G31) -> 8935744 | H32: =SUM(H31) -> 8365678.7 | I32: =SUM(I31) -> 8365678.7 | J32: =IFERROR(I32/E32-1,0) -> -0.063796071 | K32: =I32/(UNITARIO!$D$9+UNITARIO!$I$9) -> 2857.5211 | L32: =SUM(L31) -> 510613.94 | M32: =SUM(M31) -> 478038.78 | O32: =SUM(O31) -> 8365678.7 | P32: =SUM(P31) -> 0 | R32: =SUM(R31) -> 4182839.3 | S32: =SUM(S31) -> 4182839.3
B34: OBRA CIVIL | E34: =E37+E42+E46+E50+E54+E58 -> 84601548 | F34: =F37+F42+F46+F50+F54+F58 -> 82520725 | G34: =G37+G42+G46+G50+G54+G58 -> 82887572 | H34: =H37+H42+H46+H50+H54+H58 -> 95572427 | I34: =I37+I42+I46+I50+I54+I58 -> 95572427 | J34: =IFERROR(I34/E34-1,0) -> 0.12967705 | K34: =I34/(UNITARIO!$D$9+UNITARIO!$I$9) -> 32645.316 | L34: =E34/$D$1 -> 4834374.2 | M34: =I34/$D$1 -> 5461281.5 | O34: =O37+O42+O46+O50+O54+O58 -> 42960535 | P34: =P37+P42+P46+P50+P54+P58 -> 52611892 | R34: =R37+R42+R46+R50+R54+R58 -> 40448326 | S34: =S37+S42+S46+S50+S54+S58 -> 55124101
B35: CONDICIONES GENERALES
B36: Condiciones Generales | E36: =5858713.6783768*2 -> 11717427 | F36: =6751913.6783768*2 -> 13503827 | G36: 14617427 | H36: 18600593 | I36: =SUMIFS('Condiciones Generales'!$T:$T,'Condiciones Generales'!$B:$B,$B36) -> 18600593 | J36: =IFERROR(I36/E36-1,0) -> 0.5874298 | K36: =I36/(UNITARIO!$D$9+UNITARIO!$I$9) -> 6353.5296 | L36: =E36/$D$1 -> 669567.28 | M36: =I36/$D$1 -> 1062891 | O36: =SUMIFS('Condiciones Generales'!$T:$T,'Condiciones Generales'!$B:$B,$B36,'Condiciones Generales'!$V:$V,$O$4) -> 5024417.4 | P36: =SUMIFS('Condiciones Generales'!$T:$T,'Condiciones Generales'!$B:$B,$B36,'Condiciones Generales'!$V:$V,$P$4) -> 13576176 | R36: =SUMIFS('Condiciones Generales'!$T:$T,'Condiciones Generales'!$B:$B,$B36,'Condiciones Generales'!$W:$W,$R$4) -> 2512208.7 | S36: =SUMIFS('Condiciones Generales'!$T:$T,'Condiciones Generales'!$B:$B,$B36,'Condiciones Generales'!$W:$W,$S$4) -> 16088385
B37: SUBTOTAL INDIRECTOS DE OBRA | E37: =SUM(E36) -> 11717427 | F37: =SUM(F36) -> 13503827 | G37: =SUM(G36) -> 14617427 | H37: =SUM(H36) -> 18600593 | I37: =SUM(I36) -> 18600593 | J37: =IFERROR(I37/E37-1,0) -> 0.5874298 | K37: =I37/(UNITARIO!$D$9+UNITARIO!$I$9) -> 6353.5296 | L37: =E37/$D$1 -> 669567.28 | M37: =I37/$D$1 -> 1062891 | O37: =SUM(O36) -> 5024417.4 | P37: =SUM(P36) -> 13576176 | R37: =SUM(R36) -> 2512208.7 | S37: =SUM(S36) -> 16088385
B39: PRELIMINARES
B40: Trabajos Preliminares | E40: =307645.398*2 -> 615290.8 | F40: =244253.718*2 -> 488507.44 | G40: 488507.44 | H40: 488507.44 | I40: =SUMIFS(Preliminares!$T:$T,Preliminares!$C:$C,$B40) -> 488507.44 | J40: =IFERROR(I40/E40-1,0) -> -0.20605437 | K40: =I40/(UNITARIO!$D$9+UNITARIO!$I$9) -> 166.86277 | L40: =E40/$D$1 -> 35159.474 | M40: =I40/$D$1 -> 27914.711 | O40: =SUMIFS(Preliminares!$T:$T,Preliminares!$C:$C,$B40,Preliminares!$V:$V,$O$4) -> 488507.44 | P40: =SUMIFS(Preliminares!$T:$T,Preliminares!$C:$C,$B40,Preliminares!$V:$V,$P$4) -> 0 | R40: =SUMIFS(Preliminares!$T:$T,Preliminares!$C:$C,$B40,Preliminares!$W:$W,$R$4) -> 488507.44 | S40: =SUMIFS(Preliminares!$T:$T,Preliminares!$C:$C,$B40,Preliminares!$W:$W,$S$4) -> 0
B41: Plataformas | E41: =1274117.4592*2 -> 2548234.9 | F41: =1274117.4592*2 -> 2548234.9 | G41: 2548234.9 | H41: 1200109 | I41: =SUMIFS(Preliminares!$T:$T,Preliminares!$C:$C,$B41) -> 1200109 | J41: =IFERROR(I41/E41-1,0) -> -0.52904303 | K41: =I41/(UNITARIO!$D$9+UNITARIO!$I$9) -> 409.92929 | L41: =E41/$D$1 -> 145613.42 | M41: =I41/$D$1 -> 68577.657 | O41: =SUMIFS(Preliminares!$T:$T,Preliminares!$C:$C,$B41,Preliminares!$V:$V,$O$4) -> 1200109 | P41: =SUMIFS(Preliminares!$T:$T,Preliminares!$C:$C,$B41,Preliminares!$V:$V,$P$4) -> 0 | R41: =SUMIFS(Preliminares!$T:$T,Preliminares!$C:$C,$B41,Preliminares!$W:$W,$R$4) -> 1200109 | S41: =SUMIFS(Preliminares!$T:$T,Preliminares!$C:$C,$B41,Preliminares!$W:$W,$S$4) -> 0
B42: SUBTOTAL PRELIMINARES | E42: =SUM(E40:E41) -> 3163525.7 | F42: =SUM(F40:F41) -> 3036742.4 | G42: =SUM(G40:G41) -> 3036742.4 | H42: =SUM(H40:H41) -> 1688616.4 | I42: =SUM(I40:I41) -> 1688616.4 | J42: =IFERROR(I42/E42-1,0) -> -0.46622326 | K42: =I42/(UNITARIO!$D$9+UNITARIO!$I$9) -> 576.79206 | L42: =SUM(L40:L41) -> 180772.9 | M42: =SUM(M40:M41) -> 96492.368 | O42: =SUM(O40:O41) -> 1688616.4 | P42: =SUM(P40:P41) -> 0 | R42: =SUM(R40:R41) -> 1688616.4 | S42: =SUM(S40:S41) -> 0
B44: EXCAVACION - INCLUIDA EN OBRA CIVIL
B45: Excavacion | E45: 0 | F45: 0 | G45: 0 | H45: 0 | I45: =SUMIFS(Excavacion!$T:$T,Excavacion!$C:$C,$B45) -> 0 | J45: =IFERROR(I45/E45-1,0) -> 0 | K45: =I45/(UNITARIO!$D$9+UNITARIO!$I$9) -> 0 | L45: =E45/$D$1 -> 0 | M45: =I45/$D$1 -> 0 | O45: =SUMIFS(Excavacion!$T:$T,Excavacion!$C:$C,$B45,Excavacion!$V:$V,$O$4) -> 0 | P45: =SUMIFS(Excavacion!$T:$T,Excavacion!$C:$C,$B45,Excavacion!$V:$V,$P$4) -> 0 | R45: =SUMIFS(Excavacion!$T:$T,Excavacion!$C:$C,$B45,Excavacion!$W:$W,$R$4) -> 0 | S45: =SUMIFS(Excavacion!$T:$T,Excavacion!$C:$C,$B45,Excavacion!$W:$W,$S$4) -> 0
B46: SUBTOTAL EXCAVACION | E46: =SUM(E45) -> 0 | F46: =SUM(F45) -> 0 | G46: =SUM(G45) -> 0 | H46: =SUM(H45) -> 0 | I46: =SUM(I45) -> 0 | J46: =IFERROR(I46/E46-1,0) -> 0 | K46: =I46/(UNITARIO!$D$9+UNITARIO!$I$9) -> 0 | L46: =SUM(L45) -> 0 | M46: =SUM(M45) -> 0 | O46: =SUM(O45) -> 0 | P46: =SUM(P45) -> 0 | R46: =SUM(R45) -> 0 | S46: =SUM(S45) -> 0
B48: OBRA CIVIL
B49: Obra_Civil | E49: =33935932.845*2 -> 67871866 | F49: =32065713.315*2 -> 64131427 | G49: 63384673 | H49: 72495002 | I49: =SUMIFS(Obra_Civil!$T:$T,Obra_Civil!$B:$B,$B49) -> 66000000 | J49: =IFERROR(I49/E49-1,0) -> -0.027579407 | K49: =I49/(UNITARIO!$D$9+UNITARIO!$I$9) -> 22544.063 | L49: =E49/$D$1 -> 3878392.3 | M49: =I49/$D$1 -> 3771428.6 | O49: =SUMIFS(Obra_Civil!$T:$T,Obra_Civil!$B:$B,$B49,Obra_Civil!$V:$V,$O$4) -> 33000000 | P49: =SUMIFS(Obra_Civil!$T:$T,Obra_Civil!$B:$B,$B49,Obra_Civil!$V:$V,$P$4) -> 33000000 | R49: =SUMIFS(Obra_Civil!$T:$T,Obra_Civil!$B:$B,$B49,Obra_Civil!$W:$W,$R$4) -> 33000000 | S49: =SUMIFS(Obra_Civil!$T:$T,Obra_Civil!$B:$B,$B49,Obra_Civil!$W:$W,$S$4) -> 33000000
B50: SUBTOTAL OBRA CIVIL | E50: =SUM(E49) -> 67871866 | F50: =SUM(F49) -> 64131427 | G50: =SUM(G49) -> 63384673 | H50: =SUM(H49) -> 72495002 | I50: =SUM(I49) -> 66000000 | J50: =IFERROR(I50/E50-1,0) -> -0.027579407 | K50: =I50/(UNITARIO!$D$9+UNITARIO!$I$9) -> 22544.063 | L50: =SUM(L49) -> 3878392.3 | M50: =SUM(M49) -> 3771428.6 | O50: =SUM(O49) -> 33000000 | P50: =SUM(P49) -> 33000000 | R50: =SUM(R49) -> 33000000 | S50: =SUM(S49) -> 33000000
B52: ALBAÑILERIA
B53: Aplanados | E53: =0*2 -> 0 | F53: =0*2 -> 0 | G53: 0 | H53: 0 | I53: =SUMIFS('Albañilerias '!$T:$T,'Albañilerias '!$C:$C,$B53) -> 6495001.8 | J53: =IFERROR(I53/E53-1,0) -> 0 | K53: =I53/(UNITARIO!$D$9+UNITARIO!$I$9) -> 2218.5414 | L53: =E53/$D$1 -> 0 | M53: =I53/$D$1 -> 371142.96 | O53: =SUMIFS('Albañilerias '!$T:$T,'Albañilerias '!$C:$C,$B53,'Albañilerias '!$V:$V,$O$4) -> 3247500.9 | P53: =SUMIFS('Albañilerias '!$T:$T,'Albañilerias '!$C:$C,$B53,'Albañilerias '!$V:$V,$P$4) -> 3247500.9 | R53: =SUMIFS('Albañilerias '!$T:$T,'Albañilerias '!$C:$C,$B53,'Albañilerias '!$W:$W,$R$4) -> 3247500.9 | S53: =SUMIFS('Albañilerias '!$T:$T,'Albañilerias '!$C:$C,$B53,'Albañilerias '!$W:$W,$S$4) -> 3247500.9
B54: SUBTOTAL ALBAÑILERIA Y BARDAS | E54: =SUM(E53) -> 0 | F54: =SUM(F53) -> 0 | G54: =SUM(G53) -> 0 | H54: =SUM(H53) -> 0 | I54: =SUM(I53) -> 6495001.8 | J54: =IFERROR(I54/E54-1,0) -> 0 | K54: =I54/(UNITARIO!$D$9+UNITARIO!$I$9) -> 2218.5414 | L54: =SUM(L53) -> 0 | M54: =SUM(M53) -> 371142.96 | O54: =SUM(O53) -> 3247500.9 | P54: =SUM(P53) -> 3247500.9 | R54: =SUM(R53) -> 3247500.9 | S54: =SUM(S53) -> 3247500.9
B56: IMPERMEABILIZACION
B57: Impermeabilizacion | E57: 1848728.9 | F57: 1848728.9 | G57: 1848728.9 | H57: 2788215.6 | I57: =SUMIFS(Impermeabilizacion!$T:$T,Impermeabilizacion!$B:$B,$B57&"*") -> 2788215.6 | J57: =IFERROR(I57/E57-1,0) -> 0.50817977 | K57: =I57/(UNITARIO!$D$9+UNITARIO!$I$9) -> 952.38953 | L57: =E57/$D$1 -> 105641.65 | M57: =I57/$D$1 -> 159326.6 | O57: =SUMIFS(Impermeabilizacion!$T:$T,Impermeabilizacion!$B:$B,$B57&"*",Impermeabilizacion!$V:$V,$O$4) -> 0 | P57: =SUMIFS(Impermeabilizacion!$T:$T,Impermeabilizacion!$B:$B,$B57&"*",Impermeabilizacion!$V:$V,$P$4) -> 2788215.6 | R57: =SUMIFS(Impermeabilizacion!$T:$T,Impermeabilizacion!$B:$B,$B57&"*",Impermeabilizacion!$W:$W,$R$4) -> 0 | S57: =SUMIFS(Impermeabilizacion!$T:$T,Impermeabilizacion!$B:$B,$B57&"*",Impermeabilizacion!$W:$W,$S$4) -> 2788215.6
B58: SUBTOTAL IMPERMEABILIZACION | E58: =SUM(E57) -> 1848728.9 | F58: =SUM(F57) -> 1848728.9 | G58: =SUM(G57) -> 1848728.9 | H58: =SUM(H57) -> 2788215.6 | I58: =SUM(I57) -> 2788215.6 | J58: =IFERROR(I58/E58-1,0) -> 0.50817977 | K58: =I58/(UNITARIO!$D$9+UNITARIO!$I$9) -> 952.38953 | L58: =E58/$D$1 -> 105641.65 | M58: =I58/$D$1 -> 159326.6 | O58: =SUM(O57) -> 0 | P58: =SUM(P57) -> 2788215.6 | R58: =SUM(R57) -> 0 | S58: =SUM(S57) -> 2788215.6
B60: MEP | E60: =E63+E67+E71+E75+E79+E83 -> 1.1250178e+08 | F60: =F63+F67+F71+F75+F79+F83 -> 1.1249328e+08 | G60: =G63+G67+G71+G75+G79+G83 -> 1.0435262e+08 | H60: =H63+H67+H71+H75+H79+H83 -> 1.0153715e+08 | I60: =I63+I67+I71+I75+I79+I83 -> 91164432 | J60: =IFERROR(I60/E60-1,0) -> -0.18966234 | K60: =I60/(UNITARIO!$D$9+UNITARIO!$I$9) -> 31139.648 | L60: =E60/$D$1 -> 6428673.3 | M60: =I60/$D$1 -> 5209396.1 | O60: =O63+O67+O71+O75+O79+O83 -> 41631272 | P60: =P63+P67+P71+P75+P79+P83 -> 49533160 | R60: =R63+R67+R71+R75+R79+R83 -> 0 | S60: =S63+S67+S71+S75+S79+S83 -> 91164432
B61: INSTALACIONES ELECTRICAS
B62: Instalaciones Electricas | E62: =14866931.2*2 -> 29733862 | F62: =14866931.2*2 -> 29733862 | G62: 29733862 | H62: 29733862 | I62: =SUMIFS(Instalaciones_Electricas!$T:$T,Instalaciones_Electricas!$C:$C,$B62) -> 29733862 | J62: =IFERROR(I62/E62-1,0) -> 2.220446e-16 | K62: =I62/(UNITARIO!$D$9+UNITARIO!$I$9) -> 10156.395 | L62: =E62/$D$1 -> 1699077.9 | M62: =I62/$D$1 -> 1699077.9 | O62: =SUMIFS(Instalaciones_Electricas!$T:$T,Instalaciones_Electricas!$C:$C,$B62,Instalaciones_Electricas!$V:$V,$O$4) -> 0 | P62: =SUMIFS(Instalaciones_Electricas!$T:$T,Instalaciones_Electricas!$C:$C,$B62,Instalaciones_Electricas!$V:$V,$P$4) -> 29733862 | R62: =SUMIFS(Instalaciones_Electricas!$T:$T,Instalaciones_Electricas!$C:$C,$B62,Instalaciones_Electricas!$W:$W,$R$4) -> 0 | S62: =SUMIFS(Instalaciones_Electricas!$T:$T,Instalaciones_Electricas!$C:$C,$B62,Instalaciones_Electricas!$W:$W,$S$4) -> 29733862
B63: SUBTOTAL INSTALACIONES ELECTRICAS | E63: =SUM(E62) -> 29733862 | F63: =SUM(F62) -> 29733862 | G63: =SUM(G62) -> 29733862 | H63: =SUM(H62) -> 29733862 | I63: =SUM(I62) -> 29733862 | J63: =IFERROR(I63/E63-1,0) -> 2.220446e-16 | K63: =I63/(UNITARIO!$D$9+UNITARIO!$I$9) -> 10156.395 | L63: =SUM(L62) -> 1699077.9 | M63: =SUM(M62) -> 1699077.9 | O63: =SUM(O62) -> 0 | P63: =SUM(P62) -> 29733862 | R63: =SUM(R62) -> 0 | S63: =SUM(S62) -> 29733862
B65: INSTALACIONES HIDRAULICAS
B66: Instalaciones Hidrosanitarias | E66: =8362648.8*2 -> 16725298 | F66: =8362648.8*2 -> 16725298 | G66: 16725298 | H66: 16725298 | I66: =SUMIFS(Instalaciones_Hidraulicas!$T:$T,Instalaciones_Hidraulicas!$C:$C,$B66) -> 16725298 | J66: =IFERROR(I66/E66-1,0) -> -1.110223e-16 | K66: =I66/(UNITARIO!$D$9+UNITARIO!$I$9) -> 5712.9723 | L66: =E66/$D$1 -> 955731.29 | M66: =I66/$D$1 -> 955731.29 | O66: =SUMIFS(Instalaciones_Hidraulicas!$T:$T,Instalaciones_Hidraulicas!$C:$C,$B66,Instalaciones_Hidraulicas!$V:$V,$O$4) -> 0 | P66: =SUMIFS(Instalaciones_Hidraulicas!$T:$T,Instalaciones_Hidraulicas!$C:$C,$B66,Instalaciones_Hidraulicas!$V:$V,$P$4) -> 16725298 | R66: =SUMIFS(Instalaciones_Hidraulicas!$T:$T,Instalaciones_Hidraulicas!$C:$C,$B66,Instalaciones_Hidraulicas!$W:$W,$R$4) -> 0 | S66: =SUMIFS(Instalaciones_Hidraulicas!$T:$T,Instalaciones_Hidraulicas!$C:$C,$B66,Instalaciones_Hidraulicas!$W:$W,$S$4) -> 16725298
B67: SUBTOTAL INSTALACIONES HIDRAULICAS | E67: =SUM(E66) -> 16725298 | F67: =SUM(F66) -> 16725298 | G67: =SUM(G66) -> 16725298 | H67: =SUM(H66) -> 16725298 | I67: =SUM(I66) -> 16725298 | J67: =IFERROR(I67/E67-1,0) -> -1.110223e-16 | K67: =I67/(UNITARIO!$D$9+UNITARIO!$I$9) -> 5712.9723 | L67: =SUM(L66) -> 955731.29 | M67: =SUM(M66) -> 955731.29 | O67: =SUM(O66) -> 0 | P67: =SUM(P66) -> 16725298 | R67: =SUM(R66) -> 0 | S67: =SUM(S66) -> 16725298
B69: INSTALACIONES GAS
B70: Instalaciones De Gas | E70: =928000*2 -> 1856000 | F70: =928000*2 -> 1856000 | G70: 1856000 | H70: 1856000 | I70: =SUMIFS(Instalaciones_Gas!$T:$T,Instalaciones_Gas!$C:$C,$B70) -> 1856000 | J70: =IFERROR(I70/E70-1,0) -> 0 | K70: =I70/(UNITARIO!$D$9+UNITARIO!$I$9) -> 633.96639 | L70: =E70/$D$1 -> 106057.14 | M70: =I70/$D$1 -> 106057.14 | O70: =SUMIFS(Instalaciones_Gas!$T:$T,Instalaciones_Gas!$C:$C,$B70,Instalaciones_Gas!$V:$V,$O$4) -> 0 | P70: =SUMIFS(Instalaciones_Gas!$T:$T,Instalaciones_Gas!$C:$C,$B70,Instalaciones_Gas!$V:$V,$P$4) -> 1856000 | R70: =SUMIFS(Instalaciones_Gas!$T:$T,Instalaciones_Gas!$C:$C,$B70,Instalaciones_Gas!$W:$W,$R$4) -> 0 | S70: =SUMIFS(Instalaciones_Gas!$T:$T,Instalaciones_Gas!$C:$C,$B70,Instalaciones_Gas!$W:$W,$S$4) -> 1856000
B71: SUBTOTAL INSTALACIONES GAS | E71: =SUM(E70) -> 1856000 | F71: =SUM(F70) -> 1856000 | G71: =SUM(G70) -> 1856000 | H71: =SUM(H70) -> 1856000 | I71: =SUM(I70) -> 1856000 | J71: =IFERROR(I71/E71-1,0) -> 0 | K71: =I71/(UNITARIO!$D$9+UNITARIO!$I$9) -> 633.96639 | L71: =SUM(L70) -> 106057.14 | M71: =SUM(M70) -> 106057.14 | O71: =SUM(O70) -> 0 | P71: =SUM(P70) -> 1856000 | R71: =SUM(R70) -> 0 | S71: =SUM(S70) -> 1856000
B73: AUTOMATIZACION Y CONTROL ILUMINACION
B74: Automatizacion_Control_Iluminacion | E74: =20300000*2 -> 40600000 | F74: =20300000*2 -> 40600000 | G74: 30033561 | H74: 30033561 | I74: =SUMIFS(Automat_Control_Ilum!$T:$T,Automat_Control_Ilum!$B:$B,$B74) -> 19660848 | J74: =IFERROR(I74/E74-1,0) -> -0.51574267 | K74: =I74/(UNITARIO!$D$9+UNITARIO!$I$9) -> 6715.6878 | L74: =E74/$D$1 -> 2320000 | M74: =I74/$D$1 -> 1123477 | O74: =SUMIFS(Automat_Control_Ilum!$T:$T,Automat_Control_Ilum!$B:$B,$B74,Automat_Control_Ilum!$V:$V,$O$4) -> 19660848 | P74: =SUMIFS(Automat_Control_Ilum!$T:$T,Automat_Control_Ilum!$B:$B,$B74,Automat_Control_Ilum!$V:$V,$P$4) -> 0 | R74: =SUMIFS(Automat_Control_Ilum!$T:$T,Automat_Control_Ilum!$B:$B,$B74,Automat_Control_Ilum!$W:$W,$R$4) -> 0 | S74: =SUMIFS(Automat_Control_Ilum!$T:$T,Automat_Control_Ilum!$B:$B,$B74,Automat_Control_Ilum!$W:$W,$S$4) -> 19660848
B75: SUBTOTAL AUTOMATIZACION Y CONTROL ILUMINACION | E75: =SUM(E74) -> 40600000 | F75: =SUM(F74) -> 40600000 | G75: =SUM(G74) -> 30033561 | H75: =SUM(H74) -> 30033561 | I75: =SUM(I74) -> 19660848 | J75: =IFERROR(I75/E75-1,0) -> -0.51574267 | K75: =I75/(UNITARIO!$D$9+UNITARIO!$I$9) -> 6715.6878 | L75: =SUM(L74) -> 2320000 | M75: =SUM(M74) -> 1123477 | O75: =SUM(O74) -> 19660848 | P75: =SUM(P74) -> 0 | R75: =SUM(R74) -> 0 | S75: =SUM(S74) -> 19660848
B77: AIRE ACONDICIONADO Y EXTRACCION
B78: Aire_Acondicionado_Y_Extraccion | E78: =9291832*2 -> 18583664 | F78: =9287578.918*2 -> 18575158 | G78: 18575158 | H78: 15759688 | I78: =SUMIFS(Aire_Acond_Y_Extraccion!$T:$T,Aire_Acond_Y_Extraccion!$B:$B,$B78&"*") -> 15759688 | J78: =IFERROR(I78/E78-1,0) -> -0.15196011 | K78: =I78/(UNITARIO!$D$9+UNITARIO!$I$9) -> 5383.1426 | L78: =E78/$D$1 -> 1061923.7 | M78: =I78/$D$1 -> 900553.62 | O78: =SUMIFS(Aire_Acond_Y_Extraccion!$T:$T,Aire_Acond_Y_Extraccion!$B:$B,$B78&"*",Aire_Acond_Y_Extraccion!$V:$V,$O$4) -> 15759688 | P78: =SUMIFS(Aire_Acond_Y_Extraccion!$T:$T,Aire_Acond_Y_Extraccion!$B:$B,$B78&"*",Aire_Acond_Y_Extraccion!$V:$V,$P$4) -> 0 | R78: =SUMIFS(Aire_Acond_Y_Extraccion!$T:$T,Aire_Acond_Y_Extraccion!$B:$B,$B78&"*",Aire_Acond_Y_Extraccion!$W:$W,$R$4) -> 0 | S78: =SUMIFS(Aire_Acond_Y_Extraccion!$T:$T,Aire_Acond_Y_Extraccion!$B:$B,$B78&"*",Aire_Acond_Y_Extraccion!$W:$W,$S$4) -> 15759688
B79: SUBTOTAL AIRE ACONDICIONADO Y EXTRACCION | E79: =SUM(E78) -> 18583664 | F79: =SUM(F78) -> 18575158 | G79: =SUM(G78) -> 18575158 | H79: =SUM(H78) -> 15759688 | I79: =SUM(I78) -> 15759688 | J79: =IFERROR(I79/E79-1,0) -> -0.15196011 | K79: =I79/(UNITARIO!$D$9+UNITARIO!$I$9) -> 5383.1426 | L79: =E79/$D$1 -> 1061923.7 | M79: =I79/$D$1 -> 900553.62 | O79: =SUM(O78) -> 15759688 | P79: =SUM(P78) -> 0 | R79: =SUM(R78) -> 0 | S79: =SUM(S78) -> 15759688
B81: ILUMINACION
B82: Iluminacion | E82: =2501479.68*2 -> 5002959.4 | F82: =2501479.68*2 -> 5002959.4 | G82: 7428736.3 | H82: 7428736.3 | I82: =SUMIFS(Iluminacion!$T:$T,Iluminacion!$B:$B,$B82&"*") -> 7428736.3 | J82: =IFERROR(I82/E82-1,0) -> 0.4848684 | K82: =I82/(UNITARIO!$D$9+UNITARIO!$I$9) -> 2537.4834 | L82: =E82/$D$1 -> 285883.39 | M82: =I82/$D$1 -> 424499.22 | O82: =SUMIFS(Iluminacion!$T:$T,Iluminacion!$B:$B,$B82&"*",Iluminacion!$V:$V,$O$4) -> 6210736.3 | P82: =SUMIFS(Iluminacion!$T:$T,Iluminacion!$B:$B,$B82&"*",Iluminacion!$V:$V,$P$4) -> 1218000 | R82: =SUMIFS(Iluminacion!$T:$T,Iluminacion!$B:$B,$B82&"*",Iluminacion!$W:$W,$R$4) -> 0 | S82: =SUMIFS(Iluminacion!$T:$T,Iluminacion!$B:$B,$B82&"*",Iluminacion!$W:$W,$S$4) -> 7428736.3
B83: SUBTOTAL ILUMINACION | E83: =SUM(E82) -> 5002959.4 | F83: =SUM(F82) -> 5002959.4 | G83: =SUM(G82) -> 7428736.3 | H83: =SUM(H82) -> 7428736.3 | I83: =SUM(I82) -> 7428736.3 | J83: =IFERROR(I83/E83-1,0) -> 0.4848684 | K83: =I83/(UNITARIO!$D$9+UNITARIO!$I$9) -> 2537.4834 | L83: =E83/$D$1 -> 285883.39 | M83: =I83/$D$1 -> 424499.22 | O83: =SUM(O82) -> 6210736.3 | P83: =SUM(P82) -> 1218000 | R83: =SUM(R82) -> 0 | S83: =SUM(S82) -> 7428736.3
B85: ACABADOS | E85: =E88 -> 11600000 | F85: =F88 -> 5096214.1 | G85: =G88 -> 16880130 | H85: =H88 -> 16880130 | I85: =I88 -> 16880130 | J85: =IFERROR(I85/E85-1,0) -> 0.4551836 | K85: =I85/(UNITARIO!$D$9+UNITARIO!$I$9) -> 5765.8593 | L85: =E85/$D$1 -> 662857.14 | M85: =I85/$D$1 -> 964578.84 | O85: =O88 -> 0 | P85: =P88 -> 16880130 | R85: =R88 -> 0 | S85: =S88 -> 16880130
B86: ACABADOS
B87: Acabados | E87: =5800000*2 -> 11600000 | F87: =2548107.04*2 -> 5096214.1 | G87: 16880130 | H87: 16880130 | I87: =SUMIFS(Acabados!$T:$T,Acabados!$B:$B,$B87&"*") -> 16880130 | J87: =IFERROR(I87/E87-1,0) -> 0.4551836 | K87: =I87/(UNITARIO!$D$9+UNITARIO!$I$9) -> 5765.8593 | L87: =E87/$D$1 -> 662857.14 | M87: =I87/$D$1 -> 964578.84 | O87: =SUMIFS(Acabados!$T:$T,Acabados!$B:$B,$B87&"*",Acabados!$V:$V,$O$4) -> 0 | P87: =SUMIFS(Acabados!$T:$T,Acabados!$B:$B,$B87&"*",Acabados!$V:$V,$P$4) -> 16880130 | R87: =SUMIFS(Acabados!$T:$T,Acabados!$B:$B,$B87&"*",Acabados!$W:$W,$R$4) -> 0 | S87: =SUMIFS(Acabados!$T:$T,Acabados!$B:$B,$B87&"*",Acabados!$W:$W,$S$4) -> 16880130
B88: SUBTOTAL ACABADOS | E88: =SUM(E87) -> 11600000 | F88: =SUM(F87) -> 5096214.1 | G88: =SUM(G87) -> 16880130 | H88: =SUM(H87) -> 16880130 | I88: =SUM(I87) -> 16880130 | J88: =IFERROR(I88/E88-1,0) -> 0.4551836 | K88: =I88/(UNITARIO!$D$9+UNITARIO!$I$9) -> 5765.8593 | L88: =E88/$D$1 -> 662857.14 | M88: =I88/$D$1 -> 964578.84 | O88: =SUM(O87) -> 0 | P88: =SUM(P87) -> 16880130 | R88: =SUM(R87) -> 0 | S88: =SUM(S87) -> 16880130
B90: COLOCACIONES | E90: =E94+E99+E104+E111+E117+E121+E130 -> 1.4598678e+08 | F90: =F94+F99+F104+F111+F117+F121+F130 -> 1.2668697e+08 | G90: =G94+G99+G104+G111+G117+G121+G130 -> 1.3599447e+08 | H90: =H94+H99+H104+H111+H117+H121+H130 -> 1.4405576e+08 | I90: =I94+I99+I104+I111+I117+I121+I130 -> 1.4449382e+08 | J90: =IFERROR(I90/E90-1,0) -> -0.01022669 | K90: =I90/(UNITARIO!$D$9+UNITARIO!$I$9) -> 49355.724 | L90: =E90/$D$1 -> 8342101.6 | M90: =I90/$D$1 -> 8256789.5 | O90: =O94+O99+O104+O111+O117+O121+O130 -> 1.0900559e+08 | P90: =P94+P99+P104+P111+P117+P121+P130 -> 35488225 | R90: =R94+R99+R104+R111+R117+R121+R130 -> 40103520 | S90: =S94+S99+S104+S111+S117+S121+S130 -> 95444818
B91: HERRERIA
B92: Herreria ( Rejillas, Anclajes, Exclusas, Tapajuntas, Soportes, Ductos ) | E92: =2320000*2 -> 4640000 | F92: 2320000 | G92: 4640000 | H92: 4640000 | I92: =SUMIFS(Herreria!$T:$T,Herreria!$C:$C,$B92) -> 4640000 | J92: =IFERROR(I92/E92-1,0) -> 0 | K92: =I92/(UNITARIO!$D$9+UNITARIO!$I$9) -> 1584.916 | L92: =E92/$D$1 -> 265142.86 | M92: =I92/$D$1 -> 265142.86 | O92: =SUMIFS(Herreria!$T:$T,Herreria!$C:$C,$B92,Herreria!$V:$V,$O$4) -> 0 | P92: =SUMIFS(Herreria!$T:$T,Herreria!$C:$C,$B92,Herreria!$V:$V,$P$4) -> 4640000 | R92: =SUMIFS(Herreria!$T:$T,Herreria!$C:$C,$B92,Herreria!$W:$W,$R$4) -> 0 | S92: =SUMIFS(Herreria!$T:$T,Herreria!$C:$C,$B92,Herreria!$W:$W,$S$4) -> 4640000
B93: Pintura Herreria. Primario / Acabado | E93: =0*2 -> 0 | F93: 0 | G93: 0 | H93: 0 | I93: =SUMIFS(Herreria!$T:$T,Herreria!$C:$C,$B93) -> 0 | J93: =IFERROR(I93/E93-1,0) -> 0 | K93: =I93/(UNITARIO!$D$9+UNITARIO!$I$9) -> 0 | L93: =E93/$D$1 -> 0 | M93: =I93/$D$1 -> 0 | O93: =SUMIFS(Herreria!$T:$T,Herreria!$C:$C,$B93,Herreria!$V:$V,$O$4) -> 0 | P93: =SUMIFS(Herreria!$T:$T,Herreria!$C:$C,$B93,Herreria!$V:$V,$P$4) -> 0 | R93: =SUMIFS(Herreria!$T:$T,Herreria!$C:$C,$B93,Herreria!$W:$W,$R$4) -> 0 | S93: =SUMIFS(Herreria!$T:$T,Herreria!$C:$C,$B93,Herreria!$W:$W,$S$4) -> 0
B94: SUBTOTAL HERRERIA | E94: =SUM(E92:E93) -> 4640000 | F94: =SUM(F92:F93) -> 2320000 | G94: =SUM(G92:G93) -> 4640000 | H94: =SUM(H92:H93) -> 4640000 | I94: =SUM(I92:I93) -> 4640000 | J94: =IFERROR(I94/E94-1,0) -> 0 | K94: =I94/(UNITARIO!$D$9+UNITARIO!$I$9) -> 1584.916 | L94: =SUM(L92:L93) -> 265142.86 | M94: =SUM(M92:M93) -> 265142.86 | O94: =SUM(O92:O93) -> 0 | P94: =SUM(P92:P93) -> 4640000 | R94: =SUM(R92:R93) -> 0 | S94: =SUM(S92:S93) -> 4640000
B96: SUMINISTRO Y COLOCACION DE MARMOL | CE96: 2
B97: Suministro de Marmol | E97: =7302034.2276091*2 -> 14604068 | F97: =7140971.6*2 -> 14281943 | G97: 8739576.3 | H97: 8739576.3 | I97: =SUMIFS(Sumin_Coloc_Marmol!$T:$T,Sumin_Coloc_Marmol!$B:$B,$B97&"*") -> 8739576.3 | J97: =IFERROR(I97/E97-1,0) -> -0.40156564 | K97: =I97/(UNITARIO!$D$9+UNITARIO!$I$9) -> 2985.2358 | L97: =E97/$D$1 -> 834518.2 | M97: =I97/$D$1 -> 499404.36 | O97: =SUMIFS(Sumin_Coloc_Marmol!$T:$T,Sumin_Coloc_Marmol!$B:$B,$B97&"*",Sumin_Coloc_Marmol!$V:$V,$O$4) -> 0 | P97: =SUMIFS(Sumin_Coloc_Marmol!$T:$T,Sumin_Coloc_Marmol!$B:$B,$B97&"*",Sumin_Coloc_Marmol!$V:$V,$P$4) -> 8739576.3 | R97: =SUMIFS(Sumin_Coloc_Marmol!$T:$T,Sumin_Coloc_Marmol!$B:$B,$B97&"*",Sumin_Coloc_Marmol!$W:$W,$R$4) -> 0 | S97: =SUMIFS(Sumin_Coloc_Marmol!$T:$T,Sumin_Coloc_Marmol!$B:$B,$B97&"*",Sumin_Coloc_Marmol!$W:$W,$S$4) -> 8739576.3
B98: Colocacion de Marmol | E98: =7118641.4923909*2 -> 14237283 | F98: =6961624*2 -> 13923248 | G98: 12634103 | H98: 12634103 | I98: =SUMIFS(Sumin_Coloc_Marmol!$T:$T,Sumin_Coloc_Marmol!$B:$B,$B98&"*") -> 12634103 | J98: =IFERROR(I98/E98-1,0) -> -0.11260436 | K98: =I98/(UNITARIO!$D$9+UNITARIO!$I$9) -> 4315.5154 | L98: =E98/$D$1 -> 813559.03 | M98: =I98/$D$1 -> 721948.74 | O98: =SUMIFS(Sumin_Coloc_Marmol!$T:$T,Sumin_Coloc_Marmol!$B:$B,$B98&"*",Sumin_Coloc_Marmol!$V:$V,$O$4) -> 0 | P98: =SUMIFS(Sumin_Coloc_Marmol!$T:$T,Sumin_Coloc_Marmol!$B:$B,$B98&"*",Sumin_Coloc_Marmol!$V:$V,$P$4) -> 12634103 | R98: =SUMIFS(Sumin_Coloc_Marmol!$T:$T,Sumin_Coloc_Marmol!$B:$B,$B98&"*",Sumin_Coloc_Marmol!$W:$W,$R$4) -> 0 | S98: =SUMIFS(Sumin_Coloc_Marmol!$T:$T,Sumin_Coloc_Marmol!$B:$B,$B98&"*",Sumin_Coloc_Marmol!$W:$W,$S$4) -> 12634103
B99: SUBTOTAL SUMINISTRO Y COLOCACION DE MARMOL | E99: =SUM(E97:E98) -> 28841351 | F99: =SUM(F97:F98) -> 28205191 | G99: =SUM(G97:G98) -> 21373679 | H99: =SUM(H97:H98) -> 21373679 | I99: =SUM(I97:I98) -> 21373679 | J99: =IFERROR(I99/E99-1,0) -> -0.25892241 | K99: =I99/(UNITARIO!$D$9+UNITARIO!$I$9) -> 7300.7512 | L99: =E99/$D$1 -> 1648077.2 | M99: =I99/$D$1 -> 1221353.1 | O99: =SUM(O97:O98) -> 0 | P99: =SUM(P97:P98) -> 21373679 | R99: =SUM(R97:R98) -> 0 | S99: =SUM(S97:S98) -> 21373679
B101: MADERA DE INGENIERIA*
B102: Pisos_Madera | E102: =0*2 -> 0 | F102: =0*2 -> 0 | G102: 0 | H102: 0 | I102: =SUMIFS(Madera_De_Ingenieria!$T:$T,Madera_De_Ingenieria!$C:$C,$B102) -> 0 | J102: =IFERROR(I102/E102-1,0) -> 0 | K102: =I102/(UNITARIO!$D$9+UNITARIO!$I$9) -> 0 | L102: =E102/$D$1 -> 0 | M102: =I102/$D$1 -> 0 | O102: =SUMIFS(Madera_De_Ingenieria!$T:$T,Madera_De_Ingenieria!$C:$C,$B102,Madera_De_Ingenieria!$V:$V,$O$4) -> 0 | P102: =SUMIFS(Madera_De_Ingenieria!$T:$T,Madera_De_Ingenieria!$C:$C,$B102,Madera_De_Ingenieria!$V:$V,$P$4) -> 0 | R102: =SUMIFS(Madera_De_Ingenieria!$T:$T,Madera_De_Ingenieria!$C:$C,$B102,Madera_De_Ingenieria!$W:$W,$R$4) -> 0 | S102: =SUMIFS(Madera_De_Ingenieria!$T:$T,Madera_De_Ingenieria!$C:$C,$B102,Madera_De_Ingenieria!$W:$W,$S$4) -> 0
B103: Madera_Puertas | E103: =0*2 -> 0 | F103: =0*2 -> 0 | G103: 0 | H103: 0 | I103: =SUMIFS(Madera_De_Ingenieria!$T:$T,Madera_De_Ingenieria!$C:$C,$B103) -> 0 | J103: =IFERROR(I103/E103-1,0) -> 0 | K103: =I103/(UNITARIO!$D$9+UNITARIO!$I$9) -> 0 | L103: =E103/$D$1 -> 0 | M103: =I103/$D$1 -> 0 | O103: =SUMIFS(Madera_De_Ingenieria!$T:$T,Madera_De_Ingenieria!$C:$C,$B103,Madera_De_Ingenieria!$V:$V,$O$4) -> 0 | P103: =SUMIFS(Madera_De_Ingenieria!$T:$T,Madera_De_Ingenieria!$C:$C,$B103,Madera_De_Ingenieria!$V:$V,$P$4) -> 0 | R103: =SUMIFS(Madera_De_Ingenieria!$T:$T,Madera_De_Ingenieria!$C:$C,$B103,Madera_De_Ingenieria!$W:$W,$R$4) -> 0 | S103: =SUMIFS(Madera_De_Ingenieria!$T:$T,Madera_De_Ingenieria!$C:$C,$B103,Madera_De_Ingenieria!$W:$W,$S$4) -> 0
B104: SUBTOTAL MADERA DE INGENIERIA | E104: =SUM(E102:E103) -> 0 | F104: =SUM(F102:F103) -> 0 | G104: =SUM(G102:G103) -> 0 | H104: =SUM(H102:H103) -> 0 | I104: =SUM(I102:I103) -> 0 | J104: =IFERROR(I104/E104-1,0) -> 0 | K104: =I104/(UNITARIO!$D$9+UNITARIO!$I$9) -> 0 | L104: =SUM(L102:L103) -> 0 | M104: =SUM(M102:M103) -> 0 | O104: =SUM(O102:O103) -> 0 | P104: =SUM(P102:P103) -> 0 | R104: =SUM(R102:R103) -> 0 | S104: =SUM(S102:S103) -> 0
B106: VIDRIOS Y CANCELES
B107: Canceles Y Vidrios | E107: =14076186.5992*2 -> 28152373 | F107: =11872148.4816*2 -> 23744297 | G107: 28152373 | H107: 28152373 | I107: =SUMIFS(Vidrios_Y_Canceles!$T:$T,Vidrios_Y_Canceles!$C:$C,$B107) -> 28152373 | J107: =IFERROR(I107/E107-1,0) -> 2.220446e-16 | K107: =I107/(UNITARIO!$D$9+UNITARIO!$I$9) -> 9616.1952 | L107: =E107/$D$1 -> 1608707 | M107: =I107/$D$1 -> 1608707 | O107: =SUMIFS(Vidrios_Y_Canceles!$T:$T,Vidrios_Y_Canceles!$C:$C,$B107,Vidrios_Y_Canceles!$V:$V,$O$4) -> 28152373 | P107: =SUMIFS(Vidrios_Y_Canceles!$T:$T,Vidrios_Y_Canceles!$C:$C,$B107,Vidrios_Y_Canceles!$V:$V,$P$4) -> 0 | R107: =SUMIFS(Vidrios_Y_Canceles!$T:$T,Vidrios_Y_Canceles!$C:$C,$B107,Vidrios_Y_Canceles!$W:$W,$R$4) -> 0 | S107: =SUMIFS(Vidrios_Y_Canceles!$T:$T,Vidrios_Y_Canceles!$C:$C,$B107,Vidrios_Y_Canceles!$W:$W,$S$4) -> 28152373
B108: Barandal de Vidrio | E108: =260736.68*2 -> 521473.36 | F108: =260736.68*2 -> 521473.36 | G108: 521473.36 | H108: 521473.36 | I108: =SUMIFS(Vidrios_Y_Canceles!$T:$T,Vidrios_Y_Canceles!$C:$C,$B108) -> 521473.36 | J108: =IFERROR(I108/E108-1,0) -> 0 | K108: =I108/(UNITARIO!$D$9+UNITARIO!$I$9) -> 178.12316 | L108: =E108/$D$1 -> 29798.478 | M108: =I108/$D$1 -> 29798.478 | O108: =SUMIFS(Vidrios_Y_Canceles!$T:$T,Vidrios_Y_Canceles!$C:$C,$B108,Vidrios_Y_Canceles!$V:$V,$O$4) -> 521473.36 | P108: =SUMIFS(Vidrios_Y_Canceles!$T:$T,Vidrios_Y_Canceles!$C:$C,$B108,Vidrios_Y_Canceles!$V:$V,$P$4) -> 0 | R108: =SUMIFS(Vidrios_Y_Canceles!$T:$T,Vidrios_Y_Canceles!$C:$C,$B108,Vidrios_Y_Canceles!$W:$W,$R$4) -> 0 | S108: =SUMIFS(Vidrios_Y_Canceles!$T:$T,Vidrios_Y_Canceles!$C:$C,$B108,Vidrios_Y_Canceles!$W:$W,$S$4) -> 521473.36
B109: Canceles de Baño | E109: =1329441.2*2 -> 2658882.4 | F109: =1329441.2*2 -> 2658882.4 | G109: 2596760.6 | H109: 2596760.6 | I109: =SUMIFS(Vidrios_Y_Canceles!$T:$T,Vidrios_Y_Canceles!$C:$C,$B109) -> 2596760.6 | J109: =IFERROR(I109/E109-1,0) -> -0.02336387 | K109: =I109/(UNITARIO!$D$9+UNITARIO!$I$9) -> 886.99297 | L109: =E109/$D$1 -> 151936.14 | M109: =I109/$D$1 -> 148386.32 | O109: =SUMIFS(Vidrios_Y_Canceles!$T:$T,Vidrios_Y_Canceles!$C:$C,$B109,Vidrios_Y_Canceles!$V:$V,$O$4) -> 2596760.6 | P109: =SUMIFS(Vidrios_Y_Canceles!$T:$T,Vidrios_Y_Canceles!$C:$C,$B109,Vidrios_Y_Canceles!$V:$V,$P$4) -> 0 | R109: =SUMIFS(Vidrios_Y_Canceles!$T:$T,Vidrios_Y_Canceles!$C:$C,$B109,Vidrios_Y_Canceles!$W:$W,$R$4) -> 0 | S109: =SUMIFS(Vidrios_Y_Canceles!$T:$T,Vidrios_Y_Canceles!$C:$C,$B109,Vidrios_Y_Canceles!$W:$W,$S$4) -> 2596760.6
B110: Celosia Fachada Principal | E110: 0 | F110: 0 | G110: 0 | H110: 7045306.4 | I110: =SUMIFS(Vidrios_Y_Canceles!$T:$T,Vidrios_Y_Canceles!$C:$C,$B110) -> 7045306.4 | J110: =IFERROR(I110/E110-1,0) -> 0 | K110: =I110/(UNITARIO!$D$9+UNITARIO!$I$9) -> 2406.5126 | L110: =E110/$D$1 -> 0 | M110: =I110/$D$1 -> 402588.94 | O110: =SUMIFS(Vidrios_Y_Canceles!$T:$T,Vidrios_Y_Canceles!$C:$C,$B110,Vidrios_Y_Canceles!$V:$V,$O$4) -> 0 | P110: =SUMIFS(Vidrios_Y_Canceles!$T:$T,Vidrios_Y_Canceles!$C:$C,$B110,Vidrios_Y_Canceles!$V:$V,$P$4) -> 7045306.4 | R110: =SUMIFS(Vidrios_Y_Canceles!$T:$T,Vidrios_Y_Canceles!$C:$C,$B110,Vidrios_Y_Canceles!$W:$W,$R$4) -> 0 | S110: =SUMIFS(Vidrios_Y_Canceles!$T:$T,Vidrios_Y_Canceles!$C:$C,$B110,Vidrios_Y_Canceles!$W:$W,$S$4) -> 7045306.4
B111: SUBTOTAL VIDRIOS Y CANCELES | E111: =SUM(E107:E110) -> 31332729 | F111: =SUM(F107:F109) -> 26924653 | G111: =SUM(G107:G109) -> 31270607 | H111: =SUM(H107:H110) -> 38315914 | I111: =SUM(I107:I110) -> 38315914 | J111: =IFERROR(I111/E111-1,0) -> 0.22287189 | K111: =I111/(UNITARIO!$D$9+UNITARIO!$I$9) -> 13087.824 | L111: =SUM(L107:L110) -> 1790441.7 | M111: =SUM(M107:M110) -> 2189480.8 | O111: =SUM(O107:O110) -> 31270607 | P111: =SUM(P107:P110) -> 7045306.4 | R111: =SUM(R107:R110) -> 0 | S111: =SUM(S107:S110) -> 38315914
B113: COCINAS | D113: meter ultima q
B114: Cocina Principal | D114: Agregra M2 de marmol de cubiertas | E114: =7511812*2 -> 15023624 | F114: =4988525.73092982*2 -> 9977051.5 | G114: 13681990 | H114: 13681990 | I114: =SUMIFS(Cocinas!$U:$U,Cocinas!$D:$D,$B114) -> 14930688 | J114: =IFERROR(I114/E114-1,0) -> -0.006186017 | K114: =I114/(UNITARIO!$D$9+UNITARIO!$I$9) -> 5099.9753 | L114: =E114/$D$1 -> 858492.8 | M114: =I114/$D$1 -> 853182.15 | O114: =SUMIFS(Cocinas!$U:$U,Cocinas!$D:$D,$B114,Cocinas!$W:$W,$O$4) -> 14930688 | P114: =SUMIFS(Cocinas!$U:$U,Cocinas!$D:$D,$B114,Cocinas!$W:$W,$P$4) -> 0 | R114: =SUMIFS(Cocinas!$U:$U,Cocinas!$D:$D,$B114,Cocinas!$X:$X,$R$4) -> 0 | S114: =SUMIFS(Cocinas!$U:$U,Cocinas!$D:$D,$B114,Cocinas!$X:$X,$S$4) -> 9320579.6
B115: Grill | E115: =6799606.8*2 -> 13599214 | F115: =3748127.04*2 -> 7496254.1 | G115: 9258152.9 | H115: 9323632.6 | I115: =SUMIFS(Cocinas!$U:$U,Cocinas!$D:$D,$B115) -> 10322743 | J115: =IFERROR(I115/E115-1,0) -> -0.24093087 | K115: =I115/(UNITARIO!$D$9+UNITARIO!$I$9) -> 3526.0088 | L115: =E115/$D$1 -> 777097.92 | M115: =I115/$D$1 -> 589871.04 | O115: =SUMIFS(Cocinas!$U:$U,Cocinas!$D:$D,$B115,Cocinas!$W:$W,$O$4) -> 9262303.8 | P115: =SUMIFS(Cocinas!$U:$U,Cocinas!$D:$D,$B115,Cocinas!$W:$W,$P$4) -> 1060439.5 | R115: =SUMIFS(Cocinas!$U:$U,Cocinas!$D:$D,$B115,Cocinas!$X:$X,$R$4) -> 0 | S115: =SUMIFS(Cocinas!$U:$U,Cocinas!$D:$D,$B115,Cocinas!$X:$X,$S$4) -> 6987372.1
B116: Laundry | E116: =423255*2 -> 846510 | F116: =423255*2 -> 846510 | G116: 846510 | H116: 846510 | I116: =SUMIFS(Cocinas!$U:$U,Cocinas!$D:$D,$B116) -> 626400 | J116: =IFERROR(I116/E116-1,0) -> -0.26002055 | K116: =I116/(UNITARIO!$D$9+UNITARIO!$I$9) -> 213.96366 | L116: =E116/$D$1 -> 48372 | M116: =I116/$D$1 -> 35794.286 | O116: =SUMIFS(Cocinas!$U:$U,Cocinas!$D:$D,$B116,Cocinas!$W:$W,$O$4) -> 0 | P116: =SUMIFS(Cocinas!$U:$U,Cocinas!$D:$D,$B116,Cocinas!$W:$W,$P$4) -> 626400 | R116: =SUMIFS(Cocinas!$U:$U,Cocinas!$D:$D,$B116,Cocinas!$X:$X,$R$4) -> 0 | S116: =SUMIFS(Cocinas!$U:$U,Cocinas!$D:$D,$B116,Cocinas!$X:$X,$S$4) -> 626400
B117: SUBTOTAL COCINAS | E117: =SUM(E114:E116) -> 29469348 | F117: =SUM(F114:F116) -> 18319816 | G117: =SUM(G114:G116) -> 23786652 | H117: =SUM(H114:H116) -> 23852132 | I117: =SUM(I114:I116) -> 25879831 | J117: =IFERROR(I117/E117-1,0) -> -0.1218051 | K117: =I117/(UNITARIO!$D$9+UNITARIO!$I$9) -> 8839.9477 | L117: =SUM(L114:L116) -> 1683962.7 | M117: =SUM(M114:M116) -> 1478847.5 | O117: =SUM(O114:O116) -> 24192991 | P117: =SUM(P114:P116) -> 1686839.5 | R117: =SUM(R114:R116) -> 0 | S117: =SUM(S114:S116) -> 16934352
B119: GRIFERIA Y ACCESORIOS DE BAÑO | D119: meter ultima q
B120: Griferia_Y_Accesorios_De_Baño | D120: Revisar quant. Agregar coladeras, cespoles, etc | E120: =3636236.282*2 -> 7272472.6 | F120: =3243218.132*2 -> 6486436.3 | G120: 7794736.6 | H120: 7794736.6 | I120: =SUMIFS(Griferia_Y_Acces_Baño!$T:$T,Griferia_Y_Acces_Baño!$B:$B,$B120&"*") -> 8061094.3 | J120: =IFERROR(I120/E120-1,0) -> 0.10843928 | K120: =I120/(UNITARIO!$D$9+UNITARIO!$I$9) -> 2753.4821 | L120: =E120/$D$1 -> 415569.86 | M120: =I120/$D$1 -> 460633.96 | O120: =SUMIFS(Griferia_Y_Acces_Baño!$T:$T,Griferia_Y_Acces_Baño!$B:$B,$B120&"*",Griferia_Y_Acces_Baño!$V:$V,$O$4) -> 8061094.3 | P120: =SUMIFS(Griferia_Y_Acces_Baño!$T:$T,Griferia_Y_Acces_Baño!$B:$B,$B120&"*",Griferia_Y_Acces_Baño!$V:$V,$P$4) -> 0 | R120: =SUMIFS(Griferia_Y_Acces_Baño!$T:$T,Griferia_Y_Acces_Baño!$B:$B,$B120&"*",Griferia_Y_Acces_Baño!$W:$W,$R$4) -> 0 | S120: =SUMIFS(Griferia_Y_Acces_Baño!$T:$T,Griferia_Y_Acces_Baño!$B:$B,$B120&"*",Griferia_Y_Acces_Baño!$W:$W,$S$4) -> 8061094.3
B121: SUBTOTAL GRIFERIA Y ACCESORIOS DE BAÑO | E121: =SUM(E120) -> 7272472.6 | F121: =SUM(F120) -> 6486436.3 | G121: =SUM(G120) -> 7794736.6 | H121: =SUM(H120) -> 7794736.6 | I121: =SUM(I120) -> 8061094.3 | J121: =IFERROR(I121/E121-1,0) -> 0.10843928 | K121: =I121/(UNITARIO!$D$9+UNITARIO!$I$9) -> 2753.4821 | L121: =E121/$D$1 -> 415569.86 | M121: =I121/$D$1 -> 460633.96 | O121: =SUM(O120) -> 8061094.3 | P121: =SUM(P120) -> 0 | R121: =SUM(R120) -> 0 | S121: =SUM(S120) -> 8061094.3
B123: CARPINTERIAS
B124: Vanityes | E124: =3726887*2 -> 7453774 | F124: =3726887*2 -> 7453774 | G124: 11020000 | H124: 10579200 | I124: =SUMIFS(Carpinterias!$U:$U,Carpinterias!$C:$C,$B124) -> 10579200 | J124: =IFERROR(I124/E124-1,0) -> 0.41930786 | K124: =I124/(UNITARIO!$D$9+UNITARIO!$I$9) -> 3613.6084 | L124: =E124/$D$1 -> 425929.94 | M124: =I124/$D$1 -> 604525.71 | O124: =SUMIFS(Carpinterias!$U:$U,Carpinterias!$C:$C,$B124,Carpinterias!$W:$W,$O$4) -> 10579200 | P124: =SUMIFS(Carpinterias!$U:$U,Carpinterias!$C:$C,$B124,Carpinterias!$W:$W,$P$4) -> 0 | R124: =SUMIFS(Carpinterias!$U:$U,Carpinterias!$C:$C,$B124,Carpinterias!$X:$X,$R$4) -> 10579200 | S124: =SUMIFS(Carpinterias!$U:$U,Carpinterias!$C:$C,$B124,Carpinterias!$X:$X,$S$4) -> 0
B125: Puertas | E125: =6449537*2 -> 12899074 | F125: =6449537*2 -> 12899074 | G125: 15024320 | H125: 14003520 | I125: =SUMIFS(Carpinterias!$U:$U,Carpinterias!$C:$C,$B125) -> 14003520 | J125: =IFERROR(I125/E125-1,0) -> 0.085622115 | K125: =I125/(UNITARIO!$D$9+UNITARIO!$I$9) -> 4783.2764 | L125: =E125/$D$1 -> 737089.94 | M125: =I125/$D$1 -> 800201.14 | O125: =SUMIFS(Carpinterias!$U:$U,Carpinterias!$C:$C,$B125,Carpinterias!$W:$W,$O$4) -> 14003520 | P125: =SUMIFS(Carpinterias!$U:$U,Carpinterias!$C:$C,$B125,Carpinterias!$W:$W,$P$4) -> 0 | R125: =SUMIFS(Carpinterias!$U:$U,Carpinterias!$C:$C,$B125,Carpinterias!$X:$X,$R$4) -> 14003520 | S125: =SUMIFS(Carpinterias!$U:$U,Carpinterias!$C:$C,$B125,Carpinterias!$X:$X,$S$4) -> 0
...

Sheet UNITARIO
C2: MXN PER USD | D2: ='Glosario Partidas'!M9 -> 17.5
C4: DEPTO | D4: Area Int. Acon. | E4: Area Ext. Techada | F4: Total AIA + AET | H4: DEPTO | I4: Area Int. Acon. | J4: Area Ext. Techada | K4: Total AIA + AET
C5: PB 1 | D5: 322.72 | E5: 106.72 | F5: =D5+E5 -> 429.44 | H5: PB 1 | I5: 322.72 | J5: 106.72 | K5: =I5+J5 -> 429.44
C6: PB 2 | D6: 322.72 | E6: 106.72 | F6: =D6+E6 -> 429.44 | H6: PB 2 | I6: 322.72 | J6: 106.72 | K6: =I6+J6 -> 429.44
C7: N1 + Roof 1 | D7: 409.18 | E7: 153.91 | F7: =D7+E7 -> 563.09 | H7: N1 + Roof 1 | I7: 409.18 | J7: 153.91 | K7: =I7+J7 -> 563.09
C8: N1 + Roof 2 | D8: 409.18 | E8: 153.91 | F8: =D8+E8 -> 563.09 | H8: N1 + Roof 2 | I8: 409.18 | J8: 153.91 | K8: =I8+J8 -> 563.09
C9: Total Torre 1 | D9: =SUM(D5:D8) -> 1463.8 | E9: 521.26 | F9: =D9+E9 -> 1985.06 | H9: Total Torre 1 | I9: =SUM(I5:I8) -> 1463.8 | J9: 521.26 | K9: =I9+J9 -> 1985.06
C11: Area Int. Acon. | H11: Area Int. Acon.
C13: Torre 1 | D13: Base | E13: Mrazo | F13: Abril | H13: Torre 2 | I13: Base | J13: Mrazo | K13: Abril
C14: MXN/M2 | D14: =('BUY OUT'!E172/2)/$D$9 -> 145908.3 | E14: =('BUY OUT'!F172/2)/$D$9 -> 136216.37 | F14: =('BUY OUT'!G172/2)/$D$9 -> 141488.7 | H14: MXN/M2 | I14: =('BUY OUT'!E172/2)/$D$9 -> 145908.3 | J14: =('BUY OUT'!F172/2)/$D$9 -> 136216.37 | K14: =('BUY OUT'!G172/2)/$D$9 -> 141488.7
C16: PB 1 | D16: =$D$14*D5 -> 47087526 | E16: =$E$14*D5 -> 43959747 | F16: =$F$14*D5 -> 45661235 | H16: PB 1 | I16: =$I$14*I5 -> 47087526 | J16: =$J$14*I5 -> 43959747 | K16: =$K$14*I5 -> 45661235
C17: PB 2 | D17: =$D$14*D6 -> 47087526 | E17: =$E$14*D6 -> 43959747 | F17: =$F$14*D6 -> 45661235 | H17: PB 2 | I17: =$I$14*I6 -> 47087526 | J17: =$J$14*I6 -> 43959747 | K17: =$K$14*I6 -> 45661235
C18: N1 + Roof 1 | D18: =$D$14*D7 -> 59702757 | E18: =$E$14*D7 -> 55737014 | F18: =$F$14*D7 -> 57894348 | H18: N1 + Roof 1 | I18: =$I$14*I7 -> 59702757 | J18: =$J$14*I7 -> 55737014 | K18: =$K$14*I7 -> 57894348
C19: N1 + Roof 2 | D19: =$D$14*D8 -> 59702757 | E19: =$E$14*D8 -> 55737014 | F19: =$F$14*D8 -> 57894348 | H19: N1 + Roof 2 | I19: =$I$14*I8 -> 59702757 | J19: =$J$14*I8 -> 55737014 | K19: =$K$14*I8 -> 57894348
C20: Total Torre 1 | D20: =SUM(D16:D19) -> 2.1358057e+08 | E20: =SUM(E16:E19) -> 1.9939352e+08 | F20: =SUM(F16:F19) -> 2.0711116e+08 | H20: Total Torre 1 | I20: =SUM(I16:I19) -> 2.1358057e+08 | J20: =SUM(J16:J19) -> 1.9939352e+08 | K20: =SUM(K16:K19) -> 2.0711116e+08
C22: USD/M2 | D22: =D14/$D$2 -> 8337.617 | E22: =E14/$D$2 -> 7783.7926 | F22: =F14/$D$2 -> 8085.0688 | H22: USD/M2 | I22: =I14/$D$2 -> 8337.617 | J22: =J14/$D$2 -> 7783.7926 | K22: =K14/$D$2 -> 8085.0688
C24: PB 1 | D24: =D16/$D$2 -> 2690715.7 | E24: =E16/$D$2 -> 2511985.5 | F24: =F16/$D$2 -> 2609213.4 | H24: PB 1 | I24: =I16/$D$2 -> 2690715.7 | J24: =J16/$D$2 -> 2511985.5 | K24: =K16/$D$2 -> 2609213.4
C25: PB 2 | D25: =D17/$D$2 -> 2690715.7 | E25: =E17/$D$2 -> 2511985.5 | F25: =F17/$D$2 -> 2609213.4 | H25: PB 2 | I25: =I17/$D$2 -> 2690715.7 | J25: =J17/$D$2 -> 2511985.5 | K25: =K17/$D$2 -> 2609213.4
C26: N1 + Roof 1 | D26: =D18/$D$2 -> 3411586.1 | E26: =E18/$D$2 -> 3184972.2 | F26: =F18/$D$2 -> 3308248.4 | H26: N1 + Roof 1 | I26: =I18/$D$2 -> 3411586.1 | J26: =J18/$D$2 -> 3184972.2 | K26: =K18/$D$2 -> 3308248.4
C27: N1 + Roof 2 | D27: =D19/$D$2 -> 3411586.1 | E27: =E19/$D$2 -> 3184972.2 | F27: =F19/$D$2 -> 3308248.4 | H27: N1 + Roof 2 | I27: =I19/$D$2 -> 3411586.1 | J27: =J19/$D$2 -> 3184972.2 | K27: =K19/$D$2 -> 3308248.4
C28: Total Torre 1 | D28: =SUM(D24:D27) -> 12204604 | E28: =SUM(E24:E27) -> 11393916 | F28: =SUM(F24:F27) -> 11834924 | H28: Total Torre 1 | I28: =SUM(I24:I27) -> 12204604 | J28: =SUM(J24:J27) -> 11393916 | K28: =SUM(K24:K27) -> 11834924

Sheet PPTO vs PAR
B2: Partidas | D2: Total | E2: % del Total | F2: PPTO | G2: PARAMETRICO | J2: MXN/DEPTO | K2: USD/DEPTO
B3: Obra_Civil | D3: =SUMIFS(Obra_Civil!$T:$T,Obra_Civil!$B:$B,'PPTO vs PAR'!B3) -> 66000000 | E3: =IFERROR(D3/$D$36,0) -> 0.15270544 | F3: =SUMIFS(Obra_Civil!$T:$T,Obra_Civil!$V:$V,'PPTO vs PAR'!F2) -> 33000000 | G3: =SUMIFS(Obra_Civil!$T:$T,Obra_Civil!$V:$V,'PPTO vs PAR'!G2) -> 33000000 | J3: =D3/8 -> 8250000 | K3: =J3/17.5 -> 471428.57
B4: Carpinterias | D4: =SUMIFS(Carpinterias!$U:$U,Carpinterias!$B:$B,'PPTO vs PAR'!B4) -> 46223299 | E4: =IFERROR(D4/$D$36,0) -> 0.10694772 | F4: =SUMIFS(Carpinterias!$U:$U,Carpinterias!$W:$W,F$2) -> 45480899 | G4: =SUMIFS(Carpinterias!$U:$U,Carpinterias!$W:$W,G$2) -> 742400 | J4: =D4/8 -> 5777912.4 | K4: =J4/17.5 -> 330166.42
B5: Automatizacion_Control_Iluminacion | D5: =SUMIFS(Automat_Control_Ilum!$T:$T,Automat_Control_Ilum!$B:$B,'PPTO vs PAR'!B5) -> 19660848 | E5: =IFERROR(D5/$D$36,0) -> 0.045489673 | F5: =SUMIFS(Automat_Control_Ilum!$T:$T,Automat_Control_Ilum!$V:$V,F$2) -> 19660848 | G5: =SUMIFS(Automat_Control_Ilum!$T:$T,Automat_Control_Ilum!$V:$V,G$2) -> 0 | J5: =D5/8 -> 2457605.9 | K5: =J5/17.5 -> 140434.63
B6: Instalaciones_Electricas | D6: =SUMIFS(Instalaciones_Electricas!$T:$T,Instalaciones_Electricas!$B:$B,'PPTO vs PAR'!B6) -> 29733862 | E6: =IFERROR(D6/$D$36,0) -> 0.068795796 | F6: =SUMIFS(Instalaciones_Electricas!$T:$T,Instalaciones_Electricas!$V:$V,F$2) -> 0 | G6: =SUMIFS(Instalaciones_Electricas!$T:$T,Instalaciones_Electricas!$V:$V,G$2) -> 29733862 | J6: =D6/8 -> 3716732.8 | K6: =J6/17.5 -> 212384.73
B7: Vidrios_Y_Canceles | D7: =SUMIFS(Vidrios_Y_Canceles!$T:$T,Vidrios_Y_Canceles!$B:$B,'PPTO vs PAR'!B7) -> 38315914 | E7: =IFERROR(D7/$D$36,0) -> 0.08865225 | F7: =SUMIFS(Vidrios_Y_Canceles!$T:$T,Vidrios_Y_Canceles!$V:$V,F$2) -> 31270607 | G7: =SUMIFS(Vidrios_Y_Canceles!$T:$T,Vidrios_Y_Canceles!$V:$V,G$2) -> 7045306.4 | J7: =D7/8 -> 4789489.2 | K7: =J7/17.5 -> 273685.1
B8: Albercas | D8: =SUMIFS(Albercas!$T:$T,Albercas!$B:$B,'PPTO vs PAR'!B8) -> 23140260 | E8: =IFERROR(D8/$D$36,0) -> 0.053540055 | F8: =SUMIFS(Albercas!$T:$T,Albercas!$V:$V,F$2) -> 23140260 | G8: =SUMIFS(Albercas!$T:$T,Albercas!$V:$V,G$2) -> 0 | J8: =D8/8 -> 2892532.5 | K8: =J8/17.5 -> 165287.57
B9: Exteriores | D9: =SUMIFS(Exteriores!$T:$T,Exteriores!$B:$B,'PPTO vs PAR'!B9) -> 19989130 | E9: =IFERROR(D9/$D$36,0) -> 0.046249226 | F9: =SUMIFS(Exteriores!$T:$T,Exteriores!$V:$V,F$2) -> 0 | G9: =SUMIFS(Exteriores!$T:$T,Exteriores!$V:$V,G$2) -> 19989130 | J9: =D9/8 -> 2498641.2 | K9: =J9/17.5 -> 142779.5
B10: Aire_Acondicionado_Y_Extraccion | D10: =SUMIFS(Aire_Acond_Y_Extraccion!$T:$T,Aire_Acond_Y_Extraccion!$B:$B,'PPTO vs PAR'!B10) -> 15759688 | E10: =IFERROR(D10/$D$36,0) -> 0.036463487 | F10: =SUMIFS(Aire_Acond_Y_Extraccion!$T:$T,Aire_Acond_Y_Extraccion!$V:$V,F$2) -> 15759688 | G10: =SUMIFS(Aire_Acond_Y_Extraccion!$T:$T,Aire_Acond_Y_Extraccion!$V:$V,G$2) -> 0 | J10: =D10/8 -> 1969961 | K10: =J10/17.5 -> 112569.2
B11: Cocinas | D11: =SUMIFS(Cocinas!$U:$U,Cocinas!$B:$B,'PPTO vs PAR'!B11) -> 25879831 | E11: =IFERROR(D11/$D$36,0) -> 0.059878651 | F11: =SUMIFS(Cocinas!$U:$U,Cocinas!$W:$W,F$2) -> 24192991 | G11: =SUMIFS(Cocinas!$U:$U,Cocinas!$W:$W,G$2) -> 1686839.5 | J11: =D11/8 -> 3234978.9 | K11: =J11/17.5 -> 184855.93
B12: Acabados | D12: =SUMIFS(Acabados!$T:$T,Acabados!$B:$B,'PPTO vs PAR'!B12) -> 16880130 | E12: =IFERROR(D12/$D$36,0) -> 0.039055874 | F12: =SUMIFS(Acabados!$T:$T,Acabados!$V:$V,F$2) -> 0 | G12: =SUMIFS(Acabados!$T:$T,Acabados!$V:$V,G$2) -> 16880130 | J12: =D12/8 -> 2110016.2 | K12: =J12/17.5 -> 120572.36
B13: Instalaciones_Hidraulicas | D13: =SUMIFS(Instalaciones_Hidraulicas!$T:$T,Instalaciones_Hidraulicas!$B:$B,'PPTO vs PAR'!B13) -> 16725298 | E13: =IFERROR(D13/$D$36,0) -> 0.038697636 | F13: =SUMIFS(Instalaciones_Hidraulicas!$T:$T,Instalaciones_Hidraulicas!$V:$V,F$2) -> 0 | G13: =SUMIFS(Instalaciones_Hidraulicas!$T:$T,Instalaciones_Hidraulicas!$V:$V,G$2) -> 16725298 | J13: =D13/8 -> 2090662.2 | K13: =J13/17.5 -> 119466.41
B14: Colocacion de Marmol | D14: =SUMIFS(Sumin_Coloc_Marmol!$T:$T,Sumin_Coloc_Marmol!$B:$B,'PPTO vs PAR'!B14) -> 12634103 | E14: =IFERROR(D14/$D$36,0) -> 0.029231761 | F14: =SUMIFS(Sumin_Coloc_Marmol!$T:$T,Sumin_Coloc_Marmol!$B:$B,$B14,Sumin_Coloc_Marmol!$V:$V,F$2) -> 0 | G14: =SUMIFS(Sumin_Coloc_Marmol!$T:$T,Sumin_Coloc_Marmol!$B:$B,$B14,Sumin_Coloc_Marmol!$V:$V,G$2) -> 12634103 | J14: =D14/8 -> 1579262.9 | K14: =J14/17.5 -> 90243.592
B15: Condiciones Generales | D15: =SUMIFS('Condiciones Generales'!$T:$T,'Condiciones Generales'!$B:$B,'PPTO vs PAR'!B15) -> 18600593 | E15: =IFERROR(D15/$D$36,0) -> 0.043036543 | F15: =SUMIFS('Condiciones Generales'!$T:$T,'Condiciones Generales'!$V:$V,F$2) -> 5024417.4 | G15: =SUMIFS('Condiciones Generales'!$T:$T,'Condiciones Generales'!$V:$V,G$2) -> 13576176 | J15: =D15/8 -> 2325074.2 | K15: =J15/17.5 -> 132861.38
B16: Contingencias | D16: =SUMIFS(Contingencias!$T:$T,Contingencias!$B:$B,'PPTO vs PAR'!B16) -> 12000000 | E16: =IFERROR(D16/$D$36,0) -> 0.027764626 | F16: =SUMIFS(Contingencias!$T:$T,Contingencias!$V:$V,F$2) -> 0 | G16: =SUMIFS(Contingencias!$T:$T,Contingencias!$V:$V,G$2) -> 12000000 | J16: =D16/8 -> 1500000 | K16: =J16/17.5 -> 85714.286
B17: Suministro de Marmol | D17: =SUMIFS(Sumin_Coloc_Marmol!$T:$T,Sumin_Coloc_Marmol!$B:$B,'PPTO vs PAR'!B17) -> 8739576.3 | E17: =IFERROR(D17/$D$36,0) -> 0.020220922 | F17: =SUMIFS(Sumin_Coloc_Marmol!$T:$T,Sumin_Coloc_Marmol!$B:$B,$B17,Sumin_Coloc_Marmol!$V:$V,F$2) -> 0 | G17: =SUMIFS(Sumin_Coloc_Marmol!$T:$T,Sumin_Coloc_Marmol!$B:$B,$B17,Sumin_Coloc_Marmol!$V:$V,G$2) -> 8739576.3 | J17: =D17/8 -> 1092447 | K17: =J17/17.5 -> 62425.545
B18: Pilas | D18: =SUMIFS(Pilas!$T:$T,Pilas!$B:$B,'PPTO vs PAR'!B18) -> 8365678.7 | E18: =IFERROR(D18/$D$36,0) -> 0.019355828 | F18: =SUMIFS(Pilas!$T:$T,Pilas!$V:$V,F$2) -> 8365678.7 | G18: =SUMIFS(Pilas!$T:$T,Pilas!$V:$V,G$2) -> 0 | J18: =D18/8 -> 1045709.8 | K18: =J18/17.5 -> 59754.848
B19: Griferia_Y_Accesorios_De_Baño | D19: =SUMIFS(Griferia_Y_Acces_Baño!$T:$T,Griferia_Y_Acces_Baño!$B:$B,'PPTO vs PAR'!B19) -> 8061094.3 | E19: =IFERROR(D19/$D$36,0) -> 0.018651105 | F19: =SUMIFS(Griferia_Y_Acces_Baño!$T:$T,Griferia_Y_Acces_Baño!$V:$V,F$2) -> 8061094.3 | G19: =SUMIFS(Griferia_Y_Acces_Baño!$T:$T,Griferia_Y_Acces_Baño!$V:$V,G$2) -> 0 | J19: =D19/8 -> 1007636.8 | K19: =J19/17.5 -> 57579.245
B20: Jardineria_Y_Riego | D20: =SUMIFS(Jardineria_Y_Riego!$T:$T,Jardineria_Y_Riego!$B:$B,'PPTO vs PAR'!B20) -> 7400800 | E20: =IFERROR(D20/$D$36,0) -> 0.01712337 | F20: =SUMIFS(Jardineria_Y_Riego!$T:$T,Jardineria_Y_Riego!$V:$V,F$2) -> 0 | G20: =SUMIFS(Jardineria_Y_Riego!$T:$T,Jardineria_Y_Riego!$V:$V,G$2) -> 7400800 | J20: =D20/8 -> 925100 | K20: =J20/17.5 -> 52862.857
B21: Iluminacion | D21: =SUMIFS(Iluminacion!$T:$T,Iluminacion!$B:$B,'PPTO vs PAR'!B21) -> 7428736.3 | E21: =IFERROR(D21/$D$36,0) -> 0.017188007 | F21: =SUMIFS(Iluminacion!$T:$T,Iluminacion!$V:$V,F$2) -> 6210736.3 | G21: =SUMIFS(Iluminacion!$T:$T,Iluminacion!$V:$V,G$2) -> 1218000 | J21: =D21/8 -> 928592.04 | K21: =J21/17.5 -> 53062.402
B22: Preliminares | D22: =SUMIFS(Preliminares!$T:$T,Preliminares!$B:$B,'PPTO vs PAR'!B22) -> 1688616.4 | E22: =IFERROR(D22/$D$36,0) -> 0.0039069836 | F22: =SUMIFS(Preliminares!$T:$T,Preliminares!$V:$V,F$2) -> 1688616.4 | G22: =SUMIFS(Preliminares!$T:$T,Preliminares!$V:$V,G$2) -> 0 | J22: =D22/8 -> 211077.05 | K22: =J22/17.5 -> 12061.546
B23: Elevador | D23: =SUMIFS(Elevador!$T:$T,Elevador!$B:$B,'PPTO vs PAR'!B23) -> 3394998.7 | E23: =IFERROR(D23/$D$36,0) -> 0.0078550723 | F23: =SUMIFS(Elevador!$T:$T,Elevador!$V:$V,F$2) -> 0 | G23: =SUMIFS(Elevador!$T:$T,Elevador!$V:$V,G$2) -> 3394998.7 | J23: =D23/8 -> 424374.83 | K23: =J23/17.5 -> 24249.991
B24: Garden and Privacy Walls | D24: =SUMIFS('Garden and Privacy Walls'!$T:$T,'Garden and Privacy Walls'!$B:$B,'PPTO vs PAR'!B24) -> 1192410 | E24: =IFERROR(D24/$D$36,0) -> 0.0027589014 | F24: =SUMIFS('Garden and Privacy Walls'!$T:$T,'Garden and Privacy Walls'!$V:$V,F$2) -> 960409.98 | G24: =SUMIFS('Garden and Privacy Walls'!$T:$T,'Garden and Privacy Walls'!$V:$V,G$2) -> 232000 | J24: =D24/8 -> 149051.25 | K24: =J24/17.5 -> 8517.2141
B25: Herreria | D25: =SUMIFS(Herreria!$T:$T,Herreria!$B:$B,'PPTO vs PAR'!B25) -> 4640000 | E25: =IFERROR(D25/$D$36,0) -> 0.010735655 | F25: =SUMIFS(Herreria!$T:$T,Herreria!$V:$V,F$2) -> 0 | G25: =SUMIFS(Herreria!$T:$T,Herreria!$V:$V,G$2) -> 4640000 | J25: =D25/8 -> 580000 | K25: =J25/17.5 -> 33142.857
B26: Ingenierias_Y_Topografia | D26: =SUMIFS(Ingenierias_Y_Topografia!$T:$T,Ingenierias_Y_Topografia!$B:$B,'PPTO vs PAR'!B26) -> 2229156.1 | E26: =IFERROR(D26/$D$36,0) -> 0.0051576404 | F26: =SUMIFS(Ingenierias_Y_Topografia!$T:$T,Ingenierias_Y_Topografia!$V:$V,F$2) -> 2229156.1 | G26: =SUMIFS(Ingenierias_Y_Topografia!$T:$T,Ingenierias_Y_Topografia!$V:$V,G$2) -> 0 | J26: =D26/8 -> 278644.51 | K26: =J26/17.5 -> 15922.544
B27: Instalaciones_Gas | D27: =SUMIFS(Instalaciones_Gas!$T:$T,Instalaciones_Gas!$B:$B,'PPTO vs PAR'!B27) -> 1856000 | E27: =IFERROR(D27/$D$36,0) -> 0.0042942621 | F27: =SUMIFS(Instalaciones_Gas!$T:$T,Instalaciones_Gas!$V:$V,F$2) -> 0 | G27: =SUMIFS(Instalaciones_Gas!$T:$T,Instalaciones_Gas!$V:$V,G$2) -> 1856000 | J27: =D27/8 -> 232000 | K27: =J27/17.5 -> 13257.143
B28: Impermeabilizacion | D28: =SUMIFS(Impermeabilizacion!$T:$T,Impermeabilizacion!$B:$B,'PPTO vs PAR'!B28) -> 2788215.6 | E28: =IFERROR(D28/$D$36,0) -> 0.0064511468 | F28: =SUMIFS(Impermeabilizacion!$T:$T,Impermeabilizacion!$V:$V,F$2) -> 0 | G28: =SUMIFS(Impermeabilizacion!$T:$T,Impermeabilizacion!$V:$V,G$2) -> 2788215.6 | J28: =D28/8 -> 348526.95 | K28: =J28/17.5 -> 19915.826
B29: Infraestructura | D29: =SUMIFS(Infraestructura!$T:$T,Infraestructura!$B:$B,'PPTO vs PAR'!B29) -> 812000 | E29: =IFERROR(D29/$D$36,0) -> 0.0018787397 | F29: =SUMIFS(Infraestructura!$T:$T,Infraestructura!$V:$V,F$2) -> 0 | G29: =SUMIFS(Infraestructura!$T:$T,Infraestructura!$V:$V,G$2) -> 812000 | J29: =D29/8 -> 101500 | K29: =J29/17.5 -> 5800
B30: Otros | D30: =SUMIFS(Otros!$T:$T,Otros!$B:$B,'PPTO vs PAR'!B30) -> 2640000 | E30: =IFERROR(D30/$D$36,0) -> 0.0061082176 | F30: =SUMIFS(Otros!$T:$T,Otros!$V:$V,F$2) -> 0 | G30: =SUMIFS(Otros!$T:$T,Otros!$V:$V,G$2) -> 2640000 | J30: =D30/8 -> 330000 | K30: =J30/17.5 -> 18857.143
B31: Arquitectura | D31: =SUMIFS(Arquitectura!$T:$T,Arquitectura!$B:$B,'PPTO vs PAR'!B31) -> 2929400 | E31: =IFERROR(D31/$D$36,0) -> 0.0067778079 | F31: =SUMIFS(Arquitectura!$T:$T,Arquitectura!$V:$V,F$2) -> 2929400 | G31: =SUMIFS(Arquitectura!$T:$T,Arquitectura!$V:$V,G$2) -> 0 | J31: =D31/8 -> 366175 | K31: =J31/17.5 -> 20924.286
B32: Excavacion | D32: =SUMIFS(Excavacion!$T:$T,Excavacion!$B:$B,'PPTO vs PAR'!B32) -> 0 | E32: =IFERROR(D32/$D$36,0) -> 0 | F32: =SUMIFS(Excavacion!$T:$T,Excavacion!$V:$V,F$2) -> 0 | G32: =SUMIFS(Excavacion!$T:$T,Excavacion!$V:$V,G$2) -> 0 | J32: =D32/8 -> 0 | K32: =J32/17.5 -> 0
B33: Albañilerias | D33: =SUMIFS('Albañilerias '!$T:$T,'Albañilerias '!$B:$B,'PPTO vs PAR'!B33) -> 6495001.8 | E33: =IFERROR(D33/$D$36,0) -> 0.015027608 | F33: =SUMIFS('Albañilerias '!$T:$T,'Albañilerias '!$V:$V,F$2) -> 3247500.9 | G33: =SUMIFS('Albañilerias '!$T:$T,'Albañilerias '!$V:$V,G$2) -> 3247500.9
B34: Madera_De_Ingenieria | D34: =SUMIFS(Madera_De_Ingenieria!$T:$T,Madera_De_Ingenieria!$B:$B,'PPTO vs PAR'!B34) -> 0 | E34: =IFERROR(D34/$D$36,0) -> 0 | F34: =SUMIFS(Madera_De_Ingenieria!$T$2:$T$61,Madera_De_Ingenieria!$V$2:$V$61,F$2) -> 0 | G34: =SUMIFS(Madera_De_Ingenieria!$T$2:$T$61,Madera_De_Ingenieria!$V$2:$V$61,G$2) -> 0
B36: Total | D36: =SUM(D3:D34) -> 4.3220464e+08 | F36: =SUM(F3:F34) -> 2.312223e+08 | G36: =SUM(G3:G34) -> 2.0098234e+08
D37: =D36-'BUY OUT'!I172 -> 12067000 | F37: =F36/D36 -> 0.53498339 | G37: =G36/D36 -> 0.46501661

Sheet BF vs Golf
B2: Partidas | D2: Total | E2: m2 | F2: $/m2 | H2: GOLF VILLAS | I2: M2 | J2: $/m2
B3: Obra_Civil | D3: =SUMIFS(Obra_Civil!$T:$T,Obra_Civil!$B:$B,'BF vs Golf'!B3) -> 66000000 | E3: 3970 | F3: =IFERROR(D3/E3,0) -> 16624.685 | H3: 6200000 | I3: 633 | J3: =IFERROR(H3/I3,0) -> 9794.6288
B4: Carpinterias | D4: =SUMIFS(Carpinterias!$U:$U,Carpinterias!$B:$B,'BF vs Golf'!B4) -> 46223299 | E4: 3970 | F4: =IFERROR(D4/E4,0) -> 11643.148 | H4: 3298000 | I4: 255 | J4: =IFERROR(H4/I4,0) -> 12933.333
B5: Automatizacion_Control_Iluminacion | D5: =SUMIFS(Automat_Control_Ilum!$T:$T,Automat_Control_Ilum!$B:$B,'BF vs Golf'!B5) -> 19660848 | E5: 5996 | F5: =IFERROR(D5/E5,0) -> 3278.9939 | H5: 585000 | I5: 255 | J5: =IFERROR(H5/I5,0) -> 2294.1176
B6: Instalaciones_Electricas | D6: =SUMIFS(Instalaciones_Electricas!$T:$T,Instalaciones_Electricas!$B:$B,'BF vs Golf'!B6) -> 29733862 | E6: 3970 | F6: =IFERROR(D6/E6,0) -> 7489.6379 | H6: 1718000 | I6: 633 | J6: =IFERROR(H6/I6,0) -> 2714.06
B7: Suministro de Marmol | D7: =SUMIFS(Sumin_Coloc_Marmol!$T:$T,Sumin_Coloc_Marmol!$B:$B,'BF vs Golf'!B7) -> 8739576.3 | E7: 3970 | F7: =IFERROR(D7/E7,0) -> 2201.4046 | H7: 625000 | I7: 633 | J7: =IFERROR(H7/I7,0) -> 987.36177
B8: Colocacion de Marmol | D8: =SUMIFS(Sumin_Coloc_Marmol!$T:$T,Sumin_Coloc_Marmol!$B:$B,'BF vs Golf'!B8) -> 12634103 | E8: 3970 | F8: =IFERROR(D8/E8,0) -> 3182.3937
B9: Albercas | D9: =SUMIFS(Albercas!$T:$T,Albercas!$B:$B,'BF vs Golf'!B9) -> 23140260 | E9: 286 | F9: =IFERROR(D9/E9,0) -> 80910 | H9: 2325000 | I9: 45 | J9: =IFERROR(H9/I9,0) -> 51666.667
B10: Vidrios_Y_Canceles | D10: =SUMIFS(Vidrios_Y_Canceles!$T:$T,Vidrios_Y_Canceles!$B:$B,'BF vs Golf'!B10) -> 38315914 | E10: 3970 | F10: =IFERROR(D10/E10,0) -> 9651.3636 | H10: 2690000 | I10: 633 | J10: =IFERROR(H10/I10,0) -> 4249.6051
B11: Exteriores | D11: =SUMIFS(Exteriores!$T:$T,Exteriores!$B:$B,'BF vs Golf'!B11) -> 19989130 | E11: 3970 | F11: =IFERROR(D11/E11,0) -> 5035.0453 | H11: En infraestructura | I11: =+I9 -> 45 | J11: =IFERROR(H11/I11,0) -> 0
B12: Aire_Acondicionado_Y_Extraccion | D12: =SUMIFS(Aire_Acond_Y_Extraccion!$T:$T,Aire_Acond_Y_Extraccion!$B:$B,'BF vs Golf'!B12) -> 15759688 | E12: 2998 | F12: =IFERROR(D12/E12,0) -> 5256.7339 | H12: 1589000 | I12: 255 | J12: =IFERROR(H12/I12,0) -> 6231.3725
B13: Cocinas | D13: =SUMIFS(Cocinas!$U:$U,Cocinas!$B:$B,'BF vs Golf'!B13) -> 25879831 | E13: 2998 | F13: =IFERROR(D13/E13,0) -> 8632.3652 | H13: 1370000 | I13: 255 | J13: =IFERROR(H13/I13,0) -> 5372.549
B14: Instalaciones_Hidraulicas | D14: =SUMIFS(Instalaciones_Hidraulicas!$T:$T,Instalaciones_Hidraulicas!$B:$B,'BF vs Golf'!B14) -> 16725298 | E14: 3970 | F14: =IFERROR(D14/E14,0) -> 4212.9213 | H14: 972000 | I14: 633 | J14: =IFERROR(H14/I14,0) -> 1535.545
B15: Condiciones Generales | D15: =SUMIFS('Condiciones Generales'!$T:$T,'Condiciones Generales'!$B:$B,'BF vs Golf'!B15) -> 18600593 | E15: 3970 | F15: =IFERROR(D15/E15,0) -> 4685.288
B16: Contingencias | D16: =SUMIFS(Contingencias!$T:$T,Contingencias!$B:$B,'BF vs Golf'!B16) -> 12000000 | E16: 3970 | F16: =IFERROR(D16/E16,0) -> 3022.67
B17: Pilas | D17: =SUMIFS(Pilas!$T:$T,Pilas!$B:$B,'BF vs Golf'!B17) -> 8365678.7 | E17: 2998 | F17: =IFERROR(D17/E17,0) -> 2790.4198 | H17: N/A | I17: 255 | J17: =IFERROR(H17/I17,0) -> 0
B18: Griferia_Y_Accesorios_De_Baño | D18: =SUMIFS(Griferia_Y_Acces_Baño!$T:$T,Griferia_Y_Acces_Baño!$B:$B,'BF vs Golf'!B18) -> 8061094.3 | E18: 2998 | F18: =IFERROR(D18/E18,0) -> 2688.824 | H18: 557000 | I18: 255 | J18: =IFERROR(H18/I18,0) -> 2184.3137
B19: Jardineria_Y_Riego | D19: =SUMIFS(Jardineria_Y_Riego!$T:$T,Jardineria_Y_Riego!$B:$B,'BF vs Golf'!B19) -> 7400800 | E19: 2998 | F19: =IFERROR(D19/E19,0) -> 2468.5791 | H19: En infraestructura | I19: 255 | J19: =IFERROR(H19/I19,0) -> 0
B20: Iluminacion | D20: =SUMIFS(Iluminacion!$T:$T,Iluminacion!$B:$B,'BF vs Golf'!B20) -> 7428736.3 | E20: 3970 | F20: =IFERROR(D20/E20,0) -> 1871.2182 | H20: 321000 | I20: 633 | J20: =IFERROR(H20/I20,0) -> 507.109
B21: Preliminares | D21: =SUMIFS(Preliminares!$T:$T,Preliminares!$B:$B,'BF vs Golf'!B21) -> 1688616.4 | E21: 2998 | F21: =IFERROR(D21/E21,0) -> 563.24764 | H21: En obra civil | I21: 255 | J21: =IFERROR(H21/I21,0) -> 0
B22: Elevador | D22: =SUMIFS(Elevador!$T:$T,Elevador!$B:$B,'BF vs Golf'!B22) -> 3394998.7 | E22: 2998 | F22: =IFERROR(D22/E22,0) -> 1132.4212 | H22: N/A | I22: 255 | J22: =IFERROR(H22/I22,0) -> 0
B23: Garden and Privacy Walls | D23: =SUMIFS('Garden and Privacy Walls'!$T:$T,'Garden and Privacy Walls'!$B:$B,'BF vs Golf'!B23) -> 1192410 | E23: 2998 | F23: =IFERROR(D23/E23,0) -> 397.73515 | H23: N/A | I23: 255 | J23: =IFERROR(H23/I23,0) -> 0
B24: Herreria | D24: =SUMIFS(Herreria!$T:$T,Herreria!$B:$B,'BF vs Golf'!B24) -> 4640000 | E24: 3970 | F24: =IFERROR(D24/E24,0) -> 1168.7657 | H24: 780000 | I24: 633 | J24: =IFERROR(H24/I24,0) -> 1232.2275
B25: Ingenierias_Y_Topografia | D25: =SUMIFS(Ingenierias_Y_Topografia!$T:$T,Ingenierias_Y_Topografia!$B:$B,'BF vs Golf'!B25) -> 2229156.1 | E25: 3970 | F25: =IFERROR(D25/E25,0) -> 561.50028 | H25: 538000 | I25: =+I20 -> 633 | J25: =IFERROR(H25/I25,0) -> 849.92101
B26: Instalaciones_Gas | D26: =SUMIFS(Instalaciones_Gas!$T:$T,Instalaciones_Gas!$B:$B,'BF vs Golf'!B26) -> 1856000 | E26: 3970 | F26: =IFERROR(D26/E26,0) -> 467.5063 | H26: 173000 | I26: =+I20 -> 633 | J26: =IFERROR(H26/I26,0) -> 273.30174
B27: Impermeabilizacion | D27: =SUMIFS(Impermeabilizacion!$T:$T,Impermeabilizacion!$B:$B,'BF vs Golf'!B27) -> 0 | E27: 2998 | F27: =IFERROR(D27/E27,0) -> 0 | H27: En acabados | I27: 255 | J27: =IFERROR(H27/I27,0) -> 0
B28: Infraestructura | D28: =SUMIFS(Infraestructura!$T:$T,Infraestructura!$B:$B,'BF vs Golf'!B28) -> 812000 | E28: 3970 | F28: =IFERROR(D28/E28,0) -> 204.53401 | H28: 7012509.3 | I28: 633 | J28: =IFERROR(H28/I28,0) -> 11078.214
B29: Otros | D29: =SUMIFS(Otros!$T:$T,Otros!$B:$B,'BF vs Golf'!B29) -> 2640000 | E29: 3970 | F29: =IFERROR(D29/E29,0) -> 664.98741
B30: Arquitectura | D30: =SUMIFS(Arquitectura!$T:$T,Arquitectura!$B:$B,'BF vs Golf'!B30) -> 2929400 | E30: 0 | F30: =IFERROR(D30/E30,0) -> 0 | I30: 255 | J30: =IFERROR(H30/I30,0) -> 0
B31: Excavacion | D31: =SUMIFS(Excavacion!$T:$T,Excavacion!$B:$B,'BF vs Golf'!B31) -> 0 | E31: 0 | F31: =IFERROR(D31/E31,0) -> 0 | H31: En obra civil | I31: 0 | J31: =IFERROR(H31/I31,0) -> 0
B32: Albañileria_Y_Bardas | D32: =SUMIFS(#REF!,#REF!,'BF vs Golf'!B32) -> #REF! | E32: 0 | F32: =IFERROR(D32/E32,0) -> 0 | H32: En obra civil | I32: 0 | J32: =IFERROR(H32/I32,0) -> 0
B33: Acabados | D33: =SUMIFS(Acabados!$T:$T,Acabados!$B:$B,'BF vs Golf'!B33) -> 16880130 | E33: 0 | F33: =IFERROR(D33/E33,0) -> 0 | H33: 5095000 | I33: 633 | J33: =IFERROR(H33/I33,0) -> 8048.9731
B34: Madera_De_Ingenieria | D34: =SUMIFS(Madera_De_Ingenieria!$T:$T,Madera_De_Ingenieria!$B:$B,'BF vs Golf'!B34) -> 0 | E34: 0 | F34: =IFERROR(D34/E34,0) -> 0 | H34: N/A | I34: 255 | J34: =IFERROR(H34/I34,0) -> 0
B36: Total | H36: =38000000/255 -> 149019.61

Sheet Glosario Deptos
A1: GLOSARIO DE DEPARTAMENTOS
A3: TORRE | B3: TIPO | C3: PISO(S) | D3: DEPTO | E3: DEPTO (ID ACABADOS) | F3: 5TA RECÁMARA
A4: TORRE 1 | B4: PB | C4: PB | D4: 101 | E4: 101 | F4: NO | G4: 62
A5: TORRE 1 | B5: PB | C5: PB | D5: 201 | E5: 201 | F5: NO | G5: 62
A6: TORRE 1 | B6: Dúplex (N1+N1R) | C6: N1 + N1R | D6: 102 / 103 | E6: 102 (N1) + 103 (N1R) | F6: NO | G6: 72
A7: TORRE 1 | B7: Dúplex (N1+N1R) | C7: N1 + N1R | D7: 202 / 203 | E7: 202 (N1) + 203 (N1R) | F7: NO | G7: 72
A8: TORRE 2 | B8: PB | C8: PB | D8: 301 | E8: 301 | F8: NO | G8: 62
A9: TORRE 2 | B9: PB | C9: PB | D9: 401 | E9: 401 | F9: SÍ | G9: 74
A10: TORRE 2 | B10: Dúplex (N1+N1R) | C10: N1 + N1R | D10: 302 / 303 | E10: 302 (N1) + 303 (N1R) | F10: NO | G10: 72
A11: TORRE 2 | B11: Dúplex (N1+N1R) | C11: N1 + N1R | D11: 402 / 403 | E11: 402 (N1) + 403 (N1R) | F11: SÍ | G11: 82
A13: NOTAS:
A14: • 2 Torres, 4 departamentos por torre (2 PB + 2 Dúplex N1+N1R) = 8 departamentos únicos en total
A15: • Los pisos N1 y N1R corresponden al mismo departamento dúplex (planta baja y planta alta del dúplex)
A16: • En Torre 2, los deptos 401 (PB) y 402/403 (Dúplex) cuentan con quinta recámara
A17: • En Acabados, los deptos dúplex aparecen con IDs separados por piso (ej: 102 en N1 y 103 en N1R)

Sheet Prompt
B10: PROMPT: Consolidar sección en BUY OUT
B12: Consolida la sección [NOMBRE DE SECCIÓN] en la hoja "BUY OUT" en una sola línea de datos, siguiendo este proceso exacto:
B14: Estructura final deseada (4 filas):
B16: Sub-header — fila azul claro (#D9E2F3) con el nombre en mayúsculas, bold
B17: Línea de datos — fondo blanco, una sola fila con:
B18: Col B: Nombre de la categoría (debe coincidir con col B del tab fuente)
B19: Col R: =valorHistorico/2*2 (azul #0000FF) — valor original de PRESUPUESTO BASE sumado de todas las filas de detalle, dividido entre 2 y multiplicado por 2
B20: Col S: =valorHistorico/2*2 (azul #0000FF) — valor original de PPTO MARZO sumado de todas las filas de detalle, dividido entre 2 y multiplicado por 2
B21: Col T: =SUMIFS(TabFuente!$T:$T,TabFuente!$B:$B,$B[fila]&"*") (verde #008000) — SUMIFS dinámico que referencia la celda B en lugar de texto hardcodeado. Usar &"*" wildcard por si hay espacios trailing en el tab fuente
B22: Cols U,V,W,X: Fórmulas derivadas estándar: =IFERROR(T/R-1,0), =S/UNITARIO!$D$9, =R/$D$2, =S/$D$2
B23: SUBTOTAL — fila verde (#E2EFDA), bold, con =SUM() de la fila de datos. Schedule cols (Z
B24: ) también en verde
... B37: Caso especial — dividir en 2 categorías (como Mármol): Si se necesitan 2 líneas (ej: Suministro vs Colocación), para R y S usar la proporción del actual: =totalHistórico * IFERROR(SUMIFS(tab!$T:$T,tab!$B:$B,$B[fila]&"*") / SUM(tab!$T$2:$T$[últimaFilaDatos]),0)⚠️ En el denominador usar rango acotado $T$2:$T$n para excluir la fila "Total" del tab fuente.

Sheet PPT
B3: TORRE 1
B5: RESUMEN | C5: M2 | D5: USD/M2 | E5: USD | G5: USD = 17.5 MXN
B6: M2 PB DEPTO 1 | C6: =SUM($C$17:$C$18) -> 429.44 | D6: =$D$14 -> 485.91924 | E6: =C6*D6 -> 208673.16
B7: M2 PB DEPTO 2 | C7: =SUM($C$17:$C$18) -> 429.44 | D7: =$D$14 -> 485.91924 | E7: =C7*D7 -> 208673.16
B8: M2 N1 + Roof DEPTO 1 | C8: =SUM($D$17:$D$18) -> 563.09 | D8: =$D$14 -> 485.91924 | E8: =C8*D8 -> 273616.26
B9: M2 N1 + Roof DEPTO 2 | C9: =SUM($D$17:$D$18) -> 563.09 | D9: =$D$14 -> 485.91924 | E9: =C9*D9 -> 273616.26
B10: Total Torre 1 | C10: =SUM(C6:C9) -> 1985.06 | D10: =AVERAGE(D6:D9) -> 485.91924 | E10: =SUM(E6:E9) -> 964578.84
B12: COSTO | C12: MXN | D12: USD
B13: Costo Total MXN | C13: ='PPTO vs PAR'!D12 -> 16880130 | D13: =C13/'Glosario Partidas'!$M$9 -> 964578.84
B14: Costo Total M2 | C14: =C13/C10 -> 8503.5867 | D14: =C14/'Glosario Partidas'!$M$9 -> 485.91924
B16: AREAS | C16: PB | D16: N1 y Roof
B17: Area Interior Acondicionado | C17: 322.72 | D17: 409.18
B18: Area Exterior Techada | C18: 106.72 | D18: 153.91
B19: Area Exterior Pavimentada sin Techar | C19: 204.37 | D19: 258.65
B20: Total | C20: =SUM(C17:C19) -> 633.81 | D20: =SUM(D17:D19) -> 821.74
B22: USD M2 | C22: PB | D22: N1 y Roof
B23: Area Interior Acondicionado | C23: =C17*$D$14 -> 156815.86 | D23: =D17*$D$14 -> 198828.43
B24: Area Exterior Techada | C24: =C18*$D$14 -> 51857.301 | D24: =D18*$D$14 -> 74787.83
B25: Area Exterior Pavimentada sin Techar | C25: =C19*$D$14 -> 99307.315 | D25: =D19*$D$14 -> 125683.01
B26: Total | C26: =SUM(C23:C25) -> 307980.47 | D26: =SUM(D23:D25) -> 399299.27
B30: DEPTO | C30: Area Int. Acon. | D30: Area Ext. Techada | E30: Area Exterior Pav. sin Techar | F30: Total m2
B31: PB 1 | C31: 322.72 | D31: 106.72 | E31: 204.37 | F31: 633.81
B32: PB 2 | C32: 322.72 | D32: 106.72 | E32: 204.37 | F32: 633.81
B33: N1 + Roof 1 | C33: 409.18 | D33: 153.91 | E33: 258.65 | F33: 821.74
B34: N1 + Roof 2 | C34: 409.18 | D34: 153.91 | E34: 258.65 | F34: 821.74
B35: Total Torre 1 | C35: 1463.8 | D35: 521.26 | E35: 926.04 | F35: 2911.1
B38: AREA | C38: M2 Totales | D38: Costo Total | E38: USD/M2
B39: Area Int. Acon. | C39: =C35 -> 1463.8 | D39: =$D$13 -> 964578.84 | E39: =D39/C39 -> 658.95535
B40: Area Int. Acon. + Area Ext. Techada | C40: =C35+D35 -> 1985.06 | D40: =$D$13 -> 964578.84 | E40: =D40/C40 -> 485.91924
B41: Area Total | C41: =C40+E35 -> 2911.1 | D41: =$D$13 -> 964578.84 | E41: =D41/C41 -> 331.34514
B45: Comparativa
B47: AREA | C47: Beach Front | D47: Lote 3 | E47: Golf Villas
B48: Area Int. Acon. | C48: =C39 -> 1463.8 | D48: 1225 | E48: 328.06
B49: Area Int. Acon. + Area Ext. Techada | C49: =C40 -> 1985.06 | D49: 1457 | E49: 509.27
B50: Costo Total | C50: =D13 -> 964578.84 | D50: =122259740.143488/19 -> 6434723.2 | E50: =38000000/19 -> 2000000
B52: USD/M2 | C52: Beach Front | D52: Lote 3 | E52: Golf Villas
B53: Area Int. Acon. | C53: =C$50/C48 -> 658.95535 | D53: =D$50/D48 -> 5252.8352 | E53: =E$50/E48 -> 6096.4458
B54: Area Int. Acon. + Area Ext. Techada | C54: =C$50/C49 -> 485.91924 | D54: =D$50/D49 -> 4416.4195 | E54: =E$50/E49 -> 3927.1899
H55: 17.5
B56: Partidas | C56: Beach Front | D56: Lote 3 | E56: Golf Villas | G56: Partidas | H56: Beach Front | I56: Lote 3 | J56: Golf Villas | L56: Partidas | M56: Beach Front | N56: Lote 3 | O56: Golf Villas
B57: Obra_Civil | C57: =SUMIFS(BD!$T:$T,BD!$B:$B,PPT!B57) -> 32427043 | D57: 38300000 | E57: 8097846.3 | G57: Obra_Civil | H57: =C57/$H$55 -> 1852973.9 | I57: =D57/$H$55 -> 2188571.4 | J57: =E57/$H$55 -> 462734.08 | L57: Obra_Civil | M57: =C57/C$49 -> 16335.548 | N57: =D57/D$49 -> 26286.891 | O57: =E57/E$49 -> 15900.89
B58: Carpinterias | C58: =SUMIFS(BD!$T:$T,BD!$B:$B,PPT!B58) -> 26840470 | D58: 12893254 | E58: 5272477.5 | G58: Carpinterias | H58: =C58/$H$55 -> 1533741.1 | I58: =D58/$H$55 -> 736757.39 | J58: =E58/$H$55 -> 301284.43 | L58: Carpinterias | M58: =C58/C$49 -> 13521.239 | N58: =D58/D$49 -> 8849.1793 | O58: =E58/E$49 -> 10353.01
B59: Albercas | C59: =SUMIFS(BD!$T:$T,BD!$B:$B,PPT!B59) -> 15620096 | D59: 5125627 | E59: 2845876.3 | G59: Albercas | H59: =C59/$H$55 -> 892576.91 | I59: =D59/$H$55 -> 292892.97 | J59: =E59/$H$55 -> 162621.5 | L59: Albercas | M59: =C59/C$49 -> 7868.8281 | N59: =D59/D$49 -> 3517.9321 | O59: =E59/E$49 -> 5588.1483
B60: Cocinas | C60: =SUMIFS(BD!$T:$T,BD!$B:$B,PPT!B60) -> 14734674 | D60: 6390795 | E60: 3585802.1 | G60: Cocinas | H60: =C60/$H$55 -> 841981.36 | I60: =D60/$H$55 -> 365188.29 | J60: =E60/$H$55 -> 204902.98 | L60: Cocinas | M60: =C60/C$49 -> 7422.7851 | N60: =D60/D$49 -> 4386.2697 | O60: =E60/E$49 -> 7041.063
B61: Suministro_Y_Colocacion_De_Marmol | C61: =SUMIFS(BD!$T:$T,BD!$B:$B,PPT!B61) -> 11832617 | D61: 3710217.8 | E61: 1876043.6 | G61: Suministro_Y_Colocacion_De_Marmol | H61: =C61/$H$55 -> 676149.55 | I61: =D61/$H$55 -> 212012.44 | J61: =E61/$H$55 -> 107202.49 | L61: Suministro_Y_Colocacion_De_Marmol | M61: =C61/C$49 -> 5960.836 | N61: =D61/D$49 -> 2546.4775 | O61: =E61/E$49 -> 3683.7898
B62: Indirectos_De_Obra | C62: =SUMIFS(BD!$T:$T,BD!$B:$B,PPT!B62) -> 11555951 | D62: 3608000 | E62: 2082200 | G62: Indirectos_De_Obra | H62: =C62/$H$55 -> 660340.05 | I62: =D62/$H$55 -> 206171.43 | J62: =E62/$H$55 -> 118982.86 | L62: Indirectos_De_Obra | M62: =C62/C$49 -> 5821.4617 | N62: =D62/D$49 -> 2476.3212 | O62: =E62/E$49 -> 4088.5974
B63: Vidrios_Y_Canceles | C63: =SUMIFS(BD!$T:$T,BD!$B:$B,PPT!B63) -> 11735091 | D63: 9688739.9 | E63: 2605041 | G63: Vidrios_Y_Canceles | H63: =C63/$H$55 -> 670576.64 | I63: =D63/$H$55 -> 553642.28 | J63: =E63/$H$55 -> 148859.49 | L63: Vidrios_Y_Canceles | M63: =C63/C$49 -> 5911.7061 | N63: =D63/D$49 -> 6649.7872 | O63: =E63/E$49 -> 5115.2454
B64: Automatizacion_Control_Iluminacion | C64: =SUMIFS(BD!$T:$T,BD!$B:$B,PPT!B64) -> 10438960 | D64: 5359006.8 | E64: 2427819.5 | G64: Automatizacion_Control_Iluminacion | H64: =C64/$H$55 -> 596512.02 | I64: =D64/$H$55 -> 306228.96 | J64: =E64/$H$55 -> 138732.54 | L64: Automatizacion_Control_Iluminacion | M64: =C64/C$49 -> 5258.7631 | N64: =D64/D$49 -> 3678.1103 | O64: =E64/E$49 -> 4767.2541
B65: Aire_Acondicionado_Y_Extraccion | C65: =SUMIFS(BD!$T:$T,BD!$B:$B,PPT!B65) -> 8734322.1 | D65: 5497575.1 | E65: 2050247.5 | G65: Aire_Acondicionado_Y_Extraccion | H65: =C65/$H$55 -> 499104.12 | I65: =D65/$H$55 -> 314147.15 | J65: =E65/$H$55 -> 117157 | L65: Aire_Acondicionado_Y_Extraccion | M65: =C65/C$49 -> 4400.0293 | N65: =D65/D$49 -> 3773.2156 | O65: =E65/E$49 -> 4025.8556
B66: Instalaciones_Hidraulicas | C66: =SUMIFS(BD!$T:$T,BD!$B:$B,PPT!B66) -> 8362648.8 | D66: 6874023.8 | E66: 1168443.1 | G66: Instalaciones_Hidraulicas | H66: =C66/$H$55 -> 477865.65 | I66: =D66/$H$55 -> 392801.36 | J66: =E66/$H$55 -> 66768.175 | L66: Instalaciones_Hidraulicas | M66: =C66/C$49 -> 4212.794 | N66: =D66/D$49 -> 4717.9298 | O66: =E66/E$49 -> 2294.3489
B67: Instalaciones_Electricas | C67: =SUMIFS(BD!$T:$T,BD!$B:$B,PPT!B67) -> 8362648.8 | D67: 6399093 | E67: 0 | G67: Instalaciones_Electricas | H67: =C67/$H$55 -> 477865.65 | I67: =D67/$H$55 -> 365662.46 | J67: =E67/$H$55 -> 0 | L67: Instalaciones_Electricas | M67: =C67/C$49 -> 4212.794 | N67: =D67/D$49 -> 4391.965
B68: Griferia_Y_Accesorios_De_Baño | C68: =SUMIFS(BD!$T:$T,BD!$B:$B,PPT!B68) -> 3636236.3 | D68: 1719206.6 | E68: 628695.41 | G68: Griferia_Y_Accesorios_De_Baño | H68: =C68/$H$55 -> 207784.93 | I68: =D68/$H$55 -> 98240.377 | J68: =E68/$H$55 -> 35925.452 | L68: Griferia_Y_Accesorios_De_Baño | M68: =C68/C$49 -> 1831.8017 | N68: =D68/D$49 -> 1179.9634 | O68: =E68/E$49 -> 1234.5031
B69: Madera_De_Ingenieria | C69: =SUMIFS(BD!$T:$T,BD!$B:$B,PPT!B69) -> 2952821.8 | D69: 3803911.2 | E69: 2335705.2 | G69: Madera_De_Ingenieria | H69: =C69/$H$55 -> 168732.67 | I69: =D69/$H$55 -> 217366.35 | J69: =E69/$H$55 -> 133468.87 | L69: Madera_De_Ingenieria | M69: =C69/C$49 -> 1487.5227 | N69: =D69/D$49 -> 2610.7832 | O69: =E69/E$49 -> 4586.379
B70: Iluminacion | C70: =SUMIFS(BD!$T:$T,BD!$B:$B,PPT!B70) -> 2501479.7 | D70: 2777040 | E70: 742400 | G70: Iluminacion | H70: =C70/$H$55 -> 142941.7 | I70: =D70/$H$55 -> 158688 | J70: =E70/$H$55 -> 42422.857 | L70: Iluminacion | M70: =C70/C$49 -> 1260.1532 | N70: =D70/D$49 -> 1905.9986 | O70: =E70/E$49 -> 1457.7729
B71: Impermeabilizacion | C71: =SUMIFS(BD!$T:$T,BD!$B:$B,PPT!B71) -> 1848728.9 | D71: 887818.18 | E71: 864339.23 | G71: Impermeabilizacion | H71: =C71/$H$55 -> 105641.65 | I71: =D71/$H$55 -> 50732.467 | J71: =E71/$H$55 -> 49390.813 | L71: Impermeabilizacion | M71: =C71/C$49 -> 931.32143 | N71: =D71/D$49 -> 609.34673 | O71: =E71/E$49 -> 1697.2121
B72: Elevador | C72: =SUMIFS(BD!$T:$T,BD!$B:$B,PPT!B72) -> 900000 | D72: 0 | E72: 0 | G72: Elevador | H72: =C72/$H$55 -> 51428.571 | I72: =D72/$H$55 -> 0 | J72: =E72/$H$55 -> 0 | L72: Elevador | M72: =C72/C$49 -> 453.3868
B73: Instalaciones_Gas | C73: =SUMIFS(BD!$T:$T,BD!$B:$B,PPT!B73) -> 928000 | D73: 536878.16 | E73: 199523.78 | G73: Instalaciones_Gas | H73: =C73/$H$55 -> 53028.571 | I73: =D73/$H$55 -> 30678.752 | J73: =E73/$H$55 -> 11401.359 | L73: Instalaciones_Gas | M73: =C73/C$49 -> 467.49217 | N73: =D73/D$49 -> 368.48192 | O73: =E73/E$49 -> 391.78389
B74: Ingenierias_Y_Topografia | C74: =SUMIFS(BD!$T:$T,BD!$B:$B,PPT!B74) -> 441385 | D74: 0 | E74: 0 | G74: Ingenierias_Y_Topografia | H74: =C74/$H$55 -> 25222 | I74: =D74/$H$55 -> 0 | J74: =E74/$H$55 -> 0 | L74: Ingenierias_Y_Topografia | M74: =C74/C$49 -> 222.35348 | N74: =D74/D$49 -> 0 | O74: =E74/E$49 -> 0
B75: Excavacion | C75: =SUMIFS(BD!$T:$T,BD!$B:$B,PPT!B75) -> 232000 | D75: 0 | E75: 0 | G75: Excavacion | H75: =C75/$H$55 -> 13257.143 | I75: =D75/$H$55 -> 0 | J75: =E75/$H$55 -> 0 | L75: Excavacion | M75: =C75/C$49 -> 116.87304 | N75: =D75/D$49 -> 0 | O75: =E75/E$49 -> 0
B76: Exteriores | C76: =SUMIFS(BD!$T:$T,BD!$B:$B,PPT!B76) -> 9373352.9 | D76: 0 | E76: 0 | G76: Exteriores | H76: =C76/$H$55 -> 535620.17 | I76: =D76/$H$55 -> 0 | J76: =E76/$H$55 -> 0 | L76: Exteriores | M76: =C76/C$49 -> 4721.9494 | N76: =D76/D$49 -> 0 | O76: =E76/E$49 -> 0
B77: Albañileria_Y_Bardas | C77: =SUMIFS(BD!$T:$T,BD!$B:$B,PPT!B77) -> 0 | D77: 2865375.9 | E77: 0 | G77: Albañileria_Y_Bardas | H77: =C77/$H$55 -> 0 | I77: =D77/$H$55 -> 163735.77 | J77: =E77/$H$55 -> 0 | L77: Albañileria_Y_Bardas | M77: =C77/C$49 -> 0 | N77: =D77/D$49 -> 1966.6273 | O77: =E77/E$49 -> 0
B78: Arquitectura | C78: =SUMIFS(BD!$T:$T,BD!$B:$B,PPT!B78) -> 0 | D78: 343360 | E78: 0 | G78: Arquitectura | H78: =C78/$H$55 -> 0 | I78: =D78/$H$55 -> 19620.571 | J78: =E78/$H$55 -> 0 | L78: Arquitectura | M78: =C78/C$49 -> 0 | N78: =D78/D$49 -> 235.66232 | O78: =E78/E$49 -> 0
B79: Herreria | C79: =SUMIFS(BD!$T:$T,BD!$B:$B,PPT!B79) -> 2320000 | D79: 2830243.2 | E79: 1032202.3 | G79: Herreria | H79: =C79/$H$55 -> 132571.43 | I79: =D79/$H$55 -> 161728.18 | J79: =E79/$H$55 -> 58982.988 | L79: Herreria | M79: =C79/C$49 -> 1168.7304 | N79: =D79/D$49 -> 1942.5142 | O79: =E79/E$49 -> 2026.8272
B80: Jardineria_Y_Riego | C80: =SUMIFS(BD!$T:$T,BD!$B:$B,PPT!B80) -> 2173741.1 | D80: 1162900 | E80: 0 | G80: Jardineria_Y_Riego | H80: =C80/$H$55 -> 124213.78 | I80: =D80/$H$55 -> 66451.429 | J80: =E80/$H$55 -> 0 | L80: Jardineria_Y_Riego | M80: =C80/C$49 -> 1095.0506 | N80: =D80/D$49 -> 798.14688
B81: Acabados | C81: =SUMIFS(BD!$T:$T,BD!$B:$B,PPT!B81) -> 5800000 | D81: 1486674.2 | E81: 5599356.6 | G81: Acabados | H81: =C81/$H$55 -> 331428.57 | I81: =D81/$H$55 -> 84952.812 | J81: =E81/$H$55 -> 319963.23 | L81: Acabados | M81: =C81/C$49 -> 2921.826 | N81: =D81/D$49 -> 1020.3667 | O81: =E81/E$49 -> 10994.868
B82: Total | C82: =SUM(C57:C81) -> 1.9375227e+08 | D82: =SUM(D57:D81) -> 1.2225974e+08 | E82: =SUM(E57:E81) -> 43414019 | G82: Total | H82: =C82/$H$55 -> 11071558 | I82: =D82/$H$55 -> 6986270.9 | J82: =E82/$H$55 -> 2480801.1 | L82: Total | M82: =C82/C$49 -> 97605.245 | N82: =D82/D$49 -> 83911.97 | O82: =E82/E$49 -> 85247.549

Sheet BD >>

Sheet BD
B2: DROPDOWN | C2: DROPDOWN | D2: DROPDOWN | G2: INPUT | H2: INPUT | I2: DROPDOWN | J2: INPUT | K2: DROPDOWN | L2: INPUT | M2: NA | O2: NA | Q2: NA | R2: NA | S2: INPUT | T2: NA | U2: INPUT | V2: INPUT
A4: x | B4: CATEGORÍA | C4: CONCEPTO | D4: DETALLE | E4: TORRE | F4: PISO | G4: DEPTO | H4: PROVEEDOR | I4: UNIDAD | J4: CANTIDAD | K4: MONEDA | L4: $ UNITARIO | M4: IMPORTE SIN IVA | N4: SOBRECOSTO | O4: TOTAL SOBRECOSTO | P4: % IVA | Q4: $ IVA | R4: IMPORTE TOTAL | S4: T.C | T4: TOTAL MXN | U4: NOTAS | V4: PARAMETRICO/PPTO
B5: Arquitectura | C5: Diseño Iluminacion | D5: S/D | E5: TORRE 1 | F5: S/D | G5: S/D | H5: NA | I5: Lote | J5: 0 | K5: MXN | L5: 116000 | M5: =J5*L5 -> 0 | N5: 0 | O5: =M5*N5 -> 0 | P5: 0.16 | Q5: =(M5+O5)*P5 -> 0 | R5: =M5+O5+Q5 -> 0 | S5: =INDEX('Glosario Partidas'!$M$8:$M$10,MATCH(BD!K5,'Glosario Partidas'!$L$8:$L$10,0)) -> 1 | T5: =R5*S5 -> 0 | U5: ########### | V5: PARAMETRICO
B6: Arquitectura | C6: Supervision Diseño Iluminacion | D6: S/D | E6: TORRE 1 | F6: S/D | G6: S/D | H6: NA | I6: Lote | J6: 0 | K6: MXN | L6: 0 | M6: =J6*L6 -> 0 | N6: 0 | O6: =M6*N6 -> 0 | P6: 0 | Q6: =(M6+O6)*P6 -> 0 | R6: =M6+O6+Q6 -> 0 | S6: =INDEX('Glosario Partidas'!$M$8:$M$10,MATCH(BD!K6,'Glosario Partidas'!$L$8:$L$10,0)) -> 1 | T6: =R6*S6 -> 0 | U6: ########### | V6: PARAMETRICO
B7: Arquitectura | C7: Diseño Jardineria | D7: S/D | E7: TORRE 1 | F7: S/D | G7: S/D | H7: NA | I7: Lote | J7: 0 | K7: MXN | L7: 180000 | M7: =J7*L7 -> 0 | N7: 0 | O7: =M7*N7 -> 0 | P7: 0.16 | Q7: =(M7+O7)*P7 -> 0 | R7: =M7+O7+Q7 -> 0 | S7: =INDEX('Glosario Partidas'!$M$8:$M$10,MATCH(BD!K7,'Glosario Partidas'!$L$8:$L$10,0)) -> 1 | T7: =R7*S7 -> 0 | U7: ########### | V7: PARAMETRICO
B8: Arquitectura | C8: Supervision Diseño Jardineria | D8: S/D | E8: TORRE 1 | F8: S/D | G8: S/D | H8: NA | I8: Lote | J8: 0 | K8: MXN | L8: 0 | M8: =J8*L8 -> 0 | N8: 0 | O8: =M8*N8 -> 0 | P8: 0 | Q8: =(M8+O8)*P8 -> 0 | R8: =M8+O8+Q8 -> 0 | S8: =INDEX('Glosario Partidas'!$M$8:$M$10,MATCH(BD!K8,'Glosario Partidas'!$L$8:$L$10,0)) -> 1 | T8: =R8*S8 -> 0 | U8: ########### | V8: PARAMETRICO
B9: Ingenierias_Y_Topografia | C9: Topografia Gestoria | D9: S/D | E9: TORRE 1 | F9: S/D | G9: S/D | H9: NA | I9: Lote | J9: 0 | K9: MXN | L9: 0 | M9: =J9*L9 -> 0 | N9: 0 | O9: =M9*N9 -> 0 | P9: 0 | Q9: =(M9+O9)*P9 -> 0 | R9: =M9+O9+Q9 -> 0 | S9: =INDEX('Glosario Partidas'!$M$8:$M$10,MATCH(BD!K9,'Glosario Partidas'!$L$8:$L$10,0)) -> 1 | T9: =R9*S9 -> 0 | U9: ########### | V9: PARAMETRICO
B10: Ingenierias_Y_Topografia | C10: Topografia Obra | D10: S/D | E10: TORRE 1 | F10: S/D | G10: S/D | H10: NA | I10: Semana | J10: 0 | K10: MXN | L10: 0 | M10: =J10*L10 -> 0 | N10: 0 | O10: =M10*N10 -> 0 | P10: 0 | Q10: =(M10+O10)*P10 -> 0 | R10: =M10+O10+Q10 -> 0 | S10: =INDEX('Glosario Partidas'!$M$8:$M$10,MATCH(BD!K10,'Glosario Partidas'!$L$8:$L$10,0)) -> 1 | T10: =R10*S10 -> 0 | U10: ########### | V10: PARAMETRICO
B11: Ingenierias_Y_Topografia | C11: Mecanica De Suelos | D11: S/D | E11: TORRE 1 | F11: S/D | G11: S/D | H11: NA | I11: Lote | J11: 1 | K11: MXN | L11: 156385 | M11: =J11*L11 -> 156385 | N11: 0 | O11: =M11*N11 -> 0 | P11: 0 | Q11: =(M11+O11)*P11 -> 0 | R11: =M11+O11+Q11 -> 156385 | S11: =INDEX('Glosario Partidas'!$M$8:$M$10,MATCH(BD!K11,'Glosario Partidas'!$L$8:$L$10,0)) -> 1 | T11: =R11*S11 -> 156385 | U11: ########### | V11: PPTO
B12: Ingenierias_Y_Topografia | C12: Calculo Estructural | D12: S/D | E12: TORRE 1 | F12: S/D | G12: S/D | H12: NA | I12: Lote | J12: 1 | K12: MXN | L12: 285000 | M12: =J12*L12 -> 285000 | N12: 0 | O12: =M12*N12 -> 0 | P12: 0 | Q12: =(M12+O12)*P12 -> 0 | R12: =M12+O12+Q12 -> 285000 | S12: =INDEX('Glosario Partidas'!$M$8:$M$10,MATCH(BD!K12,'Glosario Partidas'!$L$8:$L$10,0)) -> 1 | T12: =R12*S12 -> 285000 | U12: ########### | V12: PPTO
B13: Ingenierias_Y_Topografia | C13: Diseño Instalaciones. Electricas, Ihs, Alberca, Gas, Etc. | D13: S/D | E13: TORRE 1 | F13: S/D | G13: S/D | H13: NA | I13: Lote | J13: 0 | K13: MXN | L13: 0 | M13: =J13*L13 -> 0 | N13: 0 | O13: =M13*N13 -> 0 | P13: 0 | Q13: =(M13+O13)*P13 -> 0 | R13: =M13+O13+Q13 -> 0 | S13: =INDEX('Glosario Partidas'!$M$8:$M$10,MATCH(BD!K13,'Glosario Partidas'!$L$8:$L$10,0)) -> 1 | T13: =R13*S13 -> 0 | U13: ########### | V13: PARAMETRICO
B14: Indirectos_De_Obra | C14: Trabajos_Preliminares | D14: Despalme | E14: TORRE 1 | F14: S/D | G14: S/D | H14: NA | I14: Lote | J14: 1 | K14: MXN | L14: 58344 | M14: =J14*L14 -> 58344 | N14: 0 | O14: =M14*N14 -> 0 | P14: 0.16 | Q14: =(M14+O14)*P14 -> 9335.04 | R14: =M14+O14+Q14 -> 67679.04 | S14: =INDEX('Glosario Partidas'!$M$8:$M$10,MATCH(BD!K14,'Glosario Partidas'!$L$8:$L$10,0)) -> 1 | T14: =R14*S14 -> 67679.04 | U14: ########### | V14: PPTO
B15: Indirectos_De_Obra | C15: Trabajos_Preliminares | D15: Malla | E15: TORRE 1 | F15: S/D | G15: S/D | H15: NA | I15: Lote | J15: 1 | K15: MXN | L15: 206867.55 | M15: =J15*L15 -> 206867.55 | N15: 0 | O15: =M15*N15 -> 0 | P15: 0.16 | Q15: =(M15+O15)*P15 -> 33098.808 | R15: =M15+O15+Q15 -> 239966.36 | S15: =INDEX('Glosario Partidas'!$M$8:$M$10,MATCH(BD!K15,'Glosario Partidas'!$L$8:$L$10,0)) -> 1 | T15: =R15*S15 -> 239966.36 | U15: ########### | V15: PPTO
B16: Indirectos_De_Obra | C16: Trabajos_Preliminares | D16: Papeleria | E16: TORRE 1 | F16: S/D | G16: S/D | H16: NA | I16: Lote | J16: 1 | K16: MXN | L16: 56815 | M16: =J16*L16 -> 56815 | N16: 0 | O16: =M16*N16 -> 0 | P16: 0.16 | Q16: =(M16+O16)*P16 -> 9090.4 | R16: =M16+O16+Q16 -> 65905.4 | S16: =INDEX('Glosario Partidas'!$M$8:$M$10,MATCH(BD!K16,'Glosario Partidas'!$L$8:$L$10,0)) -> 1 | T16: =R16*S16 -> 65905.4 | U16: ########### | V16: PPTO
B17: Indirectos_De_Obra | C17: Renta Generadores de Luz | D17: Generador 1 | E17: TORRE 1 | F17: S/D | G17: S/D | H17: NA | I17: Lote | J17: 14 | K17: MXN | L17: =33600/2 -> 16800 | M17: =J17*L17 -> 235200 | N17: 0 | O17: =M17*N17 -> 0 | P17: 0.16 | Q17: =(M17+O17)*P17 -> 37632 | R17: =M17+O17+Q17 -> 272832 | S17: =INDEX('Glosario Partidas'!$M$8:$M$10,MATCH(BD!K17,'Glosario Partidas'!$L$8:$L$10,0)) -> 1 | T17: =R17*S17 -> 272832 | U17: ########### | V17: PPTO
B18: Indirectos_De_Obra | C18: Renta Generadores de Luz | D18: Generador 2 | E18: TORRE 1 | F18: S/D | G18: S/D | H18: NA | I18: Lote | J18: 14 | K18: MXN | L18: =33600/2 -> 16800 | M18: =J18*L18 -> 235200 | N18: 0 | O18: =M18*N18 -> 0 | P18: 0.16 | Q18: =(M18+O18)*P18 -> 37632 | R18: =M18+O18+Q18 -> 272832 | S18: =INDEX('Glosario Partidas'!$M$8:$M$10,MATCH(BD!K18,'Glosario Partidas'!$L$8:$L$10,0)) -> 1 | T18: =R18*S18 -> 272832 | U18: ########### | V18: PPTO
B19: Indirectos_De_Obra | C19: Renta Generadores de Luz | D19: Diesel | E19: TORRE 1 | F19: S/D | G19: S/D | H19: NA | I19: Lote | J19: 14 | K19: MXN | L19: 62400 | M19: =J19*L19 -> 873600 | N19: 0 | O19: =M19*N19 -> 0 | P19: 0.16 | Q19: =(M19+O19)*P19 -> 139776 | R19: =M19+O19+Q19 -> 1013376 | S19: =INDEX('Glosario Partidas'!$M$8:$M$10,MATCH(BD!K19,'Glosario Partidas'!$L$8:$L$10,0)) -> 1 | T19: =R19*S19 -> 1013376 | U19: ########### | V19: PARAMETRICO
B20: Indirectos_De_Obra | C20: Renta Generadores de Luz | D20: Operador de Generador | E20: TORRE 1 | F20: S/D | G20: S/D | H20: NA | I20: Lote | J20: 14 | K20: MXN | L20: 20000 | M20: =J20*L20 -> 280000 | N20: 0 | O20: =M20*N20 -> 0 | P20: 0.16 | Q20: =(M20+O20)*P20 -> 44800 | R20: =M20+O20+Q20 -> 324800 | S20: =INDEX('Glosario Partidas'!$M$8:$M$10,MATCH(BD!K20,'Glosario Partidas'!$L$8:$L$10,0)) -> 1 | T20: =R20*S20 -> 324800 | U20: ########### | V20: PARAMETRICO
B21: Indirectos_De_Obra | C21: Renta Camper | D21: S/D | E21: TORRE 1 | F21: S/D | G21: S/D | H21: NA | I21: Mes | J21: 24 | K21: MXN | L21: 24000 | M21: =J21*L21 -> 576000 | N21: 0 | O21: =M21*N21 -> 0 | P21: 0.16 | Q21: =(M21+O21)*P21 -> 92160 | R21: =M21+O21+Q21 -> 668160 | S21: =INDEX('Glosario Partidas'!$M$8:$M$10,MATCH(BD!K21,'Glosario Partidas'!$L$8:$L$10,0)) -> 1 | T21: =R21*S21 -> 668160 | U21: ########### | V21: PARAMETRICO
B22: Indirectos_De_Obra | C22: Auxiliar De Residente ( + 2 Meses ) | D22: S/D | E22: TORRE 1 | F22: S/D | G22: S/D | H22: NA | I22: Mes | J22: 26 | K22: MXN | L22: 45000 | M22: =J22*L22 -> 1170000 | N22: 0 | O22: =M22*N22 -> 0 | P22: 0.16 | Q22: =(M22+O22)*P22 -> 187200 | R22: =M22+O22+Q22 -> 1357200 | S22: =INDEX('Glosario Partidas'!$M$8:$M$10,MATCH(BD!K22,'Glosario Partidas'!$L$8:$L$10,0)) -> 1 | T22: =R22*S22 -> 1357200 | U22: ########### | V22: PARAMETRICO
B23: Indirectos_De_Obra | C23: Honorarios Residente ( + 2 Meses ) | D23: S/D | E23: TORRE 1 | F23: S/D | G23: S/D | H23: NA | I23: Mes | J23: 26 | K23: MXN | L23: 70000 | M23: =J23*L23 -> 1820000 | N23: 0 | O23: =M23*N23 -> 0 | P23: 0.16 | Q23: =(M23+O23)*P23 -> 291200 | R23: =M23+O23+Q23 -> 2111200 | S23: =INDEX('Glosario Partidas'!$M$8:$M$10,MATCH(BD!K23,'Glosario Partidas'!$L$8:$L$10,0)) -> 1 | T23: =R23*S23 -> 2111200 | U23: ########### | V23: PARAMETRICO
B24: Indirectos_De_Obra | C24: Coordinador MEPS | D24: S/D | E24: TORRE 1 | F24: S/D | G24: S/D | H24: NA | I24: Mes | J24: 26 | K24: MXN | L24: 25000 | M24: =J24*L24 -> 650000 | N24: 0 | O24: =M24*N24 -> 0 | P24: 0.16 | Q24: =(M24+O24)*P24 -> 104000 | R24: =M24+O24+Q24 -> 754000 | S24: =INDEX('Glosario Partidas'!$M$8:$M$10,MATCH(BD!K24,'Glosario Partidas'!$L$8:$L$10,0)) -> 1 | T24: =R24*S24 -> 754000 | U24: ########### | V24: PARAMETRICO
B25: Indirectos_De_Obra | C25: Viaticos | D25: S/D | E25: TORRE 1 | F25: S/D | G25: S/D | H25: NA | I25: Mes | J25: 26 | K25: MXN | L25: 60000 | M25: =J25*L25 -> 1560000 | N25: 0 | O25: =M25*N25 -> 0 | P25: 0.16 | Q25: =(M25+O25)*P25 -> 249600 | R25: =M25+O25+Q25 -> 1809600 | S25: =INDEX('Glosario Partidas'!$M$8:$M$10,MATCH(BD!K25,'Glosario Partidas'!$L$8:$L$10,0)) -> 1 | T25: =R25*S25 -> 1809600 | U25: ########### | V25: PARAMETRICO
B26: Indirectos_De_Obra | C26: Mantenimiento Y Limpieza | D26: S/D | E26: TORRE 1 | F26: S/D | G26: S/D | H26: NA | I26: Mes | J26: 14 | K26: MXN | L26: 40000 | M26: =J26*L26 -> 560000 | N26: 0 | O26: =M26*N26 -> 0 | P26: 0.16 | Q26: =(M26+O26)*P26 -> 89600 | R26: =M26+O26+Q26 -> 649600 | S26: =INDEX('Glosario Partidas'!$M$8:$M$10,MATCH(BD!K26,'Glosario Partidas'!$L$8:$L$10,0)) -> 1 | T26: =R26*S26 -> 649600 | U26: ########### | V26: PARAMETRICO
B27: Indirectos_De_Obra | C27: Caja Chica De Obra | D27: S/D | E27: TORRE 1 | F27: S/D | G27: S/D | H27: NA | I27: Mes | J27: 14 | K27: MXN | L27: 60000 | M27: =J27*L27 -> 840000 | N27: 0 | O27: =M27*N27 -> 0 | P27: 0.16 | Q27: =(M27+O27)*P27 -> 134400 | R27: =M27+O27+Q27 -> 974400 | S27: =INDEX('Glosario Partidas'!$M$8:$M$10,MATCH(BD!K27,'Glosario Partidas'!$L$8:$L$10,0)) -> 1 | T27: =R27*S27 -> 974400 | U27: ########### | V27: PARAMETRICO
B28: Indirectos_De_Obra | C28: IMSS | D28: S/D | E28: TORRE 1 | F28: S/D | G28: S/D | H28: NA | I28: Mes | J28: 24 | K28: MXN | L28: 35000 | M28: =J28*L28 -> 840000 | N28: 0 | O28: =M28*N28 -> 0 | P28: 0.16 | Q28: =(M28+O28)*P28 -> 134400 | R28: =M28+O28+Q28 -> 974400 | S28: =INDEX('Glosario Partidas'!$M$8:$M$10,MATCH(BD!K28,'Glosario Partidas'!$L$8:$L$10,0)) -> 1 | T28: =R28*S28 -> 974400 | U28: ########### | V28: PARAMETRICO
B29: Excavacion | C29: Excavacion | D29: S/D | E29: TORRE 1 | F29: S/D | G29: S/D | H29: NA | I29: Lote | J29: 1 | K29: MXN | L29: 200000 | M29: =J29*L29 -> 200000 | N29: 0 | O29: =M29*N29 -> 0 | P29: 0.16 | Q29: =(M29+O29)*P29 -> 32000 | R29: =M29+O29+Q29 -> 232000 | S29: =INDEX('Glosario Partidas'!$M$8:$M$10,MATCH(BD!K29,'Glosario Partidas'!$L$8:$L$10,0)) -> 1 | T29: =R29*S29 -> 232000 | U29: ########### | V29: PARAMETRICO
B30: Obra_Civil | C30: Obra Civil | D30: S/D | E30: TORRE 1 | F30: S/D | G30: S/D | H30: ANTEUS | I30: M2 | J30: 1600 | K30: MXN | L30: 17250 | M30: =J30*L30 -> 27600000 | N30: 0 | O30: =M30*N30 -> 0 | P30: 0.16 | Q30: =(M30+O30)*P30 -> 4416000 | R30: =M30+O30+Q30 -> 32016000 | S30: =INDEX('Glosario Partidas'!$M$8:$M$10,MATCH(BD!K30,'Glosario Partidas'!$L$8:$L$10,0)) -> 1 | T30: =R30*S30 -> 32016000 | U30: ########### | V30: PARAMETRICO
... B59: Herreria | C59: Pintura Herreria. Primario / Acabado | D59: S/D | E59: TORRE 1 | F59: S/D | G59: S/D | H59: NA | I59: Lote | J59: 0 | K59: MXN | L59: 592338.6 | M59: =J59*L59 -> 0 | N59: 0 | O59: =M59*N59 -> 0 | P59: 0.16 | Q59: =(M59+O59)*P59 -> 0 | R59: =M59+O59+Q59 -> 0 | S59: =INDEX('Glosario Partidas'!$M$8:$M$10,MATCH(BD!K59,'Glosario Partidas'!$L$8:$L$10,0)) -> 1 | T59: =R59*S59 -> 0 | U59: ########### | V59: PARAMETRICO
B60: Instalaciones_Electricas | C60: Instalaciones Electricas | D60: S/D | E60: TORRE 1 | F60: PB | G60: DEPTO 01 | H60: NA | I60: M2 | J60: =323.83*1.1 -> 356.213 | K60: MXN | L60: 4500 | M60: =J60*L60 -> 1602958.5 | N60: 0 | O60: =M60*N60 -> 0 | P60: 0.16 | Q60: =(M60+O60)*P60 -> 256473.36 | R60: =M60+O60+Q60 -> 1859431.9 | S60: =INDEX('Glosario Partidas'!$M$8:$M$10,MATCH(BD!K60,'Glosario Partidas'!$L$8:$L$10,0)) -> 1 | T60: =R60*S60 -> 1859431.9 | U60: ########### | V60: PARAMETRICO
B61: Instalaciones_Electricas | C61: Instalaciones Electricas | D61: S/D | E61: TORRE 1 | F61: N1 y N1R | G61: DEPTO 01 | H61: NA | I61: M2 | J61: =404.37*1.1 -> 444.807 | K61: MXN | L61: 4500 | M61: =J61*L61 -> 2001631.5 | N61: 0 | O61: =M61*N61 -> 0 | P61: 0.16 | Q61: =(M61+O61)*P61 -> 320261.04 | R61: =M61+O61+Q61 -> 2321892.5 | S61: =INDEX('Glosario Partidas'!$M$8:$M$10,MATCH(BD!K61,'Glosario Partidas'!$L$8:$L$10,0)) -> 1 | T61: =R61*S61 -> 2321892.5 | U61: ########### | V61: PARAMETRICO
B62: Instalaciones_Hidraulicas | C62: Instalaciones Hidrosanitarias | D62: S/D | E62: TORRE 1 | F62: PB | G62: DEPTO 01 | H62: NA | I62: M2 | J62: =323.83*1.1 -> 356.213 | K62: MXN | L62: 4500 | M62: =J62*L62 -> 1602958.5 | N62: 0 | O62: =M62*N62 -> 0 | P62: 0.16 | Q62: =(M62+O62)*P62 -> 256473.36 | R62: =M62+O62+Q62 -> 1859431.9 | S62: =INDEX('Glosario Partidas'!$M$8:$M$10,MATCH(BD!K62,'Glosario Partidas'!$L$8:$L$10,0)) -> 1 | T62: =R62*S62 -> 1859431.9 | U62: ########### | V62: PARAMETRICO
B63: Instalaciones_Hidraulicas | C63: Instalaciones Hidrosanitarias | D63: S/D | E63: TORRE 1 | F63: N1 y N1R | G63: DEPTO 01 | H63: NA | I63: M2 | J63: =404.37*1.1 -> 444.807 | K63: MXN | L63: 4500 | M63: =J63*L63 -> 2001631.5 | N63: 0 | O63: =M63*N63 -> 0 | P63: 0.16 | Q63: =(M63+O63)*P63 -> 320261.04 | R63: =M63+O63+Q63 -> 2321892.5 | S63: =INDEX('Glosario Partidas'!$M$8:$M$10,MATCH(BD!K63,'Glosario Partidas'!$L$8:$L$10,0)) -> 1 | T63: =R63*S63 -> 2321892.5 | U63: ########### | V63: PARAMETRICO
B64: Albercas | C64: Alberca Completa | D64: S/D | E64: TORRE 1 | F64: PB | G64: DEPTO 01 | H64: AQUA CONCEPTS | I64: M2 | J64: 84.16 | K64: MXN | L64: 40000 | M64: =J64*L64 -> 3366400 | N64: 0 | O64: =M64*N64 -> 0 | P64: 0.16 | Q64: =(M64+O64)*P64 -> 538624 | R64: =M64+O64+Q64 -> 3905024 | S64: =INDEX('Glosario Partidas'!$M$8:$M$10,MATCH(BD!K64,'Glosario Partidas'!$L$8:$L$10,0)) -> 1 | T64: =R64*S64 -> 3905024 | U64: Incluye desde impermiabilizacion, hasta acabados y funcionamiento | V64: PARAMETRICO
B65: Albercas | C65: Alberca Completa | D65: S/D | E65: TORRE 1 | F65: N1R | G65: DEPTO 01 | H65: AQUA CONCEPTS | I65: M2 | J65: 84.16 | K65: MXN | L65: 40000 | M65: =J65*L65 -> 3366400 | N65: 0 | O65: =M65*N65 -> 0 | P65: 0.16 | Q65: =(M65+O65)*P65 -> 538624 | R65: =M65+O65+Q65 -> 3905024 | S65: =INDEX('Glosario Partidas'!$M$8:$M$10,MATCH(BD!K65,'Glosario Partidas'!$L$8:$L$10,0)) -> 1 | T65: =R65*S65 -> 3905024 | U65: Incluye desde impermiabilizacion, hasta acabados y funcionamiento | V65: PARAMETRICO
B66: Automatizacion_Control_Iluminacion | C66: S/D | D66: S/D | E66: TORRE 1 | F66: PB | G66: DEPTO 01 | H66: TENCO | I66: Lote | J66: =323.83*1.1 -> 356.213 | K66: MXN | L66: 5617.2778 | M66: =J66*L66 -> 2000947.4 | N66: 0 | O66: =M66*N66 -> 0 | P66: 0.16 | Q66: =(M66+O66)*P66 -> 320151.58 | R66: =M66+O66+Q66 -> 2321099 | S66: =INDEX('Glosario Partidas'!$M$8:$M$10,MATCH(BD!K66,'Glosario Partidas'!$L$8:$L$10,0)) -> 1 | T66: =R66*S66 -> 2321099 | U66: ########### | V66: PARAMETRICO
B67: Automatizacion_Control_Iluminacion | C67: S/D | D67: S/D | E67: TORRE 1 | F67: N1 y N1R | G67: DEPTO 01 | H67: TENCO | I67: Lote | J67: =404.37*1.1 -> 444.807 | K67: MXN | L67: 5617.2778 | M67: =J67*L67 -> 2498604.5 | N67: 0 | O67: =M67*N67 -> 0 | P67: 0.16 | Q67: =(M67+O67)*P67 -> 399776.72 | R67: =M67+O67+Q67 -> 2898381.2 | S67: =INDEX('Glosario Partidas'!$M$8:$M$10,MATCH(BD!K67,'Glosario Partidas'!$L$8:$L$10,0)) -> 1 | T67: =R67*S67 -> 2898381.2 | U67: ########### | V67: PARAMETRICO
B68: Instalaciones_Gas | C68: Instalaciones De Gas | D68: S/D | E68: TORRE 1 | F68: S/D | G68: S/D | H68: NA | I68: Lote | J68: 1 | K68: MXN | L68: 800000 | M68: =J68*L68 -> 800000 | N68: 0 | O68: =M68*N68 -> 0 | P68: 0.16 | Q68: =(M68+O68)*P68 -> 128000 | R68: =M68+O68+Q68 -> 928000 | S68: =INDEX('Glosario Partidas'!$M$8:$M$10,MATCH(BD!K68,'Glosario Partidas'!$L$8:$L$10,0)) -> 1 | T68: =R68*S68 -> 928000 | U68: ########### | V68: PARAMETRICO
B69: Aire_Acondicionado_Y_Extraccion | C69: Sistema De Aire Acondicionado Y Extraccion. Usd | D69: S/D | E69: TORRE 1 | F69: PB | G69: DEPTO 01 | H69: CYVSA | I69: M2 | J69: =323.83*1.1 -> 356.213 | K69: USD | M69: =J69*L69 -> 0 | N69: 0 | O69: =M69*N69 -> 0 | P69: 0.16 | Q69: =(M69+O69)*P69 -> 0 | R69: =M69+O69+Q69 -> 0 | S69: =INDEX('Glosario Partidas'!$M$8:$M$10,MATCH(BD!K69,'Glosario Partidas'!$L$8:$L$10,0)) -> 17.5 | T69: =R69*S69 -> 0 | U69: ########### | V69: PARAMETRICO
B70: Aire_Acondicionado_Y_Extraccion | C70: Sistema De Aire Acondicionado Y Extraccion. MXN | D70: S/D | E70: TORRE 1 | F70: PB | G70: DEPTO 01 | H70: CYVSA | I70: M2 | J70: =323.83*1.1 -> 356.213 | K70: MXN | L70: 4700 | M70: =J70*L70 -> 1674201.1 | N70: 0 | O70: =M70*N70 -> 0 | P70: 0.16 | Q70: =(M70+O70)*P70 -> 267872.18 | R70: =M70+O70+Q70 -> 1942073.3 | S70: =INDEX('Glosario Partidas'!$M$8:$M$10,MATCH(BD!K70,'Glosario Partidas'!$L$8:$L$10,0)) -> 1 | T70: =R70*S70 -> 1942073.3 | U70: ########### | V70: PARAMETRICO
B71: Aire_Acondicionado_Y_Extraccion | C71: Sistema De Aire Acondicionado Y Extraccion. Usd | D71: S/D | E71: TORRE 1 | F71: N1 y N1R | G71: DEPTO 01 | H71: CYVSA | I71: M2 | J71: =404.37*1.1 -> 444.807 | K71: USD | M71: =J71*L71 -> 0 | N71: 0 | O71: =M71*N71 -> 0 | P71: 0.16 | Q71: =(M71+O71)*P71 -> 0 | R71: =M71+O71+Q71 -> 0 | S71: =INDEX('Glosario Partidas'!$M$8:$M$10,MATCH(BD!K71,'Glosario Partidas'!$L$8:$L$10,0)) -> 17.5 | T71: =R71*S71 -> 0 | U71: ########### | V71: PARAMETRICO
B72: Aire_Acondicionado_Y_Extraccion | C72: Sistema De Aire Acondicionado Y Extraccion. MXN | D72: S/D | E72: TORRE 1 | F72: N1 y N1R | G72: DEPTO 01 | H72: CYVSA | I72: M2 | J72: =404.37*1.1 -> 444.807 | K72: MXN | L72: 4700 | M72: =J72*L72 -> 2090592.9 | N72: 0 | O72: =M72*N72 -> 0 | P72: 0.16 | Q72: =(M72+O72)*P72 -> 334494.86 | R72: =M72+O72+Q72 -> 2425087.8 | S72: =INDEX('Glosario Partidas'!$M$8:$M$10,MATCH(BD!K72,'Glosario Partidas'!$L$8:$L$10,0)) -> 1 | T72: =R72*S72 -> 2425087.8 | U72: ########### | V72: PARAMETRICO
B73: Iluminacion | C73: Luminarias Interior | D73: S/D | E73: TORRE 1 | F73: PB | G73: DEPTO 01 | H73: NA | I73: M2 | J73: 323.83 | K73: USD | L73: 60 | M73: =J73*L73 -> 19429.8 | N73: 0 | O73: =M73*N73 -> 0 | P73: 0.16 | Q73: =(M73+O73)*P73 -> 3108.768 | R73: =M73+O73+Q73 -> 22538.568 | S73: =INDEX('Glosario Partidas'!$M$8:$M$10,MATCH(BD!K73,'Glosario Partidas'!$L$8:$L$10,0)) -> 17.5 | T73: =R73*S73 -> 394424.94 | U73: ########### | V73: PARAMETRICO
B74: Iluminacion | C74: Luminarias Interior | D74: S/D | E74: TORRE 1 | F74: N1 y N1R | G74: DEPTO 01 | H74: NA | I74: M2 | J74: 404.37 | K74: USD | L74: 60 | M74: =J74*L74 -> 24262.2 | N74: 0 | O74: =M74*N74 -> 0 | P74: 0.16 | Q74: =(M74+O74)*P74 -> 3881.952 | R74: =M74+O74+Q74 -> 28144.152 | S74: =INDEX('Glosario Partidas'!$M$8:$M$10,MATCH(BD!K74,'Glosario Partidas'!$L$8:$L$10,0)) -> 17.5 | T74: =R74*S74 -> 492522.66 | U74: ########### | V74: PARAMETRICO
B75: Iluminacion | C75: Luminarias Exterior | D75: S/D | E75: TORRE 1 | F75: PB | G75: DEPTO 01 | H75: NA | I75: M2 | J75: 203.17 | K75: USD | L75: 40 | M75: =J75*L75 -> 8126.8 | N75: 0 | O75: =M75*N75 -> 0 | P75: 0.16 | Q75: =(M75+O75)*P75 -> 1300.288 | R75: =M75+O75+Q75 -> 9427.088 | S75: =INDEX('Glosario Partidas'!$M$8:$M$10,MATCH(BD!K75,'Glosario Partidas'!$L$8:$L$10,0)) -> 17.5 | T75: =R75*S75 -> 164974.04 | U75: ########### | V75: PARAMETRICO
B76: Iluminacion | C76: Luminarias Exterior | D76: S/D | E76: TORRE 1 | F76: N1 y N1R | G76: DEPTO 01 | H76: NA | I76: M2 | J76: 244.85 | K76: USD | L76: 40 | M76: =J76*L76 -> 9794 | N76: 0 | O76: =M76*N76 -> 0 | P76: 0.16 | Q76: =(M76+O76)*P76 -> 1567.04 | R76: =M76+O76+Q76 -> 11361.04 | S76: =INDEX('Glosario Partidas'!$M$8:$M$10,MATCH(BD!K76,'Glosario Partidas'!$L$8:$L$10,0)) -> 17.5 | T76: =R76*S76 -> 198818.2 | U76: ########### | V76: PARAMETRICO
B77: Suministro_Y_Colocacion_De_Marmol | C77: Marmol Pisos | D77: Marmol En Pisos Inc. Desperdicio | E77: TORRE 1 | F77: PB | G77: DEPTO 01 | H77: NA | I77: M2 | J77: 423.6 | K77: USD | L77: 60 | M77: =J77*L77 -> 25416 | N77: 0 | O77: =M77*N77 -> 0 | P77: 0.16 | Q77: =(M77+O77)*P77 -> 4066.56 | R77: =M77+O77+Q77 -> 29482.56 | S77: =INDEX('Glosario Partidas'!$M$8:$M$10,MATCH(BD!K77,'Glosario Partidas'!$L$8:$L$10,0)) -> 17.5 | T77: =R77*S77 -> 515944.8 | U77: ########### | V77: PARAMETRICO
B78: Suministro_Y_Colocacion_De_Marmol | C78: Marmol Pisos | D78: Marmol En Pisos Inc. Desperdicio | E78: TORRE 1 | F78: N1 | G78: DEPTO 01 | H78: NA | I78: M2 | J78: 235.2 | K78: USD | L78: 70 | M78: =J78*L78 -> 16464 | N78: 0 | O78: =M78*N78 -> 0 | P78: 0.16 | Q78: =(M78+O78)*P78 -> 2634.24 | R78: =M78+O78+Q78 -> 19098.24 | S78: =INDEX('Glosario Partidas'!$M$8:$M$10,MATCH(BD!K78,'Glosario Partidas'!$L$8:$L$10,0)) -> 17.5 | T78: =R78*S78 -> 334219.2 | U78: ########### | V78: PARAMETRICO
B79: Suministro_Y_Colocacion_De_Marmol | C79: Marmol Pisos | D79: Marmol En Pisos Inc. Desperdicio | E79: TORRE 1 | F79: N1R | G79: DEPTO 01 | H79: NA | I79: M2 | J79: 302.4 | K79: USD | L79: 70 | M79: =J79*L79 -> 21168 | N79: 0 | O79: =M79*N79 -> 0 | P79: 0.16 | Q79: =(M79+O79)*P79 -> 3386.88 | R79: =M79+O79+Q79 -> 24554.88 | S79: =INDEX('Glosario Partidas'!$M$8:$M$10,MATCH(BD!K79,'Glosario Partidas'!$L$8:$L$10,0)) -> 17.5 | T79: =R79*S79 -> 429710.4 | U79: ########### | V79: PARAMETRICO
B80: Suministro_Y_Colocacion_De_Marmol | C80: Marmol Pisos | D80: Colocacion Marmol | E80: TORRE 1 | F80: PB | G80: DEPTO 01 | H80: BIARQ | I80: M2 | J80: 353 | K80: MXN | L80: 1900 | M80: =J80*L80 -> 670700 | N80: 0 | O80: =M80*N80 -> 0 | P80: 0.16 | Q80: =(M80+O80)*P80 -> 107312 | R80: =M80+O80+Q80 -> 778012 | S80: =INDEX('Glosario Partidas'!$M$8:$M$10,MATCH(BD!K80,'Glosario Partidas'!$L$8:$L$10,0)) -> 1 | T80: =R80*S80 -> 778012 | U80: ########### | V80: PARAMETRICO
B81: Suministro_Y_Colocacion_De_Marmol | C81: Marmol Pisos | D81: Colocacion Marmol | E81: TORRE 1 | F81: N1 | G81: DEPTO 01 | H81: BIARQ | I81: M2 | J81: 196 | K81: MXN | L81: 1900 | M81: =J81*L81 -> 372400 | N81: 0 | O81: =M81*N81 -> 0 | P81: 0.16 | Q81: =(M81+O81)*P81 -> 59584 | R81: =M81+O81+Q81 -> 431984 | S81: =INDEX('Glosario Partidas'!$M$8:$M$10,MATCH(BD!K81,'Glosario Partidas'!$L$8:$L$10,0)) -> 1 | T81: =R81*S81 -> 431984 | U81: ########### | V81: PARAMETRICO
B82: Suministro_Y_Colocacion_De_Marmol | C82: Marmol Pisos | D82: Colocacion Marmol | E82: TORRE 1 | F82: N1R | G82: DEPTO 01 | H82: BIARQ | I82: M2 | J82: 252 | K82: MXN | L82: 1900 | M82: =J82*L82 -> 478800 | N82: 0 | O82: =M82*N82 -> 0 | P82: 0.16 | Q82: =(M82+O82)*P82 -> 76608 | R82: =M82+O82+Q82 -> 555408 | S82: =INDEX('Glosario Partidas'!$M$8:$M$10,MATCH(BD!K82,'Glosario Partidas'!$L$8:$L$10,0)) -> 1 | T82: =R82*S82 -> 555408 | U82: ########### | V82: PARAMETRICO
B83: Suministro_Y_Colocacion_De_Marmol | C83: Marmol Pisos | D83: Marmol En Pisos Inc. Desperdicio BAÑOS | E83: TORRE 1 | F83: N1 | G83: DEPTO 01 | H83: NA | I83: M2 | J83: 20 | K83: USD | L83: 250 | M83: =J83*L83 -> 5000 | N83: 0 | O83: =M83*N83 -> 0 | P83: 0.16 | Q83: =(M83+O83)*P83 -> 800 | R83: =M83+O83+Q83 -> 5800 | S83: =INDEX('Glosario Partidas'!$M$8:$M$10,MATCH(BD!K83,'Glosario Partidas'!$L$8:$L$10,0)) -> 17.5 | T83: =R83*S83 -> 101500 | U83: ########### | V83: PARAMETRICO
B84: Suministro_Y_Colocacion_De_Marmol | C84: Marmol Pisos | D84: Colocacion Marmol BAÑOS | E84: TORRE 1 | F84: N1 | G84: DEPTO 01 | H84: BIARQ | I84: M2 | J84: 22 | K84: MXN | L84: 1900 | M84: =J84*L84 -> 41800 | N84: 0 | O84: =M84*N84 -> 0 | P84: 0.16 | Q84: =(M84+O84)*P84 -> 6688 | R84: =M84+O84+Q84 -> 48488 | S84: =INDEX('Glosario Partidas'!$M$8:$M$10,MATCH(BD!K84,'Glosario Partidas'!$L$8:$L$10,0)) -> 1 | T84: =R84*S84 -> 48488 | U84: ########### | V84: PARAMETRICO
... B129: Vidrios_Y_Canceles | C129: Puertas de Vidrio | D129: Baño 5 | E129: TORRE 1 | F129: N1R | G129: DEPTO 01 | H129: ALUMILUX | I129: M2 | J129: 1 | K129: MXN | L129: 68179 | M129: =J129*L129 -> 68179 | N129: 0 | O129: =M129*N129 -> 0 | P129: 0.16 | Q129: =(M129+O129)*P129 -> 10908.64 | R129: =M129+O129+Q129 -> 79087.64 | S129: =INDEX('Glosario Partidas'!$M$8:$M$10,MATCH(BD!K129,'Glosario Partidas'!$L$8:$L$10,0)) -> 1 | T129: =R129*S129 -> 79087.64 | U129: ########### | V129: PARAMETRICO
B130: Cocinas | C130: Cocina Principal | D130: S/D | E130: TORRE 1 | F130: PB | G130: DEPTO 01 | H130: DIECI | I130: Lote | J130: 1 | K130: EUR | L130: =24000+(24000*0.3)+(24000*0.15) -> 34800 | M130: =J130*L130 -> 34800 | N130: 0 | O130: =M130*N130 -> 0 | P130: 0.16 | Q130: =(M130+O130)*P130 -> 5568 | R130: =M130+O130+Q130 -> 40368 | S130: =INDEX('Glosario Partidas'!$M$8:$M$10,MATCH(BD!K130,'Glosario Partidas'!$L$8:$L$10,0)) -> 22 | T130: =R130*S130 -> 888096 | U130: CON INSTALACION E IMPORTACION | V130: PPTO
B131: Cocinas | C131: Cocina Principal | D131: S/D | E131: TORRE 1 | F131: N1 | G131: DEPTO 01 | H131: DIECI | I131: Lote | J131: 1 | K131: EUR | L131: =24000+(24000*0.3)+(24000*0.15) -> 34800 | M131: =J131*L131 -> 34800 | N131: 0 | O131: =M131*N131 -> 0 | P131: 0.16 | Q131: =(M131+O131)*P131 -> 5568 | R131: =M131+O131+Q131 -> 40368 | S131: =INDEX('Glosario Partidas'!$M$8:$M$10,MATCH(BD!K131,'Glosario Partidas'!$L$8:$L$10,0)) -> 22 | T131: =R131*S131 -> 888096 | U131: CON INSTALACION E IMPORTACION | V131: PPTO
B132: Cocinas | C132: Cocina Principal | D132: S/D | E132: TORRE 1 | F132: N1R | G132: DEPTO 01 | H132: DIECI | I132: Lote | J132: 0 | K132: EUR | L132: =35000+(35000*0.3)+(35000*0.05) -> 47250 | M132: =J132*L132 -> 0 | N132: 0 | O132: =M132*N132 -> 0 | P132: 0.16 | Q132: =(M132+O132)*P132 -> 0 | R132: =M132+O132+Q132 -> 0 | S132: =INDEX('Glosario Partidas'!$M$8:$M$10,MATCH(BD!K132,'Glosario Partidas'!$L$8:$L$10,0)) -> 22 | T132: =R132*S132 -> 0 | U132: CON INSTALACION E IMPORTACION | V132: PPTO
B133: Cocinas | C133: Cocina Exterior | D133: S/D | E133: TORRE 1 | F133: PB | G133: DEPTO 01 | H133: DIECI | I133: Lote | J133: 1 | K133: EUR | L133: =20000+(20000*0.3)+(20000*0.15) -> 29000 | M133: =J133*L133 -> 29000 | N133: 0 | O133: =M133*N133 -> 0 | P133: 0.16 | Q133: =(M133+O133)*P133 -> 4640 | R133: =M133+O133+Q133 -> 33640 | S133: =INDEX('Glosario Partidas'!$M$8:$M$10,MATCH(BD!K133,'Glosario Partidas'!$L$8:$L$10,0)) -> 22 | T133: =R133*S133 -> 740080 | U133: CON INSTALACION E IMPORTACION | V133: PPTO
B134: Cocinas | C134: Cocina Exterior | D134: S/D | E134: TORRE 1 | F134: N1 | G134: DEPTO 01 | H134: DIECI | I134: Lote | J134: 0 | K134: EUR | L134: =30360+(30360*0.3)+(30360*0.05) -> 40986 | M134: =J134*L134 -> 0 | N134: 0 | O134: =M134*N134 -> 0 | P134: 0.16 | Q134: =(M134+O134)*P134 -> 0 | R134: =M134+O134+Q134 -> 0 | S134: =INDEX('Glosario Partidas'!$M$8:$M$10,MATCH(BD!K134,'Glosario Partidas'!$L$8:$L$10,0)) -> 22 | T134: =R134*S134 -> 0 | U134: CON INSTALACION E IMPORTACION | V134: PPTO
B135: Cocinas | C135: Cocina Exterior | D135: S/D | E135: TORRE 1 | F135: N1R | G135: DEPTO 01 | H135: DIECI | I135: Lote | J135: 1 | K135: EUR | L135: =33500+(33500*0.3)+(33500*0.15) -> 48575 | M135: =J135*L135 -> 48575 | N135: 0 | O135: =M135*N135 -> 0 | P135: 0.16 | Q135: =(M135+O135)*P135 -> 7772 | R135: =M135+O135+Q135 -> 56347 | S135: =INDEX('Glosario Partidas'!$M$8:$M$10,MATCH(BD!K135,'Glosario Partidas'!$L$8:$L$10,0)) -> 22 | T135: =R135*S135 -> 1239634 | U135: CON INSTALACION E IMPORTACION | V135: PPTO
B136: Cocinas | C136: Equipos de Cocina Principal | D136: Subzero Refrigerador 91Cm Panelable | E136: TORRE 1 | F136: PB | G136: DEPTO 01 | H136: HOMEA | I136: PZA | J136: 1 | K136: USD | L136: 14921 | M136: =J136*L136 -> 14921 | N136: 0 | O136: =M136*N136 -> 0 | P136: 0.16 | Q136: =(M136+O136)*P136 -> 2387.36 | R136: =M136+O136+Q136 -> 17308.36 | S136: =INDEX('Glosario Partidas'!$M$8:$M$10,MATCH(BD!K136,'Glosario Partidas'!$L$8:$L$10,0)) -> 17.5 | T136: =R136*S136 -> 302896.3 | U136: ########### | V136: PPTO
B137: Cocinas | C137: Equipos de Cocina Principal | D137: Subzero Jaladera Tubular Acero Inox | E137: TORRE 1 | F137: PB | G137: DEPTO 01 | H137: HOMEA | I137: PZA | J137: 3 | K137: USD | L137: 254 | M137: =J137*L137 -> 762 | N137: 0 | O137: =M137*N137 -> 0 | P137: 0.16 | Q137: =(M137+O137)*P137 -> 121.92 | R137: =M137+O137+Q137 -> 883.92 | S137: =INDEX('Glosario Partidas'!$M$8:$M$10,MATCH(BD!K137,'Glosario Partidas'!$L$8:$L$10,0)) -> 17.5 | T137: =R137*S137 -> 15468.6 | U137: ########### | V137: PPTO
B138: Cocinas | C138: Equipos de Cocina Principal | D138: Subzero Cava Vino 60Cm Panelable 42 Bote | E138: TORRE 1 | F138: PB | G138: DEPTO 01 | H138: HOMEA | I138: PZA | J138: 1 | K138: USD | L138: 5843 | M138: =J138*L138 -> 5843 | N138: 0 | O138: =M138*N138 -> 0 | P138: 0.16 | Q138: =(M138+O138)*P138 -> 934.88 | R138: =M138+O138+Q138 -> 6777.88 | S138: =INDEX('Glosario Partidas'!$M$8:$M$10,MATCH(BD!K138,'Glosario Partidas'!$L$8:$L$10,0)) -> 17.5 | T138: =R138*S138 -> 118612.9 | U138: ########### | V138: PPTO
B139: Cocinas | C139: Equipos de Cocina Principal | D139: Subzero Manija Tubular 52Cm Acero Inox | E139: TORRE 1 | F139: PB | G139: DEPTO 01 | H139: HOMEA | I139: PZA | J139: 1 | K139: USD | L139: 242 | M139: =J139*L139 -> 242 | N139: 0 | O139: =M139*N139 -> 0 | P139: 0.16 | Q139: =(M139+O139)*P139 -> 38.72 | R139: =M139+O139+Q139 -> 280.72 | S139: =INDEX('Glosario Partidas'!$M$8:$M$10,MATCH(BD!K139,'Glosario Partidas'!$L$8:$L$10,0)) -> 17.5 | T139: =R139*S139 -> 4912.6 | U139: ########### | V139: PPTO
B140: Cocinas | C140: Equipos de Cocina Principal | D140: Scotsman Maquina De Hielo Scotsman 15" C | E140: TORRE 1 | F140: PB | G140: DEPTO 01 | H140: HOMEA | I140: PZA | J140: 1 | K140: USD | L140: 5420 | M140: =J140*L140 -> 5420 | N140: 0 | O140: =M140*N140 -> 0 | P140: 0.16 | Q140: =(M140+O140)*P140 -> 867.2 | R140: =M140+O140+Q140 -> 6287.2 | S140: =INDEX('Glosario Partidas'!$M$8:$M$10,MATCH(BD!K140,'Glosario Partidas'!$L$8:$L$10,0)) -> 17.5 | T140: =R140*S140 -> 110026 | U140: ########### | V140: PPTO
B141: Cocinas | C141: Equipos de Cocina Principal | D141: Wolf Parrilla 106Cm Inox Gas Lp Exterior | E141: TORRE 1 | F141: PB | G141: DEPTO 01 | H141: HOMEA | I141: PZA | J141: 1 | K141: USD | L141: 10265 | M141: =J141*L141 -> 10265 | N141: 0 | O141: =M141*N141 -> 0 | P141: 0.16 | Q141: =(M141+O141)*P141 -> 1642.4 | R141: =M141+O141+Q141 -> 11907.4 | S141: =INDEX('Glosario Partidas'!$M$8:$M$10,MATCH(BD!K141,'Glosario Partidas'!$L$8:$L$10,0)) -> 17.5 | T141: =R141*S141 -> 208379.5 | U141: ########### | V141: PPTO
B142: Cocinas | C142: Equipos de Cocina Principal | D142: Subzero Refrigerador 60Cm Inox Bajo Most | E142: TORRE 1 | F142: PB | G142: DEPTO 01 | H142: HOMEA | I142: PZA | J142: 1 | K142: USD | L142: 5085 | M142: =J142*L142 -> 5085 | N142: 0 | O142: =M142*N142 -> 0 | P142: 0.16 | Q142: =(M142+O142)*P142 -> 813.6 | R142: =M142+O142+Q142 -> 5898.6 | S142: =INDEX('Glosario Partidas'!$M$8:$M$10,MATCH(BD!K142,'Glosario Partidas'!$L$8:$L$10,0)) -> 17.5 | T142: =R142*S142 -> 103225.5 | U142: ########### | V142: PPTO
B143: Cocinas | C143: Equipos de Cocina Principal | D143: Blanco Tarja 69Cm Antracita Electrica | E143: TORRE 1 | F143: PB | G143: DEPTO 01 | H143: HOMEA | I143: PZA | J143: 1 | K143: USD | L143: 623 | M143: =J143*L143 -> 623 | N143: 0 | O143: =M143*N143 -> 0 | P143: 0.16 | Q143: =(M143+O143)*P143 -> 99.68 | R143: =M143+O143+Q143 -> 722.68 | S143: =INDEX('Glosario Partidas'!$M$8:$M$10,MATCH(BD!K143,'Glosario Partidas'!$L$8:$L$10,0)) -> 17.5 | T143: =R143*S143 -> 12646.9 | U143: ########### | V143: PPTO
B144: Cocinas | C144: Equipos de Cocina Principal | D144: Blanco Monomando Extraible Acero Inoxida | E144: TORRE 1 | F144: PB | G144: DEPTO 01 | H144: HOMEA | I144: PZA | J144: 1 | K144: USD | L144: 580 | M144: =J144*L144 -> 580 | N144: 0 | O144: =M144*N144 -> 0 | P144: 0.16 | Q144: =(M144+O144)*P144 -> 92.8 | R144: =M144+O144+Q144 -> 672.8 | S144: =INDEX('Glosario Partidas'!$M$8:$M$10,MATCH(BD!K144,'Glosario Partidas'!$L$8:$L$10,0)) -> 17.5 | T144: =R144*S144 -> 11774 | U144: ########### | V144: PPTO
B145: Cocinas | C145: Equipos de Cocina Principal | D145: Cove Lavavajillas 60Cm Panelable | E145: TORRE 1 | F145: PB | G145: DEPTO 01 | H145: HOMEA | I145: PZA | J145: 1 | K145: USD | L145: 3800 | M145: =J145*L145 -> 3800 | N145: 0 | O145: =M145*N145 -> 0 | P145: 0.16 | Q145: =(M145+O145)*P145 -> 608 | R145: =M145+O145+Q145 -> 4408 | S145: =INDEX('Glosario Partidas'!$M$8:$M$10,MATCH(BD!K145,'Glosario Partidas'!$L$8:$L$10,0)) -> 17.5 | T145: =R145*S145 -> 77140 | U145: ########### | V145: PPTO
B146: Cocinas | C146: Equipos de Cocina Principal | D146: Blanco Tarja Doble 91Cm Acero Inoxidable | E146: TORRE 1 | F146: PB | G146: DEPTO 01 | H146: HOMEA | I146: PZA | J146: 1 | K146: USD | L146: 1389 | M146: =J146*L146 -> 1389 | N146: 0 | O146: =M146*N146 -> 0 | P146: 0.16 | Q146: =(M146+O146)*P146 -> 222.24 | R146: =M146+O146+Q146 -> 1611.24 | S146: =INDEX('Glosario Partidas'!$M$8:$M$10,MATCH(BD!K146,'Glosario Partidas'!$L$8:$L$10,0)) -> 17.5 | T146: =R146*S146 -> 28196.7 | U146: ########### | V146: PPTO
B147: Cocinas | C147: Equipos de Cocina Principal | D147: Blanco Contracanasta Para Triturador | E147: TORRE 1 | F147: PB | G147: DEPTO 01 | H147: HOMEA | I147: PZA | J147: 3 | K147: USD | L147: 128 | M147: =J147*L147 -> 384 | N147: 0 | O147: =M147*N147 -> 0 | P147: 0.16 | Q147: =(M147+O147)*P147 -> 61.44 | R147: =M147+O147+Q147 -> 445.44 | S147: =INDEX('Glosario Partidas'!$M$8:$M$10,MATCH(BD!K147,'Glosario Partidas'!$L$8:$L$10,0)) -> 17.5 | T147: =R147*S147 -> 7795.2 | U147: ########### | V147: PPTO
... B308: Carpinterias | C308: Lavanderia | D308: Mueble Lavanderia | E308: TORRE 1 | F308: N1R | G308: DEPTO 01 | H308: HAMUI | I308: PZA | J308: 1 | K308: MXN | L308: 88057 | M308: =J308*L308 -> 88057 | N308: 0 | O308: =M308*N308 -> 0 | P308: 0.16 | Q308: =(M308+O308)*P308 -> 14089.12 | R308: =M308+O308+Q308 -> 102146.12 | S308: =INDEX('Glosario Partidas'!$M$8:$M$10,MATCH(BD!K308,'Glosario Partidas'!$L$8:$L$10,0)) -> 1 | T308: =R308*S308 -> 102146.12 | U308: REVISAR | V308: PPTO
B309: Carpinterias | C309: Pergolas | D309: S/D | E309: TORRE 1 | F309: PB | G309: DEPTO 01 | H309: NA | I309: PZA | J309: 1 | K309: MXN | L309: =3900000/4 -> 975000 | M309: =J309*L309 -> 975000 | N309: 0 | O309: =M309*N309 -> 0 | P309: 0.16 | Q309: =(M309+O309)*P309 -> 156000 | R309: =M309+O309+Q309 -> 1131000 | S309: =INDEX('Glosario Partidas'!$M$8:$M$10,MATCH(BD!K309,'Glosario Partidas'!$L$8:$L$10,0)) -> 1 | T309: =R309*S309 -> 1131000 | U309: REVISAR | V309: PPTO
B310: Carpinterias | C310: Pergolas | D310: S/D | E310: TORRE 1 | F310: N1 | G310: DEPTO 01 | H310: NA | I310: PZA | J310: 1 | K310: MXN | L310: =975000/2 -> 487500 | M310: =J310*L310 -> 487500 | N310: 0 | O310: =M310*N310 -> 0 | P310: 0.16 | Q310: =(M310+O310)*P310 -> 78000 | R310: =M310+O310+Q310 -> 565500 | S310: =INDEX('Glosario Partidas'!$M$8:$M$10,MATCH(BD!K310,'Glosario Partidas'!$L$8:$L$10,0)) -> 1 | T310: =R310*S310 -> 565500 | U310: REVISAR | V310: PPTO
B311: Carpinterias | C311: Pergolas | D311: S/D | E311: TORRE 1 | F311: N1R | G311: DEPTO 01 | H311: NA | I311: PZA | J311: 1 | K311: MXN | L311: =975000/2 -> 487500 | M311: =J311*L311 -> 487500 | N311: 0 | O311: =M311*N311 -> 0 | P311: 0.16 | Q311: =(M311+O311)*P311 -> 78000 | R311: =M311+O311+Q311 -> 565500 | S311: =INDEX('Glosario Partidas'!$M$8:$M$10,MATCH(BD!K311,'Glosario Partidas'!$L$8:$L$10,0)) -> 1 | T311: =R311*S311 -> 565500 | U311: REVISAR | V311: PPTO
B312: Jardineria_Y_Riego | C312: Jardineria | D312: S/D | E312: TORRE 1 | F312: S/D | G312: S/D | H312: NA | I312: M2 | J312: =1754/2 -> 877 | K312: MXN | L312: 1623.62 | M312: =J312*L312 -> 1423914.7 | N312: 0 | O312: =M312*N312 -> 0 | P312: 0.16 | Q312: =(M312+O312)*P312 -> 227826.36 | R312: =M312+O312+Q312 -> 1651741.1 | S312: =INDEX('Glosario Partidas'!$M$8:$M$10,MATCH(BD!K312,'Glosario Partidas'!$L$8:$L$10,0)) -> 1 | T312: =R312*S312 -> 1651741.1 | U312: ########### | V312: PARAMETRICO | W312: PARAMETRICO UNA TORRE
B313: Jardineria_Y_Riego | C313: Sistema De Riego | D313: S/D | E313: TORRE 1 | F313: S/D | G313: S/D | H313: NA | I313: M2 | J313: 1 | K313: MXN | L313: 450000 | M313: =J313*L313 -> 450000 | N313: 0 | O313: =M313*N313 -> 0 | P313: 0.16 | Q313: =(M313+O313)*P313 -> 72000 | R313: =M313+O313+Q313 -> 522000 | S313: =INDEX('Glosario Partidas'!$M$8:$M$10,MATCH(BD!K313,'Glosario Partidas'!$L$8:$L$10,0)) -> 1 | T313: =R313*S313 -> 522000 | U313: ########### | V313: PARAMETRICO | W313: PARAMETRICO UNA TORRE
B314: Elevador | C314: Elevador | D314: S/D | E314: TORRE 1 | F314: S/D | G314: S/D | H314: NA | I314: Lote | J314: 1 | K314: MXN | L314: 900000 | M314: =J314*L314 -> 900000 | N314: 0 | O314: =M314*N314 -> 0 | P314: 0 | Q314: =(M314+O314)*P314 -> 0 | R314: =M314+O314+Q314 -> 900000 | S314: =INDEX('Glosario Partidas'!$M$8:$M$10,MATCH(BD!K314,'Glosario Partidas'!$L$8:$L$10,0)) -> 1 | T314: =R314*S314 -> 900000 | U314: ########### | V314: PPTO
B315: Exteriores | C315: Piedra | D315: S/D | E315: TORRE 1 | F315: S/D | G315: S/D | H315: NA | I315: M2 | J315: =1349/2 -> 674.5 | K315: MXN | L315: 3221.7 | M315: =J315*L315 -> 2173036.6 | N315: 0 | O315: =M315*N315 -> 0 | P315: 0.16 | Q315: =(M315+O315)*P315 -> 347685.86 | R315: =M315+O315+Q315 -> 2520722.5 | S315: =INDEX('Glosario Partidas'!$M$8:$M$10,MATCH(BD!K315,'Glosario Partidas'!$L$8:$L$10,0)) -> 1 | T315: =R315*S315 -> 2520722.5 | U315: ########### | V315: PARAMETRICO | W315: PARAMETRICO UNA TORRE
B316: Exteriores | C316: Garage | D316: S/D | E316: TORRE 1 | F316: S/D | G316: S/D | H316: NA | I316: M2 | J316: 1 | K316: MXN | L316: 5907440 | M316: =J316*L316 -> 5907440 | N316: 0 | O316: =M316*N316 -> 0 | P316: 0.16 | Q316: =(M316+O316)*P316 -> 945190.4 | R316: =M316+O316+Q316 -> 6852630.4 | S316: =INDEX('Glosario Partidas'!$M$8:$M$10,MATCH(BD!K316,'Glosario Partidas'!$L$8:$L$10,0)) -> 1 | T316: =R316*S316 -> 6852630.4 | U316: REVISAR | V316: PARAMETRICO | W316: PARAMETRICO UNA TORRE
B317: Albañileria_Y_Bardas | C317: Pisos | D317: Concreto Lavado Con Agregado Impermeabilizante_7 | E317: TORRE 1 | F317: Concreto Lavado Con Agregado Impermeabilizante_7 | G317: DEPTO 02 | H317: NA | I317: M2 | J317: 0 | K317: MXN | L317: 905.769 | M317: =J317*L317 -> 0 | N317: 0 | O317: =M317*N317 -> 0 | P317: 0.16 | Q317: =(M317+O317)*P317 -> 0 | R317: =M317+O317+Q317 -> 0 | S317: =INDEX('Glosario Partidas'!$M$8:$M$10,MATCH(BD!K317,'Glosario Partidas'!$L$8:$L$10,0)) -> 1 | T317: =R317*S317 -> 0 | U317: ########### | V317: PARAMETRICO
B318: Albañileria_Y_Bardas | C318: Muros | D318: Muros De Piedra Braza | E318: TORRE 1 | F318: Muros De Piedra Braza | G318: DEPTO 02 | H318: NA | I318: M2 | J318: 0 | K318: MXN | L318: 3593.941 | M318: =J318*L318 -> 0 | N318: 0 | O318: =M318*N318 -> 0 | P318: 0.16 | Q318: =(M318+O318)*P318 -> 0 | R318: =M318+O318+Q318 -> 0 | S318: =INDEX('Glosario Partidas'!$M$8:$M$10,MATCH(BD!K318,'Glosario Partidas'!$L$8:$L$10,0)) -> 1 | T318: =R318*S318 -> 0 | U318: ########### | V318: PARAMETRICO
B319: Albañileria_Y_Bardas | C319: Muros | D319: Sillares Con Piedra De La Region | E319: TORRE 1 | F319: Sillares Con Piedra De La Region | G319: DEPTO 02 | H319: NA | I319: M2 | J319: 0 | K319: MXN | L319: 3593.941 | M319: =J319*L319 -> 0 | N319: 0 | O319: =M319*N319 -> 0 | P319: 0.16 | Q319: =(M319+O319)*P319 -> 0 | R319: =M319+O319+Q319 -> 0 | S319: =INDEX('Glosario Partidas'!$M$8:$M$10,MATCH(BD!K319,'Glosario Partidas'!$L$8:$L$10,0)) -> 1 | T319: =R319*S319 -> 0 | U319: ########### | V319: PARAMETRICO
B320: Albañileria_Y_Bardas | C320: Acarreos | D320: Acarreos Verticales / Horizontales Y Traslados | E320: TORRE 1 | F320: Acarreos Verticales / Horizontales Y Traslados | G320: DEPTO 02 | H320: NA | I320: Semana | J320: 0 | K320: MXN | L320: 12880 | M320: =J320*L320 -> 0 | N320: 0 | O320: =M320*N320 -> 0 | P320: 0.16 | Q320: =(M320+O320)*P320 -> 0 | R320: =M320+O320+Q320 -> 0 | S320: =INDEX('Glosario Partidas'!$M$8:$M$10,MATCH(BD!K320,'Glosario Partidas'!$L$8:$L$10,0)) -> 1 | T320: =R320*S320 -> 0 | U320: ########### | V320: PARAMETRICO
B321: Acabados | C321: Yeso Según Especificacion | D321: S/D | E321: TORRE 1 | F321: S/D | G321: DEPTO 02 | H321: NA | I321: M2 | J321: 0 | K321: MXN | L321: 175 | M321: =J321*L321 -> 0 | N321: 0 | O321: =M321*N321 -> 0 | P321: 0.16 | Q321: =(M321+O321)*P321 -> 0 | R321: =M321+O321+Q321 -> 0 | S321: =INDEX('Glosario Partidas'!$M$8:$M$10,MATCH(BD!K321,'Glosario Partidas'!$L$8:$L$10,0)) -> 1 | T321: =R321*S321 -> 0 | U321: ########### | V321: PARAMETRICO
B322: Acabados | C322: Plafon Tablaroca | D322: S/D | E322: TORRE 1 | F322: S/D | G322: DEPTO 02 | H322: NA | I322: M2 | J322: 0 | K322: MXN | L322: 1066 | M322: =J322*L322 -> 0 | N322: 0 | O322: =M322*N322 -> 0 | P322: 0.16 | Q322: =(M322+O322)*P322 -> 0 | R322: =M322+O322+Q322 -> 0 | S322: =INDEX('Glosario Partidas'!$M$8:$M$10,MATCH(BD!K322,'Glosario Partidas'!$L$8:$L$10,0)) -> 1 | T322: =R322*S322 -> 0 | U322: ########### | V322: PARAMETRICO
B323: Acabados | C323: Pasta En Plafon | D323: S/D | E323: TORRE 1 | F323: S/D | G323: DEPTO 02 | H323: NA | I323: M2 | J323: 0 | K323: MXN | L323: 494 | M323: =J323*L323 -> 0 | N323: 0 | O323: =M323*N323 -> 0 | P323: 0.16 | Q323: =(M323+O323)*P323 -> 0 | R323: =M323+O323+Q323 -> 0 | S323: =INDEX('Glosario Partidas'!$M$8:$M$10,MATCH(BD!K323,'Glosario Partidas'!$L$8:$L$10,0)) -> 1 | T323: =R323*S323 -> 0 | U323: ########### | V323: PARAMETRICO
B324: Acabados | C324: Plafon Durock | D324: S/D | E324: TORRE 1 | F324: S/D | G324: DEPTO 02 | H324: NA | I324: M2 | J324: 0 | K324: MXN | L324: 1279.2 | M324: =J324*L324 -> 0 | N324: 0 | O324: =M324*N324 -> 0 | P324: 0.16 | Q324: =(M324+O324)*P324 -> 0 | R324: =M324+O324+Q324 -> 0 | S324: =INDEX('Glosario Partidas'!$M$8:$M$10,MATCH(BD!K324,'Glosario Partidas'!$L$8:$L$10,0)) -> 1 | T324: =R324*S324 -> 0 | U324: ########### | V324: PARAMETRICO
B325: Acabados | C325: Suministro_Y_Colocacion_De_Ceramica | D325: Piso | E325: TORRE 1 | F325: Piso | G325: DEPTO 02 | H325: NA | I325: M2 | J325: 0 | K325: MXN | L325: 1050 | M325: =J325*L325 -> 0 | N325: 0 | O325: =M325*N325 -> 0 | P325: 0.16 | Q325: =(M325+O325)*P325 -> 0 | R325: =M325+O325+Q325 -> 0 | S325: =INDEX('Glosario Partidas'!$M$8:$M$10,MATCH(BD!K325,'Glosario Partidas'!$L$8:$L$10,0)) -> 1 | T325: =R325*S325 -> 0 | U325: ########### | V325: PARAMETRICO
B326: Acabados | C326: Suministro_Y_Colocacion_De_Ceramica | D326: Muros | E326: TORRE 1 | F326: Muros | G326: DEPTO 02 | H326: NA | I326: M2 | J326: 0 | K326: MXN | L326: 1000 | M326: =J326*L326 -> 0 | N326: 0 | O326: =M326*N326 -> 0 | P326: 0.16 | Q326: =(M326+O326)*P326 -> 0 | R326: =M326+O326+Q326 -> 0 | S326: =INDEX('Glosario Partidas'!$M$8:$M$10,MATCH(BD!K326,'Glosario Partidas'!$L$8:$L$10,0)) -> 1 | T326: =R326*S326 -> 0 | U326: ########### | V326: PARAMETRICO
B327: Acabados | C327: Plafon_Acustico | D327: Muros | E327: TORRE 1 | F327: Muros | G327: DEPTO 02 | H327: NA | I327: M2 | J327: 0 | K327: MXN | L327: 680 | M327: =J327*L327 -> 0 | N327: 0 | O327: =M327*N327 -> 0 | P327: 0.16 | Q327: =(M327+O327)*P327 -> 0 | R327: =M327+O327+Q327 -> 0 | S327: =INDEX('Glosario Partidas'!$M$8:$M$10,MATCH(BD!K327,'Glosario Partidas'!$L$8:$L$10,0)) -> 1 | T327: =R327*S327 -> 0 | U327: ########### | V327: PARAMETRICO
B328: Acabados | C328: Plafon_Acustico | D328: Plafon | E328: TORRE 1 | F328: Plafon | G328: DEPTO 02 | H328: NA | I328: M2 | J328: 0 | K328: MXN | L328: 884 | M328: =J328*L328 -> 0 | N328: 0 | O328: =M328*N328 -> 0 | P328: 0.16 | Q328: =(M328+O328)*P328 -> 0 | R328: =M328+O328+Q328 -> 0 | S328: =INDEX('Glosario Partidas'!$M$8:$M$10,MATCH(BD!K328,'Glosario Partidas'!$L$8:$L$10,0)) -> 1 | T328: =R328*S328 -> 0 | U328: ########### | V328: PARAMETRICO
B329: Herreria | C329: Pintura Herreria. Primario / Acabado | D329: S/D | E329: TORRE 1 | F329: S/D | G329: DEPTO 02 | H329: NA | I329: Lote | J329: 0 | K329: MXN | L329: 592338.6 | M329: =J329*L329 -> 0 | N329: 0 | O329: =M329*N329 -> 0 | P329: 0.16 | Q329: =(M329+O329)*P329 -> 0 | R329: =M329+O329+Q329 -> 0 | S329: =INDEX('Glosario Partidas'!$M$8:$M$10,MATCH(BD!K329,'Glosario Partidas'!$L$8:$L$10,0)) -> 1 | T329: =R329*S329 -> 0 | U329: ########### | V329: PARAMETRICO
B330: Instalaciones_Electricas | C330: Instalaciones Electricas | D330: S/D | E330: TORRE 1 | F330: PB | G330: DEPTO 02 | H330: NA | I330: M2 | J330: =323.83*1.1 -> 356.213 | K330: MXN | L330: 4500 | M330: =J330*L330 -> 1602958.5 | N330: 0 | O330: =M330*N330 -> 0 | P330: 0.16 | Q330: =(M330+O330)*P330 -> 256473.36 | R330: =M330+O330+Q330 -> 1859431.9 | S330: =INDEX('Glosario Partidas'!$M$8:$M$10,MATCH(BD!K330,'Glosario Partidas'!$L$8:$L$10,0)) -> 1 | T330: =R330*S330 -> 1859431.9 | U330: ########### | V330: PARAMETRICO
B331: Instalaciones_Electricas | C331: Instalaciones Electricas | D331: S/D | E331: TORRE 1 | F331: N1 y N1R | G331: DEPTO 02 | H331: NA | I331: M2 | J331: =404.37*1.1 -> 444.807 | K331: MXN | L331: 4500 | M331: =J331*L331 -> 2001631.5 | N331: 0 | O331: =M331*N331 -> 0 | P331: 0.16 | Q331: =(M331+O331)*P331 -> 320261.04 | R331: =M331+O331+Q331 -> 2321892.5 | S331: =INDEX('Glosario Partidas'!$M$8:$M$10,MATCH(BD!K331,'Glosario Partidas'!$L$8:$L$10,0)) -> 1 | T331: =R331*S331 -> 2321892.5 | U331: ########### | V331: PARAMETRICO
B332: Instalaciones_Hidraulicas | C332: Instalaciones Hidrosanitarias | D332: S/D | E332: TORRE 1 | F332: PB | G332: DEPTO 02 | H332: NA | I332: M2 | J332: =323.83*1.1 -> 356.213 | K332: MXN | L332: 4500 | M332: =J332*L332 -> 1602958.5 | N332: 0 | O332: =M332*N332 -> 0 | P332: 0.16 | Q332: =(M332+O332)*P332 -> 256473.36 | R332: =M332+O332+Q332 -> 1859431.9 | S332: =INDEX('Glosario Partidas'!$M$8:$M$10,MATCH(BD!K332,'Glosario Partidas'!$L$8:$L$10,0)) -> 1 | T332: =R332*S332 -> 1859431.9 | U332: ########### | V332: PARAMETRICO
B333: Instalaciones_Hidraulicas | C333: Instalaciones Hidrosanitarias | D333: S/D | E333: TORRE 1 | F333: N1 y N1R | G333: DEPTO 02 | H333: NA | I333: M2 | J333: =404.37*1.1 -> 444.807 | K333: MXN | L333: 4500 | M333: =J333*L333 -> 2001631.5 | N333: 0 | O333: =M333*N333 -> 0 | P333: 0.16 | Q333: =(M333+O333)*P333 -> 320261.04 | R333: =M333+O333+Q333 -> 2321892.5 | S333: =INDEX('Glosario Partidas'!$M$8:$M$10,MATCH(BD!K333,'Glosario Partidas'!$L$8:$L$10,0)) -> 1 | T333: =R333*S333 -> 2321892.5 | U333: ########### | V333: PARAMETRICO
B334: Albercas | C334: Alberca Completa | D334: S/D | E334: TORRE 1 | F334: PB | G334: DEPTO 02 | H334: AQUA CONCEPTS | I334: M2 | J334: 84.16 | K334: MXN | L334: 40000 | M334: =J334*L334 -> 3366400 | N334: 0 | O334: =M334*N334 -> 0 | P334: 0.16 | Q334: =(M334+O334)*P334 -> 538624 | R334: =M334+O334+Q334 -> 3905024 | S334: =INDEX('Glosario Partidas'!$M$8:$M$10,MATCH(BD!K334,'Glosario Partidas'!$L$8:$L$10,0)) -> 1 | T334: =R334*S334 -> 3905024 | U334: Incluye desde impermiabilizacion, hasta acabados y funcionamiento | V334: PARAMETRICO
...

Sheet PU >>

Sheet Arquitectura
A1: ⬅ Resumen PU | B1: CATEGORÍA | C1: CONCEPTO | D1: DETALLE | E1: TORRE | F1: PISO | G1: DEPTO | H1: PROVEEDOR | I1: UNIDAD | J1: CANTIDAD | K1: MONEDA | L1: $ UNITARIO | M1: IMPORTE SIN IVA | N1: SOBRECOSTO | O1: TOTAL SOBRECOSTO | P1: % IVA | Q1: $ IVA | R1: IMPORTE TOTAL | S1: T.C | T1: TOTAL MXN | U1: NOTAS | V1: PARAMETRICO/PPTO | W1: Contratado/No Contratado | X1: 5 Recamara | AB1: CONTRATADO | AC1: NO CONTRATADO
B2: Arquitectura | C2: Supervision Diseño Iluminacion | D2: S/D | F2: S/D | G2: S/D | H2: NA | I2: Lote | J2: 0 | K2: MXN | L2: 0 | M2: =J2*L2 -> 0 | N2: 0 | O2: =M2*N2 -> 0 | P2: 0 | Q2: =(M2+O2)*P2 -> 0 | R2: =M2+O2+Q2 -> 0 | S2: =INDEX('Glosario Partidas'!$M$8:$M$10,MATCH(K2,'Glosario Partidas'!$L$8:$L$10,0)) -> 1 | T2: =R2*S2 -> 0 | U2: ########### | V2: PARAMETRICO | W2: No Contratado
B3: Arquitectura | C3: Diseño Arquitectonico | D3: S/D | F3: S/D | G3: S/D | H3: AOR | I3: Lote | J3: 1 | K3: MXN | L3: 2700000 | M3: =J3*L3 -> 2700000 | N3: 0 | O3: =M3*N3 -> 0 | P3: 0 | Q3: =(M3+O3)*P3 -> 0 | R3: =M3+O3+Q3 -> 2700000 | S3: =INDEX('Glosario Partidas'!$M$8:$M$10,MATCH(K3,'Glosario Partidas'!$L$8:$L$10,0)) -> 1 | T3: =R3*S3 -> 2700000 | U3: ########### | V3: PPTO | W3: Contratado
B4: Arquitectura | C4: Diseño Jardineria | D4: S/D | F4: S/D | G4: S/D | H4: NA | I4: Lote | J4: 1 | K4: MXN | L4: 140000 | M4: =J4*L4 -> 140000 | N4: 0 | O4: =M4*N4 -> 0 | P4: 0.16 | Q4: =(M4+O4)*P4 -> 22400 | R4: =M4+O4+Q4 -> 162400 | S4: =INDEX('Glosario Partidas'!$M$8:$M$10,MATCH(K4,'Glosario Partidas'!$L$8:$L$10,0)) -> 1 | T4: =R4*S4 -> 162400 | U4: ########### | V4: PPTO | W4: No Contratado
B5: Arquitectura | C5: Cuantificacion | D5: S/D | F5: S/D | G5: S/D | H5: M2 | I5: Lote | J5: 1 | K5: MXN | L5: 67000 | M5: =J5*L5 -> 67000 | N5: 0 | O5: =M5*N5 -> 0 | P5: 0 | Q5: =(M5+O5)*P5 -> 0 | R5: =M5+O5+Q5 -> 67000 | S5: =INDEX('Glosario Partidas'!$M$8:$M$10,MATCH(K5,'Glosario Partidas'!$L$8:$L$10,0)) -> 1 | T5: =R5*S5 -> 67000 | U5: ########### | V5: PPTO | W5: No Contratado
B6: Arquitectura | C6: Supervision Diseño Jardineria | D6: S/D | F6: S/D | G6: S/D | H6: NA | I6: Lote | J6: 0 | K6: MXN | L6: 0 | M6: =J6*L6 -> 0 | N6: 0 | O6: =M6*N6 -> 0 | P6: 0 | Q6: =(M6+O6)*P6 -> 0 | R6: =M6+O6+Q6 -> 0 | S6: =INDEX('Glosario Partidas'!$M$8:$M$10,MATCH(K6,'Glosario Partidas'!$L$8:$L$10,0)) -> 1 | T6: =R6*S6 -> 0 | U6: ########### | V6: PARAMETRICO | W6: No Contratado
B7: Total | T7: =SUM(T2:T6) -> 2929400 | AB7: =SUMIFS($T:$T,$W:$W,"Contratado") -> 2700000 | AC7: =SUMIFS($T:$T,$W:$W,"No Contratado") -> 229400

Sheet Ingenierias_Y_Topografia
A1: ⬅ Resumen PU | B1: CATEGORÍA | C1: CONCEPTO | D1: DETALLE | E1: TORRE | F1: PISO | G1: DEPTO | H1: PROVEEDOR | I1: UNIDAD | J1: CANTIDAD | K1: MONEDA | L1: $ UNITARIO | M1: IMPORTE SIN IVA | N1: SOBRECOSTO | O1: TOTAL SOBRECOSTO | P1: % IVA | Q1: $ IVA | R1: IMPORTE TOTAL | S1: T.C | T1: TOTAL MXN | U1: NOTAS | V1: PARAMETRICO/PPTO | W1: Contratado/No Contratado | X1: 5 Recamara | AB1: CONTRATADO | AC1: NO CONTRATADO
B2: Ingenierias_Y_Topografia | C2: Topografia Gestoria | D2: S/D | E2: TORRE 1 | F2: S/D | G2: S/D | H2: NA | I2: Lote | J2: 0 | K2: MXN | L2: 0 | M2: =J2*L2 -> 0 | N2: 0 | O2: =M2*N2 -> 0 | P2: 0 | Q2: =(M2+O2)*P2 -> 0 | R2: =M2+O2+Q2 -> 0 | S2: =INDEX('Glosario Partidas'!$M$8:$M$10,MATCH(K2,'Glosario Partidas'!$L$8:$L$10,0)) -> 1 | T2: =R2*S2 -> 0 | U2: ########### | V2: PARAMETRICO | W2: No Contratado
B3: Ingenierias_Y_Topografia | C3: Topografia Obra | D3: S/D | E3: TORRE 1 | F3: S/D | G3: S/D | H3: NA | I3: Semana | J3: 0 | K3: MXN | L3: 0 | M3: =J3*L3 -> 0 | N3: 0 | O3: =M3*N3 -> 0 | P3: 0 | Q3: =(M3+O3)*P3 -> 0 | R3: =M3+O3+Q3 -> 0 | S3: =INDEX('Glosario Partidas'!$M$8:$M$10,MATCH(K3,'Glosario Partidas'!$L$8:$L$10,0)) -> 1 | T3: =R3*S3 -> 0 | U3: ########### | V3: PARAMETRICO | W3: No Contratado
B4: Ingenierias_Y_Topografia | C4: Mecanica De Suelos | D4: S/D | E4: TORRE 1 | F4: S/D | G4: S/D | H4: ='Mecanica de Suelos PU'!H4 -> Samstordam | I4: Lote | J4: 1 | K4: MXN | L4: =SUMIFS('Mecanica de Suelos PU'!$M:$M,'Mecanica de Suelos PU'!$E:$E,Ingenierias_Y_Topografia!E4) -> 84217.5 | M4: =J4*L4 -> 84217.5 | N4: 0 | O4: =M4*N4 -> 0 | P4: 0.16 | Q4: =(M4+O4)*P4 -> 13474.8 | R4: =M4+O4+Q4 -> 97692.3 | S4: =INDEX('Glosario Partidas'!$M$8:$M$10,MATCH(K4,'Glosario Partidas'!$L$8:$L$10,0)) -> 1 | T4: =R4*S4 -> 97692.3 | U4: ########### | V4: PPTO | W4: Contratado
B5: Ingenierias_Y_Topografia | C5: Calculo Estructural | D5: S/D | E5: TORRE 1 | F5: S/D | G5: S/D | H5: ='Calculo Estructural PU'!H4 -> MyT | I5: Lote | J5: 1 | K5: MXN | L5: =SUMIFS('Calculo Estructural PU'!$M:$M,'Calculo Estructural PU'!$E:$E,Ingenierias_Y_Topografia!E5) -> 185000 | M5: =J5*L5 -> 185000 | N5: 0 | O5: =M5*N5 -> 0 | P5: 0.16 | Q5: =(M5+O5)*P5 -> 29600 | R5: =M5+O5+Q5 -> 214600 | S5: =INDEX('Glosario Partidas'!$M$8:$M$10,MATCH(K5,'Glosario Partidas'!$L$8:$L$10,0)) -> 1 | T5: =R5*S5 -> 214600 | U5: ########### | V5: PPTO | W5: Contratado
B6: Ingenierias_Y_Topografia | C6: Diseño HVAC | D6: S/D | E6: TORRE 1 | F6: S/D | G6: S/D | H6: ='Diseño HVAC PU'!H4 -> CYVS | I6: Lote | J6: 1 | K6: MXN | L6: =SUMIFS('Diseño HVAC PU'!$M:$M,'Diseño HVAC PU'!$E:$E,Ingenierias_Y_Topografia!E6) -> 65000 | M6: =J6*L6 -> 65000 | N6: 0 | O6: =M6*N6 -> 0 | P6: 0.16 | Q6: =(M6+O6)*P6 -> 10400 | R6: =M6+O6+Q6 -> 75400 | S6: =INDEX('Glosario Partidas'!$M$8:$M$10,MATCH(K6,'Glosario Partidas'!$L$8:$L$10,0)) -> 1 | T6: =R6*S6 -> 75400 | U6: ########### | V6: PPTO | W6: Contratado
B7: Ingenierias_Y_Topografia | C7: Diseño Alberca | D7: S/D | E7: TORRE 1 | F7: S/D | G7: S/D | H7: ='Diseño Albercas PU'!H4 -> AQUACONCEPTS | I7: Lote | J7: 1 | K7: MXN | L7: =SUMIFS('Diseño Albercas PU'!$M:$M,'Diseño Albercas PU'!$E:$E,Ingenierias_Y_Topografia!E7) -> 60000 | M7: =J7*L7 -> 60000 | N7: 0 | O7: =M7*N7 -> 0 | P7: 0.16 | Q7: =(M7+O7)*P7 -> 9600 | R7: =M7+O7+Q7 -> 69600 | S7: =INDEX('Glosario Partidas'!$M$8:$M$10,MATCH(K7,'Glosario Partidas'!$L$8:$L$10,0)) -> 1 | T7: =R7*S7 -> 69600 | U7: ########### | V7: PPTO | W7: Contratado
B8: Ingenierias_Y_Topografia | C8: Diseño Instalaciones HS-E-G | D8: S/D | E8: TORRE 1 | F8: S/D | G8: S/D | H8: ='Diseño Instalaciones PU'!H4 -> UNINAPS | I8: Lote | J8: 1 | K8: MXN | L8: =SUMIFS('Diseño Instalaciones PU'!$M:$M,'Diseño Instalaciones PU'!$E:$E,Ingenierias_Y_Topografia!E8) -> 190400 | M8: =J8*L8 -> 190400 | N8: 0 | O8: =M8*N8 -> 0 | P8: 0.16 | Q8: =(M8+O8)*P8 -> 30464 | R8: =M8+O8+Q8 -> 220864 | S8: =INDEX('Glosario Partidas'!$M$8:$M$10,MATCH(K8,'Glosario Partidas'!$L$8:$L$10,0)) -> 1 | T8: =R8*S8 -> 220864 | U8: ########### | V8: PPTO | W8: Contratado
B9: Ingenierias_Y_Topografia | C9: Diseño Iluminacion | D9: S/D | E9: TORRE 1 | F9: S/D | G9: S/D | H9: ='Diseño Iluminacion PU'!H4 -> ARTEC | I9: Lote | J9: 1 | K9: USD | L9: =SUMIFS('Diseño Iluminacion PU'!$M:$M,'Diseño Iluminacion PU'!$E:$E,Ingenierias_Y_Topografia!E9) -> 16572.5 | M9: =J9*L9 -> 16572.5 | N9: 0 | O9: =M9*N9 -> 0 | P9: 0.16 | Q9: =(M9+O9)*P9 -> 2651.6 | R9: =M9+O9+Q9 -> 19224.1 | S9: =INDEX('Glosario Partidas'!$M$8:$M$10,MATCH(K9,'Glosario Partidas'!$L$8:$L$10,0)) -> 17.5 | T9: =R9*S9 -> 336421.75 | U9: ########### | V9: PPTO | W9: Contratado
B10: Ingenierias_Y_Topografia | C10: Diseño Acustica | D10: S/D | E10: TORRE 1 | F10: S/D | G10: S/D | H10: ='Diseño Acustica'!H4 -> SAAD | I10: Lote | J10: 1 | K10: MXN | L10: =SUMIFS('Diseño Acustica'!$M:$M,'Diseño Acustica'!$E:$E,Ingenierias_Y_Topografia!E10) -> 86206.897 | M10: =J10*L10 -> 86206.897 | N10: 0 | O10: =M10*N10 -> 0 | P10: 0.16 | Q10: =(M10+O10)*P10 -> 13793.103 | R10: =M10+O10+Q10 -> 100000 | S10: =INDEX('Glosario Partidas'!$M$8:$M$10,MATCH(K10,'Glosario Partidas'!$L$8:$L$10,0)) -> 1 | T10: =R10*S10 -> 100000 | U10: ########### | V10: PPTO | W10: Contratado
B11: Ingenierias_Y_Topografia | C11: Topografia Gestoria | D11: S/D | E11: TORRE 1 | F11: S/D | G11: S/D | H11: NA | I11: Lote | J11: 0 | K11: MXN | L11: 0 | M11: =J11*L11 -> 0 | N11: 0 | O11: =M11*N11 -> 0 | P11: 0 | Q11: =(M11+O11)*P11 -> 0 | R11: =M11+O11+Q11 -> 0 | S11: =INDEX('Glosario Partidas'!$M$8:$M$10,MATCH(K11,'Glosario Partidas'!$L$8:$L$10,0)) -> 1 | T11: =R11*S11 -> 0 | U11: ########### | V11: PARAMETRICO | W11: Contratado
B12: Ingenierias_Y_Topografia | C12: Topografia Obra | D12: S/D | E12: TORRE 1 | F12: S/D | G12: S/D | H12: NA | I12: Semana | J12: 0 | K12: MXN | L12: 0 | M12: =J12*L12 -> 0 | N12: 0 | O12: =M12*N12 -> 0 | P12: 0 | Q12: =(M12+O12)*P12 -> 0 | R12: =M12+O12+Q12 -> 0 | S12: =INDEX('Glosario Partidas'!$M$8:$M$10,MATCH(K12,'Glosario Partidas'!$L$8:$L$10,0)) -> 1 | T12: =R12*S12 -> 0 | U12: ########### | V12: PARAMETRICO | W12: Contratado
B13: Ingenierias_Y_Topografia | C13: Mecanica De Suelos | D13: S/D | E13: TORRE 2 | F13: S/D | G13: S/D | H13: ='Mecanica de Suelos PU'!H12 -> Samstordam | I13: Lote | J13: 1 | K13: MXN | L13: =SUMIFS('Mecanica de Suelos PU'!$M:$M,'Mecanica de Suelos PU'!$E:$E,Ingenierias_Y_Topografia!E13) -> 84217.5 | M13: =J13*L13 -> 84217.5 | N13: 0 | O13: =M13*N13 -> 0 | P13: 0.16 | Q13: =(M13+O13)*P13 -> 13474.8 | R13: =M13+O13+Q13 -> 97692.3 | S13: =INDEX('Glosario Partidas'!$M$8:$M$10,MATCH(K13,'Glosario Partidas'!$L$8:$L$10,0)) -> 1 | T13: =R13*S13 -> 97692.3 | U13: ########### | V13: PPTO | W13: Contratado
B14: Ingenierias_Y_Topografia | C14: Calculo Estructural | D14: S/D | E14: TORRE 2 | F14: S/D | G14: S/D | H14: ='Calculo Estructural PU'!H9 -> MyT | I14: Lote | J14: 1 | K14: MXN | L14: =SUMIFS('Calculo Estructural PU'!$M:$M,'Calculo Estructural PU'!$E:$E,Ingenierias_Y_Topografia!E14) -> 185000 | M14: =J14*L14 -> 185000 | N14: 0 | O14: =M14*N14 -> 0 | P14: 0.16 | Q14: =(M14+O14)*P14 -> 29600 | R14: =M14+O14+Q14 -> 214600 | S14: =INDEX('Glosario Partidas'!$M$8:$M$10,MATCH(K14,'Glosario Partidas'!$L$8:$L$10,0)) -> 1 | T14: =R14*S14 -> 214600 | U14: ########### | V14: PPTO | W14: Contratado
B15: Ingenierias_Y_Topografia | C15: Diseño HVAC | D15: S/D | E15: TORRE 2 | F15: S/D | G15: S/D | H15: ='Diseño HVAC PU'!H5 -> CYVS | I15: Lote | J15: 1 | K15: MXN | L15: =SUMIFS('Diseño HVAC PU'!$M:$M,'Diseño HVAC PU'!$E:$E,Ingenierias_Y_Topografia!E15) -> 65000 | M15: =J15*L15 -> 65000 | N15: 0 | O15: =M15*N15 -> 0 | P15: 0.16 | Q15: =(M15+O15)*P15 -> 10400 | R15: =M15+O15+Q15 -> 75400 | S15: =INDEX('Glosario Partidas'!$M$8:$M$10,MATCH(K15,'Glosario Partidas'!$L$8:$L$10,0)) -> 1 | T15: =R15*S15 -> 75400 | U15: ########### | V15: PPTO | W15: Contratado
B16: Ingenierias_Y_Topografia | C16: Diseño Alberca | D16: S/D | E16: TORRE 2 | F16: S/D | G16: S/D | H16: ='Diseño Albercas PU'!H5 -> AQUACONCEPTS | I16: Lote | J16: 1 | K16: MXN | L16: =SUMIFS('Diseño Albercas PU'!$M:$M,'Diseño Albercas PU'!$E:$E,Ingenierias_Y_Topografia!E16) -> 60000 | M16: =J16*L16 -> 60000 | N16: 0 | O16: =M16*N16 -> 0 | P16: 0.16 | Q16: =(M16+O16)*P16 -> 9600 | R16: =M16+O16+Q16 -> 69600 | S16: =INDEX('Glosario Partidas'!$M$8:$M$10,MATCH(K16,'Glosario Partidas'!$L$8:$L$10,0)) -> 1 | T16: =R16*S16 -> 69600 | U16: ########### | V16: PPTO | W16: Contratado
B17: Ingenierias_Y_Topografia | C17: Diseño Instalaciones HS-E-G | D17: S/D | E17: TORRE 2 | F17: S/D | G17: S/D | H17: ='Diseño Instalaciones PU'!H5 -> UNINAPS | I17: Lote | J17: 1 | K17: MXN | L17: =SUMIFS('Diseño Instalaciones PU'!$M:$M,'Diseño Instalaciones PU'!$E:$E,Ingenierias_Y_Topografia!E17) -> 190400 | M17: =J17*L17 -> 190400 | N17: 0 | O17: =M17*N17 -> 0 | P17: 0.16 | Q17: =(M17+O17)*P17 -> 30464 | R17: =M17+O17+Q17 -> 220864 | S17: =INDEX('Glosario Partidas'!$M$8:$M$10,MATCH(K17,'Glosario Partidas'!$L$8:$L$10,0)) -> 1 | T17: =R17*S17 -> 220864 | U17: ########### | V17: PPTO | W17: Contratado
B18: Ingenierias_Y_Topografia | C18: Diseño Iluminacion | D18: S/D | E18: TORRE 2 | F18: S/D | G18: S/D | H18: ='Diseño Iluminacion PU'!H5 -> ARTEC | I18: Lote | J18: 1 | K18: USD | L18: =SUMIFS('Diseño Iluminacion PU'!$M:$M,'Diseño Iluminacion PU'!$E:$E,Ingenierias_Y_Topografia!E18) -> 16572.5 | M18: =J18*L18 -> 16572.5 | N18: 0 | O18: =M18*N18 -> 0 | P18: 0.16 | Q18: =(M18+O18)*P18 -> 2651.6 | R18: =M18+O18+Q18 -> 19224.1 | S18: =INDEX('Glosario Partidas'!$M$8:$M$10,MATCH(K18,'Glosario Partidas'!$L$8:$L$10,0)) -> 17.5 | T18: =R18*S18 -> 336421.75 | U18: ########### | V18: PPTO | W18: Contratado
B19: Ingenierias_Y_Topografia | C19: Diseño Acustica | D19: S/D | E19: TORRE 2 | F19: S/D | G19: S/D | H19: ='Diseño Acustica'!H5 -> SAAD | I19: Lote | J19: 1 | K19: MXN | L19: =SUMIFS('Diseño Acustica'!$M:$M,'Diseño Acustica'!$E:$E,Ingenierias_Y_Topografia!E19) -> 86206.897 | M19: =J19*L19 -> 86206.897 | N19: 0 | O19: =M19*N19 -> 0 | P19: 0.16 | Q19: =(M19+O19)*P19 -> 13793.103 | R19: =M19+O19+Q19 -> 100000 | S19: =INDEX('Glosario Partidas'!$M$8:$M$10,MATCH(K19,'Glosario Partidas'!$L$8:$L$10,0)) -> 1 | T19: =R19*S19 -> 100000 | U19: ########### | V19: PPTO | W19: Contratado
B20: Total | T20: =SUM(T2:T19) -> 2229156.1 | AB20: =SUMIFS($T:$T,$W:$W,"Contratado") -> 2229156.1 | AC20: =SUMIFS($T:$T,$W:$W,"No Contratado") -> 0

Sheet Mecanica de Suelos PU
A2: 46054 | B2: VIGENTE
A3: ⬅ Resumen PU | B3: CATEGORÍA | C3: CONCEPTO | D3: DETALLE | E3: TORRE | F3: PISO | G3: DEPTO | H3: PROVEEDOR | I3: UNIDAD | J3: CANTIDAD | K3: MONEDA | L3: $ UNITARIO | M3: IMPORTE SIN IVA | N3: SOBRECOSTO | O3: TOTAL SOBRECOSTO | P3: % IVA | Q3: $ IVA | R3: IMPORTE TOTAL | S3: T.C | T3: TOTAL MXN | U3: NOTAS | V3: PARAMETRICO/PPTO
B4: Ingenierias_Y_Topografia | C4: Estudio Geotécnico | D4: Traslado foráneo del equipo de perforación y personal del almacén al sitio de exploración. | E4: TORRE 1 | H4: Samstordam | I4: Lote | J4: =1/2 -> 0.5 | K4: MXN | L4: 8750 | M4: =J4*L4 -> 4375 | N4: 0 | O4: =M4*N4 -> 0 | P4: 0.16 | Q4: =(M4+O4)*P4 -> 700 | R4: =M4+O4+Q4 -> 5075 | S4: =INDEX('Glosario Partidas'!$M$8:$M$10,MATCH(K4,'Glosario Partidas'!$L$8:$L$10,0)) -> 1 | T4: =R4*S4 -> 5075 | V4: PPTO
B5: Ingenierias_Y_Topografia | C5: Estudio Geotécnico | D5: Traslado local del equipo de perforación y personal del almacén al sitio de exploración. | E5: TORRE 1 | H5: Samstordam | I5: Lote | J5: =2/2 -> 1 | K5: MXN | L5: 3000 | M5: =J5*L5 -> 3000 | N5: 0 | O5: =M5*N5 -> 0 | P5: 0.16 | Q5: =(M5+O5)*P5 -> 480 | R5: =M5+O5+Q5 -> 3480 | S5: =INDEX('Glosario Partidas'!$M$8:$M$10,MATCH(K5,'Glosario Partidas'!$L$8:$L$10,0)) -> 1 | T5: =R5*S5 -> 3480 | V5: PPTO
B6: Ingenierias_Y_Topografia | C6: Estudio Geotécnico | D6: Sondeo de exploración, con la técnica de penetración estándar según la NORMA NMX-C-431-ONNCCE-2002 obteniendo muestras alteradas. | E6: TORRE 1 | H6: Samstordam | I6: ml | J6: =44/2 -> 22 | K6: MXN | L6: 1000 | M6: =J6*L6 -> 22000 | N6: 0 | O6: =M6*N6 -> 0 | P6: 0.16 | Q6: =(M6+O6)*P6 -> 3520 | R6: =M6+O6+Q6 -> 25520 | S6: =INDEX('Glosario Partidas'!$M$8:$M$10,MATCH(K6,'Glosario Partidas'!$L$8:$L$10,0)) -> 1 | T6: =R6*S6 -> 25520 | V6: PPTO
B7: Ingenierias_Y_Topografia | C7: Estudio Geotécnico | D7: Perforación en roca en diámetro NQ obteniendo núcleos con barril | E7: TORRE 1 | H7: Samstordam | I7: ml | J7: =1/2 -> 0.5 | K7: MXN | L7: 2500 | M7: =J7*L7 -> 1250 | N7: 0 | O7: =M7*N7 -> 0 | P7: 0.16 | Q7: =(M7+O7)*P7 -> 200 | R7: =M7+O7+Q7 -> 1450 | S7: =INDEX('Glosario Partidas'!$M$8:$M$10,MATCH(K7,'Glosario Partidas'!$L$8:$L$10,0)) -> 1 | T7: =R7*S7 -> 1450 | V7: PPTO
B8: Ingenierias_Y_Topografia | C8: Estudio Geotécnico | D8: Suministro y colocación de ademe metálico recuperable. | E8: TORRE 1 | H8: Samstordam | I8: ml | J8: =1/2 -> 0.5 | K8: MXN | L8: 500 | M8: =J8*L8 -> 250 | N8: 0 | O8: =M8*N8 -> 0 | P8: 0.16 | Q8: =(M8+O8)*P8 -> 40 | R8: =M8+O8+Q8 -> 290 | S8: =INDEX('Glosario Partidas'!$M$8:$M$10,MATCH(K8,'Glosario Partidas'!$L$8:$L$10,0)) -> 1 | T8: =R8*S8 -> 290 | V8: PPTO
B9: Ingenierias_Y_Topografia | C9: Estudio Geotécnico | D9: Viáticos de brigada (1 Ingeniero + 1 Perforista + 2 Ayudantes) durante los trabajos de campo. | E9: TORRE 1 | H9: Samstordam | I9: Día | J9: =5/2 -> 2.5 | K9: MXN | L9: 1500 | M9: =J9*L9 -> 3750 | N9: 0 | O9: =M9*N9 -> 0 | P9: 0.16 | Q9: =(M9+O9)*P9 -> 600 | R9: =M9+O9+Q9 -> 4350 | S9: =INDEX('Glosario Partidas'!$M$8:$M$10,MATCH(K9,'Glosario Partidas'!$L$8:$L$10,0)) -> 1 | T9: =R9*S9 -> 4350 | V9: PPTO
B10: Ingenierias_Y_Topografia | C10: Estudio Geotécnico | D10: Hospedaje de brigada (1 Ingeniero + 1 Perforista + 2 Ayudantes) durante los trabajos de campo. | E10: TORRE 1 | H10: Samstordam | I10: Día | J10: =5/2 -> 2.5 | K10: MXN | L10: 2000 | M10: =J10*L10 -> 5000 | N10: 0 | O10: =M10*N10 -> 0 | P10: 0.16 | Q10: =(M10+O10)*P10 -> 800 | R10: =M10+O10+Q10 -> 5800 | S10: =INDEX('Glosario Partidas'!$M$8:$M$10,MATCH(K10,'Glosario Partidas'!$L$8:$L$10,0)) -> 1 | T10: =R10*S10 -> 5800 | V10: PPTO
B11: Ingenierias_Y_Topografia | C11: Estudio Geotécnico | D11: Reconocimiento geotécnico y supervisión de los trabajos de exploración por parte de un ingeniero especialista. | E11: TORRE 1 | H11: Samstordam | I11: Día | J11: =5/2 -> 2.5 | K11: MXN | L11: 850 | M11: =J11*L11 -> 2125 | N11: 0 | O11: =M11*N11 -> 0 | P11: 0.16 | Q11: =(M11+O11)*P11 -> 340 | R11: =M11+O11+Q11 -> 2465 | S11: =INDEX('Glosario Partidas'!$M$8:$M$10,MATCH(K11,'Glosario Partidas'!$L$8:$L$10,0)) -> 1 | T11: =R11*S11 -> 2465 | V11: PPTO
B12: Ingenierias_Y_Topografia | C12: Estudio Geotécnico | D12: Clasificación SUCS (Sistema Unificado de Clasificación de Suelos) NORMA ASTM D-2487. | E12: TORRE 1 | H12: Samstordam | I12: Pba. | J12: =25/2 -> 12.5 | K12: MXN | L12: 35 | M12: =J12*L12 -> 437.5 | N12: 0 | O12: =M12*N12 -> 0 | P12: 0.16 | Q12: =(M12+O12)*P12 -> 70 | R12: =M12+O12+Q12 -> 507.5 | S12: =INDEX('Glosario Partidas'!$M$8:$M$10,MATCH(K12,'Glosario Partidas'!$L$8:$L$10,0)) -> 1 | T12: =R12*S12 -> 507.5 | V12: PPTO
B13: Ingenierias_Y_Topografia | C13: Estudio Geotécnico | D13: Determinación del contenido de agua mediante horno NORMA NMX-C-475-ONNCCE-2013. | E13: TORRE 1 | H13: Samstordam | I13: Pba. | J13: =74/2 -> 37 | K13: MXN | L13: 40 | M13: =J13*L13 -> 1480 | N13: 0 | O13: =M13*N13 -> 0 | P13: 0.16 | Q13: =(M13+O13)*P13 -> 236.8 | R13: =M13+O13+Q13 -> 1716.8 | S13: =INDEX('Glosario Partidas'!$M$8:$M$10,MATCH(K13,'Glosario Partidas'!$L$8:$L$10,0)) -> 1 | T13: =R13*S13 -> 1716.8 | V13: PPTO
B14: Ingenierias_Y_Topografia | C14: Estudio Geotécnico | D14: Determinación de los límites de consistencia NORMA NMX-C-416-ONNCCE-2003 Cap. 6 | E14: TORRE 1 | H14: Samstordam | I14: Pba. | J14: =19/2 -> 9.5 | K14: MXN | L14: 350 | M14: =J14*L14 -> 3325 | N14: 0 | O14: =M14*N14 -> 0 | P14: 0.16 | Q14: =(M14+O14)*P14 -> 532 | R14: =M14+O14+Q14 -> 3857 | S14: =INDEX('Glosario Partidas'!$M$8:$M$10,MATCH(K14,'Glosario Partidas'!$L$8:$L$10,0)) -> 1 | T14: =R14*S14 -> 3857 | V14: PPTO
B15: Ingenierias_Y_Topografia | C15: Estudio Geotécnico | D15: Determinación del análisis granulométrico NORMA NMX-C-416-ONNCCE-2003 Cap. 5 | E15: TORRE 1 | H15: Samstordam | I15: Pba. | J15: =25/2 -> 12.5 | K15: MXN | L15: 300 | M15: =J15*L15 -> 3750 | N15: 0 | O15: =M15*N15 -> 0 | P15: 0.16 | Q15: =(M15+O15)*P15 -> 600 | R15: =M15+O15+Q15 -> 4350 | S15: =INDEX('Glosario Partidas'!$M$8:$M$10,MATCH(K15,'Glosario Partidas'!$L$8:$L$10,0)) -> 1 | T15: =R15*S15 -> 4350 | V15: PPTO
B16: Ingenierias_Y_Topografia | C16: Estudio Geotécnico | D16: Determinación de la masa volumétrica NORMA NMX-C-073-ONNCCE-2004. | E16: TORRE 1 | H16: Samstordam | I16: Pba. | J16: =25/2 -> 12.5 | K16: MXN | L16: 150 | M16: =J16*L16 -> 1875 | N16: 0 | O16: =M16*N16 -> 0 | P16: 0.16 | Q16: =(M16+O16)*P16 -> 300 | R16: =M16+O16+Q16 -> 2175 | S16: =INDEX('Glosario Partidas'!$M$8:$M$10,MATCH(K16,'Glosario Partidas'!$L$8:$L$10,0)) -> 1 | T16: =R16*S16 -> 2175 | V16: PPTO
B17: Ingenierias_Y_Topografia | C17: Estudio Geotécnico | D17: Resistencia a la compresión simple en roca, peso volumétrico y absorción NORMA ASTM D-2166-00. | E17: TORRE 1 | H17: Samstordam | I17: Pba. | J17: =1/2 -> 0.5 | K17: MXN | L17: 800 | M17: =J17*L17 -> 400 | N17: 0 | O17: =M17*N17 -> 0 | P17: 0.16 | Q17: =(M17+O17)*P17 -> 64 | R17: =M17+O17+Q17 -> 464 | S17: =INDEX('Glosario Partidas'!$M$8:$M$10,MATCH(K17,'Glosario Partidas'!$L$8:$L$10,0)) -> 1 | T17: =R17*S17 -> 464 | V17: PPTO
B18: Ingenierias_Y_Topografia | C18: Estudio Geotécnico | D18: Interpretación y redacción de los resultados de campo, laboratorio, cálculos de capacidad de carga, asentamientos y recomendaciones de la mejor opción para la cimentación. | E18: TORRE 1 | H18: Samstordam | I18: Inf. | J18: =1/2 -> 0.5 | K18: MXN | L18: 20000 | M18: =J18*L18 -> 10000 | N18: 0 | O18: =M18*N18 -> 0 | P18: 0.16 | Q18: =(M18+O18)*P18 -> 1600 | R18: =M18+O18+Q18 -> 11600 | S18: =INDEX('Glosario Partidas'!$M$8:$M$10,MATCH(K18,'Glosario Partidas'!$L$8:$L$10,0)) -> 1 | T18: =R18*S18 -> 11600 | V18: PPTO
B19: Ingenierias_Y_Topografia | C19: Piezometría | D19: Construcción de tubo de observación de 2" de diámetro a 8.00 m de profundidad para verificación de las fluctuaciones del nivel freático. | E19: TORRE 1 | H19: Samstordam | I19: Pza. | J19: =2/2 -> 1 | K19: MXN | L19: 7500 | M19: =J19*L19 -> 7500 | N19: 0 | O19: =M19*N19 -> 0 | P19: 0.16 | Q19: =(M19+O19)*P19 -> 1200 | R19: =M19+O19+Q19 -> 8700 | S19: =INDEX('Glosario Partidas'!$M$8:$M$10,MATCH(K19,'Glosario Partidas'!$L$8:$L$10,0)) -> 1 | T19: =R19*S19 -> 8700 | V19: PPTO
B20: Ingenierias_Y_Topografia | C20: Piezometría | D20: Visitas para las tomas de lectura y elaboración de reporte piezométrico. | E20: TORRE 1 | H20: Samstordam | I20: Lote | J20: =1/2 -> 0.5 | K20: MXN | L20: 5000 | M20: =J20*L20 -> 2500 | N20: 0 | O20: =M20*N20 -> 0 | P20: 0.16 | Q20: =(M20+O20)*P20 -> 400 | R20: =M20+O20+Q20 -> 2900 | S20: =INDEX('Glosario Partidas'!$M$8:$M$10,MATCH(K20,'Glosario Partidas'!$L$8:$L$10,0)) -> 1 | T20: =R20*S20 -> 2900 | V20: PPTO
B21: Ingenierias_Y_Topografia | C21: Piezometría | D21: Viáticos de brigada (1 Ingeniero + 1 Perforista + 2 Ayudantes) durante los trabajos de campo. | E21: TORRE 1 | H21: Samstordam | I21: Día | J21: =1/2 -> 0.5 | K21: MXN | L21: 1500 | M21: =J21*L21 -> 750 | N21: 0 | O21: =M21*N21 -> 0 | P21: 0.16 | Q21: =(M21+O21)*P21 -> 120 | R21: =M21+O21+Q21 -> 870 | S21: =INDEX('Glosario Partidas'!$M$8:$M$10,MATCH(K21,'Glosario Partidas'!$L$8:$L$10,0)) -> 1 | T21: =R21*S21 -> 870 | V21: PPTO
B22: Ingenierias_Y_Topografia | C22: Piezometría | D22: Hospedaje de brigada (1 Ingeniero + 1 Perforista + 2 Ayudantes) durante los trabajos de campo. | E22: TORRE 1 | H22: Samstordam | I22: Día | J22: =1/2 -> 0.5 | K22: MXN | L22: 2000 | M22: =J22*L22 -> 1000 | N22: 0 | O22: =M22*N22 -> 0 | P22: 0.16 | Q22: =(M22+O22)*P22 -> 160 | R22: =M22+O22+Q22 -> 1160 | S22: =INDEX('Glosario Partidas'!$M$8:$M$10,MATCH(K22,'Glosario Partidas'!$L$8:$L$10,0)) -> 1 | T22: =R22*S22 -> 1160 | V22: PPTO
B23: Ingenierias_Y_Topografia | C23: Piezometría | D23: Reconocimiento geotécnico y supervisión de los trabajos de exploración por parte de un ingeniero especialista. | E23: TORRE 1 | H23: Samstordam | I23: Día | J23: =1/2 -> 0.5 | K23: MXN | L23: 850 | M23: =J23*L23 -> 425 | N23: 0 | O23: =M23*N23 -> 0 | P23: 0.16 | Q23: =(M23+O23)*P23 -> 68 | R23: =M23+O23+Q23 -> 493 | S23: =INDEX('Glosario Partidas'!$M$8:$M$10,MATCH(K23,'Glosario Partidas'!$L$8:$L$10,0)) -> 1 | T23: =R23*S23 -> 493 | V23: PPTO
B24: Ingenierias_Y_Topografia | C24: Diseño de Pavimentos | D24: Traslado de equipo y personal del almacén al sitio de exploración. | E24: TORRE 1 | H24: Samstordam | I24: Lote | J24: =2/2 -> 1 | K24: MXN | L24: 2500 | M24: =J24*L24 -> 2500 | N24: 0 | O24: =M24*N24 -> 0 | P24: 0.16 | Q24: =(M24+O24)*P24 -> 400 | R24: =M24+O24+Q24 -> 2900 | S24: =INDEX('Glosario Partidas'!$M$8:$M$10,MATCH(K24,'Glosario Partidas'!$L$8:$L$10,0)) -> 1 | T24: =R24*S24 -> 2900 | V24: PPTO
B25: Ingenierias_Y_Topografia | C25: Diseño de Pavimentos | D25: Excavación de pozos a cielo abierto por medios mecánicos, levantamientos de columna estratigráfica según la NORMA NMX-C430-ONNCCE-2002. | E25: TORRE 1 | H25: Samstordam | I25: Pozo | J25: =1/2 -> 0.5 | K25: MXN | L25: 2500 | M25: =J25*L25 -> 1250 | N25: 0 | O25: =M25*N25 -> 0 | P25: 0.16 | Q25: =(M25+O25)*P25 -> 200 | R25: =M25+O25+Q25 -> 1450 | S25: =INDEX('Glosario Partidas'!$M$8:$M$10,MATCH(K25,'Glosario Partidas'!$L$8:$L$10,0)) -> 1 | T25: =R25*S25 -> 1450 | V25: PPTO
B26: Ingenierias_Y_Topografia | C26: Diseño de Pavimentos | D26: Viáticos de brigada (1 Ingeniero + 1 Perforista + 2 Ayudantes) durante los trabajos de campo. | E26: TORRE 1 | H26: Samstordam | I26: Día | J26: =1/2 -> 0.5 | K26: MXN | L26: 1500 | M26: =J26*L26 -> 750 | N26: 0 | O26: =M26*N26 -> 0 | P26: 0.16 | Q26: =(M26+O26)*P26 -> 120 | R26: =M26+O26+Q26 -> 870 | S26: =INDEX('Glosario Partidas'!$M$8:$M$10,MATCH(K26,'Glosario Partidas'!$L$8:$L$10,0)) -> 1 | T26: =R26*S26 -> 870 | V26: PPTO
B27: Ingenierias_Y_Topografia | C27: Diseño de Pavimentos | D27: Hospedaje de brigada (1 Ingeniero + 1 Perforista + 2 Ayudantes) durante los trabajos de campo. | E27: TORRE 1 | H27: Samstordam | I27: Día | J27: =1/2 -> 0.5 | K27: MXN | L27: 2000 | M27: =J27*L27 -> 1000 | N27: 0 | O27: =M27*N27 -> 0 | P27: 0.16 | Q27: =(M27+O27)*P27 -> 160 | R27: =M27+O27+Q27 -> 1160 | S27: =INDEX('Glosario Partidas'!$M$8:$M$10,MATCH(K27,'Glosario Partidas'!$L$8:$L$10,0)) -> 1 | T27: =R27*S27 -> 1160 | V27: PPTO
B28: Ingenierias_Y_Topografia | C28: Diseño de Pavimentos | D28: Clasificación SUCS (Sistema Unificado de Clasificación de Suelos) NORMA ASTM D-2487. | E28: TORRE 1 | H28: Samstordam | I28: Pba. | J28: =2/2 -> 1 | K28: MXN | L28: 35 | M28: =J28*L28 -> 35 | N28: 0 | O28: =M28*N28 -> 0 | P28: 0.16 | Q28: =(M28+O28)*P28 -> 5.6 | R28: =M28+O28+Q28 -> 40.6 | S28: =INDEX('Glosario Partidas'!$M$8:$M$10,MATCH(K28,'Glosario Partidas'!$L$8:$L$10,0)) -> 1 | T28: =R28*S28 -> 40.6 | V28: PPTO
B29: Ingenierias_Y_Topografia | C29: Diseño de Pavimentos | D29: Determinación del contenido de agua mediante horno NORMA NMX-C-475-ONNCCE-2013. | E29: TORRE 1 | H29: Samstordam | I29: Pba. | J29: =2/2 -> 1 | K29: MXN | L29: 40 | M29: =J29*L29 -> 40 | N29: 0 | O29: =M29*N29 -> 0 | P29: 0.16 | Q29: =(M29+O29)*P29 -> 6.4 | R29: =M29+O29+Q29 -> 46.4 | S29: =INDEX('Glosario Partidas'!$M$8:$M$10,MATCH(K29,'Glosario Partidas'!$L$8:$L$10,0)) -> 1 | T29: =R29*S29 -> 46.4 | V29: PPTO
B30: Ingenierias_Y_Topografia | C30: Diseño de Pavimentos | D30: Determinación de los límites de consistencia NORMA NMX-C-416-ONNCCE-2003 Cap. 6 | E30: TORRE 1 | H30: Samstordam | I30: Pba. | J30: =2/2 -> 1 | K30: MXN | L30: 350 | M30: =J30*L30 -> 350 | N30: 0 | O30: =M30*N30 -> 0 | P30: 0.16 | Q30: =(M30+O30)*P30 -> 56 | R30: =M30+O30+Q30 -> 406 | S30: =INDEX('Glosario Partidas'!$M$8:$M$10,MATCH(K30,'Glosario Partidas'!$L$8:$L$10,0)) -> 1 | T30: =R30*S30 -> 406 | V30: PPTO
B31: Ingenierias_Y_Topografia | C31: Diseño de Pavimentos | D31: Determinación del análisis granulométrico NORMA NMX-C-416-ONNCCE-2003 Cap. 5 | E31: TORRE 1 | H31: Samstordam | I31: Pba. | J31: =2/2 -> 1 | K31: MXN | L31: 300 | M31: =J31*L31 -> 300 | N31: 0 | O31: =M31*N31 -> 0 | P31: 0.16 | Q31: =(M31+O31)*P31 -> 48 | R31: =M31+O31+Q31 -> 348 | S31: =INDEX('Glosario Partidas'!$M$8:$M$10,MATCH(K31,'Glosario Partidas'!$L$8:$L$10,0)) -> 1 | T31: =R31*S31 -> 348 | V31: PPTO
B32: Ingenierias_Y_Topografia | C32: Diseño de Pavimentos | D32: Determinación del valor relativo soporte y expansión NORMA NMX-C-416-ONNCCE-2003 Cap. 10 | E32: TORRE 1 | H32: Samstordam | I32: Pba. | J32: =1/2 -> 0.5 | K32: MXN | L32: 600 | M32: =J32*L32 -> 300 | N32: 0 | O32: =M32*N32 -> 0 | P32: 0.16 | Q32: =(M32+O32)*P32 -> 48 | R32: =M32+O32+Q32 -> 348 | S32: =INDEX('Glosario Partidas'!$M$8:$M$10,MATCH(K32,'Glosario Partidas'!$L$8:$L$10,0)) -> 1 | T32: =R32*S32 -> 348 | V32: PPTO
B33: Ingenierias_Y_Topografia | C33: Diseño de Pavimentos | D33: Interpretación y redacción de los resultados de campo, laboratorio y recomendaciones geotécnicas para el diseño de pavimentos | E33: TORRE 1 | H33: Samstordam | I33: Inf. | J33: =1/2 -> 0.5 | K33: MXN | L33: 5000 | M33: =J33*L33 -> 2500 | N33: 0 | O33: =M33*N33 -> 0 | P33: 0.16 | Q33: =(M33+O33)*P33 -> 400 | R33: =M33+O33+Q33 -> 2900 | S33: =INDEX('Glosario Partidas'!$M$8:$M$10,MATCH(K33,'Glosario Partidas'!$L$8:$L$10,0)) -> 1 | T33: =R33*S33 -> 2900 | V33: PPTO
B34: Ingenierias_Y_Topografia | C34: Estudio Geotécnico | D34: Traslado foráneo del equipo de perforación y personal del almacén al sitio de exploración. | E34: TORRE 2 | H34: Samstordam | I34: Lote | J34: =1/2 -> 0.5 | K34: MXN | L34: 8750 | M34: =J34*L34 -> 4375 | N34: 0 | O34: =M34*N34 -> 0 | P34: 0.16 | Q34: =(M34+O34)*P34 -> 700 | R34: =M34+O34+Q34 -> 5075 | S34: =INDEX('Glosario Partidas'!$M$8:$M$10,MATCH(K34,'Glosario Partidas'!$L$8:$L$10,0)) -> 1 | T34: =R34*S34 -> 5075 | V34: PPTO
B35: Ingenierias_Y_Topografia | C35: Estudio Geotécnico | D35: Traslado local del equipo de perforación y personal del almacén al sitio de exploración. | E35: TORRE 2 | H35: Samstordam | I35: Lote | J35: =2/2 -> 1 | K35: MXN | L35: 3000 | M35: =J35*L35 -> 3000 | N35: 0 | O35: =M35*N35 -> 0 | P35: 0.16 | Q35: =(M35+O35)*P35 -> 480 | R35: =M35+O35+Q35 -> 3480 | S35: =INDEX('Glosario Partidas'!$M$8:$M$10,MATCH(K35,'Glosario Partidas'!$L$8:$L$10,0)) -> 1 | T35: =R35*S35 -> 3480 | V35: PPTO
B36: Ingenierias_Y_Topografia | C36: Estudio Geotécnico | D36: Sondeo de exploración, con la técnica de penetración estándar según la NORMA NMX-C-431-ONNCCE-2002 obteniendo muestras alteradas. | E36: TORRE 2 | H36: Samstordam | I36: ml | J36: =44/2 -> 22 | K36: MXN | L36: 1000 | M36: =J36*L36 -> 22000 | N36: 0 | O36: =M36*N36 -> 0 | P36: 0.16 | Q36: =(M36+O36)*P36 -> 3520 | R36: =M36+O36+Q36 -> 25520 | S36: =INDEX('Glosario Partidas'!$M$8:$M$10,MATCH(K36,'Glosario Partidas'!$L$8:$L$10,0)) -> 1 | T36: =R36*S36 -> 25520 | V36: PPTO
B37: Ingenierias_Y_Topografia | C37: Estudio Geotécnico | D37: Perforación en roca en diámetro NQ obteniendo núcleos con barril | E37: TORRE 2 | H37: Samstordam | I37: ml | J37: =1/2 -> 0.5 | K37: MXN | L37: 2500 | M37: =J37*L37 -> 1250 | N37: 0 | O37: =M37*N37 -> 0 | P37: 0.16 | Q37: =(M37+O37)*P37 -> 200 | R37: =M37+O37+Q37 -> 1450 | S37: =INDEX('Glosario Partidas'!$M$8:$M$10,MATCH(K37,'Glosario Partidas'!$L$8:$L$10,0)) -> 1 | T37: =R37*S37 -> 1450 | V37: PPTO
B38: Ingenierias_Y_Topografia | C38: Estudio Geotécnico | D38: Suministro y colocación de ademe metálico recuperable. | E38: TORRE 2 | H38: Samstordam | I38: ml | J38: =1/2 -> 0.5 | K38: MXN | L38: 500 | M38: =J38*L38 -> 250 | N38: 0 | O38: =M38*N38 -> 0 | P38: 0.16 | Q38: =(M38+O38)*P38 -> 40 | R38: =M38+O38+Q38 -> 290 | S38: =INDEX('Glosario Partidas'!$M$8:$M$10,MATCH(K38,'Glosario Partidas'!$L$8:$L$10,0)) -> 1 | T38: =R38*S38 -> 290 | V38: PPTO
B39: Ingenierias_Y_Topografia | C39: Estudio Geotécnico | D39: Viáticos de brigada (1 Ingeniero + 1 Perforista + 2 Ayudantes) durante los trabajos de campo. | E39: TORRE 2 | H39: Samstordam | I39: Día | J39: =5/2 -> 2.5 | K39: MXN | L39: 1500 | M39: =J39*L39 -> 3750 | N39: 0 | O39: =M39*N39 -> 0 | P39: 0.16 | Q39: =(M39+O39)*P39 -> 600 | R39: =M39+O39+Q39 -> 4350 | S39: =INDEX('Glosario Partidas'!$M$8:$M$10,MATCH(K39,'Glosario Partidas'!$L$8:$L$10,0)) -> 1 | T39: =R39*S39 -> 4350 | V39: PPTO
B40: Ingenierias_Y_Topografia | C40: Estudio Geotécnico | D40: Hospedaje de brigada (1 Ingeniero + 1 Perforista + 2 Ayudantes) durante los trabajos de campo. | E40: TORRE 2 | H40: Samstordam | I40: Día | J40: =5/2 -> 2.5 | K40: MXN | L40: 2000 | M40: =J40*L40 -> 5000 | N40: 0 | O40: =M40*N40 -> 0 | P40: 0.16 | Q40: =(M40+O40)*P40 -> 800 | R40: =M40+O40+Q40 -> 5800 | S40: =INDEX('Glosario Partidas'!$M$8:$M$10,MATCH(K40,'Glosario Partidas'!$L$8:$L$10,0)) -> 1 | T40: =R40*S40 -> 5800 | V40: PPTO
B41: Ingenierias_Y_Topografia | C41: Estudio Geotécnico | D41: Reconocimiento geotécnico y supervisión de los trabajos de exploración por parte de un ingeniero especialista. | E41: TORRE 2 | H41: Samstordam | I41: Día | J41: =5/2 -> 2.5 | K41: MXN | L41: 850 | M41: =J41*L41 -> 2125 | N41: 0 | O41: =M41*N41 -> 0 | P41: 0.16 | Q41: =(M41+O41)*P41 -> 340 | R41: =M41+O41+Q41 -> 2465 | S41: =INDEX('Glosario Partidas'!$M$8:$M$10,MATCH(K41,'Glosario Partidas'!$L$8:$L$10,0)) -> 1 | T41: =R41*S41 -> 2465 | V41: PPTO
B42: Ingenierias_Y_Topografia | C42: Estudio Geotécnico | D42: Clasificación SUCS (Sistema Unificado de Clasificación de Suelos) NORMA ASTM D-2487. | E42: TORRE 2 | H42: Samstordam | I42: Pba. | J42: =25/2 -> 12.5 | K42: MXN | L42: 35 | M42: =J42*L42 -> 437.5 | N42: 0 | O42: =M42*N42 -> 0 | P42: 0.16 | Q42: =(M42+O42)*P42 -> 70 | R42: =M42+O42+Q42 -> 507.5 | S42: =INDEX('Glosario Partidas'!$M$8:$M$10,MATCH(K42,'Glosario Partidas'!$L$8:$L$10,0)) -> 1 | T42: =R42*S42 -> 507.5 | V42: PPTO
B43: Ingenierias_Y_Topografia | C43: Estudio Geotécnico | D43: Determinación del contenido de agua mediante horno NORMA NMX-C-475-ONNCCE-2013. | E43: TORRE 2 | H43: Samstordam | I43: Pba. | J43: =74/2 -> 37 | K43: MXN | L43: 40 | M43: =J43*L43 -> 1480 | N43: 0 | O43: =M43*N43 -> 0 | P43: 0.16 | Q43: =(M43+O43)*P43 -> 236.8 | R43: =M43+O43+Q43 -> 1716.8 | S43: =INDEX('Glosario Partidas'!$M$8:$M$10,MATCH(K43,'Glosario Partidas'!$L$8:$L$10,0)) -> 1 | T43: =R43*S43 -> 1716.8 | V43: PPTO
B44: Ingenierias_Y_Topografia | C44: Estudio Geotécnico | D44: Determinación de los límites de consistencia NORMA NMX-C-416-ONNCCE-2003 Cap. 6 | E44: TORRE 2 | H44: Samstordam | I44: Pba. | J44: =19/2 -> 9.5 | K44: MXN | L44: 350 | M44: =J44*L44 -> 3325 | N44: 0 | O44: =M44*N44 -> 0 | P44: 0.16 | Q44: =(M44+O44)*P44 -> 532 | R44: =M44+O44+Q44 -> 3857 | S44: =INDEX('Glosario Partidas'!$M$8:$M$10,MATCH(K44,'Glosario Partidas'!$L$8:$L$10,0)) -> 1 | T44: =R44*S44 -> 3857 | V44: PPTO
B45: Ingenierias_Y_Topografia | C45: Estudio Geotécnico | D45: Determinación del análisis granulométrico NORMA NMX-C-416-ONNCCE-2003 Cap. 5 | E45: TORRE 2 | H45: Samstordam | I45: Pba. | J45: =25/2 -> 12.5 | K45: MXN | L45: 300 | M45: =J45*L45 -> 3750 | N45: 0 | O45: =M45*N45 -> 0 | P45: 0.16 | Q45: =(M45+O45)*P45 -> 600 | R45: =M45+O45+Q45 -> 4350 | S45: =INDEX('Glosario Partidas'!$M$8:$M$10,MATCH(K45,'Glosario Partidas'!$L$8:$L$10,0)) -> 1 | T45: =R45*S45 -> 4350 | V45: PPTO
B46: Ingenierias_Y_Topografia | C46: Estudio Geotécnico | D46: Determinación de la masa volumétrica NORMA NMX-C-073-ONNCCE-2004. | E46: TORRE 2 | H46: Samstordam | I46: Pba. | J46: =25/2 -> 12.5 | K46: MXN | L46: 150 | M46: =J46*L46 -> 1875 | N46: 0 | O46: =M46*N46 -> 0 | P46: 0.16 | Q46: =(M46+O46)*P46 -> 300 | R46: =M46+O46+Q46 -> 2175 | S46: =INDEX('Glosario Partidas'!$M$8:$M$10,MATCH(K46,'Glosario Partidas'!$L$8:$L$10,0)) -> 1 | T46: =R46*S46 -> 2175 | V46: PPTO
B47: Ingenierias_Y_Topografia | C47: Estudio Geotécnico | D47: Resistencia a la compresión simple en roca, peso volumétrico y absorción NORMA ASTM D-2166-00. | E47: TORRE 2 | H47: Samstordam | I47: Pba. | J47: =1/2 -> 0.5 | K47: MXN | L47: 800 | M47: =J47*L47 -> 400 | N47: 0 | O47: =M47*N47 -> 0 | P47: 0.16 | Q47: =(M47+O47)*P47 -> 64 | R47: =M47+O47+Q47 -> 464 | S47: =INDEX('Glosario Partidas'!$M$8:$M$10,MATCH(K47,'Glosario Partidas'!$L$8:$L$10,0)) -> 1 | T47: =R47*S47 -> 464 | V47: PPTO
B48: Ingenierias_Y_Topografia | C48: Estudio Geotécnico | D48: Interpretación y redacción de los resultados de campo, laboratorio, cálculos de capacidad de carga, asentamientos y recomendaciones de la mejor opción para la cimentación. | E48: TORRE 2 | H48: Samstordam | I48: Inf. | J48: =1/2 -> 0.5 | K48: MXN | L48: 20000 | M48: =J48*L48 -> 10000 | N48: 0 | O48: =M48*N48 -> 0 | P48: 0.16 | Q48: =(M48+O48)*P48 -> 1600 | R48: =M48+O48+Q48 -> 11600 | S48: =INDEX('Glosario Partidas'!$M$8:$M$10,MATCH(K48,'Glosario Partidas'!$L$8:$L$10,0)) -> 1 | T48: =R48*S48 -> 11600 | V48: PPTO
B49: Ingenierias_Y_Topografia | C49: Piezometría | D49: Construcción de tubo de observación de 2" de diámetro a 8.00 m de profundidad para verificación de las fluctuaciones del nivel freático. | E49: TORRE 2 | H49: Samstordam | I49: Pza. | J49: =2/2 -> 1 | K49: MXN | L49: 7500 | M49: =J49*L49 -> 7500 | N49: 0 | O49: =M49*N49 -> 0 | P49: 0.16 | Q49: =(M49+O49)*P49 -> 1200 | R49: =M49+O49+Q49 -> 8700 | S49: =INDEX('Glosario Partidas'!$M$8:$M$10,MATCH(K49,'Glosario Partidas'!$L$8:$L$10,0)) -> 1 | T49: =R49*S49 -> 8700 | V49: PPTO
B50: Ingenierias_Y_Topografia | C50: Piezometría | D50: Visitas para las tomas de lectura y elaboración de reporte piezométrico. | E50: TORRE 2 | H50: Samstordam | I50: Lote | J50: =1/2 -> 0.5 | K50: MXN | L50: 5000 | M50: =J50*L50 -> 2500 | N50: 0 | O50: =M50*N50 -> 0 | P50: 0.16 | Q50: =(M50+O50)*P50 -> 400 | R50: =M50+O50+Q50 -> 2900 | S50: =INDEX('Glosario Partidas'!$M$8:$M$10,MATCH(K50,'Glosario Partidas'!$L$8:$L$10,0)) -> 1 | T50: =R50*S50 -> 2900 | V50: PPTO
B51: Ingenierias_Y_Topografia | C51: Piezometría | D51: Viáticos de brigada (1 Ingeniero + 1 Perforista + 2 Ayudantes) durante los trabajos de campo. | E51: TORRE 2 | H51: Samstordam | I51: Día | J51: =1/2 -> 0.5 | K51: MXN | L51: 1500 | M51: =J51*L51 -> 750 | N51: 0 | O51: =M51*N51 -> 0 | P51: 0.16 | Q51: =(M51+O51)*P51 -> 120 | R51: =M51+O51+Q51 -> 870 | S51: =INDEX('Glosario Partidas'!$M$8:$M$10,MATCH(K51,'Glosario Partidas'!$L$8:$L$10,0)) -> 1 | T51: =R51*S51 -> 870 | V51: PPTO
B52: Ingenierias_Y_Topografia | C52: Piezometría | D52: Hospedaje de brigada (1 Ingeniero + 1 Perforista + 2 Ayudantes) durante los trabajos de campo. | E52: TORRE 2 | H52: Samstordam | I52: Día | J52: =1/2 -> 0.5 | K52: MXN | L52: 2000 | M52: =J52*L52 -> 1000 | N52: 0 | O52: =M52*N52 -> 0 | P52: 0.16 | Q52: =(M52+O52)*P52 -> 160 | R52: =M52+O52+Q52 -> 1160 | S52: =INDEX('Glosario Partidas'!$M$8:$M$10,MATCH(K52,'Glosario Partidas'!$L$8:$L$10,0)) -> 1 | T52: =R52*S52 -> 1160 | V52: PPTO
B53: Ingenierias_Y_Topografia | C53: Piezometría | D53: Reconocimiento geotécnico y supervisión de los trabajos de exploración por parte de un ingeniero especialista. | E53: TORRE 2 | H53: Samstordam | I53: Día | J53: =1/2 -> 0.5 | K53: MXN | L53: 850 | M53: =J53*L53 -> 425 | N53: 0 | O53: =M53*N53 -> 0 | P53: 0.16 | Q53: =(M53+O53)*P53 -> 68 | R53: =M53+O53+Q53 -> 493 | S53: =INDEX('Glosario Partidas'!$M$8:$M$10,MATCH(K53,'Glosario Partidas'!$L$8:$L$10,0)) -> 1 | T53: =R53*S53 -> 493 | V53: PPTO
B54: Ingenierias_Y_Topografia | C54: Diseño de Pavimentos | D54: Traslado de equipo y personal del almacén al sitio de exploración. | E54: TORRE 2 | H54: Samstordam | I54: Lote | J54: =2/2 -> 1 | K54: MXN | L54: 2500 | M54: =J54*L54 -> 2500 | N54: 0 | O54: =M54*N54 -> 0 | P54: 0.16 | Q54: =(M54+O54)*P54 -> 400 | R54: =M54+O54+Q54 -> 2900 | S54: =INDEX('Glosario Partidas'!$M$8:$M$10,MATCH(K54,'Glosario Partidas'!$L$8:$L$10,0)) -> 1 | T54: =R54*S54 -> 2900 | V54: PPTO
B55: Ingenierias_Y_Topografia | C55: Diseño de Pavimentos | D55: Excavación de pozos a cielo abierto por medios mecánicos, levantamientos de columna estratigráfica según la NORMA NMX-C430-ONNCCE-2002. | E55: TORRE 2 | H55: Samstordam | I55: Pozo | J55: =1/2 -> 0.5 | K55: MXN | L55: 2500 | M55: =J55*L55 -> 1250 | N55: 0 | O55: =M55*N55 -> 0 | P55: 0.16 | Q55: =(M55+O55)*P55 -> 200 | R55: =M55+O55+Q55 -> 1450 | S55: =INDEX('Glosario Partidas'!$M$8:$M$10,MATCH(K55,'Glosario Partidas'!$L$8:$L$10,0)) -> 1 | T55: =R55*S55 -> 1450 | V55: PPTO
B56: Ingenierias_Y_Topografia | C56: Diseño de Pavimentos | D56: Viáticos de brigada (1 Ingeniero + 1 Perforista + 2 Ayudantes) durante los trabajos de campo. | E56: TORRE 2 | H56: Samstordam | I56: Día | J56: =1/2 -> 0.5 | K56: MXN | L56: 1500 | M56: =J56*L56 -> 750 | N56: 0 | O56: =M56*N56 -> 0 | P56: 0.16 | Q56: =(M56+O56)*P56 -> 120 | R56: =M56+O56+Q56 -> 870 | S56: =INDEX('Glosario Partidas'!$M$8:$M$10,MATCH(K56,'Glosario Partidas'!$L$8:$L$10,0)) -> 1 | T56: =R56*S56 -> 870 | V56: PPTO
B57: Ingenierias_Y_Topografia | C57: Diseño de Pavimentos | D57: Hospedaje de brigada (1 Ingeniero + 1 Perforista + 2 Ayudantes) durante los trabajos de campo. | E57: TORRE 2 | H57: Samstordam | I57: Día | J57: =1/2 -> 0.5 | K57: MXN | L57: 2000 | M57: =J57*L57 -> 1000 | N57: 0 | O57: =M57*N57 -> 0 | P57: 0.16 | Q57: =(M57+O57)*P57 -> 160 | R57: =M57+O57+Q57 -> 1160 | S57: =INDEX('Glosario Partidas'!$M$8:$M$10,MATCH(K57,'Glosario Partidas'!$L$8:$L$10,0)) -> 1 | T57: =R57*S57 -> 1160 | V57: PPTO
B58: Ingenierias_Y_Topografia | C58: Diseño de Pavimentos | D58: Clasificación SUCS (Sistema Unificado de Clasificación de Suelos) NORMA ASTM D-2487. | E58: TORRE 2 | H58: Samstordam | I58: Pba. | J58: =2/2 -> 1 | K58: MXN | L58: 35 | M58: =J58*L58 -> 35 | N58: 0 | O58: =M58*N58 -> 0 | P58: 0.16 | Q58: =(M58+O58)*P58 -> 5.6 | R58: =M58+O58+Q58 -> 40.6 | S58: =INDEX('Glosario Partidas'!$M$8:$M$10,MATCH(K58,'Glosario Partidas'!$L$8:$L$10,0)) -> 1 | T58: =R58*S58 -> 40.6 | V58: PPTO
B59: Ingenierias_Y_Topografia | C59: Diseño de Pavimentos | D59: Determinación del contenido de agua mediante horno NORMA NMX-C-475-ONNCCE-2013. | E59: TORRE 2 | H59: Samstordam | I59: Pba. | J59: =2/2 -> 1 | K59: MXN | L59: 40 | M59: =J59*L59 -> 40 | N59: 0 | O59: =M59*N59 -> 0 | P59: 0.16 | Q59: =(M59+O59)*P59 -> 6.4 | R59: =M59+O59+Q59 -> 46.4 | S59: =INDEX('Glosario Partidas'!$M$8:$M$10,MATCH(K59,'Glosario Partidas'!$L$8:$L$10,0)) -> 1 | T59: =R59*S59 -> 46.4 | V59: PPTO
B60: Ingenierias_Y_Topografia | C60: Diseño de Pavimentos | D60: Determinación de los límites de consistencia NORMA NMX-C-416-ONNCCE-2003 Cap. 6 | E60: TORRE 2 | H60: Samstordam | I60: Pba. | J60: =2/2 -> 1 | K60: MXN | L60: 350 | M60: =J60*L60 -> 350 | N60: 0 | O60: =M60*N60 -> 0 | P60: 0.16 | Q60: =(M60+O60)*P60 -> 56 | R60: =M60+O60+Q60 -> 406 | S60: =INDEX('Glosario Partidas'!$M$8:$M$10,MATCH(K60,'Glosario Partidas'!$L$8:$L$10,0)) -> 1 | T60: =R60*S60 -> 406 | V60: PPTO
B61: Ingenierias_Y_Topografia | C61: Diseño de Pavimentos | D61: Determinación del análisis granulométrico NORMA NMX-C-416-ONNCCE-2003 Cap. 5 | E61: TORRE 2 | H61: Samstordam | I61: Pba. | J61: =2/2 -> 1 | K61: MXN | L61: 300 | M61: =J61*L61 -> 300 | N61: 0 | O61: =M61*N61 -> 0 | P61: 0.16 | Q61: =(M61+O61)*P61 -> 48 | R61: =M61+O61+Q61 -> 348 | S61: =INDEX('Glosario Partidas'!$M$8:$M$10,MATCH(K61,'Glosario Partidas'!$L$8:$L$10,0)) -> 1 | T61: =R61*S61 -> 348 | V61: PPTO
B62: Ingenierias_Y_Topografia | C62: Diseño de Pavimentos | D62: Determinación del valor relativo soporte y expansión NORMA NMX-C-416-ONNCCE-2003 Cap. 10 | E62: TORRE 2 | H62: Samstordam | I62: Pba. | J62: =1/2 -> 0.5 | K62: MXN | L62: 600 | M62: =J62*L62 -> 300 | N62: 0 | O62: =M62*N62 -> 0 | P62: 0.16 | Q62: =(M62+O62)*P62 -> 48 | R62: =M62+O62+Q62 -> 348 | S62: =INDEX('Glosario Partidas'!$M$8:$M$10,MATCH(K62,'Glosario Partidas'!$L$8:$L$10,0)) -> 1 | T62: =R62*S62 -> 348 | V62: PPTO
B63: Ingenierias_Y_Topografia | C63: Diseño de Pavimentos | D63: Interpretación y redacción de los resultados de campo, laboratorio y recomendaciones geotécnicas para el diseño de pavimentos | E63: TORRE 2 | H63: Samstordam | I63: Inf. | J63: =1/2 -> 0.5 | K63: MXN | L63: 5000 | M63: =J63*L63 -> 2500 | N63: 0 | O63: =M63*N63 -> 0 | P63: 0.16 | Q63: =(M63+O63)*P63 -> 400 | R63: =M63+O63+Q63 -> 2900 | S63: =INDEX('Glosario Partidas'!$M$8:$M$10,MATCH(K63,'Glosario Partidas'!$L$8:$L$10,0)) -> 1 | T63: =R63*S63 -> 2900 | V63: PPTO
B64: Total | M64: =SUM(M4:M63) -> 168435 | R64: =SUM(R4:R63) -> 195384.6 | T64: =SUM(T4:T63) -> 195384.6

Sheet Calculo Estructural PU
A2: 45901 | B2: VIGENTE
A3: ⬅ Resumen PU | B3: CATEGORÍA | C3: CONCEPTO | D3: DETALLE | E3: TORRE | F3: PISO | G3: DEPTO | H3: PROVEEDOR | I3: UNIDAD | J3: CANTIDAD | K3: MONEDA | L3: $ UNITARIO | M3: IMPORTE SIN IVA | N3: SOBRECOSTO | O3: TOTAL SOBRECOSTO | P3: % IVA | Q3: $ IVA | R3: IMPORTE TOTAL | S3: T.C | T3: TOTAL MXN | U3: NOTAS | V3: PARAMETRICO/PPTO
B4: Ingenierias_Y_Topografia | C4: Cálculo Estructural | D4: Anticipo | E4: TORRE 1 | H4: MyT | I4: Lote | J4: =1/2 -> 0.5 | K4: MXN | L4: =75000 -> 75000 | M4: =J4*L4 -> 37500 | N4: 0 | O4: =M4*N4 -> 0 | P4: 0.16 | Q4: =(M4+O4)*P4 -> 6000 | R4: =M4+O4+Q4 -> 43500 | S4: =INDEX('Glosario Partidas'!$M$8:$M$10,MATCH(K4,'Glosario Partidas'!$L$8:$L$10,0)) -> 1 | T4: =R4*S4 -> 43500 | V4: PPTO
B5: Ingenierias_Y_Topografia | C5: Cálculo Estructural | D5: Fade 1 y 2 | E5: TORRE 1 | H5: MyT | I5: Lote | J5: =1/2 -> 0.5 | K5: MXN | L5: =70000 -> 70000 | M5: =J5*L5 -> 35000 | N5: 0 | O5: =M5*N5 -> 0 | P5: 0.16 | Q5: =(M5+O5)*P5 -> 5600 | R5: =M5+O5+Q5 -> 40600 | S5: =INDEX('Glosario Partidas'!$M$8:$M$10,MATCH(K5,'Glosario Partidas'!$L$8:$L$10,0)) -> 1 | T5: =R5*S5 -> 40600 | V5: PPTO
B6: Ingenierias_Y_Topografia | C6: Cálculo Estructural | D6: Fase 3 | E6: TORRE 1 | H6: MyT | I6: Lote | J6: =1/2 -> 0.5 | K6: MXN | L6: =70000 -> 70000 | M6: =J6*L6 -> 35000 | N6: 0 | O6: =M6*N6 -> 0 | P6: 0.16 | Q6: =(M6+O6)*P6 -> 5600 | R6: =M6+O6+Q6 -> 40600 | S6: =INDEX('Glosario Partidas'!$M$8:$M$10,MATCH(K6,'Glosario Partidas'!$L$8:$L$10,0)) -> 1 | T6: =R6*S6 -> 40600 | V6: PPTO
B7: Ingenierias_Y_Topografia | C7: Cálculo Estructural | D7: Fase 4 | E7: TORRE 1 | H7: MyT | I7: Lote | J7: =1/2 -> 0.5 | K7: MXN | L7: =70000 -> 70000 | M7: =J7*L7 -> 35000 | N7: 0 | O7: =M7*N7 -> 0 | P7: 0.16 | Q7: =(M7+O7)*P7 -> 5600 | R7: =M7+O7+Q7 -> 40600 | S7: =INDEX('Glosario Partidas'!$M$8:$M$10,MATCH(K7,'Glosario Partidas'!$L$8:$L$10,0)) -> 1 | T7: =R7*S7 -> 40600 | V7: PPTO
B8: Ingenierias_Y_Topografia | C8: Cálculo Estructural | D8: Extraordinarios | E8: TORRE 1 | H8: MyT | I8: Lote | J8: =1/2 -> 0.5 | K8: MXN | L8: =85000 -> 85000 | M8: =J8*L8 -> 42500 | N8: 0 | O8: =M8*N8 -> 0 | P8: 0.16 | Q8: =(M8+O8)*P8 -> 6800 | R8: =M8+O8+Q8 -> 49300 | S8: =INDEX('Glosario Partidas'!$M$8:$M$10,MATCH(K8,'Glosario Partidas'!$L$8:$L$10,0)) -> 1 | T8: =R8*S8 -> 49300 | V8: PPTO
B9: Ingenierias_Y_Topografia | C9: Cálculo Estructural | D9: Anticipo | E9: TORRE 2 | H9: MyT | I9: Lote | J9: =1/2 -> 0.5 | K9: MXN | L9: =75000 -> 75000 | M9: =J9*L9 -> 37500 | N9: 0 | O9: =M9*N9 -> 0 | P9: 0.16 | Q9: =(M9+O9)*P9 -> 6000 | R9: =M9+O9+Q9 -> 43500 | S9: =INDEX('Glosario Partidas'!$M$8:$M$10,MATCH(K9,'Glosario Partidas'!$L$8:$L$10,0)) -> 1 | T9: =R9*S9 -> 43500 | V9: PPTO
B10: Ingenierias_Y_Topografia | C10: Cálculo Estructural | D10: Fade 1 y 2 | E10: TORRE 2 | H10: MyT | I10: Lote | J10: =1/2 -> 0.5 | K10: MXN | L10: =70000 -> 70000 | M10: =J10*L10 -> 35000 | N10: 0 | O10: =M10*N10 -> 0 | P10: 0.16 | Q10: =(M10+O10)*P10 -> 5600 | R10: =M10+O10+Q10 -> 40600 | S10: =INDEX('Glosario Partidas'!$M$8:$M$10,MATCH(K10,'Glosario Partidas'!$L$8:$L$10,0)) -> 1 | T10: =R10*S10 -> 40600 | V10: PPTO
B11: Ingenierias_Y_Topografia | C11: Cálculo Estructural | D11: Fase 3 | E11: TORRE 2 | H11: MyT | I11: Lote | J11: =1/2 -> 0.5 | K11: MXN | L11: =70000 -> 70000 | M11: =J11*L11 -> 35000 | N11: 0 | O11: =M11*N11 -> 0 | P11: 0.16 | Q11: =(M11+O11)*P11 -> 5600 | R11: =M11+O11+Q11 -> 40600 | S11: =INDEX('Glosario Partidas'!$M$8:$M$10,MATCH(K11,'Glosario Partidas'!$L$8:$L$10,0)) -> 1 | T11: =R11*S11 -> 40600 | V11: PPTO
B12: Ingenierias_Y_Topografia | C12: Cálculo Estructural | D12: Fase 4 | E12: TORRE 2 | H12: MyT | I12: Lote | J12: =1/2 -> 0.5 | K12: MXN | L12: =70000 -> 70000 | M12: =J12*L12 -> 35000 | N12: 0 | O12: =M12*N12 -> 0 | P12: 0.16 | Q12: =(M12+O12)*P12 -> 5600 | R12: =M12+O12+Q12 -> 40600 | S12: =INDEX('Glosario Partidas'!$M$8:$M$10,MATCH(K12,'Glosario Partidas'!$L$8:$L$10,0)) -> 1 | T12: =R12*S12 -> 40600 | V12: PPTO
B13: Ingenierias_Y_Topografia | C13: Cálculo Estructural | D13: Extraordinarios | E13: TORRE 2 | H13: MyT | I13: Lote | J13: =1/2 -> 0.5 | K13: MXN | L13: =85000 -> 85000 | M13: =J13*L13 -> 42500 | N13: 0 | O13: =M13*N13 -> 0 | P13: 0.16 | Q13: =(M13+O13)*P13 -> 6800 | R13: =M13+O13+Q13 -> 49300 | S13: =INDEX('Glosario Partidas'!$M$8:$M$10,MATCH(K13,'Glosario Partidas'!$L$8:$L$10,0)) -> 1 | T13: =R13*S13 -> 49300 | V13: PPTO
B14: Total | M14: =SUM(M4:M13) -> 370000 | R14: =SUM(R4:R13) -> 429200 | T14: =SUM(T4:T13) -> 429200

Sheet Diseño HVAC PU
A2: 45931 | B2: VIGENTE
A3: ⬅ Resumen PU | B3: CATEGORÍA | C3: CONCEPTO | D3: DETALLE | E3: TORRE | F3: PISO | G3: DEPTO | H3: PROVEEDOR | I3: UNIDAD | J3: CANTIDAD | K3: MONEDA | L3: $ UNITARIO | M3: IMPORTE SIN IVA | N3: SOBRECOSTO | O3: TOTAL SOBRECOSTO | P3: % IVA | Q3: $ IVA | R3: IMPORTE TOTAL | S3: T.C | T3: TOTAL MXN | U3: NOTAS | V3: PARAMETRICO/PPTO
B4: Ingenierias_Y_Topografia | C4: Diseño HVAC | D4: Ingenieria HVAC Beachfronts Nauka | E4: TORRE 1 | H4: CYVS | I4: Lote | J4: =1/2 -> 0.5 | K4: MXN | L4: =130000 -> 130000 | M4: =J4*L4 -> 65000 | N4: 0 | O4: =M4*N4 -> 0 | P4: 0.16 | Q4: =(M4+O4)*P4 -> 10400 | R4: =M4+O4+Q4 -> 75400 | S4: =INDEX('Glosario Partidas'!$M$8:$M$10,MATCH(K4,'Glosario Partidas'!$L$8:$L$10,0)) -> 1 | T4: =R4*S4 -> 75400 | V4: PPTO
B5: Ingenierias_Y_Topografia | C5: Diseño HVAC | D5: Ingenieria HVAC Beachfronts Nauka | E5: TORRE 2 | H5: CYVS | I5: Lote | J5: =1/2 -> 0.5 | K5: MXN | L5: =130000 -> 130000 | M5: =J5*L5 -> 65000 | N5: 0 | O5: =M5*N5 -> 0 | P5: 0.16 | Q5: =(M5+O5)*P5 -> 10400 | R5: =M5+O5+Q5 -> 75400 | S5: =INDEX('Glosario Partidas'!$M$8:$M$10,MATCH(K5,'Glosario Partidas'!$L$8:$L$10,0)) -> 1 | T5: =R5*S5 -> 75400 | V5: PPTO
B6: Total | M6: =SUM(M4:M5) -> 130000 | R6: =SUM(R4:R5) -> 150800 | T6: =SUM(T4:T5) -> 150800

Sheet Diseño Albercas PU
A2: 45901 | B2: VIGENTE
A3: ⬅ Resumen PU | B3: CATEGORÍA | C3: CONCEPTO | D3: DETALLE | E3: TORRE | F3: PISO | G3: DEPTO | H3: PROVEEDOR | I3: UNIDAD | J3: CANTIDAD | K3: MONEDA | L3: $ UNITARIO | M3: IMPORTE SIN IVA | N3: SOBRECOSTO | O3: TOTAL SOBRECOSTO | P3: % IVA | Q3: $ IVA | R3: IMPORTE TOTAL | S3: T.C | T3: TOTAL MXN | U3: NOTAS | V3: PARAMETRICO/PPTO
B4: Ingenierias_Y_Topografia | C4: Diseño Albercas | D4: Proyecto Albercas Beachfronts Nauka | E4: TORRE 1 | H4: AQUACONCEPTS | I4: Lote | J4: =1/2 -> 0.5 | K4: MXN | L4: =120000 -> 120000 | M4: =J4*L4 -> 60000 | N4: 0 | O4: =M4*N4 -> 0 | P4: 0.16 | Q4: =(M4+O4)*P4 -> 9600 | R4: =M4+O4+Q4 -> 69600 | S4: =INDEX('Glosario Partidas'!$M$8:$M$10,MATCH(K4,'Glosario Partidas'!$L$8:$L$10,0)) -> 1 | T4: =R4*S4 -> 69600 | V4: PPTO
B5: Ingenierias_Y_Topografia | C5: Diseño Albercas | D5: Proyecto Albercas Beachfronts Nauka | E5: TORRE 2 | H5: AQUACONCEPTS | I5: Lote | J5: =1/2 -> 0.5 | K5: MXN | L5: =120000 -> 120000 | M5: =J5*L5 -> 60000 | N5: 0 | O5: =M5*N5 -> 0 | P5: 0.16 | Q5: =(M5+O5)*P5 -> 9600 | R5: =M5+O5+Q5 -> 69600 | S5: =INDEX('Glosario Partidas'!$M$8:$M$10,MATCH(K5,'Glosario Partidas'!$L$8:$L$10,0)) -> 1 | T5: =R5*S5 -> 69600 | V5: PPTO
B6: Total | M6: =SUM(M4:M5) -> 120000 | R6: =SUM(R4:R5) -> 139200 | T6: =SUM(T4:T5) -> 139200

Sheet Diseño Instalaciones PU
A2: 45931 | B2: VIGENTE
A3: ⬅ Resumen PU | B3: CATEGORÍA | C3: CONCEPTO | D3: DETALLE | E3: TORRE | F3: PISO | G3: DEPTO | H3: PROVEEDOR | I3: UNIDAD | J3: CANTIDAD | K3: MONEDA | L3: $ UNITARIO | M3: IMPORTE SIN IVA | N3: SOBRECOSTO | O3: TOTAL SOBRECOSTO | P3: % IVA | Q3: $ IVA | R3: IMPORTE TOTAL | S3: T.C | T3: TOTAL MXN | U3: NOTAS | V3: PARAMETRICO/PPTO
B4: Ingenierias_Y_Topografia | C4: Diseño Instalaciones | D4: Instalación Eléctrica | E4: TORRE 1 | H4: UNINAPS | I4: Lote | J4: =1/2 -> 0.5 | K4: MXN | L4: =140000 -> 140000 | M4: =J4*L4 -> 70000 | N4: 0 | O4: =M4*N4 -> 0 | P4: 0.16 | Q4: =(M4+O4)*P4 -> 11200 | R4: =M4+O4+Q4 -> 81200 | S4: =INDEX('Glosario Partidas'!$M$8:$M$10,MATCH(K4,'Glosario Partidas'!$L$8:$L$10,0)) -> 1 | T4: =R4*S4 -> 81200 | V4: PPTO
B5: Ingenierias_Y_Topografia | C5: Diseño Instalaciones | D5: Instalación Hidráulica | E5: TORRE 1 | H5: UNINAPS | I5: Lote | J5: =1/2 -> 0.5 | K5: MXN | L5: =54600 -> 54600 | M5: =J5*L5 -> 27300 | N5: 0 | O5: =M5*N5 -> 0 | P5: 0.16 | Q5: =(M5+O5)*P5 -> 4368 | R5: =M5+O5+Q5 -> 31668 | S5: =INDEX('Glosario Partidas'!$M$8:$M$10,MATCH(K5,'Glosario Partidas'!$L$8:$L$10,0)) -> 1 | T5: =R5*S5 -> 31668 | V5: PPTO
B6: Ingenierias_Y_Topografia | C6: Diseño Instalaciones | D6: Instalación Sanitaria | E6: TORRE 1 | H6: UNINAPS | I6: Lote | J6: =1/2 -> 0.5 | K6: MXN | L6: =54600 -> 54600 | M6: =J6*L6 -> 27300 | N6: 0 | O6: =M6*N6 -> 0 | P6: 0.16 | Q6: =(M6+O6)*P6 -> 4368 | R6: =M6+O6+Q6 -> 31668 | S6: =INDEX('Glosario Partidas'!$M$8:$M$10,MATCH(K6,'Glosario Partidas'!$L$8:$L$10,0)) -> 1 | T6: =R6*S6 -> 31668 | V6: PPTO
B7: Ingenierias_Y_Topografia | C7: Diseño Instalaciones | D7: Instalación Aguas Pluviales | E7: TORRE 1 | H7: UNINAPS | I7: Lote | J7: =1/2 -> 0.5 | K7: MXN | L7: =18200 -> 18200 | M7: =J7*L7 -> 9100 | N7: 0 | O7: =M7*N7 -> 0 | P7: 0.16 | Q7: =(M7+O7)*P7 -> 1456 | R7: =M7+O7+Q7 -> 10556 | S7: =INDEX('Glosario Partidas'!$M$8:$M$10,MATCH(K7,'Glosario Partidas'!$L$8:$L$10,0)) -> 1 | T7: =R7*S7 -> 10556 | V7: PPTO
B8: Ingenierias_Y_Topografia | C8: Diseño Instalaciones | D8: Instalación Agua Tratada | E8: TORRE 1 | H8: UNINAPS | I8: Lote | J8: =1/2 -> 0.5 | K8: MXN | L8: =20800 -> 20800 | M8: =J8*L8 -> 10400 | N8: 0 | O8: =M8*N8 -> 0 | P8: 0.16 | Q8: =(M8+O8)*P8 -> 1664 | R8: =M8+O8+Q8 -> 12064 | S8: =INDEX('Glosario Partidas'!$M$8:$M$10,MATCH(K8,'Glosario Partidas'!$L$8:$L$10,0)) -> 1 | T8: =R8*S8 -> 12064 | V8: PPTO
B9: Ingenierias_Y_Topografia | C9: Diseño Instalaciones | D9: Instalación Red de Riego Programado | E9: TORRE 1 | H9: UNINAPS | I9: Lote | J9: =1/2 -> 0.5 | K9: MXN | L9: =29500 -> 29500 | M9: =J9*L9 -> 14750 | N9: 0 | O9: =M9*N9 -> 0 | P9: 0.16 | Q9: =(M9+O9)*P9 -> 2360 | R9: =M9+O9+Q9 -> 17110 | S9: =INDEX('Glosario Partidas'!$M$8:$M$10,MATCH(K9,'Glosario Partidas'!$L$8:$L$10,0)) -> 1 | T9: =R9*S9 -> 17110 | V9: PPTO
B10: Ingenierias_Y_Topografia | C10: Diseño Instalaciones | D10: Instalación de red de Gas L.P. y/o Natural | E10: TORRE 1 | H10: UNINAPS | I10: Lote | J10: =1/2 -> 0.5 | K10: MXN | L10: =18300 -> 18300 | M10: =J10*L10 -> 9150 | N10: 0 | O10: =M10*N10 -> 0 | P10: 0.16 | Q10: =(M10+O10)*P10 -> 1464 | R10: =M10+O10+Q10 -> 10614 | S10: =INDEX('Glosario Partidas'!$M$8:$M$10,MATCH(K10,'Glosario Partidas'!$L$8:$L$10,0)) -> 1 | T10: =R10*S10 -> 10614 | V10: PPTO
B11: Ingenierias_Y_Topografia | C11: Diseño Instalaciones | D11: Instalación sistema de extinción de incendios (SCI) | E11: TORRE 1 | H11: UNINAPS | I11: Lote | J11: =1/2 -> 0.5 | K11: MXN | L11: =22300 -> 22300 | M11: =J11*L11 -> 11150 | N11: 0 | O11: =M11*N11 -> 0 | P11: 0.16 | Q11: =(M11+O11)*P11 -> 1784 | R11: =M11+O11+Q11 -> 12934 | S11: =INDEX('Glosario Partidas'!$M$8:$M$10,MATCH(K11,'Glosario Partidas'!$L$8:$L$10,0)) -> 1 | T11: =R11*S11 -> 12934 | V11: PPTO
B12: Ingenierias_Y_Topografia | C12: Diseño Instalaciones | D12: Instalación sistema de prevención de incendios (IDH) | E12: TORRE 1 | H12: UNINAPS | I12: Lote | J12: =1/2 -> 0.5 | K12: MXN | L12: =22500 -> 22500 | M12: =J12*L12 -> 11250 | N12: 0 | O12: =M12*N12 -> 0 | P12: 0.16 | Q12: =(M12+O12)*P12 -> 1800 | R12: =M12+O12+Q12 -> 13050 | S12: =INDEX('Glosario Partidas'!$M$8:$M$10,MATCH(K12,'Glosario Partidas'!$L$8:$L$10,0)) -> 1 | T12: =R12*S12 -> 13050 | V12: PPTO
B13: Ingenierias_Y_Topografia | C13: Diseño Instalaciones | D13: Instalación Eléctrica | E13: TORRE 2 | H13: UNINAPS | I13: Lote | J13: =1/2 -> 0.5 | K13: MXN | L13: =140000 -> 140000 | M13: =J13*L13 -> 70000 | N13: 0 | O13: =M13*N13 -> 0 | P13: 0.16 | Q13: =(M13+O13)*P13 -> 11200 | R13: =M13+O13+Q13 -> 81200 | S13: =INDEX('Glosario Partidas'!$M$8:$M$10,MATCH(K13,'Glosario Partidas'!$L$8:$L$10,0)) -> 1 | T13: =R13*S13 -> 81200 | V13: PPTO
B14: Ingenierias_Y_Topografia | C14: Diseño Instalaciones | D14: Instalación Hidráulica | E14: TORRE 2 | H14: UNINAPS | I14: Lote | J14: =1/2 -> 0.5 | K14: MXN | L14: =54600 -> 54600 | M14: =J14*L14 -> 27300 | N14: 0 | O14: =M14*N14 -> 0 | P14: 0.16 | Q14: =(M14+O14)*P14 -> 4368 | R14: =M14+O14+Q14 -> 31668 | S14: =INDEX('Glosario Partidas'!$M$8:$M$10,MATCH(K14,'Glosario Partidas'!$L$8:$L$10,0)) -> 1 | T14: =R14*S14 -> 31668 | V14: PPTO
B15: Ingenierias_Y_Topografia | C15: Diseño Instalaciones | D15: Instalación Sanitaria | E15: TORRE 2 | H15: UNINAPS | I15: Lote | J15: =1/2 -> 0.5 | K15: MXN | L15: =54600 -> 54600 | M15: =J15*L15 -> 27300 | N15: 0 | O15: =M15*N15 -> 0 | P15: 0.16 | Q15: =(M15+O15)*P15 -> 4368 | R15: =M15+O15+Q15 -> 31668 | S15: =INDEX('Glosario Partidas'!$M$8:$M$10,MATCH(K15,'Glosario Partidas'!$L$8:$L$10,0)) -> 1 | T15: =R15*S15 -> 31668 | V15: PPTO
B16: Ingenierias_Y_Topografia | C16: Diseño Instalaciones | D16: Instalación Aguas Pluviales | E16: TORRE 2 | H16: UNINAPS | I16: Lote | J16: =1/2 -> 0.5 | K16: MXN | L16: =18200 -> 18200 | M16: =J16*L16 -> 9100 | N16: 0 | O16: =M16*N16 -> 0 | P16: 0.16 | Q16: =(M16+O16)*P16 -> 1456 | R16: =M16+O16+Q16 -> 10556 | S16: =INDEX('Glosario Partidas'!$M$8:$M$10,MATCH(K16,'Glosario Partidas'!$L$8:$L$10,0)) -> 1 | T16: =R16*S16 -> 10556 | V16: PPTO
B17: Ingenierias_Y_Topografia | C17: Diseño Instalaciones | D17: Instalación Agua Tratada | E17: TORRE 2 | H17: UNINAPS | I17: Lote | J17: =1/2 -> 0.5 | K17: MXN | L17: =20800 -> 20800 | M17: =J17*L17 -> 10400 | N17: 0 | O17: =M17*N17 -> 0 | P17: 0.16 | Q17: =(M17+O17)*P17 -> 1664 | R17: =M17+O17+Q17 -> 12064 | S17: =INDEX('Glosario Partidas'!$M$8:$M$10,MATCH(K17,'Glosario Partidas'!$L$8:$L$10,0)) -> 1 | T17: =R17*S17 -> 12064 | V17: PPTO
B18: Ingenierias_Y_Topografia | C18: Diseño Instalaciones | D18: Instalación Red de Riego Programado | E18: TORRE 2 | H18: UNINAPS | I18: Lote | J18: =1/2 -> 0.5 | K18: MXN | L18: =29500 -> 29500 | M18: =J18*L18 -> 14750 | N18: 0 | O18: =M18*N18 -> 0 | P18: 0.16 | Q18: =(M18+O18)*P18 -> 2360 | R18: =M18+O18+Q18 -> 17110 | S18: =INDEX('Glosario Partidas'!$M$8:$M$10,MATCH(K18,'Glosario Partidas'!$L$8:$L$10,0)) -> 1 | T18: =R18*S18 -> 17110 | V18: PPTO
B19: Ingenierias_Y_Topografia | C19: Diseño Instalaciones | D19: Instalación de red de Gas L.P. y/o Natural | E19: TORRE 2 | H19: UNINAPS | I19: Lote | J19: =1/2 -> 0.5 | K19: MXN | L19: =18300 -> 18300 | M19: =J19*L19 -> 9150 | N19: 0 | O19: =M19*N19 -> 0 | P19: 0.16 | Q19: =(M19+O19)*P19 -> 1464 | R19: =M19+O19+Q19 -> 10614 | S19: =INDEX('Glosario Partidas'!$M$8:$M$10,MATCH(K19,'Glosario Partidas'!$L$8:$L$10,0)) -> 1 | T19: =R19*S19 -> 10614 | V19: PPTO
B20: Ingenierias_Y_Topografia | C20: Diseño Instalaciones | D20: Instalación sistema de extinción de incendios (SCI) | E20: TORRE 2 | H20: UNINAPS | I20: Lote | J20: =1/2 -> 0.5 | K20: MXN | L20: =22300 -> 22300 | M20: =J20*L20 -> 11150 | N20: 0 | O20: =M20*N20 -> 0 | P20: 0.16 | Q20: =(M20+O20)*P20 -> 1784 | R20: =M20+O20+Q20 -> 12934 | S20: =INDEX('Glosario Partidas'!$M$8:$M$10,MATCH(K20,'Glosario Partidas'!$L$8:$L$10,0)) -> 1 | T20: =R20*S20 -> 12934 | V20: PPTO
B21: Ingenierias_Y_Topografia | C21: Diseño Instalaciones | D21: Instalación sistema de prevención de incendios (IDH) | E21: TORRE 2 | H21: UNINAPS | I21: Lote | J21: =1/2 -> 0.5 | K21: MXN | L21: =22500 -> 22500 | M21: =J21*L21 -> 11250 | N21: 0 | O21: =M21*N21 -> 0 | P21: 0.16 | Q21: =(M21+O21)*P21 -> 1800 | R21: =M21+O21+Q21 -> 13050 | S21: =INDEX('Glosario Partidas'!$M$8:$M$10,MATCH(K21,'Glosario Partidas'!$L$8:$L$10,0)) -> 1 | T21: =R21*S21 -> 13050 | V21: PPTO
B22: Total | M22: =SUM(M4:M21) -> 380800 | R22: =SUM(R4:R21) -> 441728 | T22: =SUM(T4:T21) -> 441728

Sheet Diseño Iluminacion PU
A2: 46023 | B2: VIGENTE
A3: ⬅ Resumen PU | B3: CATEGORÍA | C3: CONCEPTO | D3: DETALLE | E3: TORRE | F3: PISO | G3: DEPTO | H3: PROVEEDOR | I3: UNIDAD | J3: CANTIDAD | K3: MONEDA | L3: $ UNITARIO | M3: IMPORTE SIN IVA | N3: SOBRECOSTO | O3: TOTAL SOBRECOSTO | P3: % IVA | Q3: $ IVA | R3: IMPORTE TOTAL | S3: T.C | T3: TOTAL MXN | U3: NOTAS | V3: PARAMETRICO/PPTO
B4: Ingenierias_Y_Topografia | C4: Diseño Iluminación | D4: Diseño Iluminación | E4: TORRE 1 | H4: ARTEC | I4: Lote | J4: =1/2 -> 0.5 | K4: MXN | L4: =33145 -> 33145 | M4: =J4*L4 -> 16572.5 | N4: 0 | O4: =M4*N4 -> 0 | P4: 0.16 | Q4: =(M4+O4)*P4 -> 2651.6 | R4: =M4+O4+Q4 -> 19224.1 | S4: =INDEX('Glosario Partidas'!$M$8:$M$10,MATCH(K4,'Glosario Partidas'!$L$8:$L$10,0)) -> 1 | T4: =R4*S4 -> 19224.1 | V4: PPTO
B5: Ingenierias_Y_Topografia | C5: Diseño Iluminación | D5: Diseño Iluminación | E5: TORRE 2 | H5: ARTEC | I5: Lote | J5: =1/2 -> 0.5 | K5: MXN | L5: =33145 -> 33145 | M5: =J5*L5 -> 16572.5 | N5: 0 | O5: =M5*N5 -> 0 | P5: 0.16 | Q5: =(M5+O5)*P5 -> 2651.6 | R5: =M5+O5+Q5 -> 19224.1 | S5: =INDEX('Glosario Partidas'!$M$8:$M$10,MATCH(K5,'Glosario Partidas'!$L$8:$L$10,0)) -> 1 | T5: =R5*S5 -> 19224.1 | V5: PPTO
B6: Total | M6: =SUM(M4:M5) -> 33145 | R6: =SUM(R4:R5) -> 38448.2 | T6: =SUM(T4:T5) -> 38448.2

Sheet Diseño Acustica
A2: 46023 | B2: VIGENTE
A3: ⬅ Resumen PU | B3: CATEGORÍA | C3: CONCEPTO | D3: DETALLE | E3: TORRE | F3: PISO | G3: DEPTO | H3: PROVEEDOR | I3: UNIDAD | J3: CANTIDAD | K3: MONEDA | L3: $ UNITARIO | M3: IMPORTE SIN IVA | N3: SOBRECOSTO | O3: TOTAL SOBRECOSTO | P3: % IVA | Q3: $ IVA | R3: IMPORTE TOTAL | S3: T.C | T3: TOTAL MXN | U3: NOTAS | V3: PARAMETRICO/PPTO
B4: Ingenierias_Y_Topografia | C4: Diseño Acustica | D4: Diseño Acustica | E4: TORRE 1 | H4: SAAD | I4: Lote | J4: =1/2 -> 0.5 | K4: MXN | L4: 172413.79 | M4: =J4*L4 -> 86206.897 | N4: 0 | O4: =M4*N4 -> 0 | P4: 0.16 | Q4: =(M4+O4)*P4 -> 13793.103 | R4: =M4+O4+Q4 -> 100000 | S4: =INDEX('Glosario Partidas'!$M$8:$M$10,MATCH(K4,'Glosario Partidas'!$L$8:$L$10,0)) -> 1 | T4: =R4*S4 -> 100000 | V4: PPTO
B5: Ingenierias_Y_Topografia | C5: Diseño Acustica | D5: Diseño Acustica | E5: TORRE 2 | H5: SAAD | I5: Lote | J5: =1/2 -> 0.5 | K5: MXN | L5: 172413.79 | M5: =J5*L5 -> 86206.897 | N5: 0 | O5: =M5*N5 -> 0 | P5: 0.16 | Q5: =(M5+O5)*P5 -> 13793.103 | R5: =M5+O5+Q5 -> 100000 | S5: =INDEX('Glosario Partidas'!$M$8:$M$10,MATCH(K5,'Glosario Partidas'!$L$8:$L$10,0)) -> 1 | T5: =R5*S5 -> 100000 | V5: PPTO
B6: Total | M6: =SUM(M4:M5) -> 172413.79 | R6: =SUM(R4:R5) -> 200000 | T6: =SUM(T4:T5) -> 200000

Sheet Condiciones Generales
A1: ⬅ Resumen PU | B1: CATEGORÍA | C1: CONCEPTO | D1: DETALLE | E1: TORRE | F1: PISO | G1: DEPTO | H1: PROVEEDOR | I1: UNIDAD | J1: CANTIDAD | K1: MONEDA | L1: $ UNITARIO | M1: IMPORTE SIN IVA | N1: SOBRECOSTO | O1: TOTAL SOBRECOSTO | P1: % IVA | Q1: $ IVA | R1: IMPORTE TOTAL | S1: T.C | T1: TOTAL MXN | U1: NOTAS | V1: PARAMETRICO/PPTO | W1: Contratado/No Contratado | X1: 5 Recamara | AB1: CONTRATADO | AC1: NO CONTRATADO
B2: Condiciones Generales | C2: Papeleria | D2: Papeleria | E2: TORRE 1 | F2: S/D | G2: S/D | H2: ='Papeleria PU'!H3 -> Office Depot de México SA de CV | I2: Lote | J2: 1 | K2: MXN | L2: =SUMIFS('Papeleria PU'!M:M,'Papeleria PU'!E:E,E2) -> 56815.24 | M2: =J2*L2 -> 56815.24 | N2: 0 | O2: =M2*N2 -> 0 | P2: 0.16 | Q2: =(M2+O2)*P2 -> 9090.4384 | R2: =M2+O2+Q2 -> 65905.678 | S2: =INDEX('Glosario Partidas'!$M$8:$M$10,MATCH(K2,'Glosario Partidas'!$L$8:$L$10,0)) -> 1 | T2: =R2*S2 -> 65905.678 | U2: ########### | V2: PPTO | W2: Contratado
B3: Condiciones Generales | C3: Renta Generadores de Luz | D3: Generador 1 | E3: TORRE 1 | F3: S/D | G3: S/D | H3: ='Generador Luz PU'!$H$3 -> Tracsa | I3: Lote | J3: 11 | K3: MXN | L3: {=INDEX('Generador Luz PU'!L:L,MATCH(1,('Generador Luz PU'!E:E=E3)*('Generador Luz PU'!D:D="Renta Generador DE55GC"),0))} -> 14454.545 | M3: =J3*L3 -> 159000 | N3: 0 | O3: =M3*N3 -> 0 | P3: 0.16 | Q3: =(M3+O3)*P3 -> 25440 | R3: =M3+O3+Q3 -> 184440 | S3: =INDEX('Glosario Partidas'!$M$8:$M$10,MATCH(K3,'Glosario Partidas'!$L$8:$L$10,0)) -> 1 | T3: =R3*S3 -> 184440 | U3: ########### | V3: PPTO | W3: Contratado
B4: Condiciones Generales | C4: Renta Generadores de Luz | D4: Generador 2 | E4: TORRE 1 | F4: S/D | G4: S/D | H4: ='Generador Luz PU'!$H$3 -> Tracsa | I4: Lote | J4: 11 | K4: MXN | L4: {=INDEX('Generador Luz PU'!L:L,MATCH(1,('Generador Luz PU'!E:E=E4)*('Generador Luz PU'!D:D="Renta Generador DE22GC"),0))} -> 12454.545 | M4: =J4*L4 -> 137000 | N4: 0 | O4: =M4*N4 -> 0 | P4: 0.16 | Q4: =(M4+O4)*P4 -> 21920 | R4: =M4+O4+Q4 -> 158920 | S4: =INDEX('Glosario Partidas'!$M$8:$M$10,MATCH(K4,'Glosario Partidas'!$L$8:$L$10,0)) -> 1 | T4: =R4*S4 -> 158920 | U4: ########### | V4: PPTO | W4: Contratado
B5: Condiciones Generales | C5: Renta Camper | D5: S/D | E5: TORRE 1 | F5: S/D | G5: S/D | H5: ='Camper PU'!H3 -> Tracsa | I5: Mes | J5: 12 | K5: MXN | L5: =SUMIFS('Camper PU'!L:L,'Camper PU'!E:E,E5) -> 8000 | M5: =J5*L5 -> 96000 | N5: 0 | O5: =M5*N5 -> 0 | P5: 0.16 | Q5: =(M5+O5)*P5 -> 15360 | R5: =M5+O5+Q5 -> 111360 | S5: =INDEX('Glosario Partidas'!$M$8:$M$10,MATCH(K5,'Glosario Partidas'!$L$8:$L$10,0)) -> 1 | T5: =R5*S5 -> 111360 | U5: ########### | V5: PPTO | W5: Contratado
B6: Condiciones Generales | C6: Seguro de Obra | D6: S/D | E6: TORRE 1 | F6: S/D | G6: S/D | H6: NA | I6: Año | J6: 2 | K6: MXN | L6: =1716881.89655172/2 -> 858440.95 | M6: =J6*L6 -> 1716881.9 | N6: 0 | O6: =M6*N6 -> 0 | P6: 0.16 | Q6: =(M6+O6)*P6 -> 274701.1 | R6: =M6+O6+Q6 -> 1991583 | S6: =INDEX('Glosario Partidas'!$M$8:$M$10,MATCH(K6,'Glosario Partidas'!$L$8:$L$10,0)) -> 1 | T6: =R6*S6 -> 1991583 | U6: ########### | V6: PPTO | W6: Contratado
B7: Condiciones Generales | C7: Tinaco | D7: 5K Litros | E7: TORRE 1 | F7: S/D | G7: S/D | H7: NA | I7: Lote | J7: 0 | K7: MXN | L7: 20000 | M7: =J7*L7 -> 0 | N7: 0 | O7: =M7*N7 -> 0 | P7: 0.16 | Q7: =(M7+O7)*P7 -> 0 | R7: =M7+O7+Q7 -> 0 | S7: =INDEX('Glosario Partidas'!$M$8:$M$10,MATCH(K7,'Glosario Partidas'!$L$8:$L$10,0)) -> 1 | T7: =R7*S7 -> 0 | U7: ########### | V7: PARAMETRICO | W7: No Contratado
B8: Condiciones Generales | C8: Renta Baños | D8: S/D | E8: TORRE 1 | F8: S/D | G8: S/D | H8: NA | I8: Lote | J8: 12 | K8: MXN | L8: 14000 | M8: =J8*L8 -> 168000 | N8: 0 | O8: =M8*N8 -> 0 | P8: 0.16 | Q8: =(M8+O8)*P8 -> 26880 | R8: =M8+O8+Q8 -> 194880 | S8: =INDEX('Glosario Partidas'!$M$8:$M$10,MATCH(K8,'Glosario Partidas'!$L$8:$L$10,0)) -> 1 | T8: =R8*S8 -> 194880 | U8: ########### | V8: PARAMETRICO | W8: No Contratado
B9: Condiciones Generales | C9: Fosa Septica | D9: S/D | E9: TORRE 1 | F9: S/D | G9: S/D | H9: NA | I9: Lote | J9: 1 | K9: MXN | L9: 35000 | M9: =J9*L9 -> 35000 | N9: 0 | O9: =M9*N9 -> 0 | P9: 0.16 | Q9: =(M9+O9)*P9 -> 5600 | R9: =M9+O9+Q9 -> 40600 | S9: =INDEX('Glosario Partidas'!$M$8:$M$10,MATCH(K9,'Glosario Partidas'!$L$8:$L$10,0)) -> 1 | T9: =R9*S9 -> 40600 | U9: ########### | V9: PARAMETRICO | W9: No Contratado
